Workbook

Sheet sheet0
A1: INITIAL_BALANCE | B1: CREDITS | C1: DEBITS | D1: FINAL_BALANCE
A2: 10628546 | B2: 41945728 | C2: -31621394 | D2: 20952879
A4: RELEASE_DATE | B4: TRANSACTION_TYPE | C4: REFERENCE_ID | D4: TRANSACTION_NET_AMOUNT | E4: PARTIAL_BALANCE | F4: VARIOS | G4: TRANSACTION_TOTAL_AMOUNT | H4: IDC COMPRAS | I4: SIRCUPA | J4: SIRTAC | K4: Gastos | L4: IDC | M4: MOV TOTAL | O4: OBSERV
A5: 22-11-2025 | B5: Liquidación de dinero | C5: 134203029881 | D5: 101977.2 | E5: 11221513 | F5: COBRO | I5: =-IFERROR(VLOOKUP(C5,SIRCUPA!$A$21:$H$313,8,0),0) -> 0 | J5: =-IFERROR(VLOOKUP(C5,SIRTAC!$A$16:$H$2072,8,0),0) -> -1170 | K5: =-IFERROR(VLOOKUP(C5,Gastos!$A$9:$J$2065,10,0),0) -> -13150.8 | L5: =-IFERROR(VLOOKUP(C5,IDC!$A$20:$H$2401,8,0),0) -> -702 | M5: =+D5-I5-J5-K5-L5 -> 117000 | P5: =+L5/0.006 -> -117000 | Q5: =+M5+P5 -> 0
A6: 30-11-2025 | B6: Liquidación de dinero | C6: 135842753022 | D6: 196636.7 | E6: 19385744 | F6: COBRO | I6: =-IFERROR(VLOOKUP(C6,SIRCUPA!$A$21:$H$313,8,0),0) -> 0 | J6: =-IFERROR(VLOOKUP(C6,SIRTAC!$A$16:$H$2072,8,0),0) -> -2095 | K6: =-IFERROR(VLOOKUP(C6,Gastos!$A$9:$J$2065,10,0),0) -> -9511.3 | L6: =-IFERROR(VLOOKUP(C6,IDC!$A$20:$H$2401,8,0),0) -> -1257 | M6: =+D6-I6-J6-K6-L6 -> 209500 | P6: =+L6/0.006 -> -209500 | Q6: =+M6+P6 -> 0
A7: 15-11-2025 | B7: Liquidación de dinero | C7: 133316015423 | D7: 108494.05 | E7: 7099125.1 | F7: COBRO | I7: =-IFERROR(VLOOKUP(C7,SIRCUPA!$A$21:$H$313,8,0),0) -> 0 | J7: =-IFERROR(VLOOKUP(C7,SIRTAC!$A$16:$H$2072,8,0),0) -> -1195 | K7: =-IFERROR(VLOOKUP(C7,Gastos!$A$9:$J$2065,10,0),0) -> -9093.95 | L7: =-IFERROR(VLOOKUP(C7,IDC!$A$20:$H$2401,8,0),0) -> -717 | M7: =+D7-I7-J7-K7-L7 -> 119500 | P7: =+L7/0.006 -> -119500 | Q7: =+M7+P7 -> 0
A8: 01-11-2025 | B8: Liquidación de dinero | C8: 132172242648 | D8: 59966.08 | E8: 11920739 | F8: COBRO | I8: =-IFERROR(VLOOKUP(C8,SIRCUPA!$A$21:$H$313,8,0),0) -> 0 | J8: =-IFERROR(VLOOKUP(C8,SIRTAC!$A$16:$H$2072,8,0),0) -> -688 | K8: =-IFERROR(VLOOKUP(C8,Gastos!$A$9:$J$2065,10,0),0) -> -7733.12 | L8: =-IFERROR(VLOOKUP(C8,IDC!$A$20:$H$2401,8,0),0) -> -412.8 | M8: =+D8-I8-J8-K8-L8 -> 68800 | P8: =+L8/0.006 -> -68800 | Q8: =+M8+P8 -> 0
A9: 30-11-2025 | B9: Liquidación de dinero | C9: 135324608697 | D9: 58658.68 | E9: 20701657 | F9: COBRO | I9: =-IFERROR(VLOOKUP(C9,SIRCUPA!$A$21:$H$313,8,0),0) -> 0 | J9: =-IFERROR(VLOOKUP(C9,SIRTAC!$A$16:$H$2072,8,0),0) -> -673 | K9: =-IFERROR(VLOOKUP(C9,Gastos!$A$9:$J$2065,10,0),0) -> -7564.52 | L9: =-IFERROR(VLOOKUP(C9,IDC!$A$20:$H$2401,8,0),0) -> -403.8 | M9: =+D9-I9-J9-K9-L9 -> 67300 | P9: =+L9/0.006 -> -67300 | Q9: =+M9+P9 -> 0
A10: 22-11-2025 | B10: Liquidación de dinero | C10: 134821855786 | D10: 87067.61 | E10: 12404263 | F10: COBRO | I10: =-IFERROR(VLOOKUP(C10,SIRCUPA!$A$21:$H$313,8,0),0) -> 0 | J10: =-IFERROR(VLOOKUP(C10,SIRTAC!$A$16:$H$2072,8,0),0) -> -959 | K10: =-IFERROR(VLOOKUP(C10,Gastos!$A$9:$J$2065,10,0),0) -> -7297.99 | L10: =-IFERROR(VLOOKUP(C10,IDC!$A$20:$H$2401,8,0),0) -> -575.4 | M10: =+D10-I10-J10-K10-L10 -> 95900 | P10: =+L10/0.006 -> -95900 | Q10: =+M10+P10 -> 0
A11: 06-11-2025 | B11: Liquidación de dinero | C11: 132197936925 | D11: 54562.16 | E11: 9954234.7 | F11: COBRO | I11: =-IFERROR(VLOOKUP(C11,SIRCUPA!$A$21:$H$313,8,0),0) -> 0 | J11: =-IFERROR(VLOOKUP(C11,SIRTAC!$A$16:$H$2072,8,0),0) -> -626 | K11: =-IFERROR(VLOOKUP(C11,Gastos!$A$9:$J$2065,10,0),0) -> -7036.24 | L11: =-IFERROR(VLOOKUP(C11,IDC!$A$20:$H$2401,8,0),0) -> -375.6 | M11: =+D11-I11-J11-K11-L11 -> 62600 | P11: =+L11/0.006 -> -62600 | Q11: =+M11+P11 -> 0
A12: 01-11-2025 | B12: Liquidación de dinero | C12: 131458138389 | D12: 83617.59 | E12: 11102244 | F12: COBRO | I12: =-IFERROR(VLOOKUP(C12,SIRCUPA!$A$21:$H$313,8,0),0) -> 0 | J12: =-IFERROR(VLOOKUP(C12,SIRTAC!$A$16:$H$2072,8,0),0) -> -921 | K12: =-IFERROR(VLOOKUP(C12,Gastos!$A$9:$J$2065,10,0),0) -> -7008.81 | L12: =-IFERROR(VLOOKUP(C12,IDC!$A$20:$H$2401,8,0),0) -> -552.6 | M12: =+D12-I12-J12-K12-L12 -> 92100 | P12: =+L12/0.006 -> -92100 | Q12: =+M12+P12 -> 0
A13: 22-11-2025 | B13: Liquidación de dinero | C13: 134208327789 | D13: 147089.79 | E13: 12713382 | F13: COBRO | I13: =-IFERROR(VLOOKUP(C13,SIRCUPA!$A$21:$H$313,8,0),0) -> 0 | J13: =-IFERROR(VLOOKUP(C13,SIRTAC!$A$16:$H$2072,8,0),0) -> -1557 | K13: =-IFERROR(VLOOKUP(C13,Gastos!$A$9:$J$2065,10,0),0) -> -6119.01 | L13: =-IFERROR(VLOOKUP(C13,IDC!$A$20:$H$2401,8,0),0) -> -934.2 | M13: =+D13-I13-J13-K13-L13 -> 155700 | P13: =+L13/0.006 -> -155700 | Q13: =+M13+P13 -> 0
A14: 21-11-2025 | B14: Liquidación de dinero | C14: 134071810937 | D14: 70634.62 | E14: 10033631 | F14: COBRO | I14: =-IFERROR(VLOOKUP(C14,SIRCUPA!$A$21:$H$313,8,0),0) -> 0 | J14: =-IFERROR(VLOOKUP(C14,SIRTAC!$A$16:$H$2072,8,0),0) -> -778 | K14: =-IFERROR(VLOOKUP(C14,Gastos!$A$9:$J$2065,10,0),0) -> -5920.58 | L14: =-IFERROR(VLOOKUP(C14,IDC!$A$20:$H$2401,8,0),0) -> -466.8 | M14: =+D14-I14-J14-K14-L14 -> 77800 | P14: =+L14/0.006 -> -77800 | Q14: =+M14+P14 -> 0
A15: 13-11-2025 | B15: Liquidación de dinero | C15: 133633841754 | D15: 138398.55 | E15: 3902095.6 | F15: COBRO | I15: =-IFERROR(VLOOKUP(C15,SIRCUPA!$A$21:$H$313,8,0),0) -> 0 | J15: =-IFERROR(VLOOKUP(C15,SIRTAC!$A$16:$H$2072,8,0),0) -> -1465 | K15: =-IFERROR(VLOOKUP(C15,Gastos!$A$9:$J$2065,10,0),0) -> -5757.45 | L15: =-IFERROR(VLOOKUP(C15,IDC!$A$20:$H$2401,8,0),0) -> -879 | M15: =+D15-I15-J15-K15-L15 -> 146500 | P15: =+L15/0.006 -> -146500 | Q15: =+M15+P15 -> 0
A16: 08-11-2025 | B16: Liquidación de dinero | C16: 132376967049 | D16: 68546.45 | E16: 13004941 | F16: COBRO | I16: =-IFERROR(VLOOKUP(C16,SIRCUPA!$A$21:$H$313,8,0),0) -> 0 | J16: =-IFERROR(VLOOKUP(C16,SIRTAC!$A$16:$H$2072,8,0),0) -> -755 | K16: =-IFERROR(VLOOKUP(C16,Gastos!$A$9:$J$2065,10,0),0) -> -5745.55 | L16: =-IFERROR(VLOOKUP(C16,IDC!$A$20:$H$2401,8,0),0) -> -453 | M16: =+D16-I16-J16-K16-L16 -> 75500 | P16: =+L16/0.006 -> -75500 | Q16: =+M16+P16 -> 0
... A1135: 22-11-2025 | B1135: Liquidación de dinero | C1135: 134821033406 | D1135: 12958.19 | E1135: 12078820 | F1135: COBRO | I1135: =-IFERROR(VLOOKUP(C1135,SIRCUPA!$A$21:$H$313,8,0),0) -> 0 | J1135: =-IFERROR(VLOOKUP(C1135,SIRTAC!$A$16:$H$2072,8,0),0) -> -133 | K1135: =-IFERROR(VLOOKUP(C1135,Gastos!$A$9:$J$2065,10,0),0) -> -129.01 | L1135: =-IFERROR(VLOOKUP(C1135,IDC!$A$20:$H$2401,8,0),0) -> -79.8 | M1135: =+D1135-I1135-J1135-K1135-L1135 -> 13300 | P1135: =+L1135/0.006 -> -13300 | Q1135: =+M1135+P1135 -> 0
A1136: 21-11-2025 | B1136: Liquidación de dinero | C1136: 134186435163 | D1136: 7644.83 | E1136: 10432762 | F1136: COBRO | I1136: =-IFERROR(VLOOKUP(C1136,SIRCUPA!$A$21:$H$313,8,0),0) -> 0 | J1136: -79 | K1136: -128.77 | L1136: -47.4 | M1136: =+D1136-I1136-J1136-K1136-L1136 -> 7900 | P1136: =+L1136/0.006 -> -7900 | Q1136: =+M1136+P1136 -> 0
A1137: 02-11-2025 | B1137: Liquidación de dinero | C1137: 132179457042 | D1137: 12860.76 | E1137: 12995613 | F1137: COBRO | I1137: =-IFERROR(VLOOKUP(C1137,SIRCUPA!$A$21:$H$313,8,0),0) -> 0 | J1137: =-IFERROR(VLOOKUP(C1137,SIRTAC!$A$16:$H$2072,8,0),0) -> -132 | K1137: =-IFERROR(VLOOKUP(C1137,Gastos!$A$9:$J$2065,10,0),0) -> -128.04 | L1137: =-IFERROR(VLOOKUP(C1137,IDC!$A$20:$H$2401,8,0),0) -> -79.2 | M1137: =+D1137-I1137-J1137-K1137-L1137 -> 13200 | P1137: =+L1137/0.006 -> -13200 | Q1137: =+M1137+P1137 -> 0
A1138: 28-11-2025 | B1138: Liquidación de dinero | C1138: 135692455994 | D1138: 12860.76 | E1138: 17146449 | F1138: COBRO | I1138: =-IFERROR(VLOOKUP(C1138,SIRCUPA!$A$21:$H$313,8,0),0) -> 0 | J1138: =-IFERROR(VLOOKUP(C1138,SIRTAC!$A$16:$H$2072,8,0),0) -> -132 | K1138: =-IFERROR(VLOOKUP(C1138,Gastos!$A$9:$J$2065,10,0),0) -> -128.04 | L1138: =-IFERROR(VLOOKUP(C1138,IDC!$A$20:$H$2401,8,0),0) -> -79.2 | M1138: =+D1138-I1138-J1138-K1138-L1138 -> 13200 | P1138: =+L1138/0.006 -> -13200 | Q1138: =+M1138+P1138 -> 0
A1139: 09-11-2025 | B1139: Liquidación de dinero | C1139: 132508284689 | D1139: 12763.33 | E1139: 15487511 | F1139: COBRO | I1139: =-IFERROR(VLOOKUP(C1139,SIRCUPA!$A$21:$H$313,8,0),0) -> 0 | J1139: =-IFERROR(VLOOKUP(C1139,SIRTAC!$A$16:$H$2072,8,0),0) -> -131 | K1139: =-IFERROR(VLOOKUP(C1139,Gastos!$A$9:$J$2065,10,0),0) -> -127.07 | L1139: =-IFERROR(VLOOKUP(C1139,IDC!$A$20:$H$2401,8,0),0) -> -78.6 | M1139: =+D1139-I1139-J1139-K1139-L1139 -> 13100 | P1139: =+L1139/0.006 -> -13100 | Q1139: =+M1139+P1139 -> 0
A1140: 28-11-2025 | B1140: Liquidación de dinero | C1140: 135545497110 | D1140: 12763.33 | E1140: 16313125 | F1140: COBRO | I1140: =-IFERROR(VLOOKUP(C1140,SIRCUPA!$A$21:$H$313,8,0),0) -> 0 | J1140: =-IFERROR(VLOOKUP(C1140,SIRTAC!$A$16:$H$2072,8,0),0) -> -131 | K1140: =-IFERROR(VLOOKUP(C1140,Gastos!$A$9:$J$2065,10,0),0) -> -127.07 | L1140: =-IFERROR(VLOOKUP(C1140,IDC!$A$20:$H$2401,8,0),0) -> -78.6 | M1140: =+D1140-I1140-J1140-K1140-L1140 -> 13100 | P1140: =+L1140/0.006 -> -13100 | Q1140: =+M1140+P1140 -> 0
A1141: 22-11-2025 | B1141: Liquidación de dinero | C1141: 134310436849 | D1141: 12665.9 | E1141: 13601589 | F1141: COBRO | I1141: =-IFERROR(VLOOKUP(C1141,SIRCUPA!$A$21:$H$313,8,0),0) -> 0 | J1141: =-IFERROR(VLOOKUP(C1141,SIRTAC!$A$16:$H$2072,8,0),0) -> -130 | K1141: =-IFERROR(VLOOKUP(C1141,Gastos!$A$9:$J$2065,10,0),0) -> -126.1 | L1141: =-IFERROR(VLOOKUP(C1141,IDC!$A$20:$H$2401,8,0),0) -> -78 | M1141: =+D1141-I1141-J1141-K1141-L1141 -> 13000 | P1141: =+L1141/0.006 -> -13000 | Q1141: =+M1141+P1141 -> 0
A1142: 22-11-2025 | B1142: Liquidación de dinero | C1142: 134311810627 | D1142: 12665.9 | E1142: 13851622 | F1142: COBRO | I1142: =-IFERROR(VLOOKUP(C1142,SIRCUPA!$A$21:$H$313,8,0),0) -> 0 | J1142: =-IFERROR(VLOOKUP(C1142,SIRTAC!$A$16:$H$2072,8,0),0) -> -130 | K1142: =-IFERROR(VLOOKUP(C1142,Gastos!$A$9:$J$2065,10,0),0) -> -126.1 | L1142: =-IFERROR(VLOOKUP(C1142,IDC!$A$20:$H$2401,8,0),0) -> -78 | M1142: =+D1142-I1142-J1142-K1142-L1142 -> 13000 | P1142: =+L1142/0.006 -> -13000 | Q1142: =+M1142+P1142 -> 0
A1143: 22-11-2025 | B1143: Liquidación de dinero | C1143: 134311936019 | D1143: 12665.9 | E1143: 13942782 | F1143: COBRO | I1143: =-IFERROR(VLOOKUP(C1143,SIRCUPA!$A$21:$H$313,8,0),0) -> 0 | J1143: =-IFERROR(VLOOKUP(C1143,SIRTAC!$A$16:$H$2072,8,0),0) -> -130 | K1143: =-IFERROR(VLOOKUP(C1143,Gastos!$A$9:$J$2065,10,0),0) -> -126.1 | L1143: =-IFERROR(VLOOKUP(C1143,IDC!$A$20:$H$2401,8,0),0) -> -78 | M1143: =+D1143-I1143-J1143-K1143-L1143 -> 13000 | P1143: =+L1143/0.006 -> -13000 | Q1143: =+M1143+P1143 -> 0
A1144: 22-11-2025 | B1144: Liquidación de dinero | C1144: 134928686646 | D1144: 12665.9 | E1144: 14479641 | F1144: COBRO | I1144: =-IFERROR(VLOOKUP(C1144,SIRCUPA!$A$21:$H$313,8,0),0) -> 0 | J1144: =-IFERROR(VLOOKUP(C1144,SIRTAC!$A$16:$H$2072,8,0),0) -> -130 | K1144: =-IFERROR(VLOOKUP(C1144,Gastos!$A$9:$J$2065,10,0),0) -> -126.1 | L1144: =-IFERROR(VLOOKUP(C1144,IDC!$A$20:$H$2401,8,0),0) -> -78 | M1144: =+D1144-I1144-J1144-K1144-L1144 -> 13000 | P1144: =+L1144/0.006 -> -13000 | Q1144: =+M1144+P1144 -> 0
A1145: 22-11-2025 | B1145: Liquidación de dinero | C1145: 134315807529 | D1145: 12665.9 | E1145: 14982946 | F1145: COBRO | I1145: =-IFERROR(VLOOKUP(C1145,SIRCUPA!$A$21:$H$313,8,0),0) -> 0 | J1145: =-IFERROR(VLOOKUP(C1145,SIRTAC!$A$16:$H$2072,8,0),0) -> -130 | K1145: =-IFERROR(VLOOKUP(C1145,Gastos!$A$9:$J$2065,10,0),0) -> -126.1 | L1145: =-IFERROR(VLOOKUP(C1145,IDC!$A$20:$H$2401,8,0),0) -> -78 | M1145: =+D1145-I1145-J1145-K1145-L1145 -> 13000 | P1145: =+L1145/0.006 -> -13000 | Q1145: =+M1145+P1145 -> 0
A1146: 22-11-2025 | B1146: Liquidación de dinero | C1146: 134934600128 | D1146: 12665.9 | E1146: 16287255 | F1146: COBRO | I1146: =-IFERROR(VLOOKUP(C1146,SIRCUPA!$A$21:$H$313,8,0),0) -> 0 | J1146: =-IFERROR(VLOOKUP(C1146,SIRTAC!$A$16:$H$2072,8,0),0) -> -130 | K1146: =-IFERROR(VLOOKUP(C1146,Gastos!$A$9:$J$2065,10,0),0) -> -126.1 | L1146: =-IFERROR(VLOOKUP(C1146,IDC!$A$20:$H$2401,8,0),0) -> -78 | M1146: =+D1146-I1146-J1146-K1146-L1146 -> 13000 | P1146: =+L1146/0.006 -> -13000 | Q1146: =+M1146+P1146 -> 0
A1147: 23-11-2025 | B1147: Liquidación de dinero | C1147: 134402353605 | D1147: 12665.9 | E1147: 19799496 | F1147: COBRO | I1147: =-IFERROR(VLOOKUP(C1147,SIRCUPA!$A$21:$H$313,8,0),0) -> 0 | J1147: =-IFERROR(VLOOKUP(C1147,SIRTAC!$A$16:$H$2072,8,0),0) -> -130 | K1147: =-IFERROR(VLOOKUP(C1147,Gastos!$A$9:$J$2065,10,0),0) -> -126.1 | L1147: =-IFERROR(VLOOKUP(C1147,IDC!$A$20:$H$2401,8,0),0) -> -78 | M1147: =+D1147-I1147-J1147-K1147-L1147 -> 13000 | P1147: =+L1147/0.006 -> -13000 | Q1147: =+M1147+P1147 -> 0
A1148: 23-11-2025 | B1148: Liquidación de dinero | C1148: 135020863162 | D1148: 12665.9 | E1148: 20085163 | F1148: COBRO | I1148: =-IFERROR(VLOOKUP(C1148,SIRCUPA!$A$21:$H$313,8,0),0) -> 0 | J1148: =-IFERROR(VLOOKUP(C1148,SIRTAC!$A$16:$H$2072,8,0),0) -> -130 | K1148: =-IFERROR(VLOOKUP(C1148,Gastos!$A$9:$J$2065,10,0),0) -> -126.1 | L1148: =-IFERROR(VLOOKUP(C1148,IDC!$A$20:$H$2401,8,0),0) -> -78 | M1148: =+D1148-I1148-J1148-K1148-L1148 -> 13000 | P1148: =+L1148/0.006 -> -13000 | Q1148: =+M1148+P1148 -> 0
... A2060: 23-11-2025 | B2060: Liquidación de dinero | C2060: 134323421061 | D2060: 24.36 | E2060: 17611647 | F2060: COBRO | I2060: =-IFERROR(VLOOKUP(C2060,SIRCUPA!$A$21:$H$313,8,0),0) -> 0 | J2060: =-IFERROR(VLOOKUP(C2060,SIRTAC!$A$16:$H$2072,8,0),0) -> -0.25 | K2060: =-IFERROR(VLOOKUP(C2060,Gastos!$A$9:$J$2065,10,0),0) -> -0.24 | L2060: =-IFERROR(VLOOKUP(C2060,IDC!$A$20:$H$2401,8,0),0) -> -0.15 | M2060: =+D2060-I2060-J2060-K2060-L2060 -> 25 | P2060: =+L2060/0.006 -> -25 | Q2060: =+M2060+P2060 -> 0
A2061: 11-11-2025 | B2061: Débito por deuda Facturas vencidas de Mercado Libre | C2061: 2519098607 | D2061: -29410.77 | E2061: 9626477.8 | F2061: PAGO PROVEEDOR | G2061: =+D2061/1.006 -> -29235.358 | H2061: =+D2061-G2061 -> -175.41215 | I2061: =-IFERROR(VLOOKUP(C2061,SIRCUPA!$A$21:$H$313,8,0),0) -> 0 | J2061: =-IFERROR(VLOOKUP(C2061,SIRTAC!$A$16:$H$2072,8,0),0) -> 0 | K2061: =-IFERROR(VLOOKUP(C2061,Gastos!$A$9:$J$2065,10,0),0) -> 0 | L2061: =+D2061-G2061 -> -175.41215 | M2061: =+D2061-I2061-J2061-K2061-L2061 -> -29235.358 | P2061: =+L2061/0.006 -> -29235.358 | Q2061: =+M2061-P2061 -> -2.401066e-10
A2062: 03-11-2025 | B2062: Impuesto por extracción | C2062: 131722315545 | D2062: -9506.4 | E2062: 12776153 | F2062: IDC | G2062: =+D2062/0.006 -> -1584400 | I2062: =-IFERROR(VLOOKUP(C2062,SIRCUPA!$A$21:$H$313,8,0),0) -> 0 | J2062: =-IFERROR(VLOOKUP(C2062,SIRTAC!$A$16:$H$2072,8,0),0) -> 0 | K2062: =-IFERROR(VLOOKUP(C2062,Gastos!$A$9:$J$2065,10,0),0) -> 0 | L2062: 0 | M2062: =+D2062 -> -9506.4 | P2062: =+M2062 -> -9506.4 | Q2062: =+M2062-P2062 -> 0
A2063: 04-11-2025 | B2063: Impuesto por extracción | C2063: 131912838985 | D2063: -1005.98 | E2063: 10131799 | F2063: IDC | G2063: =+D2063/0.006 -> -167663.33 | I2063: =-IFERROR(VLOOKUP(C2063,SIRCUPA!$A$21:$H$313,8,0),0) -> 0 | J2063: =-IFERROR(VLOOKUP(C2063,SIRTAC!$A$16:$H$2072,8,0),0) -> 0 | K2063: =-IFERROR(VLOOKUP(C2063,Gastos!$A$9:$J$2065,10,0),0) -> 0 | L2063: 0 | M2063: =+D2063 -> -1005.98 | P2063: =+M2063 -> -1005.98 | Q2063: =+M2063-P2063 -> 0
A2064: 04-11-2025 | B2064: Impuesto por extracción | C2064: 132510905770 | D2064: -898.05 | E2064: 10419820 | F2064: IDC | G2064: =+D2064/0.006 -> -149675 | I2064: =-IFERROR(VLOOKUP(C2064,SIRCUPA!$A$21:$H$313,8,0),0) -> 0 | J2064: =-IFERROR(VLOOKUP(C2064,SIRTAC!$A$16:$H$2072,8,0),0) -> 0 | K2064: =-IFERROR(VLOOKUP(C2064,Gastos!$A$9:$J$2065,10,0),0) -> 0 | L2064: 0 | M2064: =+D2064 -> -898.05 | P2064: =+M2064 -> -898.05 | Q2064: =+M2064-P2064 -> 0
A2065: 04-11-2025 | B2065: Impuesto por extracción | C2065: 131913010493 | D2065: -711.83 | E2065: 10300469 | F2065: IDC | G2065: =+D2065/0.006 -> -118638.33 | I2065: =-IFERROR(VLOOKUP(C2065,SIRCUPA!$A$21:$H$313,8,0),0) -> 0 | J2065: =-IFERROR(VLOOKUP(C2065,SIRTAC!$A$16:$H$2072,8,0),0) -> 0 | K2065: =-IFERROR(VLOOKUP(C2065,Gastos!$A$9:$J$2065,10,0),0) -> 0 | L2065: 0 | M2065: =+D2065 -> -711.83 | P2065: =+M2065 -> -711.83 | Q2065: =+M2065-P2065 -> 0
A2066: 05-11-2025 | B2066: Impuesto por extracción | C2066: 131986740299 | D2066: -1915.17 | E2066: 9518395.9 | F2066: IDC | G2066: =+D2066/0.006 -> -319195 | I2066: =-IFERROR(VLOOKUP(C2066,SIRCUPA!$A$21:$H$313,8,0),0) -> 0 | J2066: =-IFERROR(VLOOKUP(C2066,SIRTAC!$A$16:$H$2072,8,0),0) -> 0 | K2066: =-IFERROR(VLOOKUP(C2066,Gastos!$A$9:$J$2065,10,0),0) -> 0 | L2066: 0 | M2066: =+D2066 -> -1915.17 | P2066: =+M2066 -> -1915.17 | Q2066: =+M2066-P2066 -> 0
A2067: 05-11-2025 | B2067: Impuesto por extracción | C2067: 132561759694 | D2067: -1200 | E2067: 9839505.9 | F2067: IDC | G2067: =+D2067/0.006 -> -200000 | I2067: =-IFERROR(VLOOKUP(C2067,SIRCUPA!$A$21:$H$313,8,0),0) -> 0 | J2067: =-IFERROR(VLOOKUP(C2067,SIRTAC!$A$16:$H$2072,8,0),0) -> 0 | K2067: =-IFERROR(VLOOKUP(C2067,Gastos!$A$9:$J$2065,10,0),0) -> 0 | L2067: 0 | M2067: =+D2067 -> -1200 | P2067: =+M2067 -> -1200 | Q2067: =+M2067-P2067 -> 0
A2068: 10-11-2025 | B2068: Impuesto por extracción | C2068: 132666970807 | D2068: -4200 | E2068: 14455889 | F2068: IDC | G2068: =+D2068/0.006 -> -700000 | I2068: =-IFERROR(VLOOKUP(C2068,SIRCUPA!$A$21:$H$313,8,0),0) -> 0 | J2068: =-IFERROR(VLOOKUP(C2068,SIRTAC!$A$16:$H$2072,8,0),0) -> 0 | K2068: =-IFERROR(VLOOKUP(C2068,Gastos!$A$9:$J$2065,10,0),0) -> 0 | L2068: 0 | M2068: =+D2068 -> -4200 | P2068: =+M2068 -> -4200 | Q2068: =+M2068-P2068 -> 0
A2069: 11-11-2025 | B2069: Impuesto por extracción | C2069: 133406145550 | D2069: -2423.59 | E2069: 9105207.1 | F2069: IDC | G2069: =+D2069/0.006 -> -403931.67 | I2069: =-IFERROR(VLOOKUP(C2069,SIRCUPA!$A$21:$H$313,8,0),0) -> 0 | J2069: =-IFERROR(VLOOKUP(C2069,SIRTAC!$A$16:$H$2072,8,0),0) -> 0 | K2069: =-IFERROR(VLOOKUP(C2069,Gastos!$A$9:$J$2065,10,0),0) -> 0 | L2069: 0 | M2069: =+D2069 -> -2423.59 | P2069: =+M2069 -> -2423.59 | Q2069: =+M2069-P2069 -> 0
A2070: 11-11-2025 | B2070: Impuesto por extracción | C2070: 133387595464 | D2070: -685.38 | E2070: 9511562.4 | F2070: IDC | G2070: =+D2070/0.006 -> -114230 | I2070: =-IFERROR(VLOOKUP(C2070,SIRCUPA!$A$21:$H$313,8,0),0) -> 0 | J2070: =-IFERROR(VLOOKUP(C2070,SIRTAC!$A$16:$H$2072,8,0),0) -> 0 | K2070: =-IFERROR(VLOOKUP(C2070,Gastos!$A$9:$J$2065,10,0),0) -> 0 | L2070: 0 | M2070: =+D2070 -> -685.38 | P2070: =+M2070 -> -685.38 | Q2070: =+M2070-P2070 -> 0
A2071: 13-11-2025 | B2071: Impuesto por extracción | C2071: 133079994485 | D2071: -1134.41 | E2071: 4035045.8 | F2071: IDC | G2071: =+D2071/0.006 -> -189068.33 | I2071: =-IFERROR(VLOOKUP(C2071,SIRCUPA!$A$21:$H$313,8,0),0) -> 0 | J2071: =-IFERROR(VLOOKUP(C2071,SIRTAC!$A$16:$H$2072,8,0),0) -> 0 | K2071: =-IFERROR(VLOOKUP(C2071,Gastos!$A$9:$J$2065,10,0),0) -> 0 | L2071: 0 | M2071: =+D2071 -> -1134.41 | P2071: =+M2071 -> -1134.41 | Q2071: =+M2071-P2071 -> 0
A2072: 17-11-2025 | B2072: Impuesto por extracción | C2072: 133569285791 | D2072: -3180 | E2072: 10481368 | F2072: IDC | G2072: =+D2072/0.006 -> -530000 | I2072: =-IFERROR(VLOOKUP(C2072,SIRCUPA!$A$21:$H$313,8,0),0) -> 0 | J2072: =-IFERROR(VLOOKUP(C2072,SIRTAC!$A$16:$H$2072,8,0),0) -> 0 | K2072: =-IFERROR(VLOOKUP(C2072,Gastos!$A$9:$J$2065,10,0),0) -> 0 | L2072: 0 | M2072: =+D2072 -> -3180 | P2072: =+M2072 -> -3180 | Q2072: =+M2072-P2072 -> 0
A2073: 20-11-2025 | B2073: Impuesto por extracción | C2073: 134606861452 | D2073: -7208.4 | E2073: 9506734.5 | F2073: IDC | G2073: =+D2073/0.006 -> -1201400 | I2073: =-IFERROR(VLOOKUP(C2073,SIRCUPA!$A$21:$H$313,8,0),0) -> 0 | J2073: =-IFERROR(VLOOKUP(C2073,SIRTAC!$A$16:$H$2072,8,0),0) -> 0 | K2073: =-IFERROR(VLOOKUP(C2073,Gastos!$A$9:$J$2065,10,0),0) -> 0 | L2073: 0 | M2073: =+D2073 -> -7208.4 | P2073: =+M2073 -> -7208.4 | Q2073: =+M2073-P2073 -> 0
... A2076: 25-11-2025 | B2076: Impuesto por extracción | C2076: 135211710106 | D2076: -4200 | E2076: 22908820 | F2076: IDC | G2076: =+D2076/0.006 -> -700000 | I2076: =-IFERROR(VLOOKUP(C2076,SIRCUPA!$A$21:$H$313,8,0),0) -> 0 | J2076: =-IFERROR(VLOOKUP(C2076,SIRTAC!$A$16:$H$2072,8,0),0) -> 0 | K2076: =-IFERROR(VLOOKUP(C2076,Gastos!$A$9:$J$2065,10,0),0) -> 0 | L2076: 0 | M2076: =+D2076 -> -4200 | P2076: =+M2076 -> -4200 | Q2076: =+M2076-P2076 -> 0
A2077: 05-11-2025 | B2077: Pago con QR Coca-Cola ANDINA | C2077: 131986740299 | D2077: -319194.82 | E2077: 9520311.1 | F2077: PAGO PROVEEDOR | G2077: =+D2077/1.006 -> -317291.07 | H2077: =+D2077-G2077 -> -1903.7464 | I2077: =-IFERROR(VLOOKUP(C2077,SIRCUPA!$A$21:$H$313,8,0),0) -> 0 | J2077: =-IFERROR(VLOOKUP(C2077,SIRTAC!$A$16:$H$2072,8,0),0) -> 0 | K2077: =-IFERROR(VLOOKUP(C2077,Gastos!$A$9:$J$2065,10,0),0) -> 0 | L2077: =-IFERROR(VLOOKUP(C2077,IDC!$A$20:$H$2401,8,0),0) -> -1915.17 | M2077: =+D2077 -> -319194.82 | P2077: =+L2077/0.006 -> -319195 | Q2077: =+M2077-P2077 -> 0.18
A2078: 21-11-2025 | B2078: Pago de servicio ARCA | C2078: 134706860324 | D2078: -527445.91 | E2078: 10346249 | F2078: ARCA | G2078: =+D2078/1.006 -> -524300.11 | H2078: =+D2078-G2078 -> -3145.8007 | I2078: =-IFERROR(VLOOKUP(C2078,SIRCUPA!$A$21:$H$313,8,0),0) -> 0 | J2078: =-IFERROR(VLOOKUP(C2078,SIRTAC!$A$16:$H$2072,8,0),0) -> 0 | K2078: =-IFERROR(VLOOKUP(C2078,Gastos!$A$9:$J$2065,10,0),0) -> 0 | L2078: =+D2078-G2078 -> -3145.8007 | M2078: =+D2078-I2078-J2078-K2078-L2078 -> -524300.11 | P2078: =+L2078/0.006 -> -524300.11 | Q2078: =+M2078-P2078 -> -3.3760443e-09
A2079: 09-11-2025 | B2079: Pago de servicios ARCA | C2079: 133118582858 | D2079: -2292484.7 | E2079: 14106256 | F2079: ARCA | G2079: =+D2079/1.006 -> -2278811.8 | H2079: =+D2079-G2079 -> -13672.871 | I2079: =-IFERROR(VLOOKUP(C2079,SIRCUPA!$A$21:$H$313,8,0),0) -> 0 | J2079: =-IFERROR(VLOOKUP(C2079,SIRTAC!$A$16:$H$2072,8,0),0) -> 0 | K2079: =-IFERROR(VLOOKUP(C2079,Gastos!$A$9:$J$2065,10,0),0) -> 0 | L2079: =+D2079-G2079 -> -13672.871 | M2079: =+D2079-I2079-J2079-K2079-L2079 -> -2278811.8 | P2079: =+L2079/0.006 -> -2278811.8 | Q2079: =+M2079-P2079 -> 2.3283064e-08
A2080: 14-11-2025 | B2080: Transferencia enviada | C2080: 133268925995 | D2080: -51064.57 | E2080: 6062510.5 | F2080: PAGO PROVEEDOR | G2080: =+D2080/1.006 -> -50760.01 | H2080: =+D2080-G2080 -> -304.56006 | I2080: =-IFERROR(VLOOKUP(C2080,SIRCUPA!$A$21:$H$313,8,0),0) -> 0 | J2080: =-IFERROR(VLOOKUP(C2080,SIRTAC!$A$16:$H$2072,8,0),0) -> 0 | K2080: =-IFERROR(VLOOKUP(C2080,Gastos!$A$9:$J$2065,10,0),0) -> 0 | L2080: =+D2080-G2080 -> -304.56006 | M2080: =+D2080-I2080-J2080-K2080-L2080 -> -50760.01 | O2080: BRODE | P2080: =+L2080/0.006 -> -50760.01 | Q2080: =+M2080-P2080 -> 4.8748916e-10
A2081: 20-11-2025 | B2081: Transferencia enviada ACERO JEKLO SAS | C2081: 134606861452 | D2081: -1201400 | E2081: 9513942.9 | F2081: PAGO PROVEEDOR | G2081: =+D2081/1.006 -> -1194234.6 | H2081: =+D2081-G2081 -> -7165.4076 | I2081: =-IFERROR(VLOOKUP(C2081,SIRCUPA!$A$21:$H$313,8,0),0) -> 0 | J2081: =-IFERROR(VLOOKUP(C2081,SIRTAC!$A$16:$H$2072,8,0),0) -> 0 | K2081: =-IFERROR(VLOOKUP(C2081,Gastos!$A$9:$J$2065,10,0),0) -> 0 | L2081: =-IFERROR(VLOOKUP(C2081,IDC!$A$20:$H$2401,8,0),0) -> -7208.4 | M2081: =+D2081 -> -1201400 | P2081: =+L2081/0.006 -> -1201400 | Q2081: =+M2081-P2081 -> 0
A2082: 20-11-2025 | B2082: Transferencia enviada BASSO REPRESENT SRL | C2082: 133989028043 | D2082: -410857.44 | E2082: 10717808 | F2082: PAGO PROVEEDOR | G2082: =+D2082/1.006 -> -408407 | H2082: =+D2082-G2082 -> -2450.442 | I2082: =-IFERROR(VLOOKUP(C2082,SIRCUPA!$A$21:$H$313,8,0),0) -> 0 | J2082: =-IFERROR(VLOOKUP(C2082,SIRTAC!$A$16:$H$2072,8,0),0) -> 0 | K2082: =-IFERROR(VLOOKUP(C2082,Gastos!$A$9:$J$2065,10,0),0) -> 0 | L2082: =-IFERROR(VLOOKUP(C2082,IDC!$A$20:$H$2401,8,0),0) -> -2465.14 | M2082: =+D2082 -> -410857.44 | P2082: =+L2082/0.006 -> -410856.67 | Q2082: =+M2082-P2082 -> -0.77333333
A2083: 11-11-2025 | B2083: Transferencia enviada Cerveza Tractor | C2083: 132839727403 | D2083: -601588 | E2083: 8503619.1 | F2083: RETIRO / PROV | G2083: =+D2083/1.006 -> -598000 | H2083: =+D2083-G2083 -> -3588 | I2083: =-IFERROR(VLOOKUP(C2083,SIRCUPA!$A$21:$H$313,8,0),0) -> 0 | J2083: =-IFERROR(VLOOKUP(C2083,SIRTAC!$A$16:$H$2072,8,0),0) -> 0 | K2083: =-IFERROR(VLOOKUP(C2083,Gastos!$A$9:$J$2065,10,0),0) -> 0 | L2083: =+D2083-G2083 -> -3588 | M2083: =+D2083-I2083-J2083-K2083-L2083 -> -598000 | P2083: =+L2083/0.006 -> -598000 | Q2083: =+M2083-P2083 -> 0
A2084: 01-11-2025 | B2084: Transferencia enviada Cerveza Tractor | C2084: 131557787521 | D2084: -116696 | E2084: 11449997 | F2084: RETIRO / PROV | G2084: =+D2084/1.006 -> -116000 | H2084: =+D2084-G2084 -> -696 | I2084: =-IFERROR(VLOOKUP(C2084,SIRCUPA!$A$21:$H$313,8,0),0) -> 0 | J2084: =-IFERROR(VLOOKUP(C2084,SIRTAC!$A$16:$H$2072,8,0),0) -> 0 | K2084: =-IFERROR(VLOOKUP(C2084,Gastos!$A$9:$J$2065,10,0),0) -> 0 | L2084: =+D2084-G2084 -> -696 | M2084: =+D2084-I2084-J2084-K2084-L2084 -> -116000 | P2084: =+L2084/0.006 -> -116000 | Q2084: =+M2084-P2084 -> 0
A2085: 26-11-2025 | B2085: Transferencia enviada Cerveza Tractor Sr | C2085: 134694715899 | D2085: -2000000 | E2085: 16908820 | F2085: RETIRO / PROV | G2085: =+D2085/1.006 -> -1988071.6 | H2085: =+D2085-G2085 -> -11928.429 | I2085: =-IFERROR(VLOOKUP(C2085,SIRCUPA!$A$21:$H$313,8,0),0) -> 0 | J2085: =-IFERROR(VLOOKUP(C2085,SIRTAC!$A$16:$H$2072,8,0),0) -> 0 | K2085: =-IFERROR(VLOOKUP(C2085,Gastos!$A$9:$J$2065,10,0),0) -> 0 | L2085: 0 | M2085: =+D2085 -> -2000000 | P2085: =+M2085 -> -2000000 | Q2085: =+M2085-P2085 -> 0
A2086: 26-11-2025 | B2086: Transferencia enviada Cerveza Tractor Sr | C2086: 134694879611 | D2086: -2000000 | E2086: 18908820 | F2086: RETIRO / PROV | G2086: =+D2086/1.006 -> -1988071.6 | H2086: =+D2086-G2086 -> -11928.429 | I2086: =-IFERROR(VLOOKUP(C2086,SIRCUPA!$A$21:$H$313,8,0),0) -> 0 | J2086: =-IFERROR(VLOOKUP(C2086,SIRTAC!$A$16:$H$2072,8,0),0) -> 0 | K2086: =-IFERROR(VLOOKUP(C2086,Gastos!$A$9:$J$2065,10,0),0) -> 0 | L2086: 0 | M2086: =+D2086 -> -2000000 | P2086: =+M2086 -> -2000000 | Q2086: =+M2086-P2086 -> 0
A2087: 26-11-2025 | B2087: Transferencia enviada Cerveza Tractor Sr | C2087: 134695209423 | D2087: -2000000 | E2087: 14908820 | F2087: RETIRO / PROV | G2087: =+D2087/1.006 -> -1988071.6 | H2087: =+D2087-G2087 -> -11928.429 | I2087: =-IFERROR(VLOOKUP(C2087,SIRCUPA!$A$21:$H$313,8,0),0) -> 0 | J2087: =-IFERROR(VLOOKUP(C2087,SIRTAC!$A$16:$H$2072,8,0),0) -> 0 | K2087: =-IFERROR(VLOOKUP(C2087,Gastos!$A$9:$J$2065,10,0),0) -> 0 | L2087: 0 | M2087: =+D2087 -> -2000000 | P2087: =+M2087 -> -2000000 | Q2087: =+M2087-P2087 -> 0
A2088: 26-11-2025 | B2088: Transferencia enviada Cerveza Tractor Sr | C2088: 135310990284 | D2088: -2000000 | E2088: 20908820 | F2088: RETIRO / PROV | G2088: =+D2088/1.006 -> -1988071.6 | H2088: =+D2088-G2088 -> -11928.429 | I2088: =-IFERROR(VLOOKUP(C2088,SIRCUPA!$A$21:$H$313,8,0),0) -> 0 | J2088: =-IFERROR(VLOOKUP(C2088,SIRTAC!$A$16:$H$2072,8,0),0) -> 0 | K2088: =-IFERROR(VLOOKUP(C2088,Gastos!$A$9:$J$2065,10,0),0) -> 0 | L2088: 0 | M2088: =+D2088 -> -2000000 | P2088: =+M2088 -> -2000000 | Q2088: =+M2088-P2088 -> 0
A2089: 12-11-2025 | B2089: Transferencia enviada Cerveza Tractor Sr | C2089: 132923079891 | D2089: -1000000 | E2089: 4503619.1 | F2089: RETIRO / PROV | G2089: =+D2089/1.006 -> -994035.79 | H2089: =+D2089-G2089 -> -5964.2147 | I2089: =-IFERROR(VLOOKUP(C2089,SIRCUPA!$A$21:$H$313,8,0),0) -> 0 | J2089: =-IFERROR(VLOOKUP(C2089,SIRTAC!$A$16:$H$2072,8,0),0) -> 0 | K2089: =-IFERROR(VLOOKUP(C2089,Gastos!$A$9:$J$2065,10,0),0) -> 0 | L2089: 0 | M2089: =+D2089 -> -1000000 | P2089: =+M2089 -> -1000000 | Q2089: =+M2089-P2089 -> 0
A2090: 12-11-2025 | B2090: Transferencia enviada Cerveza Tractor Sr | C2090: 133530189326 | D2090: -1000000 | E2090: 7503619.1 | F2090: RETIRO / PROV | G2090: =+D2090/1.006 -> -994035.79 | H2090: =+D2090-G2090 -> -5964.2147 | I2090: =-IFERROR(VLOOKUP(C2090,SIRCUPA!$A$21:$H$313,8,0),0) -> 0 | J2090: =-IFERROR(VLOOKUP(C2090,SIRTAC!$A$16:$H$2072,8,0),0) -> 0 | K2090: =-IFERROR(VLOOKUP(C2090,Gastos!$A$9:$J$2065,10,0),0) -> 0 | L2090: 0 | M2090: =+D2090 -> -1000000 | P2090: =+M2090 -> -1000000 | Q2090: =+M2090-P2090 -> 0
A2091: 12-11-2025 | B2091: Transferencia enviada Cerveza Tractor Sr | C2091: 133530443268 | D2091: -1000000 | E2091: 5503619.1 | F2091: RETIRO / PROV | G2091: =+D2091/1.006 -> -994035.79 | H2091: =+D2091-G2091 -> -5964.2147 | I2091: =-IFERROR(VLOOKUP(C2091,SIRCUPA!$A$21:$H$313,8,0),0) -> 0 | J2091: =-IFERROR(VLOOKUP(C2091,SIRTAC!$A$16:$H$2072,8,0),0) -> 0 | K2091: =-IFERROR(VLOOKUP(C2091,Gastos!$A$9:$J$2065,10,0),0) -> 0 | L2091: 0 | M2091: =+D2091 -> -1000000 | P2091: =+M2091 -> -1000000 | Q2091: =+M2091-P2091 -> 0
A2092: 12-11-2025 | B2092: Transferencia enviada Cerveza Tractor Sr | C2092: 133530692746 | D2092: -1000000 | E2092: 6503619.1 | F2092: RETIRO / PROV | G2092: =+D2092/1.006 -> -994035.79 | H2092: =+D2092-G2092 -> -5964.2147 | I2092: =-IFERROR(VLOOKUP(C2092,SIRCUPA!$A$21:$H$313,8,0),0) -> 0 | J2092: =-IFERROR(VLOOKUP(C2092,SIRTAC!$A$16:$H$2072,8,0),0) -> 0 | K2092: =-IFERROR(VLOOKUP(C2092,Gastos!$A$9:$J$2065,10,0),0) -> 0 | L2092: 0 | M2092: =+D2092 -> -1000000 | P2092: =+M2092 -> -1000000 | Q2092: =+M2092-P2092 -> 0
A2093: 12-11-2025 | B2093: Transferencia enviada Cerveza Tractor Sr | C2093: 133530828872 | D2093: -1000000 | E2093: 3503619.1 | F2093: RETIRO / PROV | G2093: =+D2093/1.006 -> -994035.79 | H2093: =+D2093-G2093 -> -5964.2147 | I2093: =-IFERROR(VLOOKUP(C2093,SIRCUPA!$A$21:$H$313,8,0),0) -> 0 | J2093: =-IFERROR(VLOOKUP(C2093,SIRTAC!$A$16:$H$2072,8,0),0) -> 0 | K2093: =-IFERROR(VLOOKUP(C2093,Gastos!$A$9:$J$2065,10,0),0) -> 0 | L2093: 0 | M2093: =+D2093 -> -1000000 | P2093: =+M2093 -> -1000000 | Q2093: =+M2093-P2093 -> 0
A2094: 10-11-2025 | B2094: Transferencia enviada Cerveza Tractor Sr | C2094: 132669869775 | D2094: -500000 | E2094: 13955889 | F2094: RETIRO / PROV | G2094: =+D2094/1.006 -> -497017.89 | H2094: =+D2094-G2094 -> -2982.1074 | I2094: =-IFERROR(VLOOKUP(C2094,SIRCUPA!$A$21:$H$313,8,0),0) -> 0 | J2094: =-IFERROR(VLOOKUP(C2094,SIRTAC!$A$16:$H$2072,8,0),0) -> 0 | K2094: =-IFERROR(VLOOKUP(C2094,Gastos!$A$9:$J$2065,10,0),0) -> 0 | L2094: 0 | M2094: =+D2094 -> -500000 | P2094: =+M2094 -> -500000 | Q2094: =+M2094-P2094 -> 0
A2095: 10-11-2025 | B2095: Transferencia enviada Cerveza Tractor Sr | C2095: 132670255889 | D2095: -500000 | E2095: 12955889 | F2095: RETIRO / PROV | G2095: =+D2095/1.006 -> -497017.89 | H2095: =+D2095-G2095 -> -2982.1074 | I2095: =-IFERROR(VLOOKUP(C2095,SIRCUPA!$A$21:$H$313,8,0),0) -> 0 | J2095: =-IFERROR(VLOOKUP(C2095,SIRTAC!$A$16:$H$2072,8,0),0) -> 0 | K2095: =-IFERROR(VLOOKUP(C2095,Gastos!$A$9:$J$2065,10,0),0) -> 0 | L2095: 0 | M2095: =+D2095 -> -500000 | P2095: =+M2095 -> -500000 | Q2095: =+M2095-P2095 -> 0
A2096: 10-11-2025 | B2096: Transferencia enviada Cerveza Tractor Sr | C2096: 132671312323 | D2096: -500000 | E2096: 13455889 | F2096: RETIRO / PROV | G2096: =+D2096/1.006 -> -497017.89 | H2096: =+D2096-G2096 -> -2982.1074 | I2096: =-IFERROR(VLOOKUP(C2096,SIRCUPA!$A$21:$H$313,8,0),0) -> 0 | J2096: =-IFERROR(VLOOKUP(C2096,SIRTAC!$A$16:$H$2072,8,0),0) -> 0 | K2096: =-IFERROR(VLOOKUP(C2096,Gastos!$A$9:$J$2065,10,0),0) -> 0 | L2096: 0 | M2096: =+D2096 -> -500000 | P2096: =+M2096 -> -500000 | Q2096: =+M2096-P2096 -> 0
... A2104: 26-11-2025 | B2104: Transferencia enviada Cerveza Tractor Sr | C2104: 135311484214 | D2104: -200000 | E2104: 14708820 | F2104: RETIRO / PROV | G2104: =+D2104/1.006 -> -198807.16 | H2104: =+D2104-G2104 -> -1192.8429 | I2104: =-IFERROR(VLOOKUP(C2104,SIRCUPA!$A$21:$H$313,8,0),0) -> 0 | J2104: =-IFERROR(VLOOKUP(C2104,SIRTAC!$A$16:$H$2072,8,0),0) -> 0 | K2104: =-IFERROR(VLOOKUP(C2104,Gastos!$A$9:$J$2065,10,0),0) -> 0 | L2104: 0 | M2104: =+D2104 -> -200000 | P2104: =+M2104 -> -200000 | Q2104: =+M2104-P2104 -> 0
A2105: 11-11-2025 | B2105: Transferencia enviada DE BRABAND AGUSTIN | C2105: 133406145550 | D2105: -403931.69 | E2105: 9107630.7 | F2105: PAGO PROVEEDOR | G2105: =+D2105/1.006 -> -401522.55 | H2105: =+D2105-G2105 -> -2409.1353 | I2105: =-IFERROR(VLOOKUP(C2105,SIRCUPA!$A$21:$H$313,8,0),0) -> 0 | J2105: =-IFERROR(VLOOKUP(C2105,SIRTAC!$A$16:$H$2072,8,0),0) -> 0 | K2105: =-IFERROR(VLOOKUP(C2105,Gastos!$A$9:$J$2065,10,0),0) -> 0 | L2105: =-IFERROR(VLOOKUP(C2105,IDC!$A$20:$H$2401,8,0),0) -> -2423.59 | M2105: =+D2105 -> -403931.69 | P2105: =+L2105/0.006 -> -403931.67 | Q2105: =+M2105-P2105 -> -0.023333333
A2106: 27-11-2025 | B2106: Transferencia enviada DOÑA DORA | C2106: 134830828981 | D2106: -209761.06 | E2106: 15182156 | F2106: PAGO PROVEEDOR | G2106: =+D2106/1.006 -> -208510 | H2106: =+D2106-G2106 -> -1251.06 | I2106: =-IFERROR(VLOOKUP(C2106,SIRCUPA!$A$21:$H$313,8,0),0) -> 0 | J2106: =-IFERROR(VLOOKUP(C2106,SIRTAC!$A$16:$H$2072,8,0),0) -> 0 | K2106: =-IFERROR(VLOOKUP(C2106,Gastos!$A$9:$J$2065,10,0),0) -> 0 | L2106: =+D2106-G2106 -> -1251.06 | M2106: =+D2106-I2106-J2106-K2106-L2106 -> -208510 | P2106: =+L2106/0.006 -> -208510 | Q2106: =+M2106-P2106 -> -3.783498e-10
A2107: 10-11-2025 | B2107: Transferencia enviada EMBOTELLADORA DEL ATLANTICO S.A. | C2107: 132666970807 | D2107: -700000 | E2107: 14460089 | F2107: PAGO PROVEEDOR | G2107: =+D2107/1.006 -> -695825.05 | H2107: =+D2107-G2107 -> -4174.9503 | I2107: =-IFERROR(VLOOKUP(C2107,SIRCUPA!$A$21:$H$313,8,0),0) -> 0 | J2107: =-IFERROR(VLOOKUP(C2107,SIRTAC!$A$16:$H$2072,8,0),0) -> 0 | K2107: =-IFERROR(VLOOKUP(C2107,Gastos!$A$9:$J$2065,10,0),0) -> 0 | L2107: =-IFERROR(VLOOKUP(C2107,IDC!$A$20:$H$2401,8,0),0) -> -4200 | M2107: =+D2107 -> -700000 | P2107: =+L2107/0.006 -> -700000 | Q2107: =+M2107-P2107 -> 0
A2108: 25-11-2025 | B2108: Transferencia enviada EMBOTELLADORA DEL ATLANTICO S.A. | C2108: 135211710106 | D2108: -700000 | E2108: 22913020 | F2108: PAGO PROVEEDOR | G2108: =+D2108/1.006 -> -695825.05 | H2108: =+D2108-G2108 -> -4174.9503 | I2108: =-IFERROR(VLOOKUP(C2108,SIRCUPA!$A$21:$H$313,8,0),0) -> 0 | J2108: =-IFERROR(VLOOKUP(C2108,SIRTAC!$A$16:$H$2072,8,0),0) -> 0 | K2108: =-IFERROR(VLOOKUP(C2108,Gastos!$A$9:$J$2065,10,0),0) -> 0 | L2108: =-IFERROR(VLOOKUP(C2108,IDC!$A$20:$H$2401,8,0),0) -> -4200 | M2108: =+D2108 -> -700000 | P2108: =+L2108/0.006 -> -700000 | Q2108: =+M2108-P2108 -> 0
A2109: 17-11-2025 | B2109: Transferencia enviada EMBOTELLADORA DEL ATLANTICO S.A. | C2109: 133569285791 | D2109: -530000 | E2109: 10484548 | F2109: PAGO PROVEEDOR | G2109: =+D2109/1.006 -> -526838.97 | H2109: =+D2109-G2109 -> -3161.0338 | I2109: =-IFERROR(VLOOKUP(C2109,SIRCUPA!$A$21:$H$313,8,0),0) -> 0 | J2109: =-IFERROR(VLOOKUP(C2109,SIRTAC!$A$16:$H$2072,8,0),0) -> 0 | K2109: =-IFERROR(VLOOKUP(C2109,Gastos!$A$9:$J$2065,10,0),0) -> 0 | L2109: =-IFERROR(VLOOKUP(C2109,IDC!$A$20:$H$2401,8,0),0) -> -3180 | M2109: =+D2109 -> -530000 | P2109: =+L2109/0.006 -> -530000 | Q2109: =+M2109-P2109 -> 0
A2110: 05-11-2025 | B2110: Transferencia enviada EMBOTELLADORA DEL ATLANTICO SA | C2110: 132561759694 | D2110: -200000 | E2110: 9840705.9 | F2110: PAGO PROVEEDOR | G2110: =+D2110/1.006 -> -198807.16 | H2110: =+D2110-G2110 -> -1192.8429 | I2110: =-IFERROR(VLOOKUP(C2110,SIRCUPA!$A$21:$H$313,8,0),0) -> 0 | J2110: =-IFERROR(VLOOKUP(C2110,SIRTAC!$A$16:$H$2072,8,0),0) -> 0 | K2110: =-IFERROR(VLOOKUP(C2110,Gastos!$A$9:$J$2065,10,0),0) -> 0 | L2110: =-IFERROR(VLOOKUP(C2110,IDC!$A$20:$H$2401,8,0),0) -> -1200 | M2110: =+D2110 -> -200000 | O2110: NO COBRO IDC | P2110: =+L2110/0.006 -> -200000 | Q2110: =+M2110-P2110 -> 0
A2111: 04-11-2025 | B2111: Transferencia enviada ERPEN JULIO C. Y PONZONI ANTONELLA P. SOCIEDAD SIMPLE | C2111: 131909998387 | D2111: -1328704.7 | E2111: 10570392 | F2111: PAGO PROVEEDOR | G2111: =+D2111/1.006 -> -1320780 | H2111: =+D2111-G2111 -> -7924.68 | I2111: =-IFERROR(VLOOKUP(C2111,SIRCUPA!$A$21:$H$313,8,0),0) -> 0 | J2111: =-IFERROR(VLOOKUP(C2111,SIRTAC!$A$16:$H$2072,8,0),0) -> 0 | K2111: =-IFERROR(VLOOKUP(C2111,Gastos!$A$9:$J$2065,10,0),0) -> 0 | L2111: =+D2111-G2111 -> -7924.68 | M2111: =+D2111-I2111-J2111-K2111-L2111 -> -1320780 | P2111: =+L2111/0.006 -> -1320780 | Q2111: =+M2111-P2111 -> -1.094304e-08
A2112: 04-11-2025 | B2112: Transferencia enviada FRUVECO S R L | C2112: 131912838985 | D2112: -167664.01 | E2112: 10132805 | F2112: PAGO PROVEEDOR | G2112: =+D2112/1.006 -> -166664.03 | H2112: =+D2112-G2112 -> -999.98416 | I2112: =-IFERROR(VLOOKUP(C2112,SIRCUPA!$A$21:$H$313,8,0),0) -> 0 | J2112: =-IFERROR(VLOOKUP(C2112,SIRTAC!$A$16:$H$2072,8,0),0) -> 0 | K2112: =-IFERROR(VLOOKUP(C2112,Gastos!$A$9:$J$2065,10,0),0) -> 0 | L2112: =-IFERROR(VLOOKUP(C2112,IDC!$A$20:$H$2401,8,0),0) -> -1005.98 | M2112: =+D2112 -> -167664.01 | P2112: =+L2112/0.006 -> -167663.33 | Q2112: =+M2112-P2112 -> -0.67666667
A2113: 22-11-2025 | B2113: Transferencia recibida GUILLERMO NICOLAS MARTINEZ | C2113: 134317722679 | D2113: 19580 | E2113: 15430216 | F2113: COBRO | I2113: =-IFERROR(VLOOKUP(C2113,SIRCUPA!$A$21:$H$313,8,0),0) -> -300 | J2113: =-IFERROR(VLOOKUP(C2113,SIRTAC!$A$16:$H$2072,8,0),0) -> 0 | K2113: =-IFERROR(VLOOKUP(C2113,Gastos!$A$9:$J$2065,10,0),0) -> 0 | L2113: =-IFERROR(VLOOKUP(C2113,IDC!$A$20:$H$2401,8,0),0) -> -120 | M2113: =+D2113-I2113-J2113-K2113-L2113 -> 20000 | P2113: =+L2113/0.006 -> -20000 | Q2113: =+M2113+P2113 -> 0
A2114: 23-11-2025 | B2114: Transferencia recibida Jorge Daniel Cardozo | C2114: 134935322648 | D2114: 19580 | E2114: 16678628 | F2114: COBRO | I2114: =-IFERROR(VLOOKUP(C2114,SIRCUPA!$A$21:$H$313,8,0),0) -> -300 | J2114: =-IFERROR(VLOOKUP(C2114,SIRTAC!$A$16:$H$2072,8,0),0) -> 0 | K2114: =-IFERROR(VLOOKUP(C2114,Gastos!$A$9:$J$2065,10,0),0) -> 0 | L2114: -120 | M2114: =+D2114-I2114-J2114-K2114-L2114 -> 20000 | P2114: =+L2114/0.006 -> -20000 | Q2114: =+M2114+P2114 -> 0
A2115: 23-11-2025 | B2115: Transferencia recibida Raul Ricardo Mazzarello | C2115: 134941676542 | D2115: 19580 | E2115: 19235850 | F2115: COBRO | I2115: =-IFERROR(VLOOKUP(C2115,SIRCUPA!$A$21:$H$313,8,0),0) -> -300 | J2115: =-IFERROR(VLOOKUP(C2115,SIRTAC!$A$16:$H$2072,8,0),0) -> 0 | K2115: =-IFERROR(VLOOKUP(C2115,Gastos!$A$9:$J$2065,10,0),0) -> 0 | L2115: -120 | M2115: =+D2115-I2115-J2115-K2115-L2115 -> 20000 | P2115: =+L2115/0.006 -> -20000 | Q2115: =+M2115+P2115 -> 0
A2116: 22-11-2025 | B2116: Transferencia recibida priscila edith rodriguez | C2116: 134311953811 | D2116: 17622 | E2116: 13930116 | F2116: COBRO | I2116: =-IFERROR(VLOOKUP(C2116,SIRCUPA!$A$21:$H$313,8,0),0) -> -270 | J2116: =-IFERROR(VLOOKUP(C2116,SIRTAC!$A$16:$H$2072,8,0),0) -> 0 | K2116: =-IFERROR(VLOOKUP(C2116,Gastos!$A$9:$J$2065,10,0),0) -> 0 | L2116: =-IFERROR(VLOOKUP(C2116,IDC!$A$20:$H$2401,8,0),0) -> -108 | M2116: =+D2116-I2116-J2116-K2116-L2116 -> 18000 | P2116: =+L2116/0.006 -> -18000 | Q2116: =+M2116+P2116 -> 0
A2117: 23-11-2025 | B2117: Transferencia recibida MARCELO JAVIER ESPINDOLA | C2117: 134322835299 | D2117: 17622 | E2117: 17325960 | F2117: COBRO | I2117: =-IFERROR(VLOOKUP(C2117,SIRCUPA!$A$21:$H$313,8,0),0) -> -270 | J2117: =-IFERROR(VLOOKUP(C2117,SIRTAC!$A$16:$H$2072,8,0),0) -> 0 | K2117: =-IFERROR(VLOOKUP(C2117,Gastos!$A$9:$J$2065,10,0),0) -> 0 | L2117: =-IFERROR(VLOOKUP(C2117,IDC!$A$20:$H$2401,8,0),0) -> -108 | M2117: =+D2117-I2117-J2117-K2117-L2117 -> 18000 | P2117: =+L2117/0.006 -> -18000 | Q2117: =+M2117+P2117 -> 0
A2118: 22-11-2025 | B2118: Transferencia recibida GUILLERMO NICOLAS MARTINEZ | C2118: 134314272897 | D2118: 16643 | E2118: 14314061 | F2118: COBRO | I2118: =-IFERROR(VLOOKUP(C2118,SIRCUPA!$A$21:$H$313,8,0),0) -> -255 | J2118: =-IFERROR(VLOOKUP(C2118,SIRTAC!$A$16:$H$2072,8,0),0) -> 0 | K2118: =-IFERROR(VLOOKUP(C2118,Gastos!$A$9:$J$2065,10,0),0) -> 0 | L2118: =-IFERROR(VLOOKUP(C2118,IDC!$A$20:$H$2401,8,0),0) -> -102 | M2118: =+D2118-I2118-J2118-K2118-L2118 -> 17000 | P2118: =+L2118/0.006 -> -17000 | Q2118: =+M2118+P2118 -> 0
A2119: 23-11-2025 | B2119: Transferencia recibida Enzo Gabriel Erpen | C2119: 134323791043 | D2119: 16643 | E2119: 17832635 | F2119: COBRO | I2119: =-IFERROR(VLOOKUP(C2119,SIRCUPA!$A$21:$H$313,8,0),0) -> -255 | J2119: =-IFERROR(VLOOKUP(C2119,SIRTAC!$A$16:$H$2072,8,0),0) -> 0 | K2119: =-IFERROR(VLOOKUP(C2119,Gastos!$A$9:$J$2065,10,0),0) -> 0 | L2119: -102 | M2119: =+D2119-I2119-J2119-K2119-L2119 -> 17000 | P2119: =+L2119/0.006 -> -17000 | Q2119: =+M2119+P2119 -> 0
A2120: 23-11-2025 | B2120: Transferencia recibida SEBASTIAN GUSTAVO CERUTTI | C2120: 134937124088 | D2120: 15664 | E2120: 17460387 | F2120: COBRO | I2120: =-IFERROR(VLOOKUP(C2120,SIRCUPA!$A$21:$H$313,8,0),0) -> -240 | J2120: =-IFERROR(VLOOKUP(C2120,SIRTAC!$A$16:$H$2072,8,0),0) -> 0 | K2120: =-IFERROR(VLOOKUP(C2120,Gastos!$A$9:$J$2065,10,0),0) -> 0 | L2120: =-IFERROR(VLOOKUP(C2120,IDC!$A$20:$H$2401,8,0),0) -> -96 | M2120: =+D2120-I2120-J2120-K2120-L2120 -> 16000 | P2120: =+L2120/0.006 -> -16000 | Q2120: =+M2120+P2120 -> 0
A2121: 23-11-2025 | B2121: Transferencia recibida Antonio Ezequiel Cardozo | C2121: 134936893944 | D2121: 14685 | E2121: 17361105 | F2121: COBRO | I2121: =-IFERROR(VLOOKUP(C2121,SIRCUPA!$A$21:$H$313,8,0),0) -> -225 | J2121: =-IFERROR(VLOOKUP(C2121,SIRTAC!$A$16:$H$2072,8,0),0) -> 0 | K2121: =-IFERROR(VLOOKUP(C2121,Gastos!$A$9:$J$2065,10,0),0) -> 0 | L2121: -90 | M2121: =+D2121-I2121-J2121-K2121-L2121 -> 15000 | P2121: =+L2121/0.006 -> -15000 | Q2121: =+M2121+P2121 -> 0
A2122: 23-11-2025 | B2122: Transferencia recibida Antonio Ezequiel Cardozo | C2122: 134324938349 | D2122: 14685 | E2122: 18190283 | F2122: COBRO | I2122: =-IFERROR(VLOOKUP(C2122,SIRCUPA!$A$21:$H$313,8,0),0) -> -225 | J2122: =-IFERROR(VLOOKUP(C2122,SIRTAC!$A$16:$H$2072,8,0),0) -> 0 | K2122: =-IFERROR(VLOOKUP(C2122,Gastos!$A$9:$J$2065,10,0),0) -> 0 | L2122: -90 | M2122: =+D2122-I2122-J2122-K2122-L2122 -> 15000 | P2122: =+L2122/0.006 -> -15000 | Q2122: =+M2122+P2122 -> 0
A2123: 23-11-2025 | B2123: Transferencia recibida Antonio Ezequiel Cardozo | C2123: 134327964395 | D2123: 14685 | E2123: 19497445 | F2123: COBRO | I2123: =-IFERROR(VLOOKUP(C2123,SIRCUPA!$A$21:$H$313,8,0),0) -> -225 | J2123: =-IFERROR(VLOOKUP(C2123,SIRTAC!$A$16:$H$2072,8,0),0) -> 0 | K2123: =-IFERROR(VLOOKUP(C2123,Gastos!$A$9:$J$2065,10,0),0) -> 0 | L2123: -90 | M2123: =+D2123-I2123-J2123-K2123-L2123 -> 15000 | P2123: =+L2123/0.006 -> -15000 | Q2123: =+M2123+P2123 -> 0
A2124: 23-11-2025 | B2124: Transferencia recibida Fabricio Miguel Funes | C2124: 134935423998 | D2124: 14685 | E2124: 16776324 | F2124: COBRO | I2124: =-IFERROR(VLOOKUP(C2124,SIRCUPA!$A$21:$H$313,8,0),0) -> -225 | J2124: =-IFERROR(VLOOKUP(C2124,SIRTAC!$A$16:$H$2072,8,0),0) -> 0 | K2124: =-IFERROR(VLOOKUP(C2124,Gastos!$A$9:$J$2065,10,0),0) -> 0 | L2124: -90 | M2124: =+D2124-I2124-J2124-K2124-L2124 -> 15000 | P2124: =+L2124/0.006 -> -15000 | Q2124: =+M2124+P2124 -> 0
A2125: 23-11-2025 | B2125: Transferencia recibida Fabricio Miguel Funes | C2125: 134325903917 | D2125: 14685 | E2125: 18602028 | F2125: COBRO | I2125: =-IFERROR(VLOOKUP(C2125,SIRCUPA!$A$21:$H$313,8,0),0) -> -225 | J2125: =-IFERROR(VLOOKUP(C2125,SIRTAC!$A$16:$H$2072,8,0),0) -> 0 | K2125: =-IFERROR(VLOOKUP(C2125,Gastos!$A$9:$J$2065,10,0),0) -> 0 | L2125: -90 | M2125: =+D2125-I2125-J2125-K2125-L2125 -> 15000 | P2125: =+L2125/0.006 -> -15000 | Q2125: =+M2125+P2125 -> 0
A2126: 23-11-2025 | B2126: Transferencia recibida Ivana Soledad Aranda | C2126: 134935789778 | D2126: 14685 | E2126: 16973438 | F2126: COBRO | I2126: =-IFERROR(VLOOKUP(C2126,SIRCUPA!$A$21:$H$313,8,0),0) -> -225 | J2126: =-IFERROR(VLOOKUP(C2126,SIRTAC!$A$16:$H$2072,8,0),0) -> 0 | K2126: =-IFERROR(VLOOKUP(C2126,Gastos!$A$9:$J$2065,10,0),0) -> 0 | L2126: -90 | M2126: =+D2126-I2126-J2126-K2126-L2126 -> 15000 | P2126: =+L2126/0.006 -> -15000 | Q2126: =+M2126+P2126 -> 0
A2127: 23-11-2025 | B2127: Transferencia recibida Nahuel Iván Herrera | C2127: 134328152407 | D2127: 14685 | E2127: 19528693 | F2127: COBRO | I2127: =-IFERROR(VLOOKUP(C2127,SIRCUPA!$A$21:$H$313,8,0),0) -> -225 | J2127: =-IFERROR(VLOOKUP(C2127,SIRTAC!$A$16:$H$2072,8,0),0) -> 0 | K2127: =-IFERROR(VLOOKUP(C2127,Gastos!$A$9:$J$2065,10,0),0) -> 0 | L2127: -90 | M2127: =+D2127-I2127-J2127-K2127-L2127 -> 15000 | P2127: =+L2127/0.006 -> -15000 | Q2127: =+M2127+P2127 -> 0
A2128: 24-11-2025 | B2128: Transferencia recibida Matias Abel Hildt | C2128: 135033364546 | D2128: 14685 | E2128: 23293270 | F2128: COBRO | I2128: =-IFERROR(VLOOKUP(C2128,SIRCUPA!$A$21:$H$313,8,0),0) -> -225 | J2128: =-IFERROR(VLOOKUP(C2128,SIRTAC!$A$16:$H$2072,8,0),0) -> 0 | K2128: =-IFERROR(VLOOKUP(C2128,Gastos!$A$9:$J$2065,10,0),0) -> 0 | L2128: -90 | M2128: =+D2128-I2128-J2128-K2128-L2128 -> 15000 | P2128: =+L2128/0.006 -> -15000 | Q2128: =+M2128+P2128 -> 0
A2129: 22-11-2025 | B2129: Transferencia recibida Andres Gimenez | C2129: 134933775770 | D2129: 11748 | E2129: 16173464 | F2129: COBRO | I2129: =-IFERROR(VLOOKUP(C2129,SIRCUPA!$A$21:$H$313,8,0),0) -> -180 | J2129: =-IFERROR(VLOOKUP(C2129,SIRTAC!$A$16:$H$2072,8,0),0) -> 0 | K2129: =-IFERROR(VLOOKUP(C2129,Gastos!$A$9:$J$2065,10,0),0) -> 0 | L2129: -72 | M2129: =+D2129-I2129-J2129-K2129-L2129 -> 12000 | P2129: =+L2129/0.006 -> -12000 | Q2129: =+M2129+P2129 -> 0
A2130: 23-11-2025 | B2130: Transferencia recibida PASTORINI SANDRO LEON | C2130: 134403331949 | D2130: 11748 | E2130: 19865437 | F2130: COBRO | I2130: =-IFERROR(VLOOKUP(C2130,SIRCUPA!$A$21:$H$313,8,0),0) -> -180 | J2130: =-IFERROR(VLOOKUP(C2130,SIRTAC!$A$16:$H$2072,8,0),0) -> 0 | K2130: =-IFERROR(VLOOKUP(C2130,Gastos!$A$9:$J$2065,10,0),0) -> 0 | L2130: =-IFERROR(VLOOKUP(C2130,IDC!$A$20:$H$2401,8,0),0) -> -72 | M2130: =+D2130-I2130-J2130-K2130-L2130 -> 12000 | P2130: =+L2130/0.006 -> -12000 | Q2130: =+M2130+P2130 -> 0
A2131: 23-11-2025 | B2131: Transferencia recibida Abril Ayelen Sotto | C2131: 134941305268 | D2131: 11748 | E2131: 19073162 | F2131: COBRO | I2131: =-IFERROR(VLOOKUP(C2131,SIRCUPA!$A$21:$H$313,8,0),0) -> -180 | J2131: =-IFERROR(VLOOKUP(C2131,SIRTAC!$A$16:$H$2072,8,0),0) -> 0 | K2131: =-IFERROR(VLOOKUP(C2131,Gastos!$A$9:$J$2065,10,0),0) -> 0 | L2131: -72 | M2131: =+D2131-I2131-J2131-K2131-L2131 -> 12000 | P2131: =+L2131/0.006 -> -12000 | Q2131: =+M2131+P2131 -> 0
A2132: 23-11-2025 | B2132: Transferencia recibida FIGUEREDO, SERGIO ANDRES | C2132: 134403088539 | D2132: 10769 | E2132: 19831909 | F2132: COBRO | I2132: =-IFERROR(VLOOKUP(C2132,SIRCUPA!$A$21:$H$313,8,0),0) -> -165 | J2132: =-IFERROR(VLOOKUP(C2132,SIRTAC!$A$16:$H$2072,8,0),0) -> 0 | K2132: =-IFERROR(VLOOKUP(C2132,Gastos!$A$9:$J$2065,10,0),0) -> 0 | L2132: =-IFERROR(VLOOKUP(C2132,IDC!$A$20:$H$2401,8,0),0) -> -66 | M2132: =+D2132-I2132-J2132-K2132-L2132 -> 11000 | P2132: =+L2132/0.006 -> -11000 | Q2132: =+M2132+P2132 -> 0
A2133: 23-11-2025 | B2133: Transferencia recibida FIGUEREDO, SERGIO ANDRES | C2133: 135017256534 | D2133: 10769 | E2133: 19842678 | F2133: COBRO | I2133: =-IFERROR(VLOOKUP(C2133,SIRCUPA!$A$21:$H$313,8,0),0) -> -165 | J2133: =-IFERROR(VLOOKUP(C2133,SIRTAC!$A$16:$H$2072,8,0),0) -> 0 | K2133: =-IFERROR(VLOOKUP(C2133,Gastos!$A$9:$J$2065,10,0),0) -> 0 | L2133: =-IFERROR(VLOOKUP(C2133,IDC!$A$20:$H$2401,8,0),0) -> -66 | M2133: =+D2133-I2133-J2133-K2133-L2133 -> 11000 | P2133: =+L2133/0.006 -> -11000 | Q2133: =+M2133+P2133 -> 0
A2134: 23-11-2025 | B2134: Transferencia recibida Maria Luz Lezcano | C2134: 134324210723 | D2134: 10769 | E2134: 18008540 | F2134: COBRO | I2134: =-IFERROR(VLOOKUP(C2134,SIRCUPA!$A$21:$H$313,8,0),0) -> -165 | J2134: =-IFERROR(VLOOKUP(C2134,SIRTAC!$A$16:$H$2072,8,0),0) -> 0 | K2134: =-IFERROR(VLOOKUP(C2134,Gastos!$A$9:$J$2065,10,0),0) -> 0 | L2134: -66 | M2134: =+D2134-I2134-J2134-K2134-L2134 -> 11000 | P2134: =+L2134/0.006 -> -11000 | Q2134: =+M2134+P2134 -> 0
A2135: 15-11-2025 | B2135: Transferencia recibida Maria Isabel Agnese Fender | C2135: 133313747919 | D2135: 10651.52 | E2135: 6591964.9 | F2135: COBRO | I2135: =-IFERROR(VLOOKUP(C2135,SIRCUPA!$A$21:$H$313,8,0),0) -> -163.2 | J2135: =-IFERROR(VLOOKUP(C2135,SIRTAC!$A$16:$H$2072,8,0),0) -> 0 | K2135: =-IFERROR(VLOOKUP(C2135,Gastos!$A$9:$J$2065,10,0),0) -> 0 | L2135: =-IFERROR(VLOOKUP(C2135,IDC!$A$20:$H$2401,8,0),0) -> -65.28 | M2135: =+D2135-I2135-J2135-K2135-L2135 -> 10880 | P2135: =+L2135/0.006 -> -10880 | Q2135: =+M2135+P2135 -> 0
A2136: 07-11-2025 | B2136: Transferencia recibida Ana Victoria Destri | C2136: 132230456657 | D2136: 9790 | E2136: 12055427 | F2136: COBRO | I2136: =-IFERROR(VLOOKUP(C2136,SIRCUPA!$A$21:$H$313,8,0),0) -> -150 | J2136: =-IFERROR(VLOOKUP(C2136,SIRTAC!$A$16:$H$2072,8,0),0) -> 0 | K2136: =-IFERROR(VLOOKUP(C2136,Gastos!$A$9:$J$2065,10,0),0) -> 0 | L2136: =-IFERROR(VLOOKUP(C2136,IDC!$A$20:$H$2401,8,0),0) -> -60 | M2136: =+D2136-I2136-J2136-K2136-L2136 -> 10000 | P2136: =+L2136/0.006 -> -10000 | Q2136: =+M2136+P2136 -> 0
A2137: 22-11-2025 | B2137: Transferencia recibida Estefania Jeanette Benitez | C2137: 134934090998 | D2137: 9790 | E2137: 16199817 | F2137: COBRO | I2137: =-IFERROR(VLOOKUP(C2137,SIRCUPA!$A$21:$H$313,8,0),0) -> -150 | J2137: =-IFERROR(VLOOKUP(C2137,SIRTAC!$A$16:$H$2072,8,0),0) -> 0 | K2137: =-IFERROR(VLOOKUP(C2137,Gastos!$A$9:$J$2065,10,0),0) -> 0 | L2137: -60 | M2137: =+D2137-I2137-J2137-K2137-L2137 -> 10000 | P2137: =+L2137/0.006 -> -10000 | Q2137: =+M2137+P2137 -> 0
A2138: 22-11-2025 | B2138: Transferencia recibida Milagros Busson | C2138: 134930774018 | D2138: 9790 | E2138: 15192732 | F2138: COBRO | I2138: =-IFERROR(VLOOKUP(C2138,SIRCUPA!$A$21:$H$313,8,0),0) -> -150 | J2138: =-IFERROR(VLOOKUP(C2138,SIRTAC!$A$16:$H$2072,8,0),0) -> 0 | K2138: =-IFERROR(VLOOKUP(C2138,Gastos!$A$9:$J$2065,10,0),0) -> 0 | L2138: -60 | M2138: =+D2138-I2138-J2138-K2138-L2138 -> 10000 | P2138: =+L2138/0.006 -> -10000 | Q2138: =+M2138+P2138 -> 0
A2139: 23-11-2025 | B2139: Transferencia recibida AREGUATI LUCAS GABRIEL | C2139: 134937433044 | D2139: 9790 | E2139: 17536038 | F2139: COBRO | I2139: =-IFERROR(VLOOKUP(C2139,SIRCUPA!$A$21:$H$313,8,0),0) -> -150 | J2139: =-IFERROR(VLOOKUP(C2139,SIRTAC!$A$16:$H$2072,8,0),0) -> 0 | K2139: =-IFERROR(VLOOKUP(C2139,Gastos!$A$9:$J$2065,10,0),0) -> 0 | L2139: =-IFERROR(VLOOKUP(C2139,IDC!$A$20:$H$2401,8,0),0) -> -60 | M2139: =+D2139-I2139-J2139-K2139-L2139 -> 10000 | P2139: =+L2139/0.006 -> -10000 | Q2139: =+M2139+P2139 -> 0
...

Sheet TR
A3: Suma de MOV TOTAL | B3: Etiquetas de columna
A4: Etiquetas de fila | B4: ARCA | C4: COBRO | D4: IDC | E4: PAGO PROVEEDOR | F4: RETIRO / PROV | G4: Total general
A5: Débito por deuda Facturas vencidas de Mercado Libre | E5: -29235.358 | G5: -29235.358
A6: Impuesto por extracción | D6: -43959.35 | G6: -43959.35
A7: Liquidación de dinero | C7: 42491613 | G7: 42491613 | I7: ASIENTO 97 B | J7: COBRO DS X VENTA | K7: =SUM(G7:G8,G31:G281) -> 43614188 | L7: modificado
A8: Liquidación de dinero cancelada Venta cancelada | C8: -7900 | G8: -7900 | I8: ASIENTO 98 B | J8: PAGO PROVEEDORES | K8: =SUM(G9,G12:G14,G15,G17:G24,G26:G29) -> -10468755 | L8: modificado
A9: Pago con QR Coca-Cola ANDINA | E9: -319194.82 | G9: -319194.82 | H9: C | J9: VER SI HAY COMPRA
A10: Pago de servicio ARCA | B10: -524300.11 | G10: -524300.11 | H10: C | J10: IMPUESTOS | K10: =SUM(G10:G11) -> -2803111.9 | L10: modificado
A11: Pago de servicios ARCA | B11: -2278811.8 | G11: -2278811.8 | H11: C | J11: VER QUE ES
A12: Transferencia enviada | E12: -50760.01 | G12: -50760.01 | H12: C | J12: CERVEZA TRACTOR
A13: Transferencia enviada ACERO JEKLO SAS | E13: -1201400 | G13: -1201400 | H13: C | I13: ASIENTO 99 B | J13: CAJA | K13: =SUM(G25,G30) -> -231452.02 | L13: modificado
A14: Transferencia enviada BASSO REPRESENT SRL | E14: -410857.44 | G14: -410857.44 | H14: C
A15: Transferencia enviada Cerveza Tractor | F15: -714000 | G15: -714000 | H15: C
A16: Transferencia enviada Cerveza Tractor Sr | F16: -18000000 | G16: -18000000 | H16: C
A17: Transferencia enviada DE BRABAND AGUSTIN | E17: -403931.69 | G17: -403931.69 | H17: C
A18: Transferencia enviada DOÑA DORA | E18: -208510 | G18: -208510 | H18: C
A19: Transferencia enviada EMBOTELLADORA DEL ATLANTICO S.A. | E19: -1930000 | G19: -1930000 | H19: C
A20: Transferencia enviada EMBOTELLADORA DEL ATLANTICO SA | E20: -200000 | G20: -200000 | H20: C
A21: Transferencia enviada ERPEN JULIO C. Y PONZONI ANTONELLA P. SOCIEDAD SIMPLE | E21: -1320780 | G21: -1320780 | H21: C
A22: Transferencia enviada FRUVECO S R L | E22: -435976.75 | G22: -435976.75 | H22: C
A23: Transferencia enviada Gustavo Eugenio Gatter | E23: -90550 | G23: -90550 | H23: C
A24: Transferencia enviada LAGUNA CAPRI SAS | E24: -1584400 | G24: -1584400 | H24: C
A25: Transferencia enviada Leandro Paredes | E25: -117222.02 | G25: -117222.02 | H25: C
A26: Transferencia enviada Mariano Pedro Rebord Palazzo | E26: -735355.99 | G26: -735355.99 | H26: C
A27: Transferencia enviada PORCOMAGRO SRL | E27: -537500 | G27: -537500 | H27: C
A28: Transferencia enviada Rodolfo Oscar Bidal | E28: -136470 | G28: -136470 | H28: C
... A30: Transferencia enviada SUCESION LAPORTA FRANCISCO AN | E30: -114230 | G30: -114230 | H30: C
A31: Transferencia recibida 4b | C31: 2260 | G31: 2260
A32: Transferencia recibida Aarón Genaro Ojeda | C32: 800 | G32: 800
A33: Transferencia recibida Abigail Burguez | C33: 210 | G33: 210
A34: Transferencia recibida Abril Ayelen Sotto | C34: 12000 | G34: 12000
A35: Transferencia recibida Abril Morena Laumann Lorenzo | C35: 2535 | G35: 2535
A36: Transferencia recibida Agostina Belén Diaz | C36: 10000 | G36: 10000
A37: Transferencia recibida Agustín Daniel Bulay | C37: 300 | G37: 300
A38: Transferencia recibida Agustin Emiliano Ponce De Paoli | C38: 7670 | G38: 7670
A39: Transferencia recibida Agustin Exequiel Caceres | C39: 2250 | G39: 2250
A40: Transferencia recibida Agustin Rivero | C40: 15535 | G40: 15535
A41: Transferencia recibida Agustina Micaela Meriano | C41: 550 | G41: 550
A42: Transferencia recibida Aixa Nicole Martínez | C42: 2735 | G42: 2735
... A281: Transferencia recibida Zaira Tournoud | C281: 795 | G281: 795
A282: Total general | B282: -2803111.9 | C282: 43614188 | D282: -43959.35 | E282: -10015442 | F282: -18714000 | G282: 12037674

Sheet Hoja1
A3: Etiquetas de fila | B3: Suma de TRANSACTION_NET_AMOUNT
A4: Débito por deuda Facturas vencidas de Mercado Libre | B4: -29410.77 | C4: Contab. | D4: Percepción factura MP + IDyC (contab. Globalmente) | E4: ASIENTO 97 B | F4: COBRO DS X VENTA | G4: =SUM(B6,B7,B30:B280) -> 41938083
A5: Impuesto por extracción | B5: -43959.35 | C5: Contab. | D5: Corresponde IDyC ya contabilizados globalmente | E5: ASIENTO 98 B | F5: PAGO PROVEEDORES | G5: =SUM(B8,B12:B14,B16:B23,B25:B28)-50760.01 -> -10487989
A6: Liquidación de dinero | B6: 40838993 | C6: Contab. | F6: VER SI HAY COMPRA
A7: Liquidación de dinero cancelada Venta cancelada | B7: -7644.83 | C7: Contab. | F7: VER SI CONCILIA CON IMPUESTOS | G7: =+GETPIVOTDATA("TRANSACTION_NET_AMOUNT",$A$3,"TRANSACTION_TYPE","Pago de servicio ARCA")+GETPIVOTDATA("TRANSACTION_NET_AMOUNT",$A$3,"TRANSACTION_TYPE","Pago de servicios ARCA") -> -2819930.6
A8: Pago con QR Coca-Cola ANDINA | B8: -319194.82 | C8: Contab. | F8: VER QUE ES
A9: Pago de servicio ARCA | B9: -527445.91 | C9: Contab. | F9: CERVEZA TRACTOR
A10: Pago de servicios ARCA | B10: -2292484.7 | C10: Contab. | E10: ASIENTO 99 B | F10: CAJA | G10: =+GETPIVOTDATA("TRANSACTION_NET_AMOUNT",$A$3,"TRANSACTION_TYPE","Transferencia enviada Leandro Paredes")+GETPIVOTDATA("TRANSACTION_NET_AMOUNT",$A$3,"TRANSACTION_TYPE","Transferencia enviada SUCESION LAPORTA FRANCISCO AN") -> -232155.35
A11: Transferencia enviada | B11: -51064.57 | C11: Contab. | D11: PROVEEDORES / Brode Hermanos x $50760,01 + IDyC (contabilizado globalmente)
A12: Transferencia enviada ACERO JEKLO SAS | B12: -1201400 | C12: Contab.
A13: Transferencia enviada BASSO REPRESENT SRL | B13: -410857.44 | C13: Contab.
A14: Transferencia enviada Cerveza Tractor | B14: -718284 | C14: Contab. | D14: Va a proveedores / Hay facturas
A15: Transferencia enviada Cerveza Tractor Sr | B15: -18000000 | C15: Contab. | D15: DEPOSITO ENTRE CUENTAS - DE MP AL BBVA
A16: Transferencia enviada DE BRABAND AGUSTIN | B16: -403931.69 | C16: Contab.
A17: Transferencia enviada DOÑA DORA | B17: -209761.06 | C17: Contab.
A18: Transferencia enviada EMBOTELLADORA DEL ATLANTICO S.A. | B18: -1930000 | C18: Contab.
A19: Transferencia enviada EMBOTELLADORA DEL ATLANTICO SA | B19: -200000 | C19: Contab.
A20: Transferencia enviada ERPEN JULIO C. Y PONZONI ANTONELLA P. SOCIEDAD SIMPLE | B20: -1328704.7 | C20: Contab.
A21: Transferencia enviada FRUVECO S R L | B21: -435976.75 | C21: Contab.
A22: Transferencia enviada Gustavo Eugenio Gatter | B22: -91093.3 | C22: Contab.
A23: Transferencia enviada LAGUNA CAPRI SAS | B23: -1584400 | C23: Contab.
A24: Transferencia enviada Leandro Paredes | B24: -117925.35 | C24: Contab.
A25: Transferencia enviada Mariano Pedro Rebord Palazzo | B25: -739768.13 | C25: Contab.
A26: Transferencia enviada PORCOMAGRO SRL | B26: -537500 | C26: Contab.
A27: Transferencia enviada Rodolfo Oscar Bidal | B27: -137288.82 | C27: Contab.
... A280: Transferencia recibida Zaira Tournoud | B280: 778.3 | C280: Contab.
A281: Total general | B281: 10324333

Sheet SIRCUPA
A1: Reporte-Retención-SIRCUPA-Noviembre-CC20250609171159-MercadoPago
A3: Usuario: | B3: CC20250609171159
A4: Impuesto: | B4: Retención SIRCUPA
A5: Fecha de descarga: | B5: 18/03/2026
A6: Intervalo de fechas consultadas: | B6: 01/11/2025 a 01/12/2025
A8: Total | B8: Monto
A9: Base imponible | B9: $1.130.475,00
A10: Tramo 1 - retenido del 01/11 al 10/11 | B10: $1.886,22
A11: Tramo 2 - retenido del 11/11 al 20/11 | B11: $1.279,61
A12: Tramo 3 - retenido del 21/11 al 30/11 | B12: $13.791,60
A13: Importe retenido | B13: $16.957,43
A14: Importe devuelto | B14: $0,00
A16: Podrás utilizar este reporte para conciliar lo que retuvimos.
A17: Podrás buscar el detalle de lo retenido en tu operación en la sección Actividad.
A19: Operación | E19: Impuesto
A20: Número de operación | B20: Fecha de operación | C20: Tipo | D20: Monto de transferencia | E20: Fecha de retención | F20: Alícuota | G20: Base imponible | H20: Importe retenido
A21: 132052626378 | B21: 31/10/2025 | C21: Transferencia | D21: 1380 | E21: 01/11/2025 | F21: 1,50 % | G21: 1380 | H21: 20.7
A22: 132052976580 | B22: 31/10/2025 | C22: Transferencia | D22: 2005 | E22: 01/11/2025 | F22: 1,50 % | G22: 2005 | H22: 30.08
A23: 131457113189 | B23: 31/10/2025 | C23: Transferencia | D23: 950 | E23: 01/11/2025 | F23: 1,50 % | G23: 950 | H23: 14.25
A24: 132059678982 | B24: 01/11/2025 | C24: Transferencia | D24: 1695 | E24: 01/11/2025 | F24: 1,50 % | G24: 1695 | H24: 25.43
A25: 132158948686 | B25: 01/11/2025 | C25: Transferencia | D25: 580 | E25: 01/11/2025 | F25: 1,50 % | G25: 580 | H25: 8.7
A26: 131558661393 | B26: 01/11/2025 | C26: Transferencia | D26: 1470 | E26: 01/11/2025 | F26: 1,50 % | G26: 1470 | H26: 22.05
A27: 132173925278 | B27: 01/11/2025 | C27: Transferencia | D27: 3870 | E27: 01/11/2025 | F27: 1,50 % | G27: 3870 | H27: 58.05
A28: 132178747024 | B28: 02/11/2025 | C28: Transferencia | D28: 795 | E28: 02/11/2025 | F28: 1,50 % | G28: 795 | H28: 11.93
A29: 131581475387 | B29: 02/11/2025 | C29: Transferencia | D29: 320 | E29: 02/11/2025 | F29: 1,50 % | G29: 320 | H29: 4.8
A30: 131581635255 | B30: 02/11/2025 | C30: Transferencia | D30: 1320 | E30: 02/11/2025 | F30: 1,50 % | G30: 1320 | H30: 19.8
A31: 131582322803 | B31: 02/11/2025 | C31: Transferencia | D31: 995 | E31: 02/11/2025 | F31: 1,50 % | G31: 995 | H31: 14.93
A32: 132181831094 | B32: 02/11/2025 | C32: Transferencia | D32: 275 | E32: 02/11/2025 | F32: 1,50 % | G32: 275 | H32: 4.13
... A313: 135932193190 | B313: 30/11/2025 | C313: Transferencia | D313: 3980 | E313: 30/11/2025 | F313: 1,50 % | G313: 3980 | H313: 59.7
G315: =SUM(G21:G314) -> 1130475 | H315: =SUM(H21:H314) -> 16957.43

Sheet SIRTAC
A1: Reporte-Retención-SIRTAC-inscripto-1ra-quincena-Noviembre-CC20250609171159-MercadoPago
A3: Usuario: | B3: CC20250609171159
A4: Impuesto: | B4: Retención SIRTAC
A5: Fecha de descarga: | B5: 18/03/2026
A6: Intervalo de fechas consultadas: | B6: 01/11/2025 a 16/11/2025
A8: Total | B8: Monto
A9: Base imponible | B9: $17.992.907,00
A10: Importe retenido | B10: $179.929,07
A11: Importe devuelto | B11: $0,00
A12: Podrás conciliar la información con otros reportes de Mercado Libre. | D12: Podrás buscar el detalle de lo retenido en tu operación en la sección Actividad.
A14: Operación | E14: Impuesto
A15: Número de operación | B15: Número de venta - Referencia externa | C15: Fecha de operación | D15: Tipo | E15: Fecha de retención | F15: Alícuota | G15: Base imponible | H15: Importe retenido
A16: 132052239804 | B16: Venta presencial | C16: 31/10/2025 | D16: Venta | E16: 01/11/2025 | F16: 1,00 % | G16: 39500 | H16: 395
A17: 131455081763 | C17: 31/10/2025 | D17: Venta | E17: 01/11/2025 | F17: 1,00 % | G17: 27600 | H17: 276
A18: 132052913658 | C18: 31/10/2025 | D18: Venta | E18: 01/11/2025 | F18: 1,00 % | G18: 40100 | H18: 401
A19: 131456214529 | C19: 31/10/2025 | D19: Venta | E19: 01/11/2025 | F19: 1,00 % | G19: 130100 | H19: 1301
A20: 132053623776 | C20: 31/10/2025 | D20: Venta | E20: 01/11/2025 | F20: 1,00 % | G20: 21700 | H20: 217
A21: 132055115248 | C21: 31/10/2025 | D21: Venta | E21: 01/11/2025 | F21: 1,00 % | G21: 14600 | H21: 146
A22: 132055387448 | B22: Venta presencial | C22: 31/10/2025 | D22: Venta | E22: 01/11/2025 | F22: 1,00 % | G22: 48900 | H22: 489
A23: 131460056581 | C23: 01/11/2025 | D23: Venta | E23: 01/11/2025 | F23: 1,00 % | G23: 41100 | H23: 411
A24: 132057557082 | C24: 01/11/2025 | D24: Venta | E24: 01/11/2025 | F24: 1,00 % | G24: 27600 | H24: 276
A25: 132058425180 | C25: 01/11/2025 | D25: Venta | E25: 01/11/2025 | F25: 1,00 % | G25: 38400 | H25: 384
A26: 131461068663 | C26: 01/11/2025 | D26: Venta | E26: 01/11/2025 | F26: 1,00 % | G26: 58600 | H26: 586
A27: 131462014055 | C27: 01/11/2025 | D27: Venta | E27: 01/11/2025 | F27: 1,00 % | G27: 29400 | H27: 294
A28: 132059566050 | C28: 01/11/2025 | D28: Venta | E28: 01/11/2025 | F28: 1,00 % | G28: 33900 | H28: 339
A29: 132059906366 | C29: 01/11/2025 | D29: Venta | E29: 01/11/2025 | F29: 1,00 % | G29: 20600 | H29: 206
A30: 131455026773 | C30: 31/10/2025 | D30: Venta | E30: 01/11/2025 | F30: 1,00 % | G30: 46200 | H30: 462
A31: 131455763539 | C31: 31/10/2025 | D31: Venta | E31: 01/11/2025 | F31: 1,00 % | G31: 11000 | H31: 110
A32: 131457190213 | C32: 31/10/2025 | D32: Venta | E32: 01/11/2025 | F32: 1,00 % | G32: 19000 | H32: 190
A33: 131458138389 | B33: Venta presencial | C33: 31/10/2025 | D33: Venta | E33: 01/11/2025 | F33: 1,00 % | G33: 92100 | H33: 921
A34: 132055965040 | C34: 01/11/2025 | D34: Venta | E34: 01/11/2025 | F34: 1,00 % | G34: 72800 | H34: 728
A35: 132056029654 | C35: 01/11/2025 | D35: Venta | E35: 01/11/2025 | F35: 1,00 % | G35: 31200 | H35: 312
A36: 131459408087 | C36: 01/11/2025 | D36: Venta | E36: 01/11/2025 | F36: 1,00 % | G36: 35100 | H36: 351
A37: 132057028190 | C37: 01/11/2025 | D37: Venta | E37: 01/11/2025 | F37: 1,00 % | G37: 17900 | H37: 179
A38: 131460571647 | C38: 01/11/2025 | D38: Venta | E38: 01/11/2025 | F38: 1,00 % | G38: 5500 | H38: 55
A39: 131461803783 | C39: 01/11/2025 | D39: Venta | E39: 01/11/2025 | F39: 1,00 % | G39: 19900 | H39: 199
A40: 132059777870 | C40: 01/11/2025 | D40: Venta | E40: 01/11/2025 | F40: 1,00 % | G40: 11000 | H40: 110
A41: 132142231840 | B41: Venta presencial | C41: 01/11/2025 | D41: Venta | E41: 01/11/2025 | F41: 1,00 % | G41: 9600 | H41: 96
A42: 131557771975 | B42: Venta presencial | C42: 01/11/2025 | D42: Venta | E42: 01/11/2025 | F42: 1,00 % | G42: 11600 | H42: 116
A43: 132156161244 | B43: Venta presencial | C43: 01/11/2025 | D43: Venta | E43: 01/11/2025 | F43: 1,00 % | G43: 14400 | H43: 144
A44: 132156880960 | B44: Venta presencial | C44: 01/11/2025 | D44: Venta | E44: 01/11/2025 | F44: 1,00 % | G44: 9800 | H44: 98
A45: 132151858318 | B45: Venta presencial | C45: 01/11/2025 | D45: Venta | E45: 01/11/2025 | F45: 1,00 % | G45: 23400 | H45: 234
A46: 132167577648 | B46: Venta presencial | C46: 01/11/2025 | D46: Venta | E46: 01/11/2025 | F46: 1,00 % | G46: 30300 | H46: 303
A47: 131570532387 | B47: Venta presencial | C47: 01/11/2025 | D47: Venta | E47: 01/11/2025 | F47: 1,00 % | G47: 26600 | H47: 266
A48: 132168375198 | B48: Venta presencial | C48: 01/11/2025 | D48: Venta | E48: 01/11/2025 | F48: 1,00 % | G48: 26000 | H48: 260
A49: 131570693323 | B49: Venta presencial | C49: 01/11/2025 | D49: Venta | E49: 01/11/2025 | F49: 1,00 % | G49: 9600 | H49: 96
A50: 131573655861 | C50: 01/11/2025 | D50: Venta | E50: 01/11/2025 | F50: 1,00 % | G50: 30000 | H50: 300
A51: 132156526470 | C51: 01/11/2025 | D51: Venta | E51: 01/11/2025 | F51: 1,00 % | G51: 29400 | H51: 294
A52: 132173642032 | B52: Venta presencial | C52: 01/11/2025 | D52: Venta | E52: 01/11/2025 | F52: 1,00 % | G52: 42400 | H52: 424
A53: 131560760339 | C53: 01/11/2025 | D53: Venta | E53: 01/11/2025 | F53: 1,00 % | G53: 21100 | H53: 211
A54: 131576573415 | B54: Venta presencial | C54: 01/11/2025 | D54: Venta | E54: 01/11/2025 | F54: 1,00 % | G54: 9600 | H54: 96
A55: 131561116095 | C55: 01/11/2025 | D55: Venta | E55: 01/11/2025 | F55: 1,00 % | G55: 11600 | H55: 116
A56: 131576856023 | C56: 01/11/2025 | D56: Venta | E56: 01/11/2025 | F56: 1,00 % | G56: 8200 | H56: 82
A57: 132174941170 | B57: Venta presencial | C57: 01/11/2025 | D57: Venta | E57: 02/11/2025 | F57: 1,00 % | G57: 10300 | H57: 103
A58: 131577618637 | B58: Venta presencial | C58: 01/11/2025 | D58: Venta | E58: 02/11/2025 | F58: 1,00 % | G58: 52800 | H58: 528
A59: 132175561740 | B59: Venta presencial | C59: 01/11/2025 | D59: Venta | E59: 02/11/2025 | F59: 1,00 % | G59: 36300 | H59: 363
A60: 131578681107 | C60: 01/11/2025 | D60: Venta | E60: 02/11/2025 | F60: 1,00 % | G60: 71900 | H60: 719
A61: 132177096328 | C61: 01/11/2025 | D61: Venta | E61: 02/11/2025 | F61: 1,00 % | G61: 77200 | H61: 772
A62: 131563913679 | C62: 01/11/2025 | D62: Venta | E62: 01/11/2025 | F62: 1,00 % | G62: 2300 | H62: 23
A63: 131564596361 | B63: Venta presencial | C63: 01/11/2025 | D63: Venta | E63: 01/11/2025 | F63: 1,00 % | G63: 14600 | H63: 146
A64: 132178184768 | B64: Venta presencial | C64: 01/11/2025 | D64: Venta | E64: 02/11/2025 | F64: 1,00 % | G64: 16000 | H64: 160
A65: 132178648016 | C65: 02/11/2025 | D65: Venta | E65: 02/11/2025 | F65: 1,00 % | G65: 15900 | H65: 159
A66: 132179069762 | C66: 02/11/2025 | D66: Venta | E66: 02/11/2025 | F66: 1,00 % | G66: 29500 | H66: 295
A67: 131581454143 | C67: 02/11/2025 | D67: Venta | E67: 02/11/2025 | F67: 1,00 % | G67: 26900 | H67: 269
A68: 131581570295 | C68: 02/11/2025 | D68: Venta | E68: 02/11/2025 | F68: 1,00 % | G68: 6400 | H68: 64
A69: 132179457042 | C69: 02/11/2025 | D69: Venta | E69: 02/11/2025 | F69: 1,00 % | G69: 13200 | H69: 132
A70: 132180177488 | C70: 02/11/2025 | D70: Venta | E70: 02/11/2025 | F70: 1,00 % | G70: 22000 | H70: 220
A71: 132180129622 | C71: 02/11/2025 | D71: Venta | E71: 02/11/2025 | F71: 1,00 % | G71: 19900 | H71: 199
A72: 132180740610 | B72: Venta presencial | C72: 02/11/2025 | D72: Venta | E72: 02/11/2025 | F72: 1,00 % | G72: 14600 | H72: 146
A73: 131582934295 | C73: 02/11/2025 | D73: Venta | E73: 02/11/2025 | F73: 1,00 % | G73: 14600 | H73: 146
A74: 131583431153 | C74: 02/11/2025 | D74: Venta | E74: 02/11/2025 | F74: 1,00 % | G74: 14400 | H74: 144
A75: 132181431006 | C75: 02/11/2025 | D75: Venta | E75: 02/11/2025 | F75: 1,00 % | G75: 9600 | H75: 96
A76: 131583691511 | C76: 02/11/2025 | D76: Venta | E76: 02/11/2025 | F76: 1,00 % | G76: 5500 | H76: 55
A77: 131583831737 | B77: Venta presencial | C77: 02/11/2025 | D77: Venta | E77: 02/11/2025 | F77: 1,00 % | G77: 37200 | H77: 372
A78: 132181912220 | C78: 02/11/2025 | D78: Venta | E78: 02/11/2025 | F78: 1,00 % | G78: 5500 | H78: 55
A79: 131584069489 | C79: 02/11/2025 | D79: Venta | E79: 02/11/2025 | F79: 1,00 % | G79: 48500 | H79: 485
A80: 132182077312 | C80: 02/11/2025 | D80: Venta | E80: 02/11/2025 | F80: 1,00 % | G80: 48500 | H80: 485
A81: 131584332677 | C81: 02/11/2025 | D81: Venta | E81: 02/11/2025 | F81: 1,00 % | G81: 18900 | H81: 189
A82: 131584416787 | C82: 02/11/2025 | D82: Venta | E82: 02/11/2025 | F82: 1,00 % | G82: 27000 | H82: 270
A83: 132182344384 | C83: 02/11/2025 | D83: Venta | E83: 02/11/2025 | F83: 1,00 % | G83: 18400 | H83: 184
A84: 132167613940 | C84: 01/11/2025 | D84: Venta | E84: 01/11/2025 | F84: 1,00 % | G84: 36200 | H84: 362
A85: 132167850164 | B85: Venta presencial | C85: 01/11/2025 | D85: Venta | E85: 01/11/2025 | F85: 1,00 % | G85: 59100 | H85: 591
A86: 132169724314 | C86: 01/11/2025 | D86: Venta | E86: 01/11/2025 | F86: 1,00 % | G86: 35400 | H86: 354
A87: 131573182899 | C87: 01/11/2025 | D87: Venta | E87: 01/11/2025 | F87: 1,00 % | G87: 30600 | H87: 306
A88: 132171323038 | C88: 01/11/2025 | D88: Venta | E88: 01/11/2025 | F88: 1,00 % | G88: 28100 | H88: 281
A89: 132172242648 | B89: Venta presencial | C89: 01/11/2025 | D89: Venta | E89: 01/11/2025 | F89: 1,00 % | G89: 68800 | H89: 688
A90: 131575087177 | C90: 01/11/2025 | D90: Venta | E90: 01/11/2025 | F90: 1,00 % | G90: 43600 | H90: 436
A91: 132172960086 | B91: Venta presencial | C91: 01/11/2025 | D91: Venta | E91: 01/11/2025 | F91: 1,00 % | G91: 55400 | H91: 554
A92: 131575571071 | C92: 01/11/2025 | D92: Venta | E92: 01/11/2025 | F92: 1,00 % | G92: 41500 | H92: 415
A93: 131575758323 | C93: 01/11/2025 | D93: Venta | E93: 01/11/2025 | F93: 1,00 % | G93: 14800 | H93: 148
A94: 131575921471 | B94: Venta presencial | C94: 01/11/2025 | D94: Venta | E94: 01/11/2025 | F94: 1,00 % | G94: 40900 | H94: 409
A95: 132173998208 | C95: 01/11/2025 | D95: Venta | E95: 01/11/2025 | F95: 1,00 % | G95: 38700 | H95: 387
A96: 131576487977 | C96: 01/11/2025 | D96: Venta | E96: 01/11/2025 | F96: 1,00 % | G96: 39800 | H96: 398
A97: 131576778161 | C97: 01/11/2025 | D97: Venta | E97: 01/11/2025 | F97: 1,00 % | G97: 12400 | H97: 124
A98: 131577259373 | C98: 01/11/2025 | D98: Venta | E98: 02/11/2025 | F98: 1,00 % | G98: 30000 | H98: 300
A99: 131577658249 | C99: 01/11/2025 | D99: Venta | E99: 02/11/2025 | F99: 1,00 % | G99: 48400 | H99: 484
A100: 132175628956 | C100: 01/11/2025 | D100: Venta | E100: 02/11/2025 | F100: 1,00 % | G100: 39900 | H100: 399
A101: 132176170110 | B101: Venta presencial | C101: 01/11/2025 | D101: Venta | E101: 02/11/2025 | F101: 1,00 % | G101: 4800 | H101: 48
A102: 132176598634 | C102: 01/11/2025 | D102: Venta | E102: 02/11/2025 | F102: 1,00 % | G102: 63300 | H102: 633
A103: 132176782308 | C103: 01/11/2025 | D103: Venta | E103: 02/11/2025 | F103: 1,00 % | G103: 13400 | H103: 134
...

Sheet Gastos
A1: Fecha de actualización | C1: 46041.35
A3: Sumamos nuevas columnas a tu reporte: Trabajamos para brindarte más detalle sobre los cargos por utilizar Mercado Pago. Por eso, a partir de ahora, en "Información sobre cargos" incluiremos las siguientes columnas: - Número del cargo: para que puedas cruzar la información con otros reportes. - Cobrado en la operación: para saber si un cargo fue cobrado en la operación o no. - Estado del cargo y Cargo que anula: para entender más sobre los cargos anulados.
A7: Información sobre cargos | J7: Información de la operación sobre la que se aplica | R7: Información sobre percepciones | T7: Accesos
A8: Operación relacionada | B8: N° de factura fiscal | C8: Fecha del cargo | D8: Número del cargo | E8: Número del movimiento | F8: Detalle | G8: Cobrado en la operacion | H8: Estado del cargo | I8: Cargo que anula | J8: Valor del cargo | K8: Tipo de operación | L8: Tipo de pago | M8: Número de sucursal | N8: Nombre de sucursal | O8: Referencia externa | P8: Cliente | Q8: Valor de la operación | R8: Alícuota | S8: Base imponible | T8: Sección de Mercado libre y de Mercado Pago
A9: 134186435163 | B9: 0067A00479529 | C9: 45982 | D9: 53561228617 | E9: 2127747648803 | F9: Anulación del cargo por cobrar con código QR | G9: No aplica | I9: 53561139866 | J9: -128.77 | K9: Pago | L9: QR | M9: 71465208 | N9: Cerveza Träctor | P9: NICOLASMARCHAND512 | Q9: 7900
A10: 134323421061 | B10: 0067A00479529 | C10: 45984 | D10: 53616537453 | E10: 2128718073234 | F10: Cargo por cobrar con código QR | G10: Si | J10: 0.24 | K10: Pago | L10: QR | M10: 71465208 | N10: Cerveza Träctor | O10: Camion | P10: LEFL2900826 | Q10: 25 | T10: Ir al Detalle de la operación en Mercado Pago
A11: 135026550898 | B11: 0067A00479529 | C11: 45984 | D11: 53655262594 | E11: 2129164479727 | F11: Cargo por cobrar con código QR | G11: Si | J11: 0.38 | K11: Pago | L11: QR | M11: 71465208 | N11: Cerveza Träctor | O11: Camion | P11: LUCIAJOSEFINAVALENTIN | Q11: 39.57 | T11: Ir al Detalle de la operación en Mercado Pago
A12: 134413406657 | B12: 0067A00479529 | C12: 45984 | D12: 53655726262 | E12: 2129284759700 | F12: Cargo por cobrar con código QR | G12: Si | J12: 0.96 | K12: Pago | L12: QR | M12: 71465208 | N12: Cerveza Träctor | O12: Camion | P12: BOAL2059999 | Q12: 98.46 | T12: Ir al Detalle de la operación en Mercado Pago
A13: 134327181895 | B13: 0067A00479529 | C13: 45984 | D13: 53618136688 | E13: 2128628854517 | F13: Cargo por cobrar con código QR | G13: Si | J13: 4.85 | K13: Pago | L13: QR | M13: 71465208 | N13: Cerveza Träctor | O13: Camion | P13: ALE_ALMA2005 | Q13: 500 | T13: Ir al Detalle de la operación en Mercado Pago
A14: 135031455468 | B14: 0067A00479529 | C14: 45985 | D14: 53657336505 | E14: 2129310029508 | F14: Cargo por cobrar con código QR | G14: Si | J14: 7.91 | K14: Pago | L14: QR | M14: 71465208 | N14: Cerveza Träctor | O14: Camion | P14: SIOMARA MAITEN | Q14: 815.29 | T14: Ir al Detalle de la operación en Mercado Pago
A15: 134306885535 | B15: 0067A00479529 | C15: 45983 | D15: 53610448170 | E15: 2128617840972 | F15: Cargo por cobrar con código QR | G15: Si | J15: 9.7 | K15: Pago | L15: QR | M15: 71465208 | N15: Cerveza Träctor | O15: Camion | P15: CORREALUCAS20211013224905 | Q15: 1000 | T15: Ir al Detalle de la operación en Mercado Pago
A16: 134311763421 | B16: 0067A00479529 | C16: 45983 | D16: 53612226144 | E16: 2128647870432 | F16: Cargo por cobrar con código QR | G16: Si | J16: 9.7 | K16: Pago | L16: QR | M16: 71465208 | N16: Cerveza Träctor | O16: Camion | P16: LAFI8577557 | Q16: 1000 | T16: Ir al Detalle de la operación en Mercado Pago
A17: 134312521803 | B17: 0067A00479529 | C17: 45983 | D17: 53612510402 | E17: 2128539716613 | F17: Cargo por cobrar con código QR | G17: Si | J17: 9.7 | K17: Pago | L17: QR | M17: 71465208 | N17: Cerveza Träctor | O17: Camion | P17: FRUDRIZARD6 | Q17: 1000 | T17: Ir al Detalle de la operación en Mercado Pago
A18: 134315804293 | B18: 0067A00479529 | C18: 45983 | D18: 53613609864 | E18: 2128558581089 | F18: Cargo por cobrar con código QR | G18: Si | J18: 9.7 | K18: Pago | L18: QR | M18: 71465208 | N18: Cerveza Träctor | O18: Camion | P18: GODA3417773 | Q18: 1000 | T18: Ir al Detalle de la operación en Mercado Pago
A19: 134324052791 | B19: 0067A00479529 | C19: 45984 | D19: 53616808120 | E19: 2128609301089 | F19: Cargo por uso de QR - Pagos Interoperables | G19: Si | J19: 9.7 | K19: Pago | L19: QR | M19: 71465208 | N19: Cerveza Träctor | O19: Camion | P19: @2489718921 | Q19: 1000
A20: 135024632518 | B20: 0067A00479529 | C20: 45984 | D20: 53654489821 | E20: 2129265408018 | F20: Cargo por cobrar con código QR | G20: Si | J20: 9.7 | K20: Pago | L20: QR | M20: 71465208 | N20: Cerveza Träctor | O20: Camion | P20: MONZONMILAGROS20210617141702 | Q20: 1000 | T20: Ir al Detalle de la operación en Mercado Pago
A21: 134925501820 | B21: 0067A00479529 | C21: 45983 | D21: 53612047646 | E21: 2128532042837 | F21: Cargo por cobrar con código QR | G21: Si | J21: 19.4 | K21: Pago | L21: QR | M21: 71465208 | N21: Cerveza Träctor | O21: Camion | P21: BUSSONMILAGROS20220505164307 | Q21: 2000 | T21: Ir al Detalle de la operación en Mercado Pago
A22: 135019133954 | B22: 0067A00479529 | C22: 45984 | D22: 53652359931 | E22: 2129231246854 | F22: Cargo por cobrar con código QR | G22: Si | J22: 19.4 | K22: Pago | L22: QR | M22: 71465208 | N22: Cerveza Träctor | O22: Camion | P22: ROSTRISKAANTONELLA | Q22: 2000 | T22: Ir al Detalle de la operación en Mercado Pago
A23: 135032112510 | B23: 0067A00479529 | C23: 45985 | D23: 53657520848 | E23: 2129313805526 | F23: Cargo por cobrar con código QR | G23: Si | J23: 19.4 | K23: Pago | L23: QR | M23: 71465208 | N23: Cerveza Träctor | O23: Camion | P23: CASTELLANOGIANELLA202302011257 | Q23: 2000 | T23: Ir al Detalle de la operación en Mercado Pago
A24: 134067688163 | B24: 0067A00479529 | C24: 45981 | D24: 53515866403 | E24: 2126987007235 | F24: Cargo por cobrar con código QR | G24: Si | J24: 22.31 | K24: Pago | L24: QR | M24: 71465208 | N24: Cerveza Träctor | P24: ZAMA7577914 | Q24: 2300 | T24: Ir al Detalle de la operación en Mercado Pago
A25: 134073366837 | B25: 0067A00479529 | C25: 45982 | D25: 53518150709 | E25: 2127021206501 | F25: Cargo por cobrar con código QR | G25: Si | J25: 23.28 | K25: Pago | L25: QR | M25: 71465208 | N25: Cerveza Träctor | P25: MARTINKLER | Q25: 2400 | T25: Ir al Detalle de la operación en Mercado Pago
A26: 135538891740 | B26: 0067A00479529 | C26: 45988 | D26: 53856599620 | E26: 2132702131663 | F26: Cargo por cobrar con código QR | G26: Si | J26: 23.28 | K26: Pago | L26: QR | M26: 71465208 | N26: Cerveza Träctor | P26: PABLOMARTINSPEKTOR | Q26: 2400 | T26: Ir al Detalle de la operación en Mercado Pago
A27: 134935568493 | B27: 0067A00479529 | C27: 45989 | D27: 53861731237 | E27: 2132925322248 | F27: Cargo por cobrar con código QR | G27: Si | J27: 23.28 | K27: Pago | L27: QR | M27: 71465208 | N27: Cerveza Träctor | P27: ALFONSOAMINA20220105150517 | Q27: 2400 | T27: Ir al Detalle de la operación en Mercado Pago
A28: 134020389566 | B28: 0067A00479529 | C28: 45976 | D28: 53249400205 | E28: 2122577277446 | F28: Cargo por cobrar con código QR | G28: Si | J28: 23.77 | K28: Pago | L28: QR | M28: 71465208 | N28: Cerveza Träctor | P28: CAMACHOAXEL20230404130753 | Q28: 2450 | T28: Ir al Detalle de la operación en Mercado Pago
A29: 135008411208 | B29: 0067A00479529 | C29: 45984 | D29: 53648017379 | E29: 2129162485972 | F29: Cargo por cobrar con código QR | G29: Si | J29: 23.77 | K29: Pago | L29: QR | M29: 71465208 | N29: Cerveza Träctor | P29: GENOUDJUAN20221005142804 | Q29: 2450 | T29: Ir al Detalle de la operación en Mercado Pago
A30: 135021547358 | B30: 0067A00479529 | C30: 45984 | D30: 53653309505 | E30: 2129246436628 | F30: Cargo por cobrar con código QR | G30: Si | J30: 24.25 | K30: Pago | L30: QR | M30: 71465208 | N30: Cerveza Träctor | O30: Camion | P30: VERITO_MANSILLA07 | Q30: 2500 | T30: Ir al Detalle de la operación en Mercado Pago
A31: 132830924598 | B31: 0067A00479529 | C31: 45968 | D31: 52780928349 | E31: 2114628177094 | F31: Cargo por cobrar con código QR | G31: Si | J31: 36.86 | K31: Pago | L31: QR | M31: 71465208 | N31: Cerveza Träctor | P31: MONTAÑANAROCIO20230307164229 | Q31: 3800 | T31: Ir al Detalle de la operación en Mercado Pago
A32: 134010890798 | B32: 0067A00479529 | C32: 45976 | D32: 53245707914 | E32: 2122411037933 | F32: Cargo por cobrar con código QR | G32: Si | J32: 36.86 | K32: Pago | L32: QR | M32: 71465208 | N32: Cerveza Träctor | P32: FIORELLACALOMINO | Q32: 3800 | T32: Ir al Detalle de la operación en Mercado Pago
A33: 135549200574 | B33: 0067A00479529 | C33: 45989 | D33: 53861058107 | E33: 2132904205686 | F33: Cargo por cobrar con código QR | G33: Si | J33: 36.86 | K33: Pago | L33: QR | M33: 71465208 | N33: Cerveza Träctor | P33: CAIRELAUTARO | Q33: 3800 | T33: Ir al Detalle de la operación en Mercado Pago
A34: 131563913679 | B34: 0070A00444640 | C34: 45962 | D34: 52509430891 | E34: 2110171847224 | F34: Cargo por cobrar con Mercado Pago | G34: Si | J34: 37.49 | K34: Pago | L34: QR | M34: 71465208 | N34: Cerveza Träctor | P34: @2027635388 | Q34: 2300 | T34: Ir al Detalle de la operación en Mercado Pago
A35: 133098804734 | B35: 0067A00479529 | C35: 45969 | D35: 52882049808 | E35: 2116360878648 | F35: Cargo por cobrar con código QR | G35: Si | J35: 38.8 | K35: Pago | L35: QR | M35: 71465208 | N35: Cerveza Träctor | P35: GARCIAIGNACIO20210806172500 | Q35: 4000 | T35: Ir al Detalle de la operación en Mercado Pago
A36: 133772453774 | B36: 0067A00479529 | C36: 45975 | D36: 53150908102 | E36: 2120845344387 | F36: Cargo por cobrar con código QR | G36: Si | J36: 38.8 | K36: Pago | L36: QR | M36: 71465208 | N36: Cerveza Träctor | P36: FLORENCIABRASLAVSKY | Q36: 4000 | T36: Ir al Detalle de la operación en Mercado Pago
A37: 133165300835 | B37: 0067A00479529 | C37: 45975 | D37: 53151335402 | E37: 2120853177839 | F37: Cargo por cobrar con código QR | G37: Si | J37: 38.8 | K37: Pago | L37: QR | M37: 71465208 | N37: Cerveza Träctor | P37: MARTIMARTINEZ2019 | Q37: 4000 | T37: Ir al Detalle de la operación en Mercado Pago
A38: 133929300798 | B38: 0067A00479529 | C38: 45976 | D38: 53210591526 | E38: 2122008453882 | F38: Cargo por cobrar con código QR | G38: Si | J38: 38.8 | K38: Pago | L38: QR | M38: 71465208 | N38: Cerveza Träctor | P38: ORZUZALOURDES20210508160023 | Q38: 4000 | T38: Ir al Detalle de la operación en Mercado Pago
A39: 134067647407 | B39: 0067A00479529 | C39: 45981 | D39: 53515868319 | E39: 2127098089410 | F39: Cargo por cobrar con código QR | G39: Si | J39: 38.8 | K39: Pago | L39: QR | M39: 71465208 | N39: Cerveza Träctor | P39: IMMA9507842 | Q39: 4000 | T39: Ir al Detalle de la operación en Mercado Pago
A40: 134682443026 | B40: 0067A00479529 | C40: 45981 | D40: 53516181230 | E40: 2126992443599 | F40: Cargo por uso de QR - Pagos Interoperables | G40: Si | J40: 38.8 | K40: Pago | L40: QR | M40: 71465208 | N40: Cerveza Träctor | P40: @2489718921 | Q40: 4000
A41: 134068585309 | B41: 0067A00479529 | C41: 45981 | D41: 53516309667 | E41: 2126994779027 | F41: Cargo por cobrar con código QR | G41: Si | J41: 38.8 | K41: Pago | L41: QR | M41: 71465208 | N41: Cerveza Träctor | P41: LUCA4546049 | Q41: 4000 | T41: Ir al Detalle de la operación en Mercado Pago
A42: 134070455607 | B42: 0067A00479529 | C42: 45982 | D42: 53516990484 | E42: 2127115614500 | F42: Cargo por cobrar con código QR | G42: Si | J42: 38.8 | K42: Pago | L42: QR | M42: 71465208 | N42: Cerveza Träctor | P42: LUDMILAMAGALIDURAND | Q42: 4000 | T42: Ir al Detalle de la operación en Mercado Pago
A43: 134686419216 | B43: 0067A00479529 | C43: 45982 | D43: 53517919239 | E43: 2127129605624 | F43: Cargo por cobrar con código QR | G43: Si | J43: 38.8 | K43: Pago | L43: QR | M43: 71465208 | N43: Cerveza Träctor | P43: LUDMILAMAGALIDURAND | Q43: 4000 | T43: Ir al Detalle de la operación en Mercado Pago
A44: 134686681060 | B44: 0067A00479529 | C44: 45982 | D44: 53518006312 | E44: 2127019409689 | F44: Cargo por cobrar con código QR | G44: Si | J44: 38.8 | K44: Pago | L44: QR | M44: 71465208 | N44: Cerveza Träctor | P44: FERNANDEZKEVIN20220611105305 | Q44: 4000 | T44: Ir al Detalle de la operación en Mercado Pago
A45: 134074235247 | B45: 0067A00479529 | C45: 45982 | D45: 53518588017 | E45: 2127028414135 | F45: Cargo por cobrar con código QR | G45: Si | J45: 38.8 | K45: Pago | L45: QR | M45: 71465208 | N45: Cerveza Träctor | P45: MARTINKLER | Q45: 4000 | T45: Ir al Detalle de la operación en Mercado Pago
A46: 134941279940 | B46: 0067A00479529 | C46: 45984 | D46: 53618139575 | E46: 2128742196112 | F46: Cargo por uso de QR - Pagos Interoperables | G46: Si | J46: 38.8 | K46: Pago | L46: QR | M46: 71465208 | N46: Cerveza Träctor | P46: @2489718921 | Q46: 4000
A47: 135033105388 | B47: 0067A00479529 | C47: 45985 | D47: 53658047058 | E47: 2129211976719 | F47: Cargo por cobrar con código QR | G47: Si | J47: 38.8 | K47: Pago | L47: QR | M47: 71465208 | N47: Cerveza Träctor | O47: Camion | P47: LAUTAROOBISPOLAUTAROOBISPO | Q47: 4000 | T47: Ir al Detalle de la operación en Mercado Pago
A48: 135546391550 | B48: 0067A00479529 | C48: 45989 | D48: 53860174089 | E48: 2132759791225 | F48: Cargo por cobrar con código QR | G48: Si | J48: 38.8 | K48: Pago | L48: QR | M48: 71465208 | N48: Cerveza Träctor | P48: MARTIMARTINEZ2019 | Q48: 4000 | T48: Ir al Detalle de la operación en Mercado Pago
A49: 134934470129 | B49: 0067A00479529 | C49: 45989 | D49: 53861340471 | E49: 2132794208151 | F49: Cargo por cobrar con código QR | G49: Si | J49: 38.8 | K49: Pago | L49: QR | M49: 71465208 | N49: Cerveza Träctor | P49: ERICKCLOTET | Q49: 4000 | T49: Ir al Detalle de la operación en Mercado Pago
A50: 134934343573 | B50: 0067A00479529 | C50: 45989 | D50: 53861419258 | E50: 2132796750231 | F50: Cargo por cobrar con código QR | G50: Si | J50: 38.8 | K50: Pago | L50: QR | M50: 71465208 | N50: Cerveza Träctor | P50: NACHIAPPELLA | Q50: 4000 | T50: Ir al Detalle de la operación en Mercado Pago
A51: 132219492745 | B51: 0067A00479529 | C51: 45967 | D51: 52776656572 | E51: 2114560683290 | F51: Cargo por cobrar con Mercado Pago | G51: Si | J51: 39.12 | K51: Pago | L51: QR | M51: 71465208 | N51: Cerveza Träctor | P51: @2113574232 | Q51: 2400 | T51: Ir al Detalle de la operación en Mercado Pago
A52: 134688044850 | B52: 0067A00479529 | C52: 45982 | D52: 53518764498 | E52: 2127142876714 | F52: Cargo por cobrar con código QR | G52: Si | J52: 39.77 | K52: Pago | L52: QR | M52: 71465208 | N52: Cerveza Träctor | P52: GADEAA08 | Q52: 4100 | T52: Ir al Detalle de la operación en Mercado Pago
A53: 133750333812 | B53: 0067A00479529 | C53: 45974 | D53: 53141883594 | E53: 2120683939053 | F53: Cargo por cobrar con código QR | G53: Si | J53: 40.74 | K53: Pago | L53: QR | M53: 71465208 | N53: Cerveza Träctor | P53: BERO461725 | Q53: 4200 | T53: Ir al Detalle de la operación en Mercado Pago
A54: 133150727985 | B54: 0067A00479529 | C54: 45974 | D54: 53145231442 | E54: 2120746244303 | F54: Cargo por cobrar con código QR | G54: Si | J54: 40.74 | K54: Pago | L54: QR | M54: 71465208 | N54: Cerveza Träctor | P54: PAMO4713774 | Q54: 4200 | T54: Ir al Detalle de la operación en Mercado Pago
A55: 133151506989 | B55: 0067A00479529 | C55: 45974 | D55: 53145451752 | E55: 2120857184098 | F55: Cargo por cobrar con código QR | G55: Si | J55: 40.74 | K55: Pago | L55: QR | M55: 71465208 | N55: Cerveza Träctor | P55: FLORENCIA AZCURRAIN | Q55: 4200 | T55: Ir al Detalle de la operación en Mercado Pago
A56: 133157085969 | B56: 0067A00479529 | C56: 45974 | D56: 53147837412 | E56: 2120902603466 | F56: Cargo por cobrar con código QR | G56: Si | J56: 40.74 | K56: Pago | L56: QR | M56: 71465208 | N56: Cerveza Träctor | P56: BUER9448221 | Q56: 4200 | T56: Ir al Detalle de la operación en Mercado Pago
A57: 133771376694 | B57: 0067A00479529 | C57: 45975 | D57: 53150345737 | E57: 2120836866759 | F57: Cargo por cobrar con código QR | G57: Si | J57: 40.74 | K57: Pago | L57: QR | M57: 71465208 | N57: Cerveza Träctor | P57: REZZONICODYLAN20230210114005 | Q57: 4200 | T57: Ir al Detalle de la operación en Mercado Pago
A58: 133169921949 | B58: 0067A00479529 | C58: 45975 | D58: 53153112736 | E58: 2120901658229 | F58: Cargo por cobrar con código QR | G58: Si | J58: 40.74 | K58: Pago | L58: QR | M58: 71465208 | N58: Cerveza Träctor | P58: MLNGRSTNR | Q58: 4200 | T58: Ir al Detalle de la operación en Mercado Pago
A59: 133443554641 | B59: 0067A00479529 | C59: 45977 | D59: 53262085851 | E59: 2122663615051 | F59: Cargo por cobrar con código QR | G59: Si | J59: 40.74 | K59: Pago | L59: QR | M59: 71465208 | N59: Cerveza Träctor | P59: ORLANDOBURGUEZ | Q59: 4200 | T59: Ir al Detalle de la operación en Mercado Pago
A60: 134683532560 | B60: 0067A00479529 | C60: 45981 | D60: 53516654201 | E60: 2127111087942 | F60: Cargo por cobrar con código QR | G60: Si | J60: 40.74 | K60: Pago | L60: QR | M60: 71465208 | N60: Cerveza Träctor | P60: IMMA9507842 | Q60: 4200 | T60: Ir al Detalle de la operación en Mercado Pago
A61: 135705512058 | B61: 0067A00479529 | C61: 45989 | D61: 53925544318 | E61: 2133952268102 | F61: Cargo por uso de QR - Pagos Interoperables | G61: Si | J61: 40.74 | K61: Pago | L61: QR | M61: 71465208 | N61: Cerveza Träctor | P61: @2489718921 | Q61: 4200
A62: 131661892121 | B62: 0070A00444640 | C62: 45963 | D62: 52551653331 | E62: 2110774392806 | F62: Cargo por uso de QR - Pagos Interoperables | G62: Si | J62: 42.68 | K62: Pago | L62: QR | M62: 71465208 | N62: Cerveza Träctor | P62: @2489718921 | Q62: 4400
A63: 132218020663 | B63: 0067A00479529 | C63: 45967 | D63: 52775975853 | E63: 2114550119062 | F63: Cargo por cobrar con código QR | G63: Si | J63: 42.68 | K63: Pago | L63: QR | M63: 71465208 | N63: Cerveza Träctor | P63: CAMILATERENZIO | Q63: 4400 | T63: Ir al Detalle de la operación en Mercado Pago
A64: 133154053485 | B64: 0067A00479529 | C64: 45974 | D64: 53146587219 | E64: 2120771854121 | F64: Cargo por cobrar con código QR | G64: Si | J64: 42.68 | K64: Pago | L64: QR | M64: 71465208 | N64: Cerveza Träctor | P64: ALLU6531034 | Q64: 4400 | T64: Ir al Detalle de la operación en Mercado Pago
A65: 134070185481 | B65: 0067A00479529 | C65: 45982 | D65: 53516858541 | E65: 2127002749743 | F65: Cargo por cobrar con código QR | G65: Si | J65: 42.68 | K65: Pago | L65: QR | M65: 71465208 | N65: Cerveza Träctor | P65: SGLUSCHANCOFF | Q65: 4400 | T65: Ir al Detalle de la operación en Mercado Pago
A66: 134068831827 | B66: 0067A00479529 | C66: 45981 | D66: 53516363264 | E66: 2127106442684 | F66: Cargo por cobrar con código QR | G66: Si | J66: 43.65 | K66: Pago | L66: QR | M66: 71465208 | N66: Cerveza Träctor | P66: AUGUSTODLF | Q66: 4500 | T66: Ir al Detalle de la operación en Mercado Pago
A67: 132830428996 | B67: 0067A00479529 | C67: 45968 | D67: 52780747959 | E67: 2114623093152 | F67: Cargo por cobrar con código QR | G67: Si | J67: 44.62 | K67: Pago | L67: QR | M67: 71465208 | N67: Cerveza Träctor | P67: TISOCCOVALENTINO | Q67: 4600 | T67: Ir al Detalle de la operación en Mercado Pago
A68: 134925388232 | B68: 0067A00479529 | C68: 45983 | D68: 53611898097 | E68: 2128529921091 | F68: Cargo por cobrar con código QR | G68: Si | J68: 44.62 | K68: Pago | L68: QR | M68: 71465208 | N68: Cerveza Träctor | P68: DIONISIOALBERTOMARTINGAONA | Q68: 4600 | T68: Ir al Detalle de la operación en Mercado Pago
A69: 135543715956 | B69: 0067A00479529 | C69: 45989 | D69: 53859082066 | E69: 2132856673908 | F69: Cargo por uso de QR - Pagos Interoperables | G69: Si | J69: 44.62 | K69: Pago | L69: QR | M69: 71465208 | N69: Cerveza Träctor | P69: @2489718921 | Q69: 4600
A70: 134934981357 | B70: 0067A00479529 | C70: 45989 | D70: 53861602913 | E70: 2132802800699 | F70: Cargo por cobrar con código QR | G70: Si | J70: 44.62 | K70: Pago | L70: QR | M70: 71465208 | N70: Cerveza Träctor | P70: AUGUSTODLF | Q70: 4600 | T70: Ir al Detalle de la operación en Mercado Pago
A71: 132228951795 | B71: 0067A00479529 | C71: 45968 | D71: 52781033982 | E71: 2114531440493 | F71: Cargo por cobrar con código QR | G71: Si | J71: 45.59 | K71: Pago | L71: QR | M71: 71465208 | N71: Cerveza Träctor | P71: TRAMONTINEVELYN20220211133510 | Q71: 4700 | T71: Ir al Detalle de la operación en Mercado Pago
A72: 132248382236 | B72: 0070A00444640 | C72: 45963 | D72: 52546984847 | E72: 2110702053964 | F72: Cargo por cobrar con código QR | G72: Si | J72: 46.08 | K72: Pago | L72: QR | M72: 71465208 | N72: Cerveza Träctor | P72: VOTOPOPULAR777 | Q72: 4750 | T72: Ir al Detalle de la operación en Mercado Pago
A73: 131581842663 | B73: 0070A00444640 | C73: 45963 | D73: 52515933108 | E73: 2110278839938 | F73: Cargo por cobrar con código QR | G73: Si | J73: 46.56 | K73: Pago | L73: QR | M73: 71465208 | N73: Cerveza Träctor | P73: RODRIGUEZSANTINO20220219204257 | Q73: 4800 | T73: Ir al Detalle de la operación en Mercado Pago
A74: 132210557029 | B74: 0067A00479529 | C74: 45967 | D74: 52772865661 | E74: 2114501751436 | F74: Cargo por cobrar con código QR | G74: Si | J74: 46.56 | K74: Pago | L74: QR | M74: 71465208 | N74: Cerveza Träctor | P74: PRADOMARAEUGENIA | Q74: 4800 | T74: Ir al Detalle de la operación en Mercado Pago
A75: 132227464067 | B75: 0067A00479529 | C75: 45968 | D75: 52780432487 | E75: 2114514483749 | F75: Cargo por cobrar con código QR | G75: Si | J75: 46.56 | K75: Pago | L75: QR | M75: 71465208 | N75: Cerveza Träctor | P75: VALENTINAPVILLANUEVA | Q75: 4800 | T75: Ir al Detalle de la operación en Mercado Pago
A76: 132830694270 | B76: 0067A00479529 | C76: 45968 | D76: 52780806434 | E76: 2114524641195 | F76: Cargo por cobrar con código QR | G76: Si | J76: 46.56 | K76: Pago | L76: QR | M76: 71465208 | N76: Cerveza Träctor | P76: DYLANMASSART | Q76: 4800 | T76: Ir al Detalle de la operación en Mercado Pago
A77: 132830714560 | B77: 0067A00479529 | C77: 45968 | D77: 52780854412 | E77: 2114525196457 | F77: Cargo por cobrar con código QR | G77: Si | J77: 46.56 | K77: Pago | L77: QR | M77: 71465208 | N77: Cerveza Träctor | P77: ENZOAFERNANDEZ | Q77: 4800 | T77: Ir al Detalle de la operación en Mercado Pago
A78: 132969991272 | B78: 0067A00479529 | C78: 45968 | D78: 52829984767 | E78: 2115458236613 | F78: Cargo por cobrar con código QR | G78: Si | J78: 46.56 | K78: Pago | L78: QR | M78: 71465208 | N78: Cerveza Träctor | P78: TROYA INDUSPORT | Q78: 4800 | T78: Ir al Detalle de la operación en Mercado Pago
A79: 133113160714 | B79: 0067A00479529 | C79: 45970 | D79: 52887471986 | E79: 2116342803275 | F79: Cargo por cobrar con código QR | G79: Si | J79: 46.56 | K79: Pago | L79: QR | M79: 71465208 | N79: Cerveza Träctor | P79: GONZLEZVANESA14 | Q79: 4800 | T79: Ir al Detalle de la operación en Mercado Pago
A80: 133189773476 | B80: 0067A00479529 | C80: 45970 | D80: 52921336342 | E80: 2116819743263 | F80: Cargo por cobrar con código QR | G80: Si | J80: 46.56 | K80: Pago | L80: QR | M80: 71465208 | N80: Cerveza Träctor | P80: LEFL2900826 | Q80: 4800 | T80: Ir al Detalle de la operación en Mercado Pago
A81: 133026993843 | B81: 0067A00479529 | C81: 45974 | D81: 53097843629 | E81: 2119997498872 | F81: Cargo por uso de QR - Pagos Interoperables | G81: Si | J81: 46.56 | K81: Pago | L81: QR | M81: 71465208 | N81: Cerveza Träctor | P81: @2489718921 | Q81: 4800
A82: 133770577278 | B82: 0067A00479529 | C82: 45974 | D82: 53149988825 | E82: 2120938477380 | F82: Cargo por cobrar con código QR | G82: Si | J82: 46.56 | K82: Pago | L82: QR | M82: 71465208 | N82: Cerveza Träctor | P82: BUSSONMILAGROS20220505164307 | Q82: 4800 | T82: Ir al Detalle de la operación en Mercado Pago
A83: 133773103680 | B83: 0067A00479529 | C83: 45975 | D83: 53151144276 | E83: 2120850028833 | F83: Cargo por cobrar con código QR | G83: Si | J83: 46.56 | K83: Pago | L83: QR | M83: 71465208 | N83: Cerveza Träctor | P83: ROUDEMARISA20210810162506 | Q83: 4800 | T83: Ir al Detalle de la operación en Mercado Pago
A84: 133167536367 | B84: 0067A00479529 | C84: 45975 | D84: 53152130783 | E84: 2120871867031 | F84: Cargo por cobrar con código QR | G84: Si | J84: 46.56 | K84: Pago | L84: QR | M84: 71465208 | N84: Cerveza Träctor | P84: PUTALLAZJUSTINA20230801181701 | Q84: 4800 | T84: Ir al Detalle de la operación en Mercado Pago
A85: 133167698681 | B85: 0067A00479529 | C85: 45975 | D85: 53152223349 | E85: 2120980870210 | F85: Cargo por cobrar con código QR | G85: Si | J85: 46.56 | K85: Pago | L85: QR | M85: 71465208 | N85: Cerveza Träctor | P85: MENESCAARTON | Q85: 4800 | T85: Ir al Detalle de la operación en Mercado Pago
A86: 133776882346 | B86: 0067A00479529 | C86: 45975 | D86: 53152497667 | E86: 2120988693478 | F86: Cargo por cobrar con código QR | G86: Si | J86: 46.56 | K86: Pago | L86: QR | M86: 71465208 | N86: Cerveza Träctor | P86: BUSSONMILAGROS20220505164307 | Q86: 4800 | T86: Ir al Detalle de la operación en Mercado Pago
A87: 133777709392 | B87: 0067A00479529 | C87: 45975 | D87: 53152859685 | E87: 2120893960557 | F87: Cargo por uso de QR - Pagos Interoperables | G87: Si | J87: 46.56 | K87: Pago | L87: QR | M87: 71465208 | N87: Cerveza Träctor | P87: @2489718921 | Q87: 4800
A88: 133169808981 | B88: 0067A00479529 | C88: 45975 | D88: 53153017760 | E88: 2120898029017 | F88: Cargo por cobrar con código QR | G88: Si | J88: 46.56 | K88: Pago | L88: QR | M88: 71465208 | N88: Cerveza Träctor | P88: BENJAMIKROLLS | Q88: 4800 | T88: Ir al Detalle de la operación en Mercado Pago
A89: 133434016937 | B89: 0067A00479529 | C89: 45976 | D89: 53257812036 | E89: 2122713658874 | F89: Cargo por cobrar con código QR | G89: Si | J89: 46.56 | K89: Pago | L89: QR | M89: 71465208 | N89: Cerveza Träctor | P89: NWILLAT | Q89: 4800 | T89: Ir al Detalle de la operación en Mercado Pago
A90: 134046455234 | B90: 0067A00479529 | C90: 45976 | D90: 53259247279 | E90: 2122735254040 | F90: Cargo por cobrar con código QR | G90: Si | J90: 46.56 | K90: Pago | L90: QR | M90: 71465208 | N90: Cerveza Träctor | P90: LUZBRISA20220504130346 | Q90: 4800 | T90: Ir al Detalle de la operación en Mercado Pago
A91: 134052241544 | B91: 0067A00479529 | C91: 45977 | D91: 53262064529 | E91: 2122770202626 | F91: Cargo por cobrar con código QR | G91: Si | J91: 46.56 | K91: Pago | L91: QR | M91: 71465208 | N91: Cerveza Träctor | P91: LOGKAREN3 | Q91: 4800 | T91: Ir al Detalle de la operación en Mercado Pago
A92: 134533479704 | B92: 0067A00479529 | C92: 45980 | D92: 53461759855 | E92: 2125968383601 | F92: Cargo por cobrar con código QR | G92: Si | J92: 46.56 | K92: Pago | L92: QR | M92: 71465208 | N92: Cerveza Träctor | P92: JUANFOLMERD1 | Q92: 4800 | T92: Ir al Detalle de la operación en Mercado Pago
A93: 134550806112 | B93: 0067A00479529 | C93: 45981 | D93: 53468450450 | E93: 2126096906671 | F93: Cargo por cobrar con código QR | G93: Si | J93: 46.56 | K93: Pago | L93: QR | M93: 71465208 | N93: Cerveza Träctor | P93: DONATOMATIAS20230211035034 | Q93: 4800 | T93: Ir al Detalle de la operación en Mercado Pago
A94: 134552251236 | B94: 0067A00479529 | C94: 45981 | D94: 53469243992 | E94: 2126111464485 | F94: Cargo por cobrar con código QR | G94: Si | J94: 46.56 | K94: Pago | L94: QR | M94: 71465208 | N94: Cerveza Träctor | P94: ALJU6086722 | Q94: 4800 | T94: Ir al Detalle de la operación en Mercado Pago
A95: 134554700444 | B95: 0067A00479529 | C95: 45981 | D95: 53469914703 | E95: 2126236786800 | F95: Cargo por cobrar con código QR | G95: Si | J95: 46.56 | K95: Pago | L95: QR | M95: 71465208 | N95: Cerveza Träctor | P95: DONATOMATIAS20230211035034 | Q95: 4800 | T95: Ir al Detalle de la operación en Mercado Pago
A96: 134685423332 | B96: 0067A00479529 | C96: 45982 | D96: 53517468797 | E96: 2127123207924 | F96: Cargo por cobrar con código QR | G96: Si | J96: 46.56 | K96: Pago | L96: QR | M96: 71465208 | N96: Cerveza Träctor | P96: SOTELOROCIO20220225184917 | Q96: 4800 | T96: Ir al Detalle de la operación en Mercado Pago
A97: 134072498127 | B97: 0067A00479529 | C97: 45982 | D97: 53517820692 | E97: 2127017004255 | F97: Cargo por cobrar con código QR | G97: Si | J97: 46.56 | K97: Pago | L97: QR | M97: 71465208 | N97: Cerveza Träctor | P97: CAIREANTONELLA | Q97: 4800 | T97: Ir al Detalle de la operación en Mercado Pago
A98: 134075280711 | B98: 0067A00479529 | C98: 45982 | D98: 53519011536 | E98: 2127148088638 | F98: Cargo por cobrar con código QR | G98: Si | J98: 46.56 | K98: Pago | L98: QR | M98: 71465208 | N98: Cerveza Träctor | P98: LLSA978645 | Q98: 4800 | T98: Ir al Detalle de la operación en Mercado Pago
A99: 134688993316 | B99: 0067A00479529 | C99: 45982 | D99: 53519073889 | E99: 2127039122911 | F99: Cargo por cobrar con código QR | G99: Si | J99: 46.56 | K99: Pago | L99: QR | M99: 71465208 | N99: Cerveza Träctor | P99: MARIAPAULABOZZOLO | Q99: 4800 | T99: Ir al Detalle de la operación en Mercado Pago
A100: 134308000199 | B100: 0067A00479529 | C100: 45983 | D100: 53610786160 | E100: 2128510934775 | F100: Cargo por uso de QR - Pagos Interoperables | G100: Si | J100: 46.56 | K100: Pago | L100: QR | M100: 71465208 | N100: Cerveza Träctor | P100: @2489718921 | Q100: 4800
A101: 134394715405 | B101: 0067A00479529 | C101: 45984 | D101: 53648238828 | E101: 2129052652171 | F101: Cargo por cobrar con código QR | G101: Si | J101: 46.56 | K101: Pago | L101: QR | M101: 71465208 | N101: Cerveza Träctor | P101: BMXVALE539 | Q101: 4800 | T101: Ir al Detalle de la operación en Mercado Pago
A102: 135534884148 | B102: 0067A00479529 | C102: 45988 | D102: 53854597687 | E102: 2132787712128 | F102: Cargo por cobrar con código QR | G102: Si | J102: 46.56 | K102: Pago | L102: QR | M102: 71465208 | N102: Cerveza Träctor | P102: BLANCCELINA20230706095544 | Q102: 4800 | T102: Ir al Detalle de la operación en Mercado Pago
A103: 135543125902 | B103: 0067A00479529 | C103: 45989 | D103: 53858803071 | E103: 2132732525511 | F103: Cargo por cobrar con código QR | G103: Si | J103: 46.56 | K103: Pago | L103: QR | M103: 71465208 | N103: Cerveza Träctor | P103: BARDISAAGUSTINA20230601114330 | Q103: 4800 | T103: Ir al Detalle de la operación en Mercado Pago
A104: 134931207185 | B104: 0067A00479529 | C104: 45989 | D104: 53860279686 | E104: 2132880110620 | F104: Cargo por cobrar con código QR | G104: Si | J104: 46.56 | K104: Pago | L104: QR | M104: 71465208 | N104: Cerveza Träctor | P104: CARABALLOMATIAS20221101124943 | Q104: 4800 | T104: Ir al Detalle de la operación en Mercado Pago
...

Sheet IDC
A1: Reporte-Retención-Impuesto-sobre-los-Créditos-y-Débitos-Noviembre-CC20250609171159-MercadoPago
A3: Usuario: | B3: CC20250609171159
A4: Impuesto: | B4: Impuesto sobre los Créditos y Débitos
A5: Fecha de descarga: | B5: 18/03/2026
A6: Intervalo de fechas consultadas: | B6: 01/11/2025 a 01/12/2025
A8: Total | B8: Monto
A9: Base imponible | B9: $57.152.697,17
A10: Importe retenido | B10: $342.916,10
A11: Importe devuelto | B11: $47,40
A13: Encuentra los movimientos de dinero en tu cuenta de Mercado Pago, en informes de balance.
A15: Este impuesto se aplica cada vez que hagas operaciones con terceros.
A16: Podrás conciliar la información con otros reportes de Mercado Libre. | D16: Podrás buscar el detalle de lo retenido en tu operación en la sección Actividad.
A18: Operación | E18: Impuesto
A19: Número de operación | B19: Número de venta - Referencia externa | C19: Fecha de operación | D19: Tipo | E19: Fecha de retención | F19: Alícuota | G19: Base imponible | H19: Importe retenido
A20: 00077lbts9 | C20: 27/11/2025 | D20: Transacción | E20: 27/11/2025 | F20: 0,60 % | G20: 208510 | H20: 1251.06
A21: 000750gp1b | C21: 24/11/2025 | D21: Transacción | E21: 24/11/2025 | F21: 0,60 % | G21: 6000 | H21: 36
A22: 00074lv99g | C22: 24/11/2025 | D22: Transacción | E22: 24/11/2025 | F22: 0,60 % | G22: 15000 | H22: 90
A23: 00074l8atq | C23: 24/11/2025 | D23: Transacción | E23: 24/11/2025 | F23: 0,60 % | G23: 6000 | H23: 36
A24: 00074ky2u4 | C24: 23/11/2025 | D24: Transacción | E24: 24/11/2025 | F24: 0,60 % | G24: 10000 | H24: 60
A25: 00074kpdm6 | C25: 23/11/2025 | D25: Transacción | E25: 24/11/2025 | F25: 0,60 % | G25: 10000 | H25: 60
A26: 00074dbutz | C26: 23/11/2025 | D26: Transacción | E26: 23/11/2025 | F26: 0,60 % | G26: 10000 | H26: 60
A27: 00074dad5n | C27: 23/11/2025 | D27: Transacción | E27: 23/11/2025 | F27: 0,60 % | G27: 5000 | H27: 30
A28: 00074d970v | C28: 23/11/2025 | D28: Transacción | E28: 23/11/2025 | F28: 0,60 % | G28: 5000 | H28: 30
A29: 00074d6333 | C29: 23/11/2025 | D29: Transacción | E29: 23/11/2025 | F29: 0,60 % | G29: 5000 | H29: 30
A30: 00074d1jvf | C30: 23/11/2025 | D30: Transacción | E30: 23/11/2025 | F30: 0,60 % | G30: 10000 | H30: 60
A31: 00074cxson | C31: 23/11/2025 | D31: Transacción | E31: 23/11/2025 | F31: 0,60 % | G31: 15000 | H31: 90
... A76: 0006upse3j | C76: 11/11/2025 | D76: Transacción | E76: 11/11/2025 | F76: 0,60 % | G76: 598000 | H76: 3588
A77: 0006u7n3o1 | B77: MELIPAYMENTS-COLLECTIONATTEMPT-24886498202025-11-05T03:13:22.708367987 | C77: 11/11/2025 | D77: Transacción | E77: 11/11/2025 | F77: 0,60 % | G77: 29235.36 | H77: 175.41
A78: 0006sne3bh | C78: 09/11/2025 | D78: Transacción | E78: 09/11/2025 | F78: 0,60 % | G78: 2278811.8 | H78: 13672.87
A79: 0006pxnuzr | C79: 06/11/2025 | D79: Transacción | E79: 06/11/2025 | F79: 0,60 % | G79: 117222.02 | H79: 703.33
A80: 0006oq9urp | C80: 04/11/2025 | D80: Transacción | E80: 04/11/2025 | F80: 0,60 % | G80: 21700.01 | H80: 130.2
A81: 0006oq7i0r | C81: 04/11/2025 | D81: Transacción | E81: 04/11/2025 | F81: 0,60 % | G81: 33750 | H81: 202.5
A82: 0006oowjax | C82: 04/11/2025 | D82: Transacción | E82: 04/11/2025 | F82: 0,60 % | G82: 150057 | H82: 900.34
A83: 0006oovf5l | C83: 04/11/2025 | D83: Transacción | E83: 04/11/2025 | F83: 0,60 % | G83: 272824 | H83: 1636.94
A84: 0006obxog6 | C84: 04/11/2025 | D84: Transacción | E84: 04/11/2025 | F84: 0,60 % | G84: 35099.99 | H84: 210.6
A85: 0006oaxrsk | C85: 04/11/2025 | D85: Transacción | E85: 04/11/2025 | F85: 0,60 % | G85: 1320780 | H85: 7924.68
A86: 0006oarz2g | C86: 04/11/2025 | D86: Transacción | E86: 04/11/2025 | F86: 0,60 % | G86: 136470 | H86: 818.82
A87: 0006oakgg8 | C87: 04/11/2025 | D87: Transacción | E87: 04/11/2025 | F87: 0,60 % | G87: 188294 | H87: 1129.76
A88: 0006oajfr2 | C88: 04/11/2025 | D88: Transacción | E88: 04/11/2025 | F88: 0,60 % | G88: 124181 | H88: 745.09
A89: 0006mhaykd | C89: 01/11/2025 | D89: Transacción | E89: 01/11/2025 | F89: 0,60 % | G89: 116000 | H89: 696
A90: 135944921672 | C90: 30/11/2025 | D90: Transacción | E90: 30/11/2025 | F90: 0,60 % | G90: 60900 | H90: 365.4
A91: 135944746702 | B91: tips-135328594423 | C91: 30/11/2025 | D91: Transacción | E91: 30/11/2025 | F91: 0,60 % | G91: 1840 | H91: 11.04
A92: 135943070818 | C92: 30/11/2025 | D92: Transacción | E92: 30/11/2025 | F92: 0,60 % | G92: 29800 | H92: 178.8
A93: 135942234542 | C93: 30/11/2025 | D93: Transacción | E93: 30/11/2025 | F93: 0,60 % | G93: 33900 | H93: 203.4
A94: 135941093414 | C94: 30/11/2025 | D94: Transacción | E94: 30/11/2025 | F94: 0,60 % | G94: 33300 | H94: 199.8
A95: 135940566342 | C95: 30/11/2025 | D95: Transacción | E95: 30/11/2025 | F95: 0,60 % | G95: 23800 | H95: 142.8
A96: 135939437774 | B96: Venta presencial | C96: 30/11/2025 | D96: Transacción | E96: 30/11/2025 | F96: 0,60 % | G96: 46000 | H96: 276
A97: 135939329734 | C97: 30/11/2025 | D97: Transacción | E97: 30/11/2025 | F97: 0,60 % | G97: 21900 | H97: 131.4
A98: 135939172708 | C98: 30/11/2025 | D98: Transacción | E98: 30/11/2025 | F98: 0,60 % | G98: 27900 | H98: 167.4
A99: 135938762800 | B99: Venta presencial | C99: 30/11/2025 | D99: Transacción | E99: 30/11/2025 | F99: 0,60 % | G99: 21300 | H99: 127.8
A100: 135938000902 | B100: Venta presencial | C100: 30/11/2025 | D100: Transacción | E100: 30/11/2025 | F100: 0,60 % | G100: 39400 | H100: 236.4
A101: 135937007864 | C101: 30/11/2025 | D101: Transacción | E101: 30/11/2025 | F101: 0,60 % | G101: 8000 | H101: 48
A102: 135935632516 | B102: Venta presencial | C102: 30/11/2025 | D102: Transacción | E102: 30/11/2025 | F102: 0,60 % | G102: 27400 | H102: 164.4
A103: 135935450296 | C103: 30/11/2025 | D103: Transacción | E103: 30/11/2025 | F103: 0,60 % | G103: 29800 | H103: 178.8
A104: 135934861598 | B104: Venta presencial | C104: 30/11/2025 | D104: Transacción | E104: 30/11/2025 | F104: 0,60 % | G104: 32100 | H104: 192.6
A105: 135934814272 | C105: 30/11/2025 | D105: Transacción | E105: 30/11/2025 | F105: 0,60 % | G105: 31700 | H105: 190.2
A106: 135932193190 | B106: tips-135316062999 | C106: 30/11/2025 | D106: Transacción | E106: 30/11/2025 | F106: 0,60 % | G106: 3980 | H106: 23.88
A107: 135930993778 | C107: 30/11/2025 | D107: Transacción | E107: 30/11/2025 | F107: 0,60 % | G107: 24800 | H107: 148.8
A108: 135930672462 | B108: tips-135930584980 | C108: 30/11/2025 | D108: Transacción | E108: 30/11/2025 | F108: 0,60 % | G108: 820 | H108: 4.92
A109: 135930584980 | C109: 30/11/2025 | D109: Transacción | E109: 30/11/2025 | F109: 0,60 % | G109: 16400 | H109: 98.4
A110: 135930158102 | B110: tips-135929957250 | C110: 30/11/2025 | D110: Transacción | E110: 30/11/2025 | F110: 0,60 % | G110: 840 | H110: 5.04
A111: 135929957250 | C111: 30/11/2025 | D111: Transacción | E111: 30/11/2025 | F111: 0,60 % | G111: 8400 | H111: 50.4
A112: 135929279262 | B112: tips-135929233448 | C112: 30/11/2025 | D112: Transacción | E112: 30/11/2025 | F112: 0,60 % | G112: 1452 | H112: 8.71
A113: 135929233448 | C113: 30/11/2025 | D113: Transacción | E113: 30/11/2025 | F113: 0,60 % | G113: 29050 | H113: 174.3
A114: 135925457670 | B114: Venta presencial | C114: 30/11/2025 | D114: Transacción | E114: 30/11/2025 | F114: 0,60 % | G114: 9800 | H114: 58.8
A115: 135924260328 | B115: Venta presencial | C115: 30/11/2025 | D115: Transacción | E115: 30/11/2025 | F115: 0,60 % | G115: 4900 | H115: 29.4
A116: 135850028136 | C116: 30/11/2025 | D116: Transacción | E116: 30/11/2025 | F116: 0,60 % | G116: 30600 | H116: 183.6
A117: 135849987232 | C117: 30/11/2025 | D117: Transacción | E117: 30/11/2025 | F117: 0,60 % | G117: 48400 | H117: 290.4
A118: 135849912440 | C118: 30/11/2025 | D118: Transacción | E118: 30/11/2025 | F118: 0,60 % | G118: 64200 | H118: 385.2
A119: 135849875202 | C119: 30/11/2025 | D119: Transacción | E119: 30/11/2025 | F119: 0,60 % | G119: 10100 | H119: 60.6
A120: 135849280792 | B120: tips-135849189542 | C120: 30/11/2025 | D120: Transacción | E120: 30/11/2025 | F120: 0,60 % | G120: 480 | H120: 2.88
A121: 135849189542 | C121: 30/11/2025 | D121: Transacción | E121: 30/11/2025 | F121: 0,60 % | G121: 9600 | H121: 57.6
A122: 135848973616 | C122: 30/11/2025 | D122: Transacción | E122: 30/11/2025 | F122: 0,60 % | G122: 24500 | H122: 147
A123: 135848599550 | B123: tips-135848579690 | C123: 30/11/2025 | D123: Transacción | E123: 30/11/2025 | F123: 0,60 % | G123: 2475 | H123: 14.85
A124: 135848579882 | C124: 30/11/2025 | D124: Transacción | E124: 30/11/2025 | F124: 0,60 % | G124: 16500 | H124: 99
A125: 135848579690 | C125: 30/11/2025 | D125: Transacción | E125: 30/11/2025 | F125: 0,60 % | G125: 16500 | H125: 99
A126: 135848575872 | B126: tips-135848579882 | C126: 30/11/2025 | D126: Transacción | E126: 30/11/2025 | F126: 0,60 % | G126: 825 | H126: 4.95
A127: 135848564258 | C127: 30/11/2025 | D127: Transacción | E127: 30/11/2025 | F127: 0,60 % | G127: 46400 | H127: 278.4
A128: 135847547580 | C128: 30/11/2025 | D128: Transacción | E128: 30/11/2025 | F128: 0,60 % | G128: 45500 | H128: 273
A129: 135846565348 | C129: 30/11/2025 | D129: Transacción | E129: 30/11/2025 | F129: 0,60 % | G129: 11000 | H129: 66
A130: 135846050946 | B130: Venta presencial | C130: 30/11/2025 | D130: Transacción | E130: 30/11/2025 | F130: 0,60 % | G130: 51100 | H130: 306.6
A131: 135844406772 | B131: tips-135228286279 | C131: 29/11/2025 | D131: Transacción | E131: 30/11/2025 | F131: 0,60 % | G131: 1065 | H131: 6.39
A132: 135844253222 | B132: Venta presencial | C132: 29/11/2025 | D132: Transacción | E132: 30/11/2025 | F132: 0,60 % | G132: 29700 | H132: 178.2
A133: 135844214656 | C133: 29/11/2025 | D133: Transacción | E133: 30/11/2025 | F133: 0,60 % | G133: 9000 | H133: 54
A134: 135842753022 | B134: Venta presencial | C134: 29/11/2025 | D134: Transacción | E134: 30/11/2025 | F134: 0,60 % | G134: 209500 | H134: 1257
A135: 135842306594 | C135: 29/11/2025 | D135: Transacción | E135: 30/11/2025 | F135: 0,60 % | G135: 9800 | H135: 58.8
A136: 135842036548 | C136: 29/11/2025 | D136: Transacción | E136: 30/11/2025 | F136: 0,60 % | G136: 5300 | H136: 31.8
A137: 135840314684 | C137: 29/11/2025 | D137: Transacción | E137: 29/11/2025 | F137: 0,60 % | G137: 21400 | H137: 128.4
A138: 135839764636 | B138: tips-135839746818 | C138: 29/11/2025 | D138: Transacción | E138: 29/11/2025 | F138: 0,60 % | G138: 2595 | H138: 15.57
A139: 135839746818 | C139: 29/11/2025 | D139: Transacción | E139: 29/11/2025 | F139: 0,60 % | G139: 51900 | H139: 311.4
A140: 135837965834 | C140: 29/11/2025 | D140: Transacción | E140: 29/11/2025 | F140: 0,60 % | G140: 4800 | H140: 28.8
A141: 135836249112 | C141: 29/11/2025 | D141: Transacción | E141: 29/11/2025 | F141: 0,60 % | G141: 44100 | H141: 264.6
A142: 135835120438 | B142: Venta presencial | C142: 29/11/2025 | D142: Transacción | E142: 29/11/2025 | F142: 0,60 % | G142: 47300 | H142: 283.8
A143: 135831963930 | C143: 29/11/2025 | D143: Transacción | E143: 29/11/2025 | F143: 0,60 % | G143: 15400 | H143: 92.4
A144: 135829030854 | C144: 29/11/2025 | D144: Transacción | E144: 29/11/2025 | F144: 0,60 % | G144: 34500 | H144: 207
A145: 135826499470 | B145: Venta presencial | C145: 29/11/2025 | D145: Transacción | E145: 29/11/2025 | F145: 0,60 % | G145: 9600 | H145: 57.6
A146: 135826289986 | C146: 29/11/2025 | D146: Transacción | E146: 29/11/2025 | F146: 0,60 % | G146: 12700 | H146: 76.2
A147: 135818197928 | C147: 29/11/2025 | D147: Transacción | E147: 29/11/2025 | F147: 0,60 % | G147: 20300 | H147: 121.8
A148: 135817909476 | B148: Venta presencial | C148: 29/11/2025 | D148: Transacción | E148: 29/11/2025 | F148: 0,60 % | G148: 9800 | H148: 58.8
A149: 135816135810 | C149: 29/11/2025 | D149: Transacción | E149: 29/11/2025 | F149: 0,60 % | G149: 9800 | H149: 58.8
...

Sheet Hoja2
F2: 47.4 | G2: -47.4 | H2: =+F2+G2 -> 0 | K2: -128.77 | L2: =+J2+K2 -> -128.77
F3: -0.01 | G3: 0.01 | H3: =+F3+G3 -> 0 | J3: -0.24 | K3: 0.24 | L3: =+J3+K3 -> 0
F4: -0.15 | G4: 0.15 | H4: =+F4+G4 -> 0 | J4: -0.38 | K4: 0.38 | L4: =+J4+K4 -> 0
F5: -0.24 | G5: 0.24 | H5: =+F5+G5 -> 0 | J5: -0.96 | K5: 0.96 | L5: =+J5+K5 -> 0
F6: -0.59 | G6: 0.59 | H6: =+F6+G6 -> 0 | J6: -4.85 | K6: 4.85 | L6: =+J6+K6 -> 0
F7: -1.14 | G7: 1.14 | H7: =+F7+G7 -> 0 | J7: -7.91 | K7: 7.91 | L7: =+J7+K7 -> 0
F8: -1.26 | G8: 1.26 | H8: =+F8+G8 -> 0 | J8: -9.7 | K8: 9.7 | L8: =+J8+K8 -> 0
F9: -1.32 | G9: 1.32 | H9: =+F9+G9 -> 0 | J9: -9.7 | K9: 9.7 | L9: =+J9+K9 -> 0
F10: -1.42 | G10: 1.42 | H10: =+F10+G10 -> 0 | J10: -9.7 | K10: 9.7 | L10: =+J10+K10 -> 0
F11: -1.44 | G11: 1.44 | H11: =+F11+G11 -> 0 | J11: -9.7 | K11: 9.7 | L11: =+J11+K11 -> 0
F12: -1.44 | G12: 1.44 | H12: =+F12+G12 -> 0 | J12: -9.7 | K12: 9.7 | L12: =+J12+K12 -> 0
F13: -1.44 | G13: 1.44 | H13: =+F13+G13 -> 0 | J13: -9.7 | K13: 9.7 | L13: =+J13+K13 -> 0
F14: -1.44 | G14: 1.44 | H14: =+F14+G14 -> 0 | J14: -19.4 | K14: 19.4 | L14: =+J14+K14 -> 0
... F43: -2.7 | G43: 2.7 | H43: =+F43+G43 -> 0 | J43: -38.8 | K43: 38.8 | L43: =+J43+K43 -> 0
F44: -2.73 | G44: 2.73 | H44: =+F44+G44 -> 0 | K44: 38.8 | L44: =+J44+K44 -> 38.8
F45: -2.76 | G45: 2.76 | H45: =+F45+G45 -> 0 | J45: -39.12 | K45: 39.12 | L45: =+J45+K45 -> 0
F46: -2.85 | G46: 2.85 | H46: =+F46+G46 -> 0 | J46: -39.77 | K46: 39.77 | L46: =+J46+K46 -> 0
F47: -2.88 | G47: 2.88 | H47: =+F47+G47 -> 0 | J47: -40.74 | K47: 40.74 | L47: =+J47+K47 -> 0
F48: -2.88 | G48: 2.88 | H48: =+F48+G48 -> 0 | J48: -40.74 | K48: 40.74 | L48: =+J48+K48 -> 0
F49: -2.88 | G49: 2.88 | H49: =+F49+G49 -> 0 | J49: -40.74 | K49: 40.74 | L49: =+J49+K49 -> 0
F50: -2.88 | G50: 2.88 | H50: =+F50+G50 -> 0 | J50: -40.74 | K50: 40.74 | L50: =+J50+K50 -> 0
F51: -2.88 | G51: 2.88 | H51: =+F51+G51 -> 0 | J51: -40.74 | K51: 40.74 | L51: =+J51+K51 -> 0
F52: -2.91 | G52: 2.91 | H52: =+F52+G52 -> 0 | J52: -40.74 | K52: 40.74 | L52: =+J52+K52 -> 0
F53: -3 | G53: 3 | H53: =+F53+G53 -> 0 | J53: -40.74 | K53: 40.74 | L53: =+J53+K53 -> 0
F54: -3 | G54: 3 | H54: =+F54+G54 -> 0 | J54: -40.74 | K54: 40.74 | L54: =+J54+K54 -> 0
F55: -3 | G55: 3 | H55: =+F55+G55 -> 0 | J55: -40.74 | K55: 40.74 | L55: =+J55+K55 -> 0
F56: -3 | G56: 3 | H56: =+F56+G56 -> 0 | J56: -42.68 | K56: 42.68 | L56: =+J56+K56 -> 0
... F121: -7.35 | G121: 7.35 | H121: =+F121+G121 -> 0 | J121: -47.53 | K121: 47.53 | L121: =+J121+K121 -> 0
F122: -7.35 | G122: 7.35 | H122: =+F122+G122 -> 0 | K122: 47.53 | L122: =+J122+K122 -> 47.53
F123: -7.38 | G123: 7.38 | H123: =+F123+G123 -> 0 | J123: -48.5 | K123: 48.5 | L123: =+J123+K123 -> 0
F124: -7.74 | G124: 7.74 | H124: =+F124+G124 -> 0 | J124: -48.5 | K124: 48.5 | L124: =+J124+K124 -> 0
F125: -7.8 | G125: 7.8 | H125: =+F125+G125 -> 0 | J125: -48.5 | K125: 48.5 | L125: =+J125+K125 -> 0
F126: -7.86 | G126: 7.86 | H126: =+F126+G126 -> 0 | J126: -48.5 | K126: 48.5 | L126: =+J126+K126 -> 0
F127: -7.89 | G127: 7.89 | H127: =+F127+G127 -> 0 | J127: -48.5 | K127: 48.5 | L127: =+J127+K127 -> 0
F128: -7.92 | G128: 7.92 | H128: =+F128+G128 -> 0 | J128: -48.5 | K128: 48.5 | L128: =+J128+K128 -> 0
F129: -7.98 | G129: 7.98 | H129: =+F129+G129 -> 0 | J129: -48.5 | K129: 48.5 | L129: =+J129+K129 -> 0
F130: -8.04 | G130: 8.04 | H130: =+F130+G130 -> 0 | J130: -48.5 | K130: 48.5 | L130: =+J130+K130 -> 0
F131: -8.22 | G131: 8.22 | H131: =+F131+G131 -> 0 | J131: -48.5 | K131: 48.5 | L131: =+J131+K131 -> 0
F132: -8.28 | G132: 8.28 | H132: =+F132+G132 -> 0 | J132: -48.5 | K132: 48.5 | L132: =+J132+K132 -> 0
F133: -8.28 | G133: 8.28 | H133: =+F133+G133 -> 0 | J133: -48.5 | K133: 48.5 | L133: =+J133+K133 -> 0
F134: -8.34 | G134: 8.34 | H134: =+F134+G134 -> 0 | J134: -48.5 | K134: 48.5 | L134: =+J134+K134 -> 0
... F961: -57.6 | G961: 57.6 | H961: =+F961+G961 -> 0 | J961: -139.68 | K961: 139.68 | L961: =+J961+K961 -> 0
F962: -57.6 | G962: 57.6 | H962: =+F962+G962 -> 0 | K962: 139.68 | L962: =+J962+K962 -> 139.68
F963: -57.6 | G963: 57.6 | H963: =+F963+G963 -> 0 | J963: -140.18 | K963: 140.18 | L963: =+J963+K963 -> 0
F964: -57.6 | G964: 57.6 | H964: =+F964+G964 -> 0 | J964: -140.65 | K964: 140.65 | L964: =+J964+K964 -> 0
F965: -57.6 | G965: 57.6 | H965: =+F965+G965 -> 0 | J965: -141.62 | K965: 141.62 | L965: =+J965+K965 -> 0
F966: -57.6 | G966: 57.6 | H966: =+F966+G966 -> 0 | J966: -141.62 | K966: 141.62 | L966: =+J966+K966 -> 0
F967: -57.6 | G967: 57.6 | H967: =+F967+G967 -> 0 | J967: -142.59 | K967: 142.59 | L967: =+J967+K967 -> 0
F968: -57.6 | G968: 57.6 | H968: =+F968+G968 -> 0 | J968: -143.56 | K968: 143.56 | L968: =+J968+K968 -> 0
F969: -57.6 | G969: 57.6 | H969: =+F969+G969 -> 0 | J969: -143.56 | K969: 143.56 | L969: =+J969+K969 -> 0
F970: -57.6 | G970: 57.6 | H970: =+F970+G970 -> 0 | J970: -143.56 | K970: 143.56 | L970: =+J970+K970 -> 0
F971: -57.6 | G971: 57.6 | H971: =+F971+G971 -> 0 | J971: -145.5 | K971: 145.5 | L971: =+J971+K971 -> 0
F972: -57.6 | G972: 57.6 | H972: =+F972+G972 -> 0 | J972: -145.5 | K972: 145.5 | L972: =+J972+K972 -> 0
F973: -57.6 | G973: 57.6 | H973: =+F973+G973 -> 0 | J973: -145.5 | K973: 145.5 | L973: =+J973+K973 -> 0
F974: -57.6 | G974: 57.6 | H974: =+F974+G974 -> 0 | J974: -145.5 | K974: 145.5 | L974: =+J974+K974 -> 0
... F1056: -60 | G1056: 60 | H1056: =+F1056+G1056 -> 0 | J1056: -160.05 | K1056: 160.05 | L1056: =+J1056+K1056 -> 0
F1057: -60 | G1057: 60 | H1057: =+F1057+G1057 -> 0 | K1057: 160.05 | L1057: =+J1057+K1057 -> 160.05
F1058: -60 | G1058: 60 | H1058: =+F1058+G1058 -> 0 | J1058: -161.13 | K1058: 161.13 | L1058: =+J1058+K1058 -> 0
F1059: -60 | G1059: 60 | H1059: =+F1059+G1059 -> 0 | J1059: -162.96 | K1059: 162.96 | L1059: =+J1059+K1059 -> 0
F1060: -60 | G1060: 60 | H1060: =+F1060+G1060 -> 0 | J1060: -162.96 | K1060: 162.96 | L1060: =+J1060+K1060 -> 0
F1061: -60 | G1061: 60 | H1061: =+F1061+G1061 -> 0 | J1061: -163 | K1061: 163 | L1061: =+J1061+K1061 -> 0
F1062: -60 | G1062: 60 | H1062: =+F1062+G1062 -> 0 | J1062: -163 | K1062: 163 | L1062: =+J1062+K1062 -> 0
F1063: -60 | G1063: 60 | H1063: =+F1063+G1063 -> 0 | J1063: -163 | K1063: 163 | L1063: =+J1063+K1063 -> 0
F1064: -60 | G1064: 60 | H1064: =+F1064+G1064 -> 0 | J1064: -163 | K1064: 163 | L1064: =+J1064+K1064 -> 0
F1065: -60 | G1065: 60 | H1065: =+F1065+G1065 -> 0 | J1065: -163 | K1065: 163 | L1065: =+J1065+K1065 -> 0
F1066: -60 | G1066: 60 | H1066: =+F1066+G1066 -> 0 | J1066: -163.93 | K1066: 163.93 | L1066: =+J1066+K1066 -> 0
F1067: -60 | G1067: 60 | H1067: =+F1067+G1067 -> 0 | J1067: -164.9 | K1067: 164.9 | L1067: =+J1067+K1067 -> 0
F1068: -60 | G1068: 60 | H1068: =+F1068+G1068 -> 0 | J1068: -164.9 | K1068: 164.9 | L1068: =+J1068+K1068 -> 0
F1069: -60 | G1069: 60 | H1069: =+F1069+G1069 -> 0 | J1069: -164.9 | K1069: 164.9 | L1069: =+J1069+K1069 -> 0
... F1791: -148.8 | G1791: 148.8 | H1791: =+F1791+G1791 -> 0 | J1791: -913.2 | K1791: 913.2 | L1791: =+J1791+K1791 -> 0
F1792: -148.8 | G1792: 148.8 | H1792: =+F1792+G1792 -> 0 | K1792: 913.62 | L1792: =+J1792+K1792 -> 913.62
F1793: -150 | G1793: 150 | H1793: =+F1793+G1793 -> 0 | J1793: -915.69 | K1793: 915.69 | L1793: =+J1793+K1793 -> 0
F1794: -150 | G1794: 150 | H1794: =+F1794+G1794 -> 0 | J1794: -919.62 | K1794: 919.62 | L1794: =+J1794+K1794 -> 0
F1795: -150 | G1795: 150 | H1795: =+F1795+G1795 -> 0 | J1795: -925.84 | K1795: 925.84 | L1795: =+J1795+K1795 -> 0
F1796: -151.2 | G1796: 151.2 | H1796: =+F1796+G1796 -> 0 | J1796: -927.48 | K1796: 927.48 | L1796: =+J1796+K1796 -> 0
F1797: -152.4 | G1797: 152.4 | H1797: =+F1797+G1797 -> 0 | J1797: -930.23 | K1797: 930.23 | L1797: =+J1797+K1797 -> 0
F1798: -152.4 | G1798: 152.4 | H1798: =+F1798+G1798 -> 0 | J1798: -932.17 | K1798: 932.17 | L1798: =+J1798+K1798 -> 0
F1799: -152.4 | G1799: 152.4 | H1799: =+F1799+G1799 -> 0 | J1799: -935.24 | K1799: 935.24 | L1799: =+J1799+K1799 -> 0
F1800: -152.4 | G1800: 152.4 | H1800: =+F1800+G1800 -> 0 | J1800: -935.24 | K1800: 935.24 | L1800: =+J1800+K1800 -> 0
F1801: -154.8 | G1801: 154.8 | H1801: =+F1801+G1801 -> 0 | J1801: -935.24 | K1801: 935.24 | L1801: =+J1801+K1801 -> 0
F1802: -154.8 | G1802: 154.8 | H1802: =+F1802+G1802 -> 0 | J1802: -939.27 | K1802: 939.27 | L1802: =+J1802+K1802 -> 0
F1803: -154.8 | G1803: 154.8 | H1803: =+F1803+G1803 -> 0 | J1803: -939.78 | K1803: 939.78 | L1803: =+J1803+K1803 -> 0
F1804: -155.4 | G1804: 155.4 | H1804: =+F1804+G1804 -> 0 | J1804: -940.51 | K1804: 940.51 | L1804: =+J1804+K1804 -> 0
... F2063: -240.6 | G2063: 240.6 | H2063: =+F2063+G2063 -> 0 | J2063: -13150.8 | K2063: 13150.8 | L2063: =+J2063+K2063 -> 0
F2064: -241.2 | G2064: 241.2 | H2064: =+F2064+G2064 -> 0
F2065: -241.2 | G2065: 241.2 | H2065: =+F2065+G2065 -> 0 | J2065: =SUM(J2:J2064) -> -972894.67 | K2065: =SUM(K2:K2064) -> 974064.61 | L2065: =SUM(L2:L2064) -> 1169.94
F2066: -241.8 | G2066: 241.8 | H2066: =+F2066+G2066 -> 0 | K2066: =+J2065+K2065 -> 1169.94
F2067: -241.8 | G2067: 241.8 | H2067: =+F2067+G2067 -> 0 | K2067: =-K2 -> 128.77
F2068: -243.6 | G2068: 243.6 | H2068: =+F2068+G2068 -> 0 | K2068: =+K2066+K2067 -> 1298.71
F2069: -243.6 | G2069: 243.6 | H2069: =+F2069+G2069 -> 0
F2070: -244.2 | G2070: 244.2 | H2070: =+F2070+G2070 -> 0
F2071: -244.8 | G2071: 244.8 | H2071: =+F2071+G2071 -> 0
F2072: -245.4 | G2072: 245.4 | H2072: =+F2072+G2072 -> 0
F2073: -245.4 | G2073: 245.4 | H2073: =+F2073+G2073 -> 0
F2074: -246 | G2074: 246 | H2074: =+F2074+G2074 -> 0
F2075: -246 | G2075: 246 | H2075: =+F2075+G2075 -> 0
F2076: -246.6 | G2076: 246.6 | H2076: =+F2076+G2076 -> 0
F2077: -246.6 | G2077: 246.6 | H2077: =+F2077+G2077 -> 0
F2078: -246.6 | G2078: 246.6 | H2078: =+F2078+G2078 -> 0
F2079: -246.6 | G2079: 246.6 | H2079: =+F2079+G2079 -> 0
...
