Workbook

Sheet sheet0
A1: INITIAL_BALANCE | B1: CREDITS | C1: DEBITS | D1: FINAL_BALANCE
A2: 12889777 | B2: 32094655 | C2: -34101823 | D2: 10882609
A4: RELEASE_DATE | B4: TRANSACTION_TYPE | C4: REFERENCE_ID | D4: TRANSACTION_NET_AMOUNT | E4: PARTIAL_BALANCE | F4: VARIOS | G4: TRANSACTION_TOTAL_AMOUNT | H4: IDC COMPRAS | I4: SIRCUPA | J4: SIRTAC | K4: Gastos | L4: IDC | M4: MOV TOTAL | O4: OBSERV
A5: 01-09-2025 | B5: Liquidación de dinero | C5: 123864040285 | D5: 14614.5 | E5: 12904392 | F5: COBRO | I5: =-IFERROR(VLOOKUP(C5,SIRCUPA!$A$21:$H$155,8,0),0) -> 0 | J5: =-IFERROR(VLOOKUP(C5,SIRTAC!$A$16:$H$1288,8,0),0) -> -150 | K5: =-IFERROR(VLOOKUP(C5,Gastos!$A$9:$J$1281,10,0),0) -> -145.5 | L5: -90 | M5: =+D5-I5-J5-K5-L5 -> 15000 | P5: =+L5/0.006 -> -15000 | Q5: =+M5+P5 -> 0
A6: 01-09-2025 | B6: Liquidación de dinero | C6: 123868184561 | D6: 9743 | E6: 12967686 | F6: COBRO | I6: =-IFERROR(VLOOKUP(C6,SIRCUPA!$A$21:$H$155,8,0),0) -> 0 | J6: =-IFERROR(VLOOKUP(C6,SIRTAC!$A$16:$H$1288,8,0),0) -> -100 | K6: =-IFERROR(VLOOKUP(C6,Gastos!$A$9:$J$1281,10,0),0) -> -97 | L6: =-IFERROR(VLOOKUP(C6,IDC!$A$25:$H$1532,8,0),0) -> -60 | M6: =+D6-I6-J6-K6-L6 -> 10000 | P6: =+L6/0.006 -> -10000 | Q6: =+M6+P6 -> 0
A7: 01-09-2025 | B7: Liquidación de dinero | C7: 123868170745 | D7: 13153.05 | E7: 12980839 | F7: COBRO | I7: =-IFERROR(VLOOKUP(C7,SIRCUPA!$A$21:$H$155,8,0),0) -> 0 | J7: =-IFERROR(VLOOKUP(C7,SIRTAC!$A$16:$H$1288,8,0),0) -> -135 | K7: =-IFERROR(VLOOKUP(C7,Gastos!$A$9:$J$1281,10,0),0) -> -130.95 | L7: =-IFERROR(VLOOKUP(C7,IDC!$A$25:$H$1532,8,0),0) -> -81 | M7: =+D7-I7-J7-K7-L7 -> 13500 | P7: =+L7/0.006 -> -13500 | Q7: =+M7+P7 -> 0
A8: 01-09-2025 | B8: Liquidación de dinero | C8: 123864645949 | D8: 17050.25 | E8: 12921442 | F8: COBRO | I8: =-IFERROR(VLOOKUP(C8,SIRCUPA!$A$21:$H$155,8,0),0) -> 0 | J8: =-IFERROR(VLOOKUP(C8,SIRTAC!$A$16:$H$1288,8,0),0) -> -175 | K8: =-IFERROR(VLOOKUP(C8,Gastos!$A$9:$J$1281,10,0),0) -> -169.75 | L8: -105 | M8: =+D8-I8-J8-K8-L8 -> 17500 | P8: =+L8/0.006 -> -17500 | Q8: =+M8+P8 -> 0
A9: 01-09-2025 | B9: Liquidación de dinero | C9: 124407346652 | D9: 11984.28 | E9: 12933426 | F9: COBRO | I9: =-IFERROR(VLOOKUP(C9,SIRCUPA!$A$21:$H$155,8,0),0) -> 0 | J9: =-IFERROR(VLOOKUP(C9,SIRTAC!$A$16:$H$1288,8,0),0) -> -132 | K9: =-IFERROR(VLOOKUP(C9,Gastos!$A$9:$J$1281,10,0),0) -> -1004.52 | L9: -79.2 | M9: =+D9-I9-J9-K9-L9 -> 13200 | P9: =+L9/0.006 -> -13200 | Q9: =+M9+P9 -> 0
A10: 01-09-2025 | B10: Transferencia recibida Juan Felipe Folmer Dondena | C10: 123865265509 | D10: 646.14 | E10: 12934072 | F10: COBRO | I10: =-IFERROR(VLOOKUP(C10,SIRCUPA!$A$21:$H$155,8,0),0) -> -9.9 | J10: =-IFERROR(VLOOKUP(C10,SIRTAC!$A$16:$H$1288,8,0),0) -> 0 | K10: =-IFERROR(VLOOKUP(C10,Gastos!$A$9:$J$1281,10,0),0) -> 0 | L10: -3.96 | M10: =+D10-I10-J10-K10-L10 -> 660 | P10: =+L10/0.006 -> -660 | Q10: =+M10+P10 -> 0
A11: 01-09-2025 | B11: Liquidación de dinero | C11: 124407749182 | D11: 23870.35 | E11: 12957943 | F11: COBRO | I11: =-IFERROR(VLOOKUP(C11,SIRCUPA!$A$21:$H$155,8,0),0) -> 0 | J11: =-IFERROR(VLOOKUP(C11,SIRTAC!$A$16:$H$1288,8,0),0) -> -245 | K11: =-IFERROR(VLOOKUP(C11,Gastos!$A$9:$J$1281,10,0),0) -> -237.65 | L11: -147 | M11: =+D11-I11-J11-K11-L11 -> 24500 | P11: =+J11/0.01 -> -24500 | Q11: =+M11+P11 -> 0
A12: 21-09-2025 | B12: Compra de Butter Roller Enmantecadora Pan Manteca Smash Hamburguesas Gris Acero Me... | C12: 127068860180 | D12: -89532.99 | E12: 11473138 | F12: PAGO PROVEEDOR | G12: =+D12/1.006 -> -88998.996 | H12: =+D12-G12 -> -533.99398 | I12: =-IFERROR(VLOOKUP(C12,SIRCUPA!$A$21:$H$155,8,0),0) -> 0 | J12: =-IFERROR(VLOOKUP(C12,SIRTAC!$A$16:$H$1288,8,0),0) -> 0 | K12: =-IFERROR(VLOOKUP(C12,Gastos!$A$9:$J$1281,10,0),0) -> 0 | L12: =+D12-G12 -> -533.99398 | M12: =+D12-I12-J12-K12-L12 -> -88998.996 | O12: SEGOVIA JUAN RAFAEL | Q12: =+L12/0.006 -> -88998.996 | R12: =+M12-Q12 -> 6.5483619e-10
A13: 22-09-2025 | B13: Compra de Butter Roller Enmantecadora Pan Manteca Smash Hamburguesas Gris Acero Me... | C13: 127126561178 | D13: -89532.99 | E13: 9722452.4 | F13: PAGO PROVEEDOR | G13: =+D13/1.006 -> -88998.996 | H13: =+D13-G13 -> -533.99398 | I13: =-IFERROR(VLOOKUP(C13,SIRCUPA!$A$21:$H$155,8,0),0) -> 0 | J13: =-IFERROR(VLOOKUP(C13,SIRTAC!$A$16:$H$1288,8,0),0) -> 0 | K13: =-IFERROR(VLOOKUP(C13,Gastos!$A$9:$J$1281,10,0),0) -> 0 | L13: =+D13-G13 -> -533.99398 | M13: =+D13-I13-J13-K13-L13 -> -88998.996 | O13: SEGOVIA JUAN RAFAEL | Q13: =+L13/0.006 -> -88998.996 | R13: =+M13-Q13 -> 6.5483619e-10
A14: 15-09-2025 | B14: Compra de Epitrónica Pack 100 Rollos Papel Térmico 80x50 48grs Ticket, Comandera, ... | C14: 125728344293 | D14: -103632.08 | E14: 12303049 | F14: PAGO PROVEEDOR | G14: =+D14/1.006 -> -103014 | H14: =+D14-G14 -> -618.08398 | I14: =-IFERROR(VLOOKUP(C14,SIRCUPA!$A$21:$H$155,8,0),0) -> 0 | J14: =-IFERROR(VLOOKUP(C14,SIRTAC!$A$16:$H$1288,8,0),0) -> 0 | K14: =-IFERROR(VLOOKUP(C14,Gastos!$A$9:$J$1281,10,0),0) -> 0 | L14: =-IFERROR(VLOOKUP(C14,IDC!$A$25:$H$1532,8,0),0) -> -618.08 | M14: =+D14-I14-J14-K14-L14 -> -103014 | O14: NOY TOMAS AGUSTIN | Q14: =+L14/0.006 -> -103013.33 | R14: =+M14-Q14 -> -0.66666667
A15: 19-09-2025 | B15: Compra de Impresora De Tickets Comandera Hasar 181 Usb Serie Ethernet P-has-181 Ne... | C15: 126810642450 | D15: -220425.67 | E15: 7333939.3 | F15: PAGO PROVEEDOR | G15: =+D15/1.006 -> -219111 | H15: =+D15-G15 -> -1314.666 | I15: =-IFERROR(VLOOKUP(C15,SIRCUPA!$A$21:$H$155,8,0),0) -> 0 | J15: =-IFERROR(VLOOKUP(C15,SIRTAC!$A$16:$H$1288,8,0),0) -> 0 | K15: =-IFERROR(VLOOKUP(C15,Gastos!$A$9:$J$1281,10,0),0) -> 0 | L15: =+D15-G15 -> -1314.666 | M15: =+D15-I15-J15-K15-L15 -> -219111 | O15: ELITRONIC ELITE ARGENTINA SA | Q15: =+L15/0.006 -> -219111 | R15: =+M15-Q15 -> 2.3574103e-09
A16: 22-09-2025 | B16: Compra de Impresora De Tickets Comandera Hasar 181 Usb Serie Ethernet P-has-181 Ne... | C16: 127126683578 | D16: -220425.67 | E16: 9502026.8 | F16: PAGO PROVEEDOR | G16: =+D16/1.006 -> -219111 | H16: =+D16-G16 -> -1314.666 | I16: =-IFERROR(VLOOKUP(C16,SIRCUPA!$A$21:$H$155,8,0),0) -> 0 | J16: =-IFERROR(VLOOKUP(C16,SIRTAC!$A$16:$H$1288,8,0),0) -> 0 | K16: =-IFERROR(VLOOKUP(C16,Gastos!$A$9:$J$1281,10,0),0) -> 0 | L16: =+D16-G16 -> -1314.666 | M16: =+D16-I16-J16-K16-L16 -> -219111 | O16: ELITRONIC ELITE ARGENTINA SA | Q16: =+L16/0.006 -> -219111 | R16: =+M16-Q16 -> 2.3574103e-09
A17: 23-09-2025 | B17: Compra de Kit Medidor Eléctrico Trifásico Wifi Hasta 80a Powermeter Mercado Libre... | C17: 126684826955 | D17: -251359.76 | E17: 8079743.6 | F17: PAGO PROVEEDOR | G17: =+D17/1.006 -> -249860.6 | H17: =+D17-G17 -> -1499.1636 | I17: =-IFERROR(VLOOKUP(C17,SIRCUPA!$A$21:$H$155,8,0),0) -> 0 | J17: =-IFERROR(VLOOKUP(C17,SIRTAC!$A$16:$H$1288,8,0),0) -> 0 | K17: =-IFERROR(VLOOKUP(C17,Gastos!$A$9:$J$1281,10,0),0) -> 0 | L17: =+D17-G17 -> -1499.1636 | M17: =+D17-I17-J17-K17-L17 -> -249860.6 | O17: POWERMETER SAS | Q17: =+L17/0.006 -> -249860.6 | R17: =+M17-Q17 -> -6.1118044e-10
A18: 12-09-2025 | B18: Compra de Manometro 63mm Post 1/4 Npt, Inox Con Glicerina 0-4 Bar/psi Mercado Libr... | C18: 125395601971 | D18: -37225.02 | E18: 9178413.7 | F18: PAGO PROVEEDOR | G18: =+D18/1.006 -> -37003.002 | H18: =+D18-G18 -> -222.01801 | I18: =-IFERROR(VLOOKUP(C18,SIRCUPA!$A$21:$H$155,8,0),0) -> 0 | J18: =-IFERROR(VLOOKUP(C18,SIRTAC!$A$16:$H$1288,8,0),0) -> 0 | K18: =-IFERROR(VLOOKUP(C18,Gastos!$A$9:$J$1281,10,0),0) -> 0 | L18: =+D18-G18 -> -222.01801 | M18: =+D18-I18-J18-K18-L18 -> -37003.002 | O18: MENDEZ DAMIAN RAFAEL | Q18: =+L18/0.006 -> -37003.002 | R18: =+M18-Q18 -> -4.292815e-10
A19: 29-09-2025 | B19: Compra Mercado Libre | C19: 127373245459 | D19: -259931.29 | E19: 12520467 | F19: PAGO PROVEEDOR | G19: =+D19/1.006 -> -258381 | H19: =+D19-G19 -> -1550.286 | I19: =-IFERROR(VLOOKUP(C19,SIRCUPA!$A$21:$H$155,8,0),0) -> 0 | J19: =-IFERROR(VLOOKUP(C19,SIRTAC!$A$16:$H$1288,8,0),0) -> 0 | K19: =-IFERROR(VLOOKUP(C19,Gastos!$A$9:$J$1281,10,0),0) -> 0 | L19: =-IFERROR(VLOOKUP(C19,IDC!$A$25:$H$1532,8,0),0) -> -1550.29 | M19: =+D19-I19-J19-K19-L19 -> -258381 | O19: EVENFLOW | Q19: =+L19/0.006 -> -258381.67 | R19: =+M19-Q19 -> 0.66666667
A20: 11-09-2025 | B20: Débito por deuda Facturas vencidas de Mercado Libre | C20: 2350344890 | D20: -25262.46 | E20: 9407525.4 | F20: PAGO PROVEEDOR | G20: =+D20/1.006 -> -25111.789 | H20: =+D20-G20 -> -150.67074 | I20: =-IFERROR(VLOOKUP(C20,SIRCUPA!$A$21:$H$155,8,0),0) -> 0 | J20: =-IFERROR(VLOOKUP(C20,SIRTAC!$A$16:$H$1288,8,0),0) -> 0 | K20: =-IFERROR(VLOOKUP(C20,Gastos!$A$9:$J$1281,10,0),0) -> 0 | L20: =+D20-G20 -> -150.67074 | M20: =+D20-I20-J20-K20-L20 -> -25111.789 | Q20: =+L20/0.006 -> -25111.789 | R20: =+M20-Q20 -> 1.3096724e-10
A21: 01-09-2025 | B21: Impuesto por extracción | C21: 124446003662 | D21: -550.29 | E21: 12726787 | F21: IDC | G21: =+D21/0.006 -> -91715 | I21: =-IFERROR(VLOOKUP(C21,SIRCUPA!$A$21:$H$155,8,0),0) -> 0 | J21: =-IFERROR(VLOOKUP(C21,SIRTAC!$A$16:$H$1288,8,0),0) -> 0 | K21: =-IFERROR(VLOOKUP(C21,Gastos!$A$9:$J$1281,10,0),0) -> 0 | L21: =-IFERROR(VLOOKUP(C21,IDC!$A$25:$H$1532,8,0),0) -> -550.29 | M21: =+D21 -> -550.29 | Q21: =+L21 -> -550.29 | R21: =+M21-Q21 -> 0
A22: 01-09-2025 | B22: Impuesto por extracción | C22: 124454118654 | D22: -1641.99 | E22: 12451480 | F22: IDC | G22: =+D22/0.006 -> -273665 | I22: =-IFERROR(VLOOKUP(C22,SIRCUPA!$A$21:$H$155,8,0),0) -> 0 | J22: =-IFERROR(VLOOKUP(C22,SIRTAC!$A$16:$H$1288,8,0),0) -> 0 | K22: =-IFERROR(VLOOKUP(C22,Gastos!$A$9:$J$1281,10,0),0) -> 0 | L22: =-IFERROR(VLOOKUP(C22,IDC!$A$25:$H$1532,8,0),0) -> -1641.99 | M22: =+D22 -> -1641.99 | Q22: =+L22 -> -1641.99 | R22: =+M22-Q22 -> 0
A23: 01-09-2025 | B23: Impuesto por extracción | C23: 124489977054 | D23: -1012.07 | E23: 12043724 | F23: IDC | G23: =+D23/0.006 -> -168678.33 | I23: =-IFERROR(VLOOKUP(C23,SIRCUPA!$A$21:$H$155,8,0),0) -> 0 | J23: =-IFERROR(VLOOKUP(C23,SIRTAC!$A$16:$H$1288,8,0),0) -> 0 | K23: =-IFERROR(VLOOKUP(C23,Gastos!$A$9:$J$1281,10,0),0) -> 0 | L23: =-IFERROR(VLOOKUP(C23,IDC!$A$25:$H$1532,8,0),0) -> -1012.07 | M23: =+D23 -> -1012.07 | Q23: =+L23 -> -1012.07 | R23: =+M23-Q23 -> 0
A24: 02-09-2025 | B24: Impuesto por extracción | C24: 124014458903 | D24: -5892.5 | E24: 11055747 | F24: IDC | G24: =+D24/0.006 -> -982083.33 | I24: =-IFERROR(VLOOKUP(C24,SIRCUPA!$A$21:$H$155,8,0),0) -> 0 | J24: =-IFERROR(VLOOKUP(C24,SIRTAC!$A$16:$H$1288,8,0),0) -> 0 | K24: =-IFERROR(VLOOKUP(C24,Gastos!$A$9:$J$1281,10,0),0) -> 0 | L24: =-IFERROR(VLOOKUP(C24,IDC!$A$25:$H$1532,8,0),0) -> -5892.5 | M24: =+D24 -> -5892.5 | Q24: =+L24 -> -5892.5 | R24: =+M24-Q24 -> 0
A25: 02-09-2025 | B25: Impuesto por extracción | C25: 124031772669 | D25: -4710.99 | E25: 9842700.2 | F25: IDC | G25: =+D25/0.006 -> -785165 | I25: =-IFERROR(VLOOKUP(C25,SIRCUPA!$A$21:$H$155,8,0),0) -> 0 | J25: =-IFERROR(VLOOKUP(C25,SIRTAC!$A$16:$H$1288,8,0),0) -> 0 | K25: =-IFERROR(VLOOKUP(C25,Gastos!$A$9:$J$1281,10,0),0) -> 0 | L25: =-IFERROR(VLOOKUP(C25,IDC!$A$25:$H$1532,8,0),0) -> -4710.99 | M25: =+D25 -> -4710.99 | Q25: =+L25 -> -4710.99 | R25: =+M25-Q25 -> 0
A26: 02-09-2025 | B26: Impuesto por extracción | C26: 124618927966 | D26: -505.77 | E26: 9757899.5 | F26: IDC | G26: =+D26/0.006 -> -84295 | I26: =-IFERROR(VLOOKUP(C26,SIRCUPA!$A$21:$H$155,8,0),0) -> 0 | J26: =-IFERROR(VLOOKUP(C26,SIRTAC!$A$16:$H$1288,8,0),0) -> 0 | K26: =-IFERROR(VLOOKUP(C26,Gastos!$A$9:$J$1281,10,0),0) -> 0 | L26: =-IFERROR(VLOOKUP(C26,IDC!$A$25:$H$1532,8,0),0) -> -505.77 | M26: =+D26 -> -505.77 | Q26: =+L26 -> -505.77 | R26: =+M26-Q26 -> 0
A27: 02-09-2025 | B27: Impuesto por extracción | C27: 124624594370 | D27: -1294.34 | E27: 9540881 | F27: IDC | G27: =+D27/0.006 -> -215723.33 | I27: =-IFERROR(VLOOKUP(C27,SIRCUPA!$A$21:$H$155,8,0),0) -> 0 | J27: =-IFERROR(VLOOKUP(C27,SIRTAC!$A$16:$H$1288,8,0),0) -> 0 | K27: =-IFERROR(VLOOKUP(C27,Gastos!$A$9:$J$1281,10,0),0) -> 0 | L27: =-IFERROR(VLOOKUP(C27,IDC!$A$25:$H$1532,8,0),0) -> -1294.34 | M27: =+D27 -> -1294.34 | Q27: =+L27 -> -1294.34 | R27: =+M27-Q27 -> 0
A28: 03-09-2025 | B28: Impuesto por extracción | C28: 124167213727 | D28: -645.69 | E28: 9432620.2 | F28: IDC | G28: =+D28/0.006 -> -107615 | I28: =-IFERROR(VLOOKUP(C28,SIRCUPA!$A$21:$H$155,8,0),0) -> 0 | J28: =-IFERROR(VLOOKUP(C28,SIRTAC!$A$16:$H$1288,8,0),0) -> 0 | K28: =-IFERROR(VLOOKUP(C28,Gastos!$A$9:$J$1281,10,0),0) -> 0 | L28: =-IFERROR(VLOOKUP(C28,IDC!$A$25:$H$1532,8,0),0) -> -645.69 | M28: =+D28 -> -645.69 | Q28: =+L28 -> -645.69 | R28: =+M28-Q28 -> 0
A29: 03-09-2025 | B29: Impuesto por extracción | C29: 124761516066 | D29: -1262.06 | E29: 9065753.9 | F29: IDC | G29: =+D29/0.006 -> -210343.33 | I29: =-IFERROR(VLOOKUP(C29,SIRCUPA!$A$21:$H$155,8,0),0) -> 0 | J29: =-IFERROR(VLOOKUP(C29,SIRTAC!$A$16:$H$1288,8,0),0) -> 0 | K29: =-IFERROR(VLOOKUP(C29,Gastos!$A$9:$J$1281,10,0),0) -> 0 | L29: =-IFERROR(VLOOKUP(C29,IDC!$A$25:$H$1532,8,0),0) -> -1262.06 | M29: =+D29 -> -1262.06 | Q29: =+L29 -> -1262.06 | R29: =+M29-Q29 -> 0
A30: 03-09-2025 | B30: Impuesto por extracción | C30: 124774089426 | D30: -271.44 | E30: 9020242.8 | F30: IDC | G30: =+D30/0.006 -> -45240 | I30: =-IFERROR(VLOOKUP(C30,SIRCUPA!$A$21:$H$155,8,0),0) -> 0 | J30: =-IFERROR(VLOOKUP(C30,SIRTAC!$A$16:$H$1288,8,0),0) -> 0 | K30: =-IFERROR(VLOOKUP(C30,Gastos!$A$9:$J$1281,10,0),0) -> 0 | L30: =-IFERROR(VLOOKUP(C30,IDC!$A$25:$H$1532,8,0),0) -> -271.44 | M30: =+D30 -> -271.44 | Q30: =+L30 -> -271.44 | R30: =+M30-Q30 -> 0
A31: 04-09-2025 | B31: Impuesto por extracción | C31: 124293086141 | D31: -7357.44 | E31: 8469978 | F31: IDC | G31: =+D31/0.006 -> -1226240 | I31: =-IFERROR(VLOOKUP(C31,SIRCUPA!$A$21:$H$155,8,0),0) -> 0 | J31: =-IFERROR(VLOOKUP(C31,SIRTAC!$A$16:$H$1288,8,0),0) -> 0 | K31: =-IFERROR(VLOOKUP(C31,Gastos!$A$9:$J$1281,10,0),0) -> 0 | L31: =-IFERROR(VLOOKUP(C31,IDC!$A$25:$H$1532,8,0),0) -> -7357.44 | M31: =+D31 -> -7357.44 | Q31: =+L31 -> -7357.44 | R31: =+M31-Q31 -> 0
A32: 03-09-2025 | B32: Liquidación de dinero | C32: 124234497707 | D32: 4774.07 | E32: 9025016.9 | F32: COBRO | I32: =-IFERROR(VLOOKUP(C32,SIRCUPA!$A$21:$H$155,8,0),0) -> 0 | J32: =-IFERROR(VLOOKUP(C32,SIRTAC!$A$16:$H$1288,8,0),0) -> -49 | K32: =-IFERROR(VLOOKUP(C32,Gastos!$A$9:$J$1281,10,0),0) -> -47.53 | L32: =-IFERROR(VLOOKUP(C32,IDC!$A$25:$H$1532,8,0),0) -> -29.4 | M32: =+D32-I32-J32-K32-L32 -> 4900 | P32: =+L32/0.006 -> -4900 | Q32: =+M32+P32 -> 0
A33: 03-09-2025 | B33: Liquidación de dinero | C33: 124781182650 | D33: 8071.96 | E33: 9033088.9 | F33: COBRO | I33: =-IFERROR(VLOOKUP(C33,SIRCUPA!$A$21:$H$155,8,0),0) -> 0 | J33: =-IFERROR(VLOOKUP(C33,SIRTAC!$A$16:$H$1288,8,0),0) -> -86 | K33: =-IFERROR(VLOOKUP(C33,Gastos!$A$9:$J$1281,10,0),0) -> -390.44 | L33: =-IFERROR(VLOOKUP(C33,IDC!$A$25:$H$1532,8,0),0) -> -51.6 | M33: =+D33-I33-J33-K33-L33 -> 8600 | P33: =+L33/0.006 -> -8600 | Q33: =+M33+P33 -> 0
A34: 03-09-2025 | B34: Liquidación de dinero | C34: 124236889607 | D34: 28546.99 | E34: 9061635.9 | F34: COBRO | I34: =-IFERROR(VLOOKUP(C34,SIRCUPA!$A$21:$H$155,8,0),0) -> 0 | J34: =-IFERROR(VLOOKUP(C34,SIRTAC!$A$16:$H$1288,8,0),0) -> -293 | K34: =-IFERROR(VLOOKUP(C34,Gastos!$A$9:$J$1281,10,0),0) -> -284.21 | L34: =-IFERROR(VLOOKUP(C34,IDC!$A$25:$H$1532,8,0),0) -> -175.8 | M34: =+D34-I34-J34-K34-L34 -> 29300 | P34: =+L34/0.006 -> -29300 | Q34: =+M34+P34 -> 0
A35: 03-09-2025 | B35: Transferencia recibida Joaquin Pedro Schenone | C35: 124236877691 | D35: 1434.23 | E35: 9063070.1 | F35: COBRO | I35: =-IFERROR(VLOOKUP(C35,SIRCUPA!$A$21:$H$155,8,0),0) -> -21.98 | J35: =-IFERROR(VLOOKUP(C35,SIRTAC!$A$16:$H$1288,8,0),0) -> 0 | K35: =-IFERROR(VLOOKUP(C35,Gastos!$A$9:$J$1281,10,0),0) -> 0 | L35: =-IFERROR(VLOOKUP(C35,IDC!$A$25:$H$1532,8,0),0) -> -8.79 | M35: =+D35-I35-J35-K35-L35 -> 1465 | P35: =+L35/0.006 -> -1465 | Q35: =+M35+P35 -> 0
A36: 03-09-2025 | B36: Liquidación de dinero | C36: 124784681512 | D36: 28144.9 | E36: 9091215 | F36: COBRO | I36: =-IFERROR(VLOOKUP(C36,SIRCUPA!$A$21:$H$155,8,0),0) -> 0 | J36: =-IFERROR(VLOOKUP(C36,SIRTAC!$A$16:$H$1288,8,0),0) -> -310 | K36: =-IFERROR(VLOOKUP(C36,Gastos!$A$9:$J$1281,10,0),0) -> -2359.1 | L36: =-IFERROR(VLOOKUP(C36,IDC!$A$25:$H$1532,8,0),0) -> -186 | M36: =+D36-I36-J36-K36-L36 -> 31000 | P36: =+L36/0.006 -> -31000 | Q36: =+M36+P36 -> 0
A37: 03-09-2025 | B37: Liquidación de dinero | C37: 124788106000 | D37: 5006.91 | E37: 9096221.9 | F37: COBRO | I37: =-IFERROR(VLOOKUP(C37,SIRCUPA!$A$21:$H$155,8,0),0) -> 0 | J37: =-IFERROR(VLOOKUP(C37,SIRTAC!$A$16:$H$1288,8,0),0) -> -53 | K37: =-IFERROR(VLOOKUP(C37,Gastos!$A$9:$J$1281,10,0),0) -> -208.29 | L37: =-IFERROR(VLOOKUP(C37,IDC!$A$25:$H$1532,8,0),0) -> -31.8 | M37: =+D37-I37-J37-K37-L37 -> 5300 | P37: =+L37/0.006 -> -5300 | Q37: =+M37+P37 -> 0
A38: 03-09-2025 | B38: Liquidación de dinero | C38: 124245392201 | D38: 33223.63 | E38: 9129445.5 | F38: COBRO | I38: =-IFERROR(VLOOKUP(C38,SIRCUPA!$A$21:$H$155,8,0),0) -> 0 | J38: =-IFERROR(VLOOKUP(C38,SIRTAC!$A$16:$H$1288,8,0),0) -> -341 | K38: =-IFERROR(VLOOKUP(C38,Gastos!$A$9:$J$1281,10,0),0) -> -330.77 | L38: =-IFERROR(VLOOKUP(C38,IDC!$A$25:$H$1532,8,0),0) -> -204.6 | M38: =+D38-I38-J38-K38-L38 -> 34100 | P38: =+L38/0.006 -> -34100 | Q38: =+M38+P38 -> 0
A39: 03-09-2025 | B39: Liquidación de dinero | C39: 124245389515 | D39: 44817.8 | E39: 9174263.3 | F39: COBRO | I39: =-IFERROR(VLOOKUP(C39,SIRCUPA!$A$21:$H$155,8,0),0) -> 0 | J39: =-IFERROR(VLOOKUP(C39,SIRTAC!$A$16:$H$1288,8,0),0) -> -460 | K39: =-IFERROR(VLOOKUP(C39,Gastos!$A$9:$J$1281,10,0),0) -> -446.2 | L39: =-IFERROR(VLOOKUP(C39,IDC!$A$25:$H$1532,8,0),0) -> -276 | M39: =+D39-I39-J39-K39-L39 -> 46000 | P39: =+L39/0.006 -> -46000 | Q39: =+M39+P39 -> 0
A40: 03-09-2025 | B40: Liquidación de dinero | C40: 124247706111 | D40: 11983.89 | E40: 9186247.2 | F40: COBRO | I40: =-IFERROR(VLOOKUP(C40,SIRCUPA!$A$21:$H$155,8,0),0) -> 0 | J40: =-IFERROR(VLOOKUP(C40,SIRTAC!$A$16:$H$1288,8,0),0) -> -123 | K40: =-IFERROR(VLOOKUP(C40,Gastos!$A$9:$J$1281,10,0),0) -> -119.31 | L40: =-IFERROR(VLOOKUP(C40,IDC!$A$25:$H$1532,8,0),0) -> -73.8 | M40: =+D40-I40-J40-K40-L40 -> 12300 | P40: =+L40/0.006 -> -12300 | Q40: =+M40+P40 -> 0
A41: 03-09-2025 | B41: Liquidación de dinero | C41: 124795296394 | D41: 19485.03 | E41: 9205732.2 | F41: COBRO | I41: =-IFERROR(VLOOKUP(C41,SIRCUPA!$A$21:$H$155,8,0),0) -> 0 | J41: =-IFERROR(VLOOKUP(C41,SIRTAC!$A$16:$H$1288,8,0),0) -> -199.99 | K41: =-IFERROR(VLOOKUP(C41,Gastos!$A$9:$J$1281,10,0),0) -> -193.99 | L41: =-IFERROR(VLOOKUP(C41,IDC!$A$25:$H$1532,8,0),0) -> -119.99 | M41: =+D41-I41-J41-K41-L41 -> 19999 | P41: =+L41/0.006 -> -19998.333 | Q41: =+M41+P41 -> 0.66666667
A42: 03-09-2025 | B42: Liquidación de dinero | C42: 124251168101 | D42: 58356.67 | E42: 9264088.9 | F42: COBRO | I42: =-IFERROR(VLOOKUP(C42,SIRCUPA!$A$21:$H$155,8,0),0) -> 0 | J42: =-IFERROR(VLOOKUP(C42,SIRTAC!$A$16:$H$1288,8,0),0) -> -598.96 | K42: =-IFERROR(VLOOKUP(C42,Gastos!$A$9:$J$1281,10,0),0) -> -580.99 | L42: =-IFERROR(VLOOKUP(C42,IDC!$A$25:$H$1532,8,0),0) -> -359.38 | M42: =+D42-I42-J42-K42-L42 -> 59896 | P42: =+L42/0.006 -> -59896.667 | Q42: =+M42+P42 -> -0.66666667
A43: 03-09-2025 | B43: Liquidación de dinero | C43: 124251556927 | D43: 69175.3 | E43: 9333264.2 | F43: COBRO | I43: =-IFERROR(VLOOKUP(C43,SIRCUPA!$A$21:$H$155,8,0),0) -> 0 | J43: =-IFERROR(VLOOKUP(C43,SIRTAC!$A$16:$H$1288,8,0),0) -> -710 | K43: =-IFERROR(VLOOKUP(C43,Gastos!$A$9:$J$1281,10,0),0) -> -688.7 | L43: =-IFERROR(VLOOKUP(C43,IDC!$A$25:$H$1532,8,0),0) -> -426 | M43: =+D43-I43-J43-K43-L43 -> 71000 | P43: =+L43/0.006 -> -71000 | Q43: =+M43+P43 -> 0
A44: 04-09-2025 | B44: Impuesto por extracción | C44: 124845509146 | D44: -1320.16 | E44: 8226901.9 | F44: IDC | G44: =+D44/0.006 -> -220026.67 | I44: =-IFERROR(VLOOKUP(C44,SIRCUPA!$A$21:$H$155,8,0),0) -> 0 | J44: =-IFERROR(VLOOKUP(C44,SIRTAC!$A$16:$H$1288,8,0),0) -> 0 | K44: =-IFERROR(VLOOKUP(C44,Gastos!$A$9:$J$1281,10,0),0) -> 0 | L44: =-IFERROR(VLOOKUP(C44,IDC!$A$25:$H$1532,8,0),0) -> -1320.16 | M44: =+D44 -> -1320.16 | Q44: =+L44 -> -1320.16 | R44: =+M44-Q44 -> 0
A45: 04-09-2025 | B45: Impuesto por extracción | C45: 124856861194 | D45: -822.12 | E45: 8089059.8 | F45: IDC | G45: =+D45/0.006 -> -137020 | I45: =-IFERROR(VLOOKUP(C45,SIRCUPA!$A$21:$H$155,8,0),0) -> 0 | J45: =-IFERROR(VLOOKUP(C45,SIRTAC!$A$16:$H$1288,8,0),0) -> 0 | K45: =-IFERROR(VLOOKUP(C45,Gastos!$A$9:$J$1281,10,0),0) -> 0 | L45: =-IFERROR(VLOOKUP(C45,IDC!$A$25:$H$1532,8,0),0) -> -822.12 | M45: =+D45 -> -822.12 | Q45: =+L45 -> -822.12 | R45: =+M45-Q45 -> 0
A46: 05-09-2025 | B46: Impuesto por extracción | C46: 124420739261 | D46: -2599.61 | E46: 9176818.9 | F46: IDC | G46: =+D46/0.006 -> -433268.33 | I46: =-IFERROR(VLOOKUP(C46,SIRCUPA!$A$21:$H$155,8,0),0) -> 0 | J46: =-IFERROR(VLOOKUP(C46,SIRTAC!$A$16:$H$1288,8,0),0) -> 0 | K46: =-IFERROR(VLOOKUP(C46,Gastos!$A$9:$J$1281,10,0),0) -> 0 | L46: =-IFERROR(VLOOKUP(C46,IDC!$A$25:$H$1532,8,0),0) -> -2599.61 | M46: =+D46 -> -2599.61 | Q46: =+L46 -> -2599.61 | R46: =+M46-Q46 -> 0
A47: 08-09-2025 | B47: Impuesto por extracción | C47: 125360500974 | D47: -1623.75 | E47: 12021865 | F47: IDC | G47: =+D47/0.006 -> -270625 | I47: =-IFERROR(VLOOKUP(C47,SIRCUPA!$A$21:$H$155,8,0),0) -> 0 | J47: =-IFERROR(VLOOKUP(C47,SIRTAC!$A$16:$H$1288,8,0),0) -> 0 | K47: =-IFERROR(VLOOKUP(C47,Gastos!$A$9:$J$1281,10,0),0) -> 0 | L47: =-IFERROR(VLOOKUP(C47,IDC!$A$25:$H$1532,8,0),0) -> -1623.75 | M47: =+D47 -> -1623.75 | Q47: =+L47 -> -1623.75 | R47: =+M47-Q47 -> 0
A48: 08-09-2025 | B48: Impuesto por extracción | C48: 125385837094 | D48: -1571.04 | E48: 10676269 | F48: IDC | G48: =+D48/0.006 -> -261840 | I48: =-IFERROR(VLOOKUP(C48,SIRCUPA!$A$21:$H$155,8,0),0) -> 0 | J48: =-IFERROR(VLOOKUP(C48,SIRTAC!$A$16:$H$1288,8,0),0) -> 0 | K48: =-IFERROR(VLOOKUP(C48,Gastos!$A$9:$J$1281,10,0),0) -> 0 | L48: =-IFERROR(VLOOKUP(C48,IDC!$A$25:$H$1532,8,0),0) -> -1571.04 | M48: =+D48 -> -1571.04 | Q48: =+L48 -> -1571.04 | R48: =+M48-Q48 -> 0
A49: 08-09-2025 | B49: Impuesto por extracción | C49: 125391966586 | D49: -570.35 | E49: 10580640 | F49: IDC | G49: =+D49/0.006 -> -95058.333 | I49: =-IFERROR(VLOOKUP(C49,SIRCUPA!$A$21:$H$155,8,0),0) -> 0 | J49: =-IFERROR(VLOOKUP(C49,SIRTAC!$A$16:$H$1288,8,0),0) -> 0 | K49: =-IFERROR(VLOOKUP(C49,Gastos!$A$9:$J$1281,10,0),0) -> 0 | L49: =-IFERROR(VLOOKUP(C49,IDC!$A$25:$H$1532,8,0),0) -> -570.35 | M49: =+D49 -> -570.35 | Q49: =+L49 -> -570.35 | R49: =+M49-Q49 -> 0
A50: 09-09-2025 | B50: Impuesto por extracción | C50: 125490840846 | D50: -935.78 | E50: 8562238.6 | F50: IDC | G50: =+D50/0.006 -> -155963.33 | I50: =-IFERROR(VLOOKUP(C50,SIRCUPA!$A$21:$H$155,8,0),0) -> 0 | J50: =-IFERROR(VLOOKUP(C50,SIRTAC!$A$16:$H$1288,8,0),0) -> 0 | K50: =-IFERROR(VLOOKUP(C50,Gastos!$A$9:$J$1281,10,0),0) -> 0 | L50: =-IFERROR(VLOOKUP(C50,IDC!$A$25:$H$1532,8,0),0) -> -935.78 | M50: =+D50 -> -935.78 | Q50: =+L50 -> -935.78 | R50: =+M50-Q50 -> 0
A51: 04-09-2025 | B51: Liquidación de dinero | C51: 124797073790 | D51: 55729.96 | E51: 9388994.2 | F51: COBRO | I51: =-IFERROR(VLOOKUP(C51,SIRCUPA!$A$21:$H$155,8,0),0) -> 0 | J51: =-IFERROR(VLOOKUP(C51,SIRTAC!$A$16:$H$1288,8,0),0) -> -572 | K51: =-IFERROR(VLOOKUP(C51,Gastos!$A$9:$J$1281,10,0),0) -> -554.84 | L51: =-IFERROR(VLOOKUP(C51,IDC!$A$25:$H$1532,8,0),0) -> -343.2 | M51: =+D51-I51-J51-K51-L51 -> 57200 | P51: =+L51/0.006 -> -57200 | Q51: =+M51+P51 -> 0
A52: 04-09-2025 | B52: Liquidación de dinero | C52: 124797394520 | D52: 35756.81 | E52: 9424751 | F52: COBRO | I52: =-IFERROR(VLOOKUP(C52,SIRCUPA!$A$21:$H$155,8,0),0) -> 0 | J52: =-IFERROR(VLOOKUP(C52,SIRTAC!$A$16:$H$1288,8,0),0) -> -367 | K52: =-IFERROR(VLOOKUP(C52,Gastos!$A$9:$J$1281,10,0),0) -> -355.99 | L52: =-IFERROR(VLOOKUP(C52,IDC!$A$25:$H$1532,8,0),0) -> -220.2 | M52: =+D52-I52-J52-K52-L52 -> 36700 | P52: =+L52/0.006 -> -36700 | Q52: =+M52+P52 -> 0
A53: 04-09-2025 | B53: Transferencia recibida Ivan Goldin | C53: 124253070499 | D53: 1796.46 | E53: 9426547.4 | F53: COBRO | I53: =-IFERROR(VLOOKUP(C53,SIRCUPA!$A$21:$H$155,8,0),0) -> -27.53 | J53: =-IFERROR(VLOOKUP(C53,SIRTAC!$A$16:$H$1288,8,0),0) -> 0 | K53: =-IFERROR(VLOOKUP(C53,Gastos!$A$9:$J$1281,10,0),0) -> 0 | L53: =-IFERROR(VLOOKUP(C53,IDC!$A$25:$H$1532,8,0),0) -> -11.01 | M53: =+D53-I53-J53-K53-L53 -> 1835 | P53: =+L53/0.006 -> -1835 | Q53: =+M53+P53 -> 0
A54: 04-09-2025 | B54: Liquidación de dinero | C54: 124797743380 | D54: 138720.76 | E54: 9565268.2 | F54: COBRO | I54: =-IFERROR(VLOOKUP(C54,SIRCUPA!$A$21:$H$155,8,0),0) -> 0 | J54: =-IFERROR(VLOOKUP(C54,SIRTAC!$A$16:$H$1288,8,0),0) -> -1527.93 | K54: =-IFERROR(VLOOKUP(C54,Gastos!$A$9:$J$1281,10,0),0) -> -11627.55 | L54: =-IFERROR(VLOOKUP(C54,IDC!$A$25:$H$1532,8,0),0) -> -916.76 | M54: =+D54-I54-J54-K54-L54 -> 152793 | P54: =+L54/0.006 -> -152793.33 | Q54: =+M54+P54 -> -0.33333333
A55: 04-09-2025 | B55: Liquidación de dinero | C55: 124797908608 | D55: 14072.45 | E55: 9579340.7 | F55: COBRO | I55: =-IFERROR(VLOOKUP(C55,SIRCUPA!$A$21:$H$155,8,0),0) -> 0 | J55: =-IFERROR(VLOOKUP(C55,SIRTAC!$A$16:$H$1288,8,0),0) -> -155 | K55: =-IFERROR(VLOOKUP(C55,Gastos!$A$9:$J$1281,10,0),0) -> -1179.55 | L55: =-IFERROR(VLOOKUP(C55,IDC!$A$25:$H$1532,8,0),0) -> -93 | M55: =+D55-I55-J55-K55-L55 -> 15500 | P55: =+L55/0.006 -> -15500 | Q55: =+M55+P55 -> 0
A56: 04-09-2025 | B56: Liquidación de dinero | C56: 124253989611 | D56: 20362.87 | E56: 9599703.5 | F56: COBRO | I56: =-IFERROR(VLOOKUP(C56,SIRCUPA!$A$21:$H$155,8,0),0) -> 0 | J56: =-IFERROR(VLOOKUP(C56,SIRTAC!$A$16:$H$1288,8,0),0) -> -209 | K56: =-IFERROR(VLOOKUP(C56,Gastos!$A$9:$J$1281,10,0),0) -> -202.73 | L56: =-IFERROR(VLOOKUP(C56,IDC!$A$25:$H$1532,8,0),0) -> -125.4 | M56: =+D56-I56-J56-K56-L56 -> 20900 | P56: =+L56/0.006 -> -20900 | Q56: =+M56+P56 -> 0
A57: 04-09-2025 | B57: Liquidación de dinero | C57: 124798439032 | D57: 27475.26 | E57: 9627178.8 | F57: COBRO | I57: =-IFERROR(VLOOKUP(C57,SIRCUPA!$A$21:$H$155,8,0),0) -> 0 | J57: =-IFERROR(VLOOKUP(C57,SIRTAC!$A$16:$H$1288,8,0),0) -> -282 | K57: =-IFERROR(VLOOKUP(C57,Gastos!$A$9:$J$1281,10,0),0) -> -273.54 | L57: =-IFERROR(VLOOKUP(C57,IDC!$A$25:$H$1532,8,0),0) -> -169.2 | M57: =+D57-I57-J57-K57-L57 -> 28200 | P57: =+L57/0.006 -> -28200 | Q57: =+M57+P57 -> 0
A58: 04-09-2025 | B58: Transferencia recibida Tahiel Heredia | C58: 124254045511 | D58: 1380.39 | E58: 9628559.2 | F58: COBRO | I58: =-IFERROR(VLOOKUP(C58,SIRCUPA!$A$21:$H$155,8,0),0) -> -21.15 | J58: =-IFERROR(VLOOKUP(C58,SIRTAC!$A$16:$H$1288,8,0),0) -> 0 | K58: =-IFERROR(VLOOKUP(C58,Gastos!$A$9:$J$1281,10,0),0) -> 0 | L58: =-IFERROR(VLOOKUP(C58,IDC!$A$25:$H$1532,8,0),0) -> -8.46 | M58: =+D58-I58-J58-K58-L58 -> 1410 | P58: =+L58/0.006 -> -1410 | Q58: =+M58+P58 -> 0
A59: 04-09-2025 | B59: Liquidación de dinero | C59: 124798706468 | D59: 9548.14 | E59: 9638107.3 | F59: COBRO | I59: =-IFERROR(VLOOKUP(C59,SIRCUPA!$A$21:$H$155,8,0),0) -> 0 | J59: =-IFERROR(VLOOKUP(C59,SIRTAC!$A$16:$H$1288,8,0),0) -> -98 | K59: =-IFERROR(VLOOKUP(C59,Gastos!$A$9:$J$1281,10,0),0) -> -95.06 | L59: =-IFERROR(VLOOKUP(C59,IDC!$A$25:$H$1532,8,0),0) -> -58.8 | M59: =+D59-I59-J59-K59-L59 -> 9800 | P59: =+L59/0.006 -> -9800 | Q59: =+M59+P59 -> 0
A60: 04-09-2025 | B60: Liquidación de dinero | C60: 124800062204 | D60: 45984.04 | E60: 9684091.4 | F60: COBRO | I60: =-IFERROR(VLOOKUP(C60,SIRCUPA!$A$21:$H$155,8,0),0) -> 0 | J60: =-IFERROR(VLOOKUP(C60,SIRTAC!$A$16:$H$1288,8,0),0) -> -471.97 | K60: =-IFERROR(VLOOKUP(C60,Gastos!$A$9:$J$1281,10,0),0) -> -457.81 | L60: =-IFERROR(VLOOKUP(C60,IDC!$A$25:$H$1532,8,0),0) -> -283.18 | M60: =+D60-I60-J60-K60-L60 -> 47197 | P60: =+L60/0.006 -> -47196.667 | Q60: =+M60+P60 -> 0.33333333
A61: 04-09-2025 | B61: Liquidación de dinero | C61: 124256095479 | D61: 19484.05 | E61: 9703575.4 | F61: COBRO | I61: =-IFERROR(VLOOKUP(C61,SIRCUPA!$A$21:$H$155,8,0),0) -> 0 | J61: =-IFERROR(VLOOKUP(C61,SIRTAC!$A$16:$H$1288,8,0),0) -> -199.98 | K61: =-IFERROR(VLOOKUP(C61,Gastos!$A$9:$J$1281,10,0),0) -> -193.98 | L61: =-IFERROR(VLOOKUP(C61,IDC!$A$25:$H$1532,8,0),0) -> -119.99 | M61: =+D61-I61-J61-K61-L61 -> 19998 | P61: =+L61/0.006 -> -19998.333 | Q61: =+M61+P61 -> -0.33333333
A62: 04-09-2025 | B62: Liquidación de dinero | C62: 124907529624 | D62: 15491.37 | E62: 8104551.2 | F62: COBRO | I62: =-IFERROR(VLOOKUP(C62,SIRCUPA!$A$21:$H$155,8,0),0) -> 0 | J62: =-IFERROR(VLOOKUP(C62,SIRTAC!$A$16:$H$1288,8,0),0) -> -159 | K62: =-IFERROR(VLOOKUP(C62,Gastos!$A$9:$J$1281,10,0),0) -> -154.23 | L62: =-IFERROR(VLOOKUP(C62,IDC!$A$25:$H$1532,8,0),0) -> -95.4 | M62: =+D62-I62-J62-K62-L62 -> 15900 | P62: =+L62/0.006 -> -15900 | Q62: =+M62+P62 -> 0
... A103: 04-09-2025 | B103: Liquidación de dinero | C103: 124931811338 | D103: 1851.17 | E103: 8684081.9 | F103: COBRO | I103: =-IFERROR(VLOOKUP(C103,SIRCUPA!$A$21:$H$155,8,0),0) -> 0 | J103: =-IFERROR(VLOOKUP(C103,SIRTAC!$A$16:$H$1288,8,0),0) -> -19 | K103: =-IFERROR(VLOOKUP(C103,Gastos!$A$9:$J$1281,10,0),0) -> -18.43 | L103: =-IFERROR(VLOOKUP(C103,IDC!$A$25:$H$1532,8,0),0) -> -11.4 | M103: =+D103-I103-J103-K103-L103 -> 1900 | P103: =+L103/0.006 -> -1900 | Q103: =+M103+P103 -> 0
A104: 10-09-2025 | B104: Impuesto por extracción | C104: 125128178537 | D104: -1738.35 | E104: 8270775.2 | F104: IDC | G104: =+D104/0.006 -> -289725 | I104: =-IFERROR(VLOOKUP(C104,SIRCUPA!$A$21:$H$155,8,0),0) -> 0 | J104: =-IFERROR(VLOOKUP(C104,SIRTAC!$A$16:$H$1288,8,0),0) -> 0 | K104: =-IFERROR(VLOOKUP(C104,Gastos!$A$9:$J$1281,10,0),0) -> 0 | L104: =-IFERROR(VLOOKUP(C104,IDC!$A$25:$H$1532,8,0),0) -> -1738.35 | M104: =+D104 -> -1738.35 | Q104: =+L104 -> -1738.35 | R104: =+M104-Q104 -> 0
A105: 10-09-2025 | B105: Impuesto por extracción | C105: 125720603672 | D105: -676.12 | E105: 8272578.8 | F105: IDC | G105: =+D105/0.006 -> -112686.67 | I105: =-IFERROR(VLOOKUP(C105,SIRCUPA!$A$21:$H$155,8,0),0) -> 0 | J105: =-IFERROR(VLOOKUP(C105,SIRTAC!$A$16:$H$1288,8,0),0) -> 0 | K105: =-IFERROR(VLOOKUP(C105,Gastos!$A$9:$J$1281,10,0),0) -> 0 | L105: =-IFERROR(VLOOKUP(C105,IDC!$A$25:$H$1532,8,0),0) -> -676.12 | M105: =+D105 -> -676.12 | Q105: =+L105 -> -676.12 | R105: =+M105-Q105 -> 0
A106: 11-09-2025 | B106: Impuesto por extracción | C106: 125232161173 | D106: -2703.05 | E106: 7712932.3 | F106: IDC | G106: =+D106/0.006 -> -450508.33 | I106: =-IFERROR(VLOOKUP(C106,SIRCUPA!$A$21:$H$155,8,0),0) -> 0 | J106: =-IFERROR(VLOOKUP(C106,SIRTAC!$A$16:$H$1288,8,0),0) -> 0 | K106: =-IFERROR(VLOOKUP(C106,Gastos!$A$9:$J$1281,10,0),0) -> 0 | L106: =-IFERROR(VLOOKUP(C106,IDC!$A$25:$H$1532,8,0),0) -> -2703.05 | M106: =+D106 -> -2703.05 | Q106: =+L106 -> -2703.05 | R106: =+M106-Q106 -> 0
A107: 11-09-2025 | B107: Impuesto por extracción | C107: 125232960111 | D107: -199.45 | E107: 8166143.6 | F107: IDC | G107: =+D107/0.006 -> -33241.667 | I107: =-IFERROR(VLOOKUP(C107,SIRCUPA!$A$21:$H$155,8,0),0) -> 0 | J107: =-IFERROR(VLOOKUP(C107,SIRTAC!$A$16:$H$1288,8,0),0) -> 0 | K107: =-IFERROR(VLOOKUP(C107,Gastos!$A$9:$J$1281,10,0),0) -> 0 | L107: =-IFERROR(VLOOKUP(C107,IDC!$A$25:$H$1532,8,0),0) -> -199.45 | M107: =+D107 -> -199.45 | Q107: =+L107 -> -199.45 | R107: =+M107-Q107 -> 0
A108: 11-09-2025 | B108: Impuesto por extracción | C108: 125259476811 | D108: -976.5 | E108: 7549205.8 | F108: IDC | G108: =+D108/0.006 -> -162750 | I108: =-IFERROR(VLOOKUP(C108,SIRCUPA!$A$21:$H$155,8,0),0) -> 0 | J108: =-IFERROR(VLOOKUP(C108,SIRTAC!$A$16:$H$1288,8,0),0) -> 0 | K108: =-IFERROR(VLOOKUP(C108,Gastos!$A$9:$J$1281,10,0),0) -> 0 | L108: =-IFERROR(VLOOKUP(C108,IDC!$A$25:$H$1532,8,0),0) -> -976.5 | M108: =+D108 -> -976.5 | Q108: =+L108 -> -976.5 | R108: =+M108-Q108 -> 0
A109: 11-09-2025 | B109: Impuesto por extracción | C109: 125778419104 | D109: -1130.42 | E109: 8199584.1 | F109: IDC | G109: =+D109/0.006 -> -188403.33 | I109: =-IFERROR(VLOOKUP(C109,SIRCUPA!$A$21:$H$155,8,0),0) -> 0 | J109: =-IFERROR(VLOOKUP(C109,SIRTAC!$A$16:$H$1288,8,0),0) -> 0 | K109: =-IFERROR(VLOOKUP(C109,Gastos!$A$9:$J$1281,10,0),0) -> 0 | L109: =-IFERROR(VLOOKUP(C109,IDC!$A$25:$H$1532,8,0),0) -> -1130.42 | M109: =+D109 -> -1130.42 | Q109: =+L109 -> -1130.42 | R109: =+M109-Q109 -> 0
A110: 05-09-2025 | B110: Liquidación de dinero | C110: 124386853415 | D110: 3799.77 | E110: 8687881.7 | F110: COBRO | I110: =-IFERROR(VLOOKUP(C110,SIRCUPA!$A$21:$H$155,8,0),0) -> 0 | J110: =-IFERROR(VLOOKUP(C110,SIRTAC!$A$16:$H$1288,8,0),0) -> -39 | K110: =-IFERROR(VLOOKUP(C110,Gastos!$A$9:$J$1281,10,0),0) -> -37.83 | L110: =-IFERROR(VLOOKUP(C110,IDC!$A$25:$H$1532,8,0),0) -> -23.4 | M110: =+D110-I110-J110-K110-L110 -> 3900 | P110: =+L110/0.006 -> -3900 | Q110: =+M110+P110 -> 0
A111: 05-09-2025 | B111: Transferencia recibida Nicanor Ormaechea | C111: 124386769841 | D111: 381.81 | E111: 8688263.5 | F111: COBRO | I111: =-IFERROR(VLOOKUP(C111,SIRCUPA!$A$21:$H$155,8,0),0) -> -5.85 | J111: =-IFERROR(VLOOKUP(C111,SIRTAC!$A$16:$H$1288,8,0),0) -> 0 | K111: =-IFERROR(VLOOKUP(C111,Gastos!$A$9:$J$1281,10,0),0) -> 0 | L111: =-IFERROR(VLOOKUP(C111,IDC!$A$25:$H$1532,8,0),0) -> -2.34 | M111: =+D111-I111-J111-K111-L111 -> 390 | P111: =+L111/0.006 -> -390 | Q111: =+M111+P111 -> 0
A112: 05-09-2025 | B112: Liquidación de dinero | C112: 124932013860 | D112: 59319.52 | E112: 8747583 | F112: COBRO | I112: =-IFERROR(VLOOKUP(C112,SIRCUPA!$A$21:$H$155,8,0),0) -> 0 | J112: =-IFERROR(VLOOKUP(C112,SIRTAC!$A$16:$H$1288,8,0),0) -> -632 | K112: =-IFERROR(VLOOKUP(C112,Gastos!$A$9:$J$1281,10,0),0) -> -2869.28 | L112: =-IFERROR(VLOOKUP(C112,IDC!$A$25:$H$1532,8,0),0) -> -379.2 | M112: =+D112-I112-J112-K112-L112 -> 63200 | P112: =+L112/0.006 -> -63200 | Q112: =+M112+P112 -> 0
A113: 05-09-2025 | B113: Liquidación de dinero | C113: 124387202427 | D113: 7989.26 | E113: 8755572.3 | F113: COBRO | I113: =-IFERROR(VLOOKUP(C113,SIRCUPA!$A$21:$H$155,8,0),0) -> 0 | J113: =-IFERROR(VLOOKUP(C113,SIRTAC!$A$16:$H$1288,8,0),0) -> -82 | K113: =-IFERROR(VLOOKUP(C113,Gastos!$A$9:$J$1281,10,0),0) -> -79.54 | L113: =-IFERROR(VLOOKUP(C113,IDC!$A$25:$H$1532,8,0),0) -> -49.2 | M113: =+D113-I113-J113-K113-L113 -> 8200 | P113: =+L113/0.006 -> -8200 | Q113: =+M113+P113 -> 0
A114: 05-09-2025 | B114: Liquidación de dinero | C114: 124387169897 | D114: 9060.99 | E114: 8764633.3 | F114: COBRO | I114: =-IFERROR(VLOOKUP(C114,SIRCUPA!$A$21:$H$155,8,0),0) -> 0 | J114: =-IFERROR(VLOOKUP(C114,SIRTAC!$A$16:$H$1288,8,0),0) -> -93 | K114: =-IFERROR(VLOOKUP(C114,Gastos!$A$9:$J$1281,10,0),0) -> -90.21 | L114: =-IFERROR(VLOOKUP(C114,IDC!$A$25:$H$1532,8,0),0) -> -55.8 | M114: =+D114-I114-J114-K114-L114 -> 9300 | P114: =+L114/0.006 -> -9300 | Q114: =+M114+P114 -> 0
A115: 05-09-2025 | B115: Liquidación de dinero | C115: 124387263837 | D115: 15491.37 | E115: 8780124.6 | F115: COBRO | I115: =-IFERROR(VLOOKUP(C115,SIRCUPA!$A$21:$H$155,8,0),0) -> 0 | J115: =-IFERROR(VLOOKUP(C115,SIRTAC!$A$16:$H$1288,8,0),0) -> -159 | K115: =-IFERROR(VLOOKUP(C115,Gastos!$A$9:$J$1281,10,0),0) -> -154.23 | L115: =-IFERROR(VLOOKUP(C115,IDC!$A$25:$H$1532,8,0),0) -> -95.4 | M115: =+D115-I115-J115-K115-L115 -> 15900 | P115: =+L115/0.006 -> -15900 | Q115: =+M115+P115 -> 0
A116: 05-09-2025 | B116: Liquidación de dinero | C116: 124932672660 | D116: 4871.5 | E116: 8784996.1 | F116: COBRO | I116: =-IFERROR(VLOOKUP(C116,SIRCUPA!$A$21:$H$155,8,0),0) -> 0 | J116: =-IFERROR(VLOOKUP(C116,SIRTAC!$A$16:$H$1288,8,0),0) -> -50 | K116: =-IFERROR(VLOOKUP(C116,Gastos!$A$9:$J$1281,10,0),0) -> -48.5 | L116: =-IFERROR(VLOOKUP(C116,IDC!$A$25:$H$1532,8,0),0) -> -30 | M116: =+D116-I116-J116-K116-L116 -> 5000 | P116: =+L116/0.006 -> -5000 | Q116: =+M116+P116 -> 0
A117: 05-09-2025 | B117: Liquidación de dinero | C117: 124932574010 | D117: 4539.5 | E117: 8789535.6 | F117: COBRO | I117: =-IFERROR(VLOOKUP(C117,SIRCUPA!$A$21:$H$155,8,0),0) -> 0 | J117: =-IFERROR(VLOOKUP(C117,SIRTAC!$A$16:$H$1288,8,0),0) -> -50 | K117: =-IFERROR(VLOOKUP(C117,Gastos!$A$9:$J$1281,10,0),0) -> -380.5 | L117: =-IFERROR(VLOOKUP(C117,IDC!$A$25:$H$1532,8,0),0) -> -30 | M117: =+D117-I117-J117-K117-L117 -> 5000 | P117: =+L117/0.006 -> -5000 | Q117: =+M117+P117 -> 0
A118: 05-09-2025 | B118: Liquidación de dinero | C118: 124387491809 | D118: 68980.44 | E118: 8858516.1 | F118: COBRO | I118: =-IFERROR(VLOOKUP(C118,SIRCUPA!$A$21:$H$155,8,0),0) -> 0 | J118: =-IFERROR(VLOOKUP(C118,SIRTAC!$A$16:$H$1288,8,0),0) -> -708 | K118: =-IFERROR(VLOOKUP(C118,Gastos!$A$9:$J$1281,10,0),0) -> -686.76 | L118: =-IFERROR(VLOOKUP(C118,IDC!$A$25:$H$1532,8,0),0) -> -424.8 | M118: =+D118-I118-J118-K118-L118 -> 70800 | P118: =+L118/0.006 -> -70800 | Q118: =+M118+P118 -> 0
A119: 05-09-2025 | B119: Liquidación de dinero | C119: 124932738810 | D119: 2143.46 | E119: 8860659.5 | F119: COBRO | I119: =-IFERROR(VLOOKUP(C119,SIRCUPA!$A$21:$H$155,8,0),0) -> 0 | J119: =-IFERROR(VLOOKUP(C119,SIRTAC!$A$16:$H$1288,8,0),0) -> -22 | K119: =-IFERROR(VLOOKUP(C119,Gastos!$A$9:$J$1281,10,0),0) -> -21.34 | L119: =-IFERROR(VLOOKUP(C119,IDC!$A$25:$H$1532,8,0),0) -> -13.2 | M119: =+D119-I119-J119-K119-L119 -> 2200 | P119: =+L119/0.006 -> -2200 | Q119: =+M119+P119 -> 0
A120: 05-09-2025 | B120: Liquidación de dinero | C120: 124933058374 | D120: 15686.23 | E120: 8876345.8 | F120: COBRO | I120: =-IFERROR(VLOOKUP(C120,SIRCUPA!$A$21:$H$155,8,0),0) -> 0 | J120: =-IFERROR(VLOOKUP(C120,SIRTAC!$A$16:$H$1288,8,0),0) -> -161 | K120: =-IFERROR(VLOOKUP(C120,Gastos!$A$9:$J$1281,10,0),0) -> -156.17 | L120: =-IFERROR(VLOOKUP(C120,IDC!$A$25:$H$1532,8,0),0) -> -96.6 | M120: =+D120-I120-J120-K120-L120 -> 16100 | P120: =+L120/0.006 -> -16100 | Q120: =+M120+P120 -> 0
A121: 05-09-2025 | B121: Liquidación de dinero | C121: 124933214738 | D121: 4189.49 | E121: 8880535.2 | F121: COBRO | I121: =-IFERROR(VLOOKUP(C121,SIRCUPA!$A$21:$H$155,8,0),0) -> 0 | J121: =-IFERROR(VLOOKUP(C121,SIRTAC!$A$16:$H$1288,8,0),0) -> -43 | K121: =-IFERROR(VLOOKUP(C121,Gastos!$A$9:$J$1281,10,0),0) -> -41.71 | L121: =-IFERROR(VLOOKUP(C121,IDC!$A$25:$H$1532,8,0),0) -> -25.8 | M121: =+D121-I121-J121-K121-L121 -> 4300 | P121: =+L121/0.006 -> -4300 | Q121: =+M121+P121 -> 0
... A206: 05-09-2025 | B206: Liquidación de dinero | C206: 124542531059 | D206: 25721.52 | E206: 7410201.4 | F206: COBRO | I206: =-IFERROR(VLOOKUP(C206,SIRCUPA!$A$21:$H$155,8,0),0) -> 0 | J206: =-IFERROR(VLOOKUP(C206,SIRTAC!$A$16:$H$1288,8,0),0) -> -264 | K206: =-IFERROR(VLOOKUP(C206,Gastos!$A$9:$J$1281,10,0),0) -> -256.08 | L206: =-IFERROR(VLOOKUP(C206,IDC!$A$25:$H$1532,8,0),0) -> -158.4 | M206: =+D206-I206-J206-K206-L206 -> 26400 | P206: =+L206/0.006 -> -26400 | Q206: =+M206+P206 -> 0
A207: 11-09-2025 | B207: Impuesto por extracción | C207: 125778500554 | D207: -1435.64 | E207: 8389117 | F207: IDC | G207: =+D207/0.006 -> -239273.33 | I207: =-IFERROR(VLOOKUP(C207,SIRCUPA!$A$21:$H$155,8,0),0) -> 0 | J207: =-IFERROR(VLOOKUP(C207,SIRTAC!$A$16:$H$1288,8,0),0) -> 0 | K207: =-IFERROR(VLOOKUP(C207,Gastos!$A$9:$J$1281,10,0),0) -> 0 | L207: =-IFERROR(VLOOKUP(C207,IDC!$A$25:$H$1532,8,0),0) -> -1435.64 | M207: =+D207 -> -1435.64 | Q207: =+L207 -> -1435.64 | R207: =+M207-Q207 -> 0
A208: 13-09-2025 | B208: Impuesto por extracción | C208: 125494013461 | D208: -3869.4 | E208: 10886070 | F208: IDC | G208: =+D208/0.006 -> -644900 | I208: =-IFERROR(VLOOKUP(C208,SIRCUPA!$A$21:$H$155,8,0),0) -> 0 | J208: =-IFERROR(VLOOKUP(C208,SIRTAC!$A$16:$H$1288,8,0),0) -> 0 | K208: =-IFERROR(VLOOKUP(C208,Gastos!$A$9:$J$1281,10,0),0) -> 0 | L208: =-IFERROR(VLOOKUP(C208,IDC!$A$25:$H$1532,8,0),0) -> -3869.4 | M208: =+D208 -> -3869.4 | Q208: =+L208 -> -3869.4 | R208: =+M208-Q208 -> 0
A209: 15-09-2025 | B209: Impuesto por extracción | C209: 125715190737 | D209: -1587.26 | E209: 12406681 | F209: IDC | G209: =+D209/0.006 -> -264543.33 | I209: =-IFERROR(VLOOKUP(C209,SIRCUPA!$A$21:$H$155,8,0),0) -> 0 | J209: =-IFERROR(VLOOKUP(C209,SIRTAC!$A$16:$H$1288,8,0),0) -> 0 | K209: =-IFERROR(VLOOKUP(C209,Gastos!$A$9:$J$1281,10,0),0) -> 0 | L209: =-IFERROR(VLOOKUP(C209,IDC!$A$25:$H$1532,8,0),0) -> -1587.26 | M209: =+D209 -> -1587.26 | Q209: =+L209 -> -1587.26 | R209: =+M209-Q209 -> 0
A210: 06-09-2025 | B210: Liquidación de dinero | C210: 125088844362 | D210: 8378.98 | E210: 7418580.4 | F210: COBRO | I210: =-IFERROR(VLOOKUP(C210,SIRCUPA!$A$21:$H$155,8,0),0) -> 0 | J210: =-IFERROR(VLOOKUP(C210,SIRTAC!$A$16:$H$1288,8,0),0) -> -86 | K210: =-IFERROR(VLOOKUP(C210,Gastos!$A$9:$J$1281,10,0),0) -> -83.42 | L210: =-IFERROR(VLOOKUP(C210,IDC!$A$25:$H$1532,8,0),0) -> -51.6 | M210: =+D210-I210-J210-K210-L210 -> 8600 | P210: =+L210/0.006 -> -8600 | Q210: =+M210+P210 -> 0
A211: 06-09-2025 | B211: Liquidación de dinero | C211: 125088894738 | D211: 12276.18 | E211: 7430856.6 | F211: COBRO | I211: =-IFERROR(VLOOKUP(C211,SIRCUPA!$A$21:$H$155,8,0),0) -> 0 | J211: =-IFERROR(VLOOKUP(C211,SIRTAC!$A$16:$H$1288,8,0),0) -> -126 | K211: =-IFERROR(VLOOKUP(C211,Gastos!$A$9:$J$1281,10,0),0) -> -122.22 | L211: =-IFERROR(VLOOKUP(C211,IDC!$A$25:$H$1532,8,0),0) -> -75.6 | M211: =+D211-I211-J211-K211-L211 -> 12600 | P211: =+L211/0.006 -> -12600 | Q211: =+M211+P211 -> 0
A212: 06-09-2025 | B212: Liquidación de dinero | C212: 125088899534 | D212: 33158.97 | E212: 7464015.5 | F212: COBRO | I212: =-IFERROR(VLOOKUP(C212,SIRCUPA!$A$21:$H$155,8,0),0) -> 0 | J212: =-IFERROR(VLOOKUP(C212,SIRTAC!$A$16:$H$1288,8,0),0) -> -351 | K212: =-IFERROR(VLOOKUP(C212,Gastos!$A$9:$J$1281,10,0),0) -> -1379.43 | L212: =-IFERROR(VLOOKUP(C212,IDC!$A$25:$H$1532,8,0),0) -> -210.6 | M212: =+D212-I212-J212-K212-L212 -> 35100 | P212: =+L212/0.006 -> -35100 | Q212: =+M212+P212 -> 0
A213: 06-09-2025 | B213: Liquidación de dinero | C213: 125088923310 | D213: 31957.04 | E213: 7495972.6 | F213: COBRO | I213: =-IFERROR(VLOOKUP(C213,SIRCUPA!$A$21:$H$155,8,0),0) -> 0 | J213: =-IFERROR(VLOOKUP(C213,SIRTAC!$A$16:$H$1288,8,0),0) -> -328 | K213: =-IFERROR(VLOOKUP(C213,Gastos!$A$9:$J$1281,10,0),0) -> -318.16 | L213: =-IFERROR(VLOOKUP(C213,IDC!$A$25:$H$1532,8,0),0) -> -196.8 | M213: =+D213-I213-J213-K213-L213 -> 32800 | P213: =+L213/0.006 -> -32800 | Q213: =+M213+P213 -> 0
A214: 06-09-2025 | B214: Transferencia recibida Laureana Paula Calvo | C214: 125088937092 | D214: 1605.56 | E214: 7497578.1 | F214: COBRO | I214: =-IFERROR(VLOOKUP(C214,SIRCUPA!$A$21:$H$155,8,0),0) -> -24.6 | J214: =-IFERROR(VLOOKUP(C214,SIRTAC!$A$16:$H$1288,8,0),0) -> 0 | K214: =-IFERROR(VLOOKUP(C214,Gastos!$A$9:$J$1281,10,0),0) -> 0 | L214: =-IFERROR(VLOOKUP(C214,IDC!$A$25:$H$1532,8,0),0) -> -9.84 | M214: =+D214-I214-J214-K214-L214 -> 1640 | P214: =+L214/0.006 -> -1640 | Q214: =+M214+P214 -> 0
A215: 06-09-2025 | B215: Liquidación de dinero | C215: 125089015400 | D215: 4161.11 | E215: 7501739.2 | F215: COBRO | I215: =-IFERROR(VLOOKUP(C215,SIRCUPA!$A$21:$H$155,8,0),0) -> 0 | J215: =-IFERROR(VLOOKUP(C215,SIRTAC!$A$16:$H$1288,8,0),0) -> -43 | K215: =-IFERROR(VLOOKUP(C215,Gastos!$A$9:$J$1281,10,0),0) -> -70.09 | L215: =-IFERROR(VLOOKUP(C215,IDC!$A$25:$H$1532,8,0),0) -> -25.8 | M215: =+D215-I215-J215-K215-L215 -> 4300 | P215: =+L215/0.006 -> -4300 | Q215: =+M215+P215 -> 0
A216: 06-09-2025 | B216: Liquidación de dinero | C216: 124543378311 | D216: 33675.96 | E216: 7535415.2 | F216: COBRO | I216: =-IFERROR(VLOOKUP(C216,SIRCUPA!$A$21:$H$155,8,0),0) -> 0 | J216: =-IFERROR(VLOOKUP(C216,SIRTAC!$A$16:$H$1288,8,0),0) -> -348 | K216: =-IFERROR(VLOOKUP(C216,Gastos!$A$9:$J$1281,10,0),0) -> -567.24 | L216: =-IFERROR(VLOOKUP(C216,IDC!$A$25:$H$1532,8,0),0) -> -208.8 | M216: =+D216-I216-J216-K216-L216 -> 34800 | P216: =+L216/0.006 -> -34800 | Q216: =+M216+P216 -> 0
A217: 06-09-2025 | B217: Liquidación de dinero | C217: 125089355560 | D217: 9060.99 | E217: 7544476.2 | F217: COBRO | I217: =-IFERROR(VLOOKUP(C217,SIRCUPA!$A$21:$H$155,8,0),0) -> 0 | J217: =-IFERROR(VLOOKUP(C217,SIRTAC!$A$16:$H$1288,8,0),0) -> -93 | K217: =-IFERROR(VLOOKUP(C217,Gastos!$A$9:$J$1281,10,0),0) -> -90.21 | L217: =-IFERROR(VLOOKUP(C217,IDC!$A$25:$H$1532,8,0),0) -> -55.8 | M217: =+D217-I217-J217-K217-L217 -> 9300 | P217: =+L217/0.006 -> -9300 | Q217: =+M217+P217 -> 0
A218: 06-09-2025 | B218: Liquidación de dinero | C218: 124543543841 | D218: 46179.12 | E218: 7590655.3 | F218: COBRO | I218: =-IFERROR(VLOOKUP(C218,SIRCUPA!$A$21:$H$155,8,0),0) -> 0 | J218: =-IFERROR(VLOOKUP(C218,SIRTAC!$A$16:$H$1288,8,0),0) -> -492 | K218: =-IFERROR(VLOOKUP(C218,Gastos!$A$9:$J$1281,10,0),0) -> -2233.68 | L218: =-IFERROR(VLOOKUP(C218,IDC!$A$25:$H$1532,8,0),0) -> -295.2 | M218: =+D218-I218-J218-K218-L218 -> 49200 | P218: =+L218/0.006 -> -49200 | Q218: =+M218+P218 -> 0
A219: 06-09-2025 | B219: Liquidación de dinero | C219: 125089683168 | D219: 44684.31 | E219: 7635339.6 | F219: COBRO | I219: =-IFERROR(VLOOKUP(C219,SIRCUPA!$A$21:$H$155,8,0),0) -> 0 | J219: =-IFERROR(VLOOKUP(C219,SIRTAC!$A$16:$H$1288,8,0),0) -> -473 | K219: =-IFERROR(VLOOKUP(C219,Gastos!$A$9:$J$1281,10,0),0) -> -1858.89 | L219: =-IFERROR(VLOOKUP(C219,IDC!$A$25:$H$1532,8,0),0) -> -283.8 | M219: =+D219-I219-J219-K219-L219 -> 47300 | P219: =+L219/0.006 -> -47300 | Q219: =+M219+P219 -> 0
A220: 06-09-2025 | B220: Liquidación de dinero | C220: 125089938206 | D220: 24649.79 | E220: 7659989.4 | F220: COBRO | I220: =-IFERROR(VLOOKUP(C220,SIRCUPA!$A$21:$H$155,8,0),0) -> 0 | J220: =-IFERROR(VLOOKUP(C220,SIRTAC!$A$16:$H$1288,8,0),0) -> -253 | K220: =-IFERROR(VLOOKUP(C220,Gastos!$A$9:$J$1281,10,0),0) -> -245.41 | L220: =-IFERROR(VLOOKUP(C220,IDC!$A$25:$H$1532,8,0),0) -> -151.8 | M220: =+D220-I220-J220-K220-L220 -> 25300 | P220: =+L220/0.006 -> -25300 | Q220: =+M220+P220 -> 0
A221: 06-09-2025 | B221: Liquidación de dinero | C221: 124544646101 | D221: 12178.75 | E221: 7672168.2 | F221: COBRO | I221: =-IFERROR(VLOOKUP(C221,SIRCUPA!$A$21:$H$155,8,0),0) -> 0 | J221: =-IFERROR(VLOOKUP(C221,SIRTAC!$A$16:$H$1288,8,0),0) -> -125 | K221: =-IFERROR(VLOOKUP(C221,Gastos!$A$9:$J$1281,10,0),0) -> -121.25 | L221: =-IFERROR(VLOOKUP(C221,IDC!$A$25:$H$1532,8,0),0) -> -75 | M221: =+D221-I221-J221-K221-L221 -> 12500 | P221: =+L221/0.006 -> -12500 | Q221: =+M221+P221 -> 0
... A264: 06-09-2025 | B264: Liquidación de dinero | C264: 124549540369 | D264: 13640.2 | E264: 8594781.9 | F264: COBRO | I264: =-IFERROR(VLOOKUP(C264,SIRCUPA!$A$21:$H$155,8,0),0) -> 0 | J264: =-IFERROR(VLOOKUP(C264,SIRTAC!$A$16:$H$1288,8,0),0) -> -140 | K264: =-IFERROR(VLOOKUP(C264,Gastos!$A$9:$J$1281,10,0),0) -> -135.8 | L264: =-IFERROR(VLOOKUP(C264,IDC!$A$25:$H$1532,8,0),0) -> -84 | M264: =+D264-I264-J264-K264-L264 -> 14000 | P264: =+L264/0.006 -> -14000 | Q264: =+M264+P264 -> 0
A265: 06-09-2025 | B265: Liquidación de dinero | C265: 125095467130 | D265: 77944 | E265: 8672725.9 | F265: COBRO | I265: =-IFERROR(VLOOKUP(C265,SIRCUPA!$A$21:$H$155,8,0),0) -> 0 | J265: -800 | K265: =-IFERROR(VLOOKUP(C265,Gastos!$A$9:$J$1281,10,0),0) -> -776 | L265: -480 | M265: =+D265-I265-J265-K265-L265 -> 80000 | P265: =+L265/0.006 -> -80000 | Q265: =+M265+P265 -> 0
A266: 06-09-2025 | B266: Liquidación de dinero cancelada Venta cancelada | C266: 125095467130 | D266: -77944 | E266: 8594781.9 | F266: COBRO | I266: =-IFERROR(VLOOKUP(C266,SIRCUPA!$A$21:$H$155,8,0),0) -> 0 | J266: =-IFERROR(VLOOKUP(C266,SIRTAC!$A$16:$H$1288,8,0),0) -> 800 | K266: 776 | L266: =-IFERROR(VLOOKUP(C266,IDC!$A$25:$H$1532,8,0),0) -> 480 | M266: =+D266-I266-J266-K266-L266 -> -80000 | P266: =+L266/0.006 -> 80000 | Q266: =+M266+P266 -> 0
A267: 06-09-2025 | B267: Liquidación de dinero | C267: 125095831262 | D267: 70247.03 | E267: 8665029 | F267: COBRO | I267: =-IFERROR(VLOOKUP(C267,SIRCUPA!$A$21:$H$155,8,0),0) -> 0 | J267: =-IFERROR(VLOOKUP(C267,SIRTAC!$A$16:$H$1288,8,0),0) -> -721 | K267: =-IFERROR(VLOOKUP(C267,Gastos!$A$9:$J$1281,10,0),0) -> -699.37 | L267: =-IFERROR(VLOOKUP(C267,IDC!$A$25:$H$1532,8,0),0) -> -432.6 | M267: =+D267-I267-J267-K267-L267 -> 72100 | P267: =+L267/0.006 -> -72100 | Q267: =+M267+P267 -> 0
...

Sheet Detallado
A1: INITIAL_BALANCE | B1: CREDITS | C1: DEBITS | D1: FINAL_BALANCE
A2: 12.889.777,09 | B2: 32.094.654,58 | C2: -34.101.823,16 | D2: 10.882.608,51
A4: RELEASE_DATE | B4: TRANSACTION_TYPE | C4: REFERENCE_ID | D4: TRANSACTION_NET_AMOUNT | E4: PARTIAL_BALANCE | F4: VARIOS | G4: TRANSACTION_TOTAL_AMOUNT | H4: IDC COMPRAS
A5: 01-09-2025 | B5: Liquidación de dinero | C5: 123864040285 | D5: 14614.5 | E5: 12904392 | F5: VENTA | G5: =+D5 -> 14614.5 | H5: 0
A6: 01-09-2025 | B6: Liquidación de dinero | C6: 123864645949 | D6: 17050.25 | E6: 12921442 | F6: VENTA | G6: =+D6 -> 17050.25 | H6: 0
A7: 01-09-2025 | B7: Liquidación de dinero | C7: 124407346652 | D7: 11984.28 | E7: 12933426 | F7: VENTA | G7: =+D7 -> 11984.28 | H7: 0
A8: 01-09-2025 | B8: Transferencia recibida Juan Felipe Folmer Dondena | C8: 123865265509 | D8: 646.14 | E8: 12934072 | F8: VENTA | G8: =+D8 -> 646.14 | H8: 0
A9: 01-09-2025 | B9: Liquidación de dinero | C9: 124407749182 | D9: 23870.35 | E9: 12957943 | F9: VENTA | G9: =+D9 -> 23870.35 | H9: 0
A10: 01-09-2025 | B10: Liquidación de dinero | C10: 123868184561 | D10: 9743 | E10: 12967686 | F10: VENTA | G10: =+D10 -> 9743 | H10: 0
A11: 01-09-2025 | B11: Liquidación de dinero | C11: 123868170745 | D11: 13153.05 | E11: 12980839 | F11: VENTA | G11: =+D11 -> 13153.05 | H11: 0
A12: 01-09-2025 | B12: Impuesto por extracción | C12: 124446003662 | D12: -550.29 | E12: 12726787 | G12: =+D12 -> -550.29
A13: 01-09-2025 | B13: Impuesto por extracción | C13: 124489977054 | D13: -1012.07 | E13: 12043724 | G13: =+D13 -> -1012.07
A14: 01-09-2025 | B14: Impuesto por extracción | C14: 124454118654 | D14: -1641.99 | E14: 12451480 | G14: =+D14 -> -1641.99
A15: 01-09-2025 | B15: Pago con QR FEPASA | C15: 124454118654 | D15: -273665.16 | E15: 12453122 | G15: =+D15/1.006 -> -272032.96 | H15: =+D15-G15 -> -1632.1978
A16: 01-09-2025 | B16: Transferencia enviada ACERO JEKLO SAS | C16: 124489977054 | D16: -168677.75 | E16: 12044736 | G16: =+D16/1.006 -> -167671.72 | H16: =+D16-G16 -> -1006.0303
A17: 01-09-2025 | B17: Transferencia enviada CDG SRL | C17: 124446003662 | D17: -91714.5 | E17: 12727337 | G17: =+D17/1.006 -> -91167.495 | H17: =+D17-G17 -> -547.00497
A18: 01-09-2025 | B18: Transferencia enviada DOÑA DORA | C18: 123897475515 | D18: -161786.93 | E18: 12819052 | G18: =+D18/1.006 -> -160822 | H18: =+D18-G18 -> -964.93199
A19: 01-09-2025 | B19: Transferencia enviada Rodolfo Oscar Bidal | C19: 124459001098 | D19: -238065.88 | E19: 12213414 | G19: =+D19/1.006 -> -236646 | H19: =+D19-G19 -> -1419.876
A20: 02-09-2025 | B20: Impuesto por extracción | C20: 124618927966 | D20: -505.77 | E20: 9757899.5 | G20: =+D20 -> -505.77
A21: 02-09-2025 | B21: Impuesto por extracción | C21: 124624594370 | D21: -1294.34 | E21: 9540881 | G21: =+D21 -> -1294.34
A22: 02-09-2025 | B22: Impuesto por extracción | C22: 124031772669 | D22: -4710.99 | E22: 9842700.2 | G22: =+D22 -> -4710.99
A23: 02-09-2025 | B23: Impuesto por extracción | C23: 124014458903 | D23: -5892.5 | E23: 11055747 | G23: =+D23 -> -5892.5
A24: 02-09-2025 | B24: Transferencia enviada BACO DE LOS ANDES SA | C24: 124014458903 | D24: -982084.1 | E24: 11061640 | G24: =+D24/1.006 -> -976226.74 | H24: =+D24-G24 -> -5857.3604
A25: 02-09-2025 | B25: Transferencia enviada Distribuidora Doña Dora | C25: 124018294619 | D25: -423171.26 | E25: 10632576 | G25: =+D25/1.006 -> -420647.38 | H25: =+D25-G25 -> -2523.8843
A26: 02-09-2025 | B26: Transferencia enviada Granja La Blanquita S.r.l. | C26: 124031772669 | D26: -785165 | E26: 9847411.2 | G26: =+D26/1.006 -> -780482.11 | H26: =+D26-G26 -> -4682.8926
A27: 02-09-2025 | B27: Transferencia enviada SUCESION DE SATTO | C27: 124618927966 | D27: -84294.94 | E27: 9758405.3 | G27: =+D27/1.006 -> -83792.187 | H27: =+D27-G27 -> -502.75312
A28: 02-09-2025 | B28: Transferencia enviada SUCESION DE SATTO | C28: 124624594370 | D28: -215724.16 | E28: 9542175.4 | G28: =+D28/1.006 -> -214437.53 | H28: =+D28-G28 -> -1286.6252
A29: 03-09-2025 | B29: Liquidación de dinero | C29: 124234497707 | D29: 4774.07 | E29: 9025016.9 | F29: VENTA | G29: =+D29 -> 4774.07 | H29: 0
A30: 03-09-2025 | B30: Liquidación de dinero | C30: 124781182650 | D30: 8071.96 | E30: 9033088.9 | F30: VENTA | G30: =+D30 -> 8071.96 | H30: 0
A31: 03-09-2025 | B31: Liquidación de dinero | C31: 124236889607 | D31: 28546.99 | E31: 9061635.9 | F31: VENTA | G31: =+D31 -> 28546.99 | H31: 0
A32: 03-09-2025 | B32: Transferencia recibida Joaquin Pedro Schenone | C32: 124236877691 | D32: 1434.23 | E32: 9063070.1 | F32: VENTA | G32: =+D32 -> 1434.23 | H32: 0
A33: 03-09-2025 | B33: Liquidación de dinero | C33: 124784681512 | D33: 28144.9 | E33: 9091215 | F33: VENTA | G33: =+D33 -> 28144.9 | H33: 0
A34: 03-09-2025 | B34: Liquidación de dinero | C34: 124788106000 | D34: 5006.91 | E34: 9096221.9 | F34: VENTA | G34: =+D34 -> 5006.91 | H34: 0
A35: 03-09-2025 | B35: Liquidación de dinero | C35: 124245392201 | D35: 33223.63 | E35: 9129445.5 | F35: VENTA | G35: =+D35 -> 33223.63 | H35: 0
A36: 03-09-2025 | B36: Liquidación de dinero | C36: 124245389515 | D36: 44817.8 | E36: 9174263.3 | F36: VENTA | G36: =+D36 -> 44817.8 | H36: 0
A37: 03-09-2025 | B37: Liquidación de dinero | C37: 124247706111 | D37: 11983.89 | E37: 9186247.2 | F37: VENTA | G37: =+D37 -> 11983.89 | H37: 0
A38: 03-09-2025 | B38: Liquidación de dinero | C38: 124795296394 | D38: 19485.03 | E38: 9205732.2 | F38: VENTA | G38: =+D38 -> 19485.03 | H38: 0
A39: 03-09-2025 | B39: Liquidación de dinero | C39: 124251168101 | D39: 58356.67 | E39: 9264088.9 | F39: VENTA | G39: =+D39 -> 58356.67 | H39: 0
A40: 03-09-2025 | B40: Liquidación de dinero | C40: 124251556927 | D40: 69175.3 | E40: 9333264.2 | F40: VENTA | G40: =+D40 -> 69175.3 | H40: 0
A41: 03-09-2025 | B41: Impuesto por extracción | C41: 124774089426 | D41: -271.44 | E41: 9020242.8 | G41: =+D41 -> -271.44
A42: 03-09-2025 | B42: Impuesto por extracción | C42: 124167213727 | D42: -645.69 | E42: 9432620.2 | G42: =+D42 -> -645.69
A43: 03-09-2025 | B43: Impuesto por extracción | C43: 124761516066 | D43: -1262.06 | E43: 9065753.9 | G43: =+D43 -> -1262.06
A44: 03-09-2025 | B44: Pago con QR Coca-Cola ANDINA | C44: 124774089426 | D44: -45239.61 | E44: 9020514.3 | G44: =+D44/1.006 -> -44969.791 | H44: =+D44-G44 -> -269.81875
A45: 03-09-2025 | B45: Pago con QR Coca-Cola ANDINA | C45: 124761516066 | D45: -210343.29 | E45: 9067015.9 | G45: =+D45/1.006 -> -209088.76 | H45: =+D45-G45 -> -1254.5325
A46: 03-09-2025 | B46: Transferencia enviada Mariano Pedro Rebord Palazzo | C46: 124169559701 | D46: -155261.01 | E46: 9277359.2 | G46: =+D46/1.006 -> -154335 | H46: =+D46-G46 -> -926.01
A47: 03-09-2025 | B47: Transferencia enviada SUCESION DE SATTO | C47: 124167213727 | D47: -107615.09 | E47: 9433265.9 | G47: =+D47/1.006 -> -106973.25 | H47: =+D47-G47 -> -641.8395
A48: 04-09-2025 | B48: Liquidación de dinero | C48: 124797073790 | D48: 55729.96 | E48: 9388994.2 | F48: VENTA | G48: =+D48 -> 55729.96 | H48: 0
A49: 04-09-2025 | B49: Liquidación de dinero | C49: 124797394520 | D49: 35756.81 | E49: 9424751 | F49: VENTA | G49: =+D49 -> 35756.81 | H49: 0
A50: 04-09-2025 | B50: Transferencia recibida Ivan Goldin | C50: 124253070499 | D50: 1796.46 | E50: 9426547.4 | F50: VENTA | G50: =+D50 -> 1796.46 | H50: 0
A51: 04-09-2025 | B51: Liquidación de dinero | C51: 124797743380 | D51: 138720.76 | E51: 9565268.2 | F51: VENTA | G51: =+D51 -> 138720.76 | H51: 0
A52: 04-09-2025 | B52: Liquidación de dinero | C52: 124797908608 | D52: 14072.45 | E52: 9579340.7 | F52: VENTA | G52: =+D52 -> 14072.45 | H52: 0
A53: 04-09-2025 | B53: Liquidación de dinero | C53: 124253989611 | D53: 20362.87 | E53: 9599703.5 | F53: VENTA | G53: =+D53 -> 20362.87 | H53: 0
A54: 04-09-2025 | B54: Liquidación de dinero | C54: 124798439032 | D54: 27475.26 | E54: 9627178.8 | F54: VENTA | G54: =+D54 -> 27475.26 | H54: 0
A55: 04-09-2025 | B55: Transferencia recibida Tahiel Heredia | C55: 124254045511 | D55: 1380.39 | E55: 9628559.2 | F55: VENTA | G55: =+D55 -> 1380.39 | H55: 0
A56: 04-09-2025 | B56: Liquidación de dinero | C56: 124798706468 | D56: 9548.14 | E56: 9638107.3 | F56: VENTA | G56: =+D56 -> 9548.14 | H56: 0
A57: 04-09-2025 | B57: Liquidación de dinero | C57: 124800062204 | D57: 45984.04 | E57: 9684091.4 | F57: VENTA | G57: =+D57 -> 45984.04 | H57: 0
A58: 04-09-2025 | B58: Liquidación de dinero | C58: 124256095479 | D58: 19484.05 | E58: 9703575.4 | F58: VENTA | G58: =+D58 -> 19484.05 | H58: 0
A59: 04-09-2025 | B59: Liquidación de dinero | C59: 124907529624 | D59: 15491.37 | E59: 8104551.2 | F59: VENTA | G59: =+D59 -> 15491.37 | H59: 0
... A100: 04-09-2025 | B100: Liquidación de dinero | C100: 124931811338 | D100: 1851.17 | E100: 8684081.9 | F100: VENTA | G100: =+D100 -> 1851.17 | H100: 0
A101: 04-09-2025 | B101: Impuesto por extracción | C101: 124856861194 | D101: -822.12 | E101: 8089059.8 | G101: =+D101 -> -822.12
A102: 04-09-2025 | B102: Impuesto por extracción | C102: 124845509146 | D102: -1320.16 | E102: 8226901.9 | G102: =+D102 -> -1320.16
A103: 04-09-2025 | B103: Impuesto por extracción | C103: 124293086141 | D103: -7357.44 | E103: 8469978 | G103: =+D103 -> -7357.44
A104: 04-09-2025 | B104: Transferencia enviada | C104: 124295531407 | D104: -21729.59 | E104: 8448248.4 | F104: BRODE | G104: =+D104/1.006 -> -21599.99 | H104: =+D104-G104 -> -129.59994
A105: 04-09-2025 | B105: Transferencia enviada FRUVECO S R L | C105: 124856861194 | D105: -137020 | E105: 8089881.9 | G105: =+D105/1.006 -> -136202.78 | H105: =+D105-G105 -> -817.2167
A106: 04-09-2025 | B106: Transferencia enviada FRUVECO S R L | C106: 124845509146 | D106: -220026.32 | E106: 8228222.1 | G106: =+D106/1.006 -> -218714.04 | H106: =+D106-G106 -> -1312.2842
A107: 04-09-2025 | B107: Transferencia enviada LAGUNA CAPRI SAS | C107: 124293086141 | D107: -1226240 | E107: 8477335.4 | G107: =+D107/1.006 -> -1218926.4 | H107: =+D107-G107 -> -7313.5586
A108: 05-09-2025 | B108: Liquidación de dinero | C108: 124386853415 | D108: 3799.77 | E108: 8687881.7 | F108: VENTA | G108: =+D108 -> 3799.77 | H108: 0
A109: 05-09-2025 | B109: Transferencia recibida Nicanor Ormaechea | C109: 124386769841 | D109: 381.81 | E109: 8688263.5 | F109: VENTA | G109: =+D109 -> 381.81 | H109: 0
A110: 05-09-2025 | B110: Liquidación de dinero | C110: 124932013860 | D110: 59319.52 | E110: 8747583 | F110: VENTA | G110: =+D110 -> 59319.52 | H110: 0
A111: 05-09-2025 | B111: Liquidación de dinero | C111: 124387202427 | D111: 7989.26 | E111: 8755572.3 | F111: VENTA | G111: =+D111 -> 7989.26 | H111: 0
A112: 05-09-2025 | B112: Liquidación de dinero | C112: 124387169897 | D112: 9060.99 | E112: 8764633.3 | F112: VENTA | G112: =+D112 -> 9060.99 | H112: 0
A113: 05-09-2025 | B113: Liquidación de dinero | C113: 124387263837 | D113: 15491.37 | E113: 8780124.6 | F113: VENTA | G113: =+D113 -> 15491.37 | H113: 0
A114: 05-09-2025 | B114: Liquidación de dinero | C114: 124932672660 | D114: 4871.5 | E114: 8784996.1 | F114: VENTA | G114: =+D114 -> 4871.5 | H114: 0
A115: 05-09-2025 | B115: Liquidación de dinero | C115: 124932574010 | D115: 4539.5 | E115: 8789535.6 | F115: VENTA | G115: =+D115 -> 4539.5 | H115: 0
A116: 05-09-2025 | B116: Liquidación de dinero | C116: 124387491809 | D116: 68980.44 | E116: 8858516.1 | F116: VENTA | G116: =+D116 -> 68980.44 | H116: 0
A117: 05-09-2025 | B117: Liquidación de dinero | C117: 124932738810 | D117: 2143.46 | E117: 8860659.5 | F117: VENTA | G117: =+D117 -> 2143.46 | H117: 0
A118: 05-09-2025 | B118: Liquidación de dinero | C118: 124933058374 | D118: 15686.23 | E118: 8876345.8 | F118: VENTA | G118: =+D118 -> 15686.23 | H118: 0
A119: 05-09-2025 | B119: Liquidación de dinero | C119: 124933214738 | D119: 4189.49 | E119: 8880535.2 | F119: VENTA | G119: =+D119 -> 4189.49 | H119: 0
... A204: 05-09-2025 | B204: Liquidación de dinero | C204: 124542531059 | D204: 25721.52 | E204: 7410201.4 | F204: VENTA | G204: =+D204 -> 25721.52 | H204: 0
A205: 05-09-2025 | B205: Impuesto por extracción | C205: 124420739261 | D205: -2599.61 | E205: 9176818.9 | G205: =+D205 -> -2599.61
A206: 05-09-2025 | B206: Pago de servicios ARCA | C206: 124474681067 | D206: -2213333.8 | E206: 6963485 | G206: =+D206/1.006 -> -2200133 | H206: =+D206-G206 -> -13200.798
A207: 05-09-2025 | B207: Transferencia enviada BASSO REPRESENT SRL | C207: 124420739261 | D207: -433268.17 | E207: 9179418.5 | G207: =+D207/1.006 -> -430684.07 | H207: =+D207-G207 -> -2584.1044
A208: 05-09-2025 | B208: Transferencia enviada Distribuidora Doña Dora | C208: 125037170650 | D208: -138386.69 | E208: 6439252.7 | G208: =+D208/1.006 -> -137561.32 | H208: =+D208-G208 -> -825.36793
A209: 05-09-2025 | B209: Transferencia enviada Distribuidora Doña Dora | C209: 124490574149 | D209: -385845.67 | E209: 6577639.4 | G209: =+D209/1.006 -> -383544.4 | H209: =+D209-G209 -> -2301.2664
A210: 06-09-2025 | B210: Liquidación de dinero | C210: 125088844362 | D210: 8378.98 | E210: 7418580.4 | F210: VENTA | G210: =+D210 -> 8378.98 | H210: 0
A211: 06-09-2025 | B211: Liquidación de dinero | C211: 125088894738 | D211: 12276.18 | E211: 7430856.6 | F211: VENTA | G211: =+D211 -> 12276.18 | H211: 0
A212: 06-09-2025 | B212: Liquidación de dinero | C212: 125088899534 | D212: 33158.97 | E212: 7464015.5 | F212: VENTA | G212: =+D212 -> 33158.97 | H212: 0
A213: 06-09-2025 | B213: Liquidación de dinero | C213: 125088923310 | D213: 31957.04 | E213: 7495972.6 | F213: VENTA | G213: =+D213 -> 31957.04 | H213: 0
A214: 06-09-2025 | B214: Transferencia recibida Laureana Paula Calvo | C214: 125088937092 | D214: 1605.56 | E214: 7497578.1 | F214: VENTA | G214: =+D214 -> 1605.56 | H214: 0
A215: 06-09-2025 | B215: Liquidación de dinero | C215: 125089015400 | D215: 4161.11 | E215: 7501739.2 | F215: VENTA | G215: =+D215 -> 4161.11 | H215: 0
A216: 06-09-2025 | B216: Liquidación de dinero | C216: 124543378311 | D216: 33675.96 | E216: 7535415.2 | F216: VENTA | G216: =+D216 -> 33675.96 | H216: 0
A217: 06-09-2025 | B217: Liquidación de dinero | C217: 125089355560 | D217: 9060.99 | E217: 7544476.2 | F217: VENTA | G217: =+D217 -> 9060.99 | H217: 0
A218: 06-09-2025 | B218: Liquidación de dinero | C218: 124543543841 | D218: 46179.12 | E218: 7590655.3 | F218: VENTA | G218: =+D218 -> 46179.12 | H218: 0
A219: 06-09-2025 | B219: Liquidación de dinero | C219: 125089683168 | D219: 44684.31 | E219: 7635339.6 | F219: VENTA | G219: =+D219 -> 44684.31 | H219: 0
A220: 06-09-2025 | B220: Liquidación de dinero | C220: 125089938206 | D220: 24649.79 | E220: 7659989.4 | F220: VENTA | G220: =+D220 -> 24649.79 | H220: 0
A221: 06-09-2025 | B221: Liquidación de dinero | C221: 124544646101 | D221: 12178.75 | E221: 7672168.2 | F221: VENTA | G221: =+D221 -> 12178.75 | H221: 0
... A417: 08-09-2025 | B417: Transferencia recibida Manuel Galvan | C417: 125315565192 | D417: 763.62 | E417: 12294113 | F417: VENTA | G417: =+D417 -> 763.62 | H417: 0
A418: 08-09-2025 | B418: Impuesto por extracción | C418: 125391966586 | D418: -570.35 | E418: 10580640 | G418: =+D418 -> -570.35
A419: 08-09-2025 | B419: Impuesto por extracción | C419: 125385837094 | D419: -1571.04 | E419: 10676269 | G419: =+D419 -> -1571.04
A420: 08-09-2025 | B420: Impuesto por extracción | C420: 125360500974 | D420: -1623.75 | E420: 12021865 | G420: =+D420 -> -1623.75
...

Sheet TR
A3: Suma de MOV TOTAL | B3: Etiquetas de columna
A4: Etiquetas de fila | B4: ARCA | C4: COBRO | D4: IDC | E4: PAGO PROVEEDOR | F4: RETIRO / PROV | G4: Total general
A5: Compra de Butter Roller Enmantecadora Pan Manteca Smash Hamburguesas Gris Acero Me... | E5: -177997.99 | G5: -177997.99 | H5: C | I5: ASIENTO 87
A6: Compra de Epitrónica Pack 100 Rollos Papel Térmico 80x50 48grs Ticket, Comandera, ... | E6: -103014 | G6: -103014 | H6: C | I6: ASIENTO 85
A7: Compra de Impresora De Tickets Comandera Hasar 181 Usb Serie Ethernet P-has-181 Ne... | E7: -438222.01 | G7: -438222.01 | H7: C | I7: ASIENTO 86
A8: Compra de Kit Medidor Eléctrico Trifásico Wifi Hasta 80a Powermeter Mercado Libre... | E8: -249860.6 | G8: -249860.6 | H8: C | I8: ASIENTO 88
A9: Compra de Manometro 63mm Post 1/4 Npt, Inox Con Glicerina 0-4 Bar/psi Mercado Libr... | E9: -37003.002 | G9: -37003.002 | H9: C | I9: ASIENTO 84
A10: Compra Mercado Libre | E10: -258381 | G10: -258381 | H10: C | I10: ASIENTO 89
A11: Débito por deuda Facturas vencidas de Mercado Libre | E11: -25111.789 | G11: -25111.789
A12: Impuesto por extracción | D12: -94412.8 | G12: -94412.8 | I12: ASIENTO 73 | J12: COBRO DS X VENTA | K12: =SUM(G13:G14,G43:G167) -> 33348336 | L12: modificado
A13: Liquidación de dinero | C13: 33176796 | G13: 33176796 | I13: ASIENTO 71 | J13: PAGO PROVEEDORES | K13: =SUM(G15:G16,G18:G37,G39:G42) -> -28998365 | L13: modificado
A14: Liquidación de dinero cancelada Venta cancelada | C14: -80000 | G14: -80000 | J14: VER SI HAY COMPRA
A15: Pago con QR Coca-Cola ANDINA | E15: -1478835.8 | G15: -1478835.8 | H15: C | J15: IMPUESTOS | K15: =SUM(GETPIVOTDATA("MOV TOTAL",$A$3,"TRANSACTION_TYPE","Pago de servicios ARCA")) -> -3527998 | L15: modificado
A16: Pago con QR FEPASA | E16: -1246696.8 | G16: -1246696.8 | H16: C | J16: VER QUE ES
A17: Pago de servicios ARCA | B17: -3527998 | G17: -3527998 | H17: C | I17: ASIENTO 71 | J17: CERVEZA TRACTOR
A18: Transferencia enviada | E18: -89279.95 | G18: -89279.95 | H18: C | I18: ASIENTO 72 | J18: CAJA | K18: =SUM(GETPIVOTDATA("MOV TOTAL",$A$3,"TRANSACTION_TYPE","Transferencia enviada NATALIA ELIZABETH BALBUENA")) -> -5000 | L18: modificado
A19: Transferencia enviada ACERO JEKLO SAS | E19: -168677.75 | G19: -168677.75 | H19: C
A20: Transferencia enviada BACO DE LOS ANDES SA | E20: -2035038.2 | G20: -2035038.2 | H20: C
A21: Transferencia enviada BASSO REPRESENT SRL | E21: -433268.17 | G21: -433268.17 | H21: C
A22: Transferencia enviada BOURLOT SA | E22: -155963.28 | G22: -155963.28 | H22: C
A23: Transferencia enviada CAMILA SCARDINO | E23: -162750 | G23: -162750 | H23: C
A24: Transferencia enviada CDG SRL | E24: -336346.37 | G24: -336346.37 | H24: C
A25: Transferencia enviada Cerveza Tractor | F25: -4672400 | G25: -4672400 | H25: C
A26: Transferencia enviada COMERCIAL RIGGIO SA | E26: -233204.26 | G26: -233204.26 | H26: C
A27: Transferencia enviada Distribuidora Doña Dora | E27: -2849940.2 | G27: -2849940.2 | H27: C
A28: Transferencia enviada DOLCET NORBERTO DAVID | E28: -261840.61 | G28: -261840.61 | H28: C
A29: Transferencia enviada DOÑA DORA | E29: -416444.19 | G29: -416444.19 | H29: C
A30: Transferencia enviada ENCODE SA | E30: -90750 | G30: -90750 | H30: C
A31: Transferencia enviada ERPEN JULIO C. Y PONZONI ANTONELLA P. SOCIEDAD SIMPLE | E31: -2705257.5 | G31: -2705257.5 | H31: C
A32: Transferencia enviada Eula Marcelo German | E32: -557501.45 | G32: -557501.45 | H32: C
A33: Transferencia enviada FRUVECO S R L | E33: -1694321.8 | G33: -1694321.8 | H33: C
A34: Transferencia enviada Granja La Blanquita S.r.l. | E34: -1430065 | G34: -1430065 | H34: C
A35: Transferencia enviada Gustavo Eugenio Gatter | E35: -109250.04 | G35: -109250.04 | H35: C
A36: Transferencia enviada LAGUNA CAPRI SAS | E36: -2776020 | G36: -2776020 | H36: C
A37: Transferencia enviada Mariano Pedro Rebord Palazzo | E37: -1645690 | G37: -1645690 | H37: C
... A42: Transferencia enviada TRES ORILLAS SRL | E42: -1162800.8 | G42: -1162800.8 | H42: C
A43: Transferencia recibida Agustin Alejandro Vizcarra | C43: 3735 | G43: 3735
A44: Transferencia recibida Agustin Fernando Loupias | C44: 1325 | G44: 1325
A45: Transferencia recibida Aixa Nicole Martínez | C45: 1840 | G45: 1840
A46: Transferencia recibida Alex Taiel Chinellato | C46: 4215 | G46: 4215
A47: Transferencia recibida Alfonso Rolando Nicolas Kraiesky | C47: 285 | G47: 285
A48: Transferencia recibida Ana Emilia Fuentes Bernay | C48: 3800 | G48: 3800
A49: Transferencia recibida Andrea Del Valle Llanes | C49: 655 | G49: 655
A50: Transferencia recibida Andres Quintar Riboli | C50: 850 | G50: 850
A51: Transferencia recibida Andres Salvador Proemmel Galeano | C51: 2669 | G51: 2669
A52: Transferencia recibida Angel Ernesto Cholson | C52: 750 | G52: 750
A53: Transferencia recibida Angelina Leopardo | C53: 215 | G53: 215
A54: Transferencia recibida Benjamín Rolls Villaud | C54: 860 | G54: 860
... A167: Transferencia recibida Yamil Jose Ale | C167: 3585 | G167: 3585
A168: Total general | B168: -3527998 | C168: 33348336 | D168: -94412.8 | E168: -25620555 | F168: -4672400 | G168: -567030.22

Sheet Tabla Resumen
A3: Etiquetas de fila | B3: Suma de TRANSACTION_NET_AMOUNT
A4: Compra de Butter Roller Enmantecadora Pan Manteca Smash Hamburguesas Gris Acero Me... | B4: -179065.98 | C4: Contab. | D4: SEGOVIA JUAN RAFAEL X $177998 | E4: ASIENTO 73 | F4: COBRO DS X VENTA | G4: =SUM(B42:B166,B12,B13) -> 32016711
A5: Compra de Epitrónica Pack 100 Rollos Papel Térmico 80x50 48grs Ticket, Comandera, ... | B5: -103632.08 | C5: Contab. | D5: NOY TOMAS AGUSTIN x $103014 | E5: ASIENTO 71 | F5: PAGO PROVEEDORES | G5: =SUM(B14:B15,B18:B24,B25:B36,B38:B41)-89279.95 -> -29077437
A6: Compra de Impresora De Tickets Comandera Hasar 181 Usb Serie Ethernet P-has-181 Ne... | B6: -440851.34 | C6: Contab. | D6: ELITRONIC ELITE ARGENTINA SA x $438222 | F6: VER SI HAY COMPRA
A7: Compra de Kit Medidor Eléctrico Trifásico Wifi Hasta 80a Powermeter Mercado Libre... | B7: -251359.76 | C7: Contab. | D7: POWERMETER SAS x $249860,60 | F7: VER SI CONCILIA CON IMPUESTOS | G7: =+GETPIVOTDATA("TRANSACTION_NET_AMOUNT",$A$3,"TRANSACTION_TYPE","Pago de servicios ARCA") -> -3549166
A8: Compra de Manometro 63mm Post 1/4 Npt, Inox Con Glicerina 0-4 Bar/psi Mercado Libr... | B8: -37225.02 | C8: Contab. | D8: MENDEZ DAMIAN RAFAEL x $37003 | F8: VER QUE ES
A9: Compra Mercado Libre | B9: -259931.29 | C9: Contab. | D9: EVENFLOW x $258381 | E9: ASIENTO 71 | F9: CERVEZA TRACTOR
A10: Débito por deuda Facturas vencidas de Mercado Libre | B10: -25262.46 | C10: Contab. | D10: Percepción factura MP + IDyC (contab. Globalmente) | E10: ASIENTO 72 | F10: CAJA | G10: =+GETPIVOTDATA("TRANSACTION_NET_AMOUNT",$A$3,"TRANSACTION_TYPE","Transferencia enviada NATALIA ELIZABETH BALBUENA") -> -5000
A11: Impuesto por extracción | B11: -94412.8 | C11: Contab. | D11: Corresponde IDyC ya contabilizados globalmente
A12: Liquidación de dinero | B12: 31848397 | C12: Contab.
A13: Liquidación de dinero cancelada Venta cancelada | B13: -77944 | C13: Contab.
A14: Pago con QR Coca-Cola ANDINA | B14: -1478835.8 | C14: Contab.
A15: Pago con QR FEPASA | B15: -1246696.8 | C15: Contab.
A16: Pago de servicios ARCA | B16: -3549166 | C16: Contab.
A17: Transferencia enviada | B17: -89815.63 | C17: Contab. | D17: PROVEEDORES / Brode Hermanos x $89279,95 + IDyC (contabilizado globalmente)
A18: Transferencia enviada ACERO JEKLO SAS | B18: -168677.75 | C18: Contab.
A19: Transferencia enviada BACO DE LOS ANDES SA | B19: -2035038.2 | C19: Contab.
A20: Transferencia enviada BASSO REPRESENT SRL | B20: -433268.17 | C20: Contab.
A21: Transferencia enviada BOURLOT SA | B21: -155963.28 | C21: Contab.
A22: Transferencia enviada CAMILA SCARDINO | B22: -162750 | C22: Contab.
A23: Transferencia enviada CDG SRL | B23: -336346.37 | C23: Contab.
A24: Transferencia enviada Cerveza Tractor | B24: -4700434.4 | C24: Contab. | D24: Va a proveedores / Hay facturas
A25: Transferencia enviada COMERCIAL RIGGIO SA | B25: -233204.26 | C25: Contab.
A26: Transferencia enviada Distribuidora Doña Dora | B26: -2867039.8 | C26: Contab.
A27: Transferencia enviada DOLCET NORBERTO DAVID | B27: -261840.61 | C27: Contab.
A28: Transferencia enviada DOÑA DORA | B28: -418942.86 | C28: Contab.
A29: Transferencia enviada ENCODE SA | B29: -90750 | C29: Contab.
A30: Transferencia enviada ERPEN JULIO C. Y PONZONI ANTONELLA P. SOCIEDAD SIMPLE | B30: -2721489.1 | C30: Contab.
A31: Transferencia enviada Eula Marcelo German | B31: -557501.45 | C31: Contab.
A32: Transferencia enviada FRUVECO S R L | B32: -1694321.8 | C32: Contab.
A33: Transferencia enviada Granja La Blanquita S.r.l. | B33: -1430065 | C33: Contab.
A34: Transferencia enviada Gustavo Eugenio Gatter | B34: -109905.54 | C34: Contab.
A35: Transferencia enviada LAGUNA CAPRI SAS | B35: -2776020 | C35: Contab.
A36: Transferencia enviada Mariano Pedro Rebord Palazzo | B36: -1655564.1 | C36: Contab.
... A166: Transferencia recibida Yamil Jose Ale | B166: 3509.71 | C166: Contab.
A167: Total general | B167: -2007168.6

Sheet SIRCUPA
A1: Reporte-Retención-SIRCUPA-Septiembre-CC20250609171159-MercadoPago
A3: Usuario: | B3: CC20250609171159
A4: Impuesto: | B4: Retención SIRCUPA
A5: Fecha de descarga: | B5: 18/03/2026
A6: Intervalo de fechas consultadas: | B6: 01/09/2025 a 01/10/2025
A8: Total | B8: Monto
A9: Base imponible | B9: $251.540,00
A10: Tramo 1 - retenido del 01/09 al 10/09 | B10: $1.131,44
A11: Tramo 2 - retenido del 11/09 al 20/09 | B11: $1.168,49
A12: Tramo 3 - retenido del 21/09 al 30/09 | B12: $1.473,43
A13: Importe retenido | B13: $3.773,36
A14: Importe devuelto | B14: $0,00
A16: Podrás utilizar este reporte para conciliar lo que retuvimos.
A17: Podrás buscar el detalle de lo retenido en tu operación en la sección Actividad.
A19: Operación | E19: Impuesto
A20: Número de operación | B20: Fecha de operación | C20: Tipo | D20: Monto de transferencia | E20: Fecha de retención | F20: Alícuota | G20: Base imponible | H20: Importe retenido
A21: 123865265509 | B21: 31/08/2025 | C21: Transferencia | D21: 660 | E21: 01/09/2025 | F21: 1,50 % | G21: 660 | H21: 9.9
A22: 124236877691 | B22: 03/09/2025 | C22: Transferencia | D22: 1465 | E22: 03/09/2025 | F22: 1,50 % | G22: 1465 | H22: 21.98
A23: 124253070499 | B23: 03/09/2025 | C23: Transferencia | D23: 1835 | E23: 04/09/2025 | F23: 1,50 % | G23: 1835 | H23: 27.53
A24: 124254045511 | B24: 03/09/2025 | C24: Transferencia | D24: 1410 | E24: 04/09/2025 | F24: 1,50 % | G24: 1410 | H24: 21.15
A25: 124362828291 | B25: 04/09/2025 | C25: Transferencia | D25: 215 | E25: 04/09/2025 | F25: 1,50 % | G25: 215 | H25: 3.23
A26: 124909138878 | B26: 04/09/2025 | C26: Transferencia | D26: 390 | E26: 04/09/2025 | F26: 1,50 % | G26: 390 | H26: 5.85
A27: 124926882200 | B27: 04/09/2025 | C27: Transferencia | D27: 175 | E27: 04/09/2025 | F27: 1,50 % | G27: 175 | H27: 2.63
A28: 124386769841 | B28: 04/09/2025 | C28: Transferencia | D28: 390 | E28: 05/09/2025 | F28: 1,50 % | G28: 390 | H28: 5.85
A29: 124382023949 | B29: 04/09/2025 | C29: Transferencia | D29: 4215 | E29: 04/09/2025 | F29: 1,50 % | G29: 4215 | H29: 63.23
A30: 124933915330 | B30: 04/09/2025 | C30: Transferencia | D30: 390 | E30: 05/09/2025 | F30: 1,50 % | G30: 390 | H30: 5.85
A31: 124389351389 | B31: 04/09/2025 | C31: Transferencia | D31: 3005 | E31: 05/09/2025 | F31: 1,50 % | G31: 3005 | H31: 45.08
A32: 124389417047 | B32: 04/09/2025 | C32: Transferencia | D32: 500 | E32: 05/09/2025 | F32: 1,50 % | G32: 500 | H32: 7.5
... A155: 127896570932 | B155: 28/09/2025 | C155: Transferencia | D155: 2465 | E155: 29/09/2025 | F155: 1,50 % | G155: 2465 | H155: 36.98
D157: =SUM(D21:D156) -> 251540 | G157: =SUM(G21:G156) -> 251540 | H157: =SUM(H21:H156) -> 3773.36

Sheet SIRTAC
A1: Reporte-Retención-SIRTAC-inscripto-1ra-quincena-Septiembre-CC20250609171159-MercadoPago
A3: Usuario: | B3: CC20250609171159
A4: Impuesto: | B4: Retención SIRTAC
A5: Fecha de descarga: | B5: 18/03/2026
A6: Intervalo de fechas consultadas: | B6: 01/09/2025 a 16/09/2025
A8: Total | B8: Monto
A9: Base imponible | B9: $17.466.793,99
A10: Importe retenido | B10: $174.667,94
A11: Importe devuelto | B11: $800,00
A12: Podrás conciliar la información con otros reportes de Mercado Libre. | D12: Podrás buscar el detalle de lo retenido en tu operación en la sección Actividad.
A14: Operación | E14: Impuesto
A15: Número de operación | B15: Número de venta - Referencia externa | C15: Fecha de operación | D15: Tipo | E15: Fecha de retención | F15: Alícuota | G15: Base imponible | H15: Importe retenido
A16: 123864645949 | C16: 31/08/2025 | D16: Venta | E16: 01/09/2025 | F16: 1,00 % | G16: 17500 | H16: 175
A17: 124407749182 | C17: 31/08/2025 | D17: Venta | E17: 01/09/2025 | F17: 1,00 % | G17: 24500 | H17: 245
A18: 123868170745 | C18: 01/09/2025 | D18: Venta | E18: 01/09/2025 | F18: 1,00 % | G18: 13500 | H18: 135
A19: 123864040285 | C19: 31/08/2025 | D19: Venta | E19: 01/09/2025 | F19: 1,00 % | G19: 15000 | H19: 150
A20: 124407346652 | C20: 31/08/2025 | D20: Venta | E20: 01/09/2025 | F20: 1,00 % | G20: 13200 | H20: 132
A21: 123868184561 | C21: 01/09/2025 | D21: Venta | E21: 01/09/2025 | F21: 1,00 % | G21: 10000 | H21: 100
A22: 124781182650 | B22: Venta presencial | C22: 03/09/2025 | D22: Venta | E22: 03/09/2025 | F22: 1,00 % | G22: 8600 | H22: 86
A23: 124234497707 | C23: 03/09/2025 | D23: Venta | E23: 03/09/2025 | F23: 1,00 % | G23: 4900 | H23: 49
A24: 124784681512 | B24: Venta presencial | C24: 03/09/2025 | D24: Venta | E24: 03/09/2025 | F24: 1,00 % | G24: 31000 | H24: 310
A25: 124236889607 | C25: 03/09/2025 | D25: Venta | E25: 03/09/2025 | F25: 1,00 % | G25: 29300 | H25: 293
A26: 124788106000 | B26: Venta presencial | C26: 03/09/2025 | D26: Venta | E26: 03/09/2025 | F26: 1,00 % | G26: 5300 | H26: 53
A27: 124245392201 | C27: 03/09/2025 | D27: Venta | E27: 03/09/2025 | F27: 1,00 % | G27: 34100 | H27: 341
A28: 124245389515 | C28: 03/09/2025 | D28: Venta | E28: 03/09/2025 | F28: 1,00 % | G28: 46000 | H28: 460
A29: 124795296394 | C29: 03/09/2025 | D29: Venta | E29: 03/09/2025 | F29: 1,00 % | G29: 19999 | H29: 199.99
A30: 124247706111 | C30: 03/09/2025 | D30: Venta | E30: 03/09/2025 | F30: 1,00 % | G30: 12300 | H30: 123
A31: 124797073790 | C31: 03/09/2025 | D31: Venta | E31: 04/09/2025 | F31: 1,00 % | G31: 57200 | H31: 572
A32: 124797908608 | C32: 03/09/2025 | D32: Venta | E32: 04/09/2025 | F32: 1,00 % | G32: 15500 | H32: 155
A33: 124253989611 | C33: 03/09/2025 | D33: Venta | E33: 04/09/2025 | F33: 1,00 % | G33: 20900 | H33: 209
A34: 124798439032 | C34: 03/09/2025 | D34: Venta | E34: 04/09/2025 | F34: 1,00 % | G34: 28200 | H34: 282
A35: 124798706468 | C35: 03/09/2025 | D35: Venta | E35: 04/09/2025 | F35: 1,00 % | G35: 9800 | H35: 98
A36: 124251168101 | C36: 03/09/2025 | D36: Venta | E36: 03/09/2025 | F36: 1,00 % | G36: 59896 | H36: 598.96
A37: 124251556927 | C37: 03/09/2025 | D37: Venta | E37: 03/09/2025 | F37: 1,00 % | G37: 71000 | H37: 710
A38: 124797394520 | C38: 03/09/2025 | D38: Venta | E38: 04/09/2025 | F38: 1,00 % | G38: 36700 | H38: 367
A39: 124797743380 | B39: Venta presencial | C39: 03/09/2025 | D39: Venta | E39: 04/09/2025 | F39: 1,00 % | G39: 152793 | H39: 1527.93
A40: 124800062204 | C40: 04/09/2025 | D40: Venta | E40: 04/09/2025 | F40: 1,00 % | G40: 47197 | H40: 471.97
A41: 124256095479 | C41: 04/09/2025 | D41: Venta | E41: 04/09/2025 | F41: 1,00 % | G41: 19998 | H41: 199.98
A42: 124907529624 | C42: 04/09/2025 | D42: Venta | E42: 04/09/2025 | F42: 1,00 % | G42: 15900 | H42: 159
A43: 124908939322 | C43: 04/09/2025 | D43: Venta | E43: 04/09/2025 | F43: 1,00 % | G43: 4300 | H43: 43
A44: 124909134908 | C44: 04/09/2025 | D44: Venta | E44: 04/09/2025 | F44: 1,00 % | G44: 7800 | H44: 78
A45: 124912912486 | C45: 04/09/2025 | D45: Venta | E45: 04/09/2025 | F45: 1,00 % | G45: 30000 | H45: 300
A46: 124362593953 | C46: 04/09/2025 | D46: Venta | E46: 04/09/2025 | F46: 1,00 % | G46: 4300 | H46: 43
A47: 124370030581 | C47: 04/09/2025 | D47: Venta | E47: 04/09/2025 | F47: 1,00 % | G47: 108900 | H47: 1089
A48: 124368294535 | B48: Venta presencial | C48: 04/09/2025 | D48: Venta | E48: 04/09/2025 | F48: 1,00 % | G48: 4300 | H48: 43
A49: 124379914851 | C49: 04/09/2025 | D49: Venta | E49: 04/09/2025 | F49: 1,00 % | G49: 4300 | H49: 43
A50: 124919880508 | C50: 04/09/2025 | D50: Venta | E50: 04/09/2025 | F50: 1,00 % | G50: 23800 | H50: 238
A51: 124375560999 | B51: Venta presencial | C51: 04/09/2025 | D51: Venta | E51: 04/09/2025 | F51: 1,00 % | G51: 4300 | H51: 43
A52: 124926524640 | C52: 04/09/2025 | D52: Venta | E52: 04/09/2025 | F52: 1,00 % | G52: 81900 | H52: 819
A53: 124926603568 | C53: 04/09/2025 | D53: Venta | E53: 04/09/2025 | F53: 1,00 % | G53: 13900 | H53: 139
A54: 124926894128 | C54: 04/09/2025 | D54: Venta | E54: 04/09/2025 | F54: 1,00 % | G54: 3500 | H54: 35
A55: 124921656040 | B55: Venta presencial | C55: 04/09/2025 | D55: Venta | E55: 04/09/2025 | F55: 1,00 % | G55: 39800 | H55: 398
A56: 124382131027 | C56: 04/09/2025 | D56: Venta | E56: 04/09/2025 | F56: 1,00 % | G56: 28100 | H56: 281
A57: 124382333979 | C57: 04/09/2025 | D57: Venta | E57: 04/09/2025 | F57: 1,00 % | G57: 12900 | H57: 129
A58: 124383268861 | C58: 04/09/2025 | D58: Venta | E58: 04/09/2025 | F58: 1,00 % | G58: 4300 | H58: 43
A59: 124928647796 | C59: 04/09/2025 | D59: Venta | E59: 04/09/2025 | F59: 1,00 % | G59: 12900 | H59: 129
A60: 124929160694 | B60: Venta presencial | C60: 04/09/2025 | D60: Venta | E60: 04/09/2025 | F60: 1,00 % | G60: 35400 | H60: 354
A61: 124379045323 | C61: 04/09/2025 | D61: Venta | E61: 04/09/2025 | F61: 1,00 % | G61: 3900 | H61: 39
A62: 124929549560 | C62: 04/09/2025 | D62: Venta | E62: 04/09/2025 | F62: 1,00 % | G62: 13600 | H62: 136
A63: 124929957960 | C63: 04/09/2025 | D63: Venta | E63: 04/09/2025 | F63: 1,00 % | G63: 4300 | H63: 43
A64: 124924939738 | C64: 04/09/2025 | D64: Venta | E64: 04/09/2025 | F64: 1,00 % | G64: 8600 | H64: 86
A65: 124930281670 | B65: Venta presencial | C65: 04/09/2025 | D65: Venta | E65: 04/09/2025 | F65: 1,00 % | G65: 8600 | H65: 86
A66: 124385652341 | C66: 04/09/2025 | D66: Venta | E66: 04/09/2025 | F66: 1,00 % | G66: 14300 | H66: 143
A67: 124930920538 | B67: Venta presencial | C67: 04/09/2025 | D67: Venta | E67: 04/09/2025 | F67: 1,00 % | G67: 21500 | H67: 215
A68: 124386234575 | B68: Venta presencial | C68: 04/09/2025 | D68: Venta | E68: 04/09/2025 | F68: 1,00 % | G68: 13200 | H68: 132
A69: 124931688378 | C69: 04/09/2025 | D69: Venta | E69: 04/09/2025 | F69: 1,00 % | G69: 9600 | H69: 96
A70: 124931738646 | C70: 04/09/2025 | D70: Venta | E70: 04/09/2025 | F70: 1,00 % | G70: 3900 | H70: 39
A71: 124931811338 | C71: 04/09/2025 | D71: Venta | E71: 04/09/2025 | F71: 1,00 % | G71: 1900 | H71: 19
A72: 124386853415 | C72: 04/09/2025 | D72: Venta | E72: 05/09/2025 | F72: 1,00 % | G72: 3900 | H72: 39
A73: 124387202427 | C73: 04/09/2025 | D73: Venta | E73: 05/09/2025 | F73: 1,00 % | G73: 8200 | H73: 82
A74: 124387169897 | C74: 04/09/2025 | D74: Venta | E74: 05/09/2025 | F74: 1,00 % | G74: 9300 | H74: 93
A75: 124932574010 | B75: Venta presencial | C75: 04/09/2025 | D75: Venta | E75: 05/09/2025 | F75: 1,00 % | G75: 5000 | H75: 50
A76: 124387491809 | C76: 04/09/2025 | D76: Venta | E76: 05/09/2025 | F76: 1,00 % | G76: 70800 | H76: 708
A77: 124932738810 | C77: 04/09/2025 | D77: Venta | E77: 05/09/2025 | F77: 1,00 % | G77: 2200 | H77: 22
A78: 124933058374 | C78: 04/09/2025 | D78: Venta | E78: 05/09/2025 | F78: 1,00 % | G78: 16100 | H78: 161
A79: 124933214738 | C79: 04/09/2025 | D79: Venta | E79: 05/09/2025 | F79: 1,00 % | G79: 4300 | H79: 43
A80: 124388057649 | C80: 04/09/2025 | D80: Venta | E80: 05/09/2025 | F80: 1,00 % | G80: 4300 | H80: 43
A81: 124933398996 | C81: 04/09/2025 | D81: Venta | E81: 05/09/2025 | F81: 1,00 % | G81: 4300 | H81: 43
A82: 124383275693 | C82: 04/09/2025 | D82: Venta | E82: 04/09/2025 | F82: 1,00 % | G82: 9300 | H82: 93
A83: 124388706943 | C83: 04/09/2025 | D83: Venta | E83: 05/09/2025 | F83: 1,00 % | G83: 3900 | H83: 39
A84: 124929201672 | C84: 04/09/2025 | D84: Venta | E84: 04/09/2025 | F84: 1,00 % | G84: 12900 | H84: 129
A85: 124929525256 | C85: 04/09/2025 | D85: Venta | E85: 04/09/2025 | F85: 1,00 % | G85: 3500 | H85: 35
A86: 124389182075 | C86: 04/09/2025 | D86: Venta | E86: 05/09/2025 | F86: 1,00 % | G86: 4300 | H86: 43
A87: 124389369351 | C87: 04/09/2025 | D87: Venta | E87: 05/09/2025 | F87: 1,00 % | G87: 60100 | H87: 601
... A95: 124386117715 | C95: 04/09/2025 | D95: Venta | E95: 04/09/2025 | F95: 1,00 % | G95: 18900 | H95: 189
A96: 124932013860 | B96: Venta presencial | C96: 04/09/2025 | D96: Venta | E96: 05/09/2025 | F96: 1,00 % | G96: 63200 | H96: 632
A97: 124936593136 | C97: 05/09/2025 | D97: Venta | E97: 05/09/2025 | F97: 1,00 % | G97: 22100 | H97: 221
A98: 124391343749 | C98: 05/09/2025 | D98: Venta | E98: 05/09/2025 | F98: 1,00 % | G98: 9300 | H98: 93
A99: 124391696277 | C99: 05/09/2025 | D99: Venta | E99: 05/09/2025 | F99: 1,00 % | G99: 4300 | H99: 43
A100: 124387263837 | C100: 04/09/2025 | D100: Venta | E100: 05/09/2025 | F100: 1,00 % | G100: 15900 | H100: 159
A101: 124932672660 | C101: 04/09/2025 | D101: Venta | E101: 05/09/2025 | F101: 1,00 % | G101: 5000 | H101: 50
A102: 124392231153 | C102: 05/09/2025 | D102: Venta | E102: 05/09/2025 | F102: 1,00 % | G102: 10000 | H102: 100
A103: 124388358883 | B103: Venta presencial | C103: 04/09/2025 | D103: Venta | E103: 05/09/2025 | F103: 1,00 % | G103: 4300 | H103: 43
A104: 124388466105 | C104: 04/09/2025 | D104: Venta | E104: 05/09/2025 | F104: 1,00 % | G104: 186200 | H104: 1862
A105: 124392818757 | C105: 05/09/2025 | D105: Venta | E105: 05/09/2025 | F105: 1,00 % | G105: 20700 | H105: 207
A106: 124392888675 | C106: 05/09/2025 | D106: Venta | E106: 05/09/2025 | F106: 1,00 % | G106: 86600 | H106: 866
A107: 124938249624 | C107: 05/09/2025 | D107: Venta | E107: 05/09/2025 | F107: 1,00 % | G107: 4300 | H107: 43
A108: 124934432228 | C108: 04/09/2025 | D108: Venta | E108: 05/09/2025 | F108: 1,00 % | G108: 4300 | H108: 43
A109: 124389390021 | B109: Venta presencial | C109: 04/09/2025 | D109: Venta | E109: 05/09/2025 | F109: 1,00 % | G109: 8500 | H109: 85
A110: 124935015006 | C110: 05/09/2025 | D110: Venta | E110: 05/09/2025 | F110: 1,00 % | G110: 4300 | H110: 43
...

Sheet Gastos
A1: Fecha de actualización | C1: 46125.4
A3: Sumamos nuevas columnas a tu reporte: Trabajamos para brindarte más detalle sobre los cargos por utilizar Mercado Pago. Por eso, a partir de ahora, en "Información sobre cargos" incluiremos las siguientes columnas: - Número del cargo: para que puedas cruzar la información con otros reportes. - Cobrado en la operación: para saber si un cargo fue cobrado en la operación o no. - Estado del cargo y Cargo que anula: para entender más sobre los cargos anulados.
A7: Información sobre cargos | J7: Información de la operación sobre la que se aplica | R7: Información sobre percepciones | T7: Accesos
A8: Operación relacionada | B8: N° de factura fiscal | C8: Fecha del cargo | D8: Número del cargo | E8: Número del movimiento | F8: Detalle | G8: Cobrado en la operacion | H8: Estado del cargo | I8: Cargo que anula | J8: Valor del cargo | K8: Tipo de operación | L8: Tipo de pago | M8: Número de sucursal | N8: Nombre de sucursal | O8: Referencia externa | P8: Cliente | Q8: Valor de la operación | R8: Alícuota | S8: Base imponible | T8: Sección de Mercado libre y de Mercado Pago
A9: 123864040285 | B9: 0067A00377504 | C9: 45901 | D9: 49609389445 | E9: 2057966565954 | F9: Cargo por cobrar con código QR | G9: Si | J9: 145.5 | K9: Pago | L9: QR | M9: 71465208 | N9: Cerveza Träctor | P9: BENJAMINRODRIGUEZ2022042507052 | Q9: 15000 | T9: Ir al Detalle de la operación en Mercado Pago
A10: 123864645949 | B10: 0067A00377504 | C10: 45901 | D10: 49609761273 | E10: 2057935812401 | F10: Cargo por cobrar con código QR | G10: Si | J10: 169.75 | K10: Pago | L10: QR | M10: 71465208 | N10: Cerveza Träctor | P10: POBR7453334 | Q10: 17500 | T10: Ir al Detalle de la operación en Mercado Pago
A11: 124407346652 | B11: 0067A00377504 | C11: 45901 | D11: 49610079372 | E11: 2057975469254 | F11: Cargo por cobrar con código QR | G11: Si | J11: 1004.52 | K11: Pago | L11: QR | M11: 71465208 | N11: Cerveza Träctor | P11: JUANFOLMERD1 | Q11: 13200 | T11: Ir al Detalle de la operación en Mercado Pago
A12: 124407749182 | B12: 0067A00377504 | C12: 45901 | D12: 49610393075 | E12: 2057943537155 | F12: Cargo por cobrar con código QR | G12: Si | J12: 237.65 | K12: Pago | L12: QR | M12: 71465208 | N12: Cerveza Träctor | P12: GASTONIZAGUIRRE2006 | Q12: 24500 | T12: Ir al Detalle de la operación en Mercado Pago
A13: 123868184561 | B13: 0067A00377504 | C13: 45901 | D13: 49612277820 | E13: 2058000895800 | F13: Cargo por cobrar con código QR | G13: Si | J13: 97 | K13: Pago | L13: QR | M13: 71465208 | N13: Cerveza Träctor | P13: MICA LARROZA | Q13: 10000 | T13: Ir al Detalle de la operación en Mercado Pago
A14: 123868170745 | B14: 0067A00377504 | C14: 45901 | D14: 49612282830 | E14: 2057965544941 | F14: Cargo por cobrar con código QR | G14: Si | J14: 130.95 | K14: Pago | L14: QR | M14: 71465208 | N14: Cerveza Träctor | P14: REBORDMARIA20220527090737 | Q14: 13500 | T14: Ir al Detalle de la operación en Mercado Pago
A15: 124234497707 | B15: 0067A00377504 | C15: 45903 | D15: 49740571037 | E15: 2060600202588 | F15: Cargo por uso de QR - Pagos Interoperables | G15: Si | J15: 47.53 | K15: Pago | L15: QR | M15: 71465208 | N15: Cerveza Träctor | P15: @2489718921 | Q15: 4900
A16: 124236889607 | B16: 0067A00377504 | C16: 45903 | D16: 49741443221 | E16: 2060616169930 | F16: Cargo por cobrar con código QR | G16: Si | J16: 284.21 | K16: Pago | L16: QR | M16: 71465208 | N16: Cerveza Träctor | P16: JOAQUINSCHENONE | Q16: 29300 | T16: Ir al Detalle de la operación en Mercado Pago
A17: 124781182650 | B17: 0067A00377504 | C17: 45903 | D17: 49741444732 | E17: 2060577299951 | F17: Cargo por cobrar con Point | G17: Si | J17: 390.44 | K17: Pago | L17: Point | M17: 71465208 | N17: Cerveza Träctor | O17: Venta presencial | P17: VENTASPRESENCIAL | Q17: 8600 | T17: Ir al Detalle de la operación en Mercado Pago
A18: 124784681512 | B18: 0067A00377504 | C18: 45903 | D18: 49742712870 | E18: 2060601512097 | F18: Cargo por cobrar con Point | G18: Si | J18: 2359.1 | K18: Pago | L18: Point | M18: 71465208 | N18: Cerveza Träctor | O18: Venta presencial | P18: VENTASPRESENCIAL | Q18: 31000 | T18: Ir al Detalle de la operación en Mercado Pago
A19: 124788106000 | B19: 0067A00377504 | C19: 45903 | D19: 49743952761 | E19: 2060664054736 | F19: Cargo por cobrar con Point | G19: Si | J19: 208.29 | K19: Pago | L19: Point | M19: 71465208 | N19: Cerveza Träctor | O19: Venta presencial | P19: VENTASPRESENCIAL | Q19: 5300 | T19: Ir al Detalle de la operación en Mercado Pago
A20: 124245392201 | B20: 0067A00377504 | C20: 45903 | D20: 49744545380 | E20: 2060674851280 | F20: Cargo por cobrar con código QR | G20: Si | J20: 330.77 | K20: Pago | L20: QR | M20: 71465208 | N20: Cerveza Träctor | P20: RITAJUVENAL | Q20: 34100 | T20: Ir al Detalle de la operación en Mercado Pago
A21: 124245389515 | B21: 0067A00377504 | C21: 45903 | D21: 49744572482 | E21: 2060675422532 | F21: Cargo por cobrar con código QR | G21: Si | J21: 446.2 | K21: Pago | L21: QR | M21: 71465208 | N21: Cerveza Träctor | P21: BARRETOCAROLINA20230707135959 | Q21: 46000 | T21: Ir al Detalle de la operación en Mercado Pago
A22: 124247706111 | B22: 0067A00377504 | C22: 45903 | D22: 49745428791 | E22: 2060692441494 | F22: Cargo por cobrar con código QR | G22: Si | J22: 119.31 | K22: Pago | L22: QR | M22: 71465208 | N22: Cerveza Träctor | P22: NUNEZNAHUE | Q22: 12300 | T22: Ir al Detalle de la operación en Mercado Pago
A23: 124795296394 | B23: 0067A00377504 | C23: 45903 | D23: 49746784038 | E23: 2060680005899 | F23: Cargo por uso de QR - Pagos Interoperables | G23: Si | J23: 193.99 | K23: Pago | L23: QR | M23: 71465208 | N23: Cerveza Träctor | P23: @2489718921 | Q23: 19999
A24: 124251168101 | B24: 0067A00377504 | C24: 45903 | D24: 49746835172 | E24: 2060719466438 | F24: Cargo por uso de QR - Pagos Interoperables | G24: Si | J24: 580.99 | K24: Pago | L24: QR | M24: 71465208 | N24: Cerveza Träctor | P24: @2489718921 | Q24: 59896
A25: 124251556927 | B25: 0067A00377504 | C25: 45903 | D25: 49747029216 | E25: 2060723239488 | F25: Cargo por cobrar con código QR | G25: Si | J25: 688.7 | K25: Pago | L25: QR | M25: 71465208 | N25: Cerveza Träctor | P25: ZAJO8737530 | Q25: 71000 | T25: Ir al Detalle de la operación en Mercado Pago
A26: 124797073790 | B26: 0067A00377504 | C26: 45904 | D26: 49747656688 | E26: 2060695417275 | F26: Cargo por cobrar con código QR | G26: Si | J26: 554.84 | K26: Pago | L26: QR | M26: 71465208 | N26: Cerveza Träctor | P26: MARIALUZALMADA | Q26: 57200 | T26: Ir al Detalle de la operación en Mercado Pago
A27: 124797394520 | B27: 0067A00377504 | C27: 45904 | D27: 49747760355 | E27: 2060735577924 | F27: Cargo por cobrar con código QR | G27: Si | J27: 355.99 | K27: Pago | L27: QR | M27: 71465208 | N27: Cerveza Träctor | P27: DUENDE- | Q27: 36700 | T27: Ir al Detalle de la operación en Mercado Pago
A28: 124797743380 | B28: 0067A00377504 | C28: 45904 | D28: 49747941888 | E28: 2060739120394 | F28: Cargo por cobrar con Point | G28: Si | J28: 11627.55 | K28: Pago | L28: Point | M28: 71465208 | N28: Cerveza Träctor | O28: Venta presencial | P28: VENTASPRESENCIAL | Q28: 152793 | T28: Ir al Detalle de la operación en Mercado Pago
A29: 124797908608 | B29: 0067A00377504 | C29: 45904 | D29: 49748001102 | E29: 2060701482483 | F29: Cargo por cobrar con código QR | G29: Si | J29: 1179.55 | K29: Pago | L29: QR | M29: 71465208 | N29: Cerveza Träctor | P29: JUANFOLMERD1 | Q29: 15500 | T29: Ir al Detalle de la operación en Mercado Pago
A30: 124253989611 | B30: 0067A00377504 | C30: 45904 | D30: 49748216398 | E30: 2060706177051 | F30: Cargo por cobrar con código QR | G30: Si | J30: 202.73 | K30: Pago | L30: QR | M30: 71465208 | N30: Cerveza Träctor | P30: MAIDANAMILE007 | Q30: 20900 | T30: Ir al Detalle de la operación en Mercado Pago
A31: 124798439032 | B31: 0067A00377504 | C31: 45904 | D31: 49748222229 | E31: 2060706427201 | F31: Cargo por cobrar con código QR | G31: Si | J31: 273.54 | K31: Pago | L31: QR | M31: 71465208 | N31: Cerveza Träctor | P31: HT20240903004220 | Q31: 28200 | T31: Ir al Detalle de la operación en Mercado Pago
A32: 124798706468 | B32: 0067A00377504 | C32: 45904 | D32: 49748310844 | E32: 2060708012861 | F32: Cargo por cobrar con código QR | G32: Si | J32: 95.06 | K32: Pago | L32: QR | M32: 71465208 | N32: Cerveza Träctor | P32: FPAG9341 | Q32: 9800 | T32: Ir al Detalle de la operación en Mercado Pago
A33: 124800062204 | B33: 0067A00377504 | C33: 45904 | D33: 49748861631 | E33: 2060759086032 | F33: Cargo por uso de QR - Pagos Interoperables | G33: Si | J33: 457.81 | K33: Pago | L33: QR | M33: 71465208 | N33: Cerveza Träctor | P33: @2489718921 | Q33: 47197
A34: 124256095479 | B34: 0067A00377504 | C34: 45904 | D34: 49749107436 | E34: 2060764045674 | F34: Cargo por cobrar con código QR | G34: Si | J34: 193.98 | K34: Pago | L34: QR | M34: 71465208 | N34: Cerveza Träctor | P34: KUAKERBOY | Q34: 19998 | T34: Ir al Detalle de la operación en Mercado Pago
A35: 124907529624 | B35: 0067A00377504 | C35: 45904 | D35: 49785711056 | E35: 2061474156915 | F35: Cargo por cobrar con código QR | G35: Si | J35: 154.23 | K35: Pago | L35: QR | M35: 71465208 | N35: Cerveza Träctor | P35: MATEOLP92 | Q35: 15900 | T35: Ir al Detalle de la operación en Mercado Pago
A36: 124362593953 | B36: 0067A00377504 | C36: 45904 | D36: 49785797411 | E36: 2061514639976 | F36: Cargo por cobrar con código QR | G36: Si | J36: 41.71 | K36: Pago | L36: QR | M36: 71465208 | N36: Cerveza Träctor | P36: COBR6408532 | Q36: 4300 | T36: Ir al Detalle de la operación en Mercado Pago
A37: 124908939322 | B37: 0067A00377504 | C37: 45904 | D37: 49786204604 | E37: 2061482154635 | F37: Cargo por uso de QR - Pagos Interoperables | G37: Si | J37: 41.71 | K37: Pago | L37: QR | M37: 71465208 | N37: Cerveza Träctor | P37: @2489718921 | Q37: 4300
A38: 124909134908 | B38: 0067A00377504 | C38: 45904 | D38: 49786243802 | E38: 2061483007505 | F38: Cargo por cobrar con código QR | G38: Si | J38: 75.66 | K38: Pago | L38: QR | M38: 71465208 | N38: Cerveza Träctor | P38: MOSCATELLIROCIO20230403183802 | Q38: 7800 | T38: Ir al Detalle de la operación en Mercado Pago
A39: 124912912486 | B39: 0067A00377504 | C39: 45904 | D39: 49787552619 | E39: 2061507024891 | F39: Cargo por cobrar con código QR | G39: Si | J39: 291 | K39: Pago | L39: QR | M39: 71465208 | N39: Cerveza Träctor | P39: FLORESMARIA20211112173853 | Q39: 30000 | T39: Ir al Detalle de la operación en Mercado Pago
A40: 124368294535 | B40: 0067A00377504 | C40: 45904 | D40: 49787756190 | E40: 2061549978588 | F40: Cargo por cobrar con Point | G40: Si | J40: 168.99 | K40: Pago | L40: Point | M40: 71465208 | N40: Cerveza Träctor | O40: Venta presencial | P40: VENTASPRESENCIAL | Q40: 4300 | T40: Ir al Detalle de la operación en Mercado Pago
A41: 124370030581 | B41: 0067A00377504 | C41: 45904 | D41: 49788389786 | E41: 2061522172415 | F41: Cargo por cobrar con código QR | G41: Si | J41: 1056.33 | K41: Pago | L41: QR | M41: 71465208 | N41: Cerveza Träctor | P41: AGUSTINADELSART | Q41: 108900 | T41: Ir al Detalle de la operación en Mercado Pago
A42: 124919880508 | B42: 0067A00377504 | C42: 45904 | D42: 49790136945 | E42: 2061593558782 | F42: Cargo por cobrar con código QR | G42: Si | J42: 230.86 | K42: Pago | L42: QR | M42: 71465208 | N42: Cerveza Träctor | P42: BRUNOBONN11 | Q42: 23800 | T42: Ir al Detalle de la operación en Mercado Pago
A43: 124375560999 | B43: 0067A00377504 | C43: 45904 | D43: 49790399712 | E43: 2061599120062 | F43: Cargo por cobrar con Point | G43: Si | J43: 168.99 | K43: Pago | L43: Point | M43: 71465208 | N43: Cerveza Träctor | O43: Venta presencial | P43: VENTASPRESENCIAL | Q43: 4300 | T43: Ir al Detalle de la operación en Mercado Pago
A44: 124921656040 | B44: 0067A00377504 | C44: 45904 | D44: 49790790742 | E44: 2061606864486 | F44: Cargo por cobrar con Point | G44: Si | J44: 1806.92 | K44: Pago | L44: Point | M44: 71465208 | N44: Cerveza Träctor | O44: Venta presencial | P44: VENTASPRESENCIAL | Q44: 39800 | T44: Ir al Detalle de la operación en Mercado Pago
A45: 124379045323 | B45: 0067A00377504 | C45: 45904 | D45: 49791732778 | E45: 2061624404602 | F45: Cargo por cobrar con código QR | G45: Si | J45: 37.83 | K45: Pago | L45: QR | M45: 71465208 | N45: Cerveza Träctor | P45: FLORJOSEFINA | Q45: 3900 | T45: Ir al Detalle de la operación en Mercado Pago
A46: 124924939738 | B46: 0067A00377504 | C46: 45904 | D46: 49792033523 | E46: 2061630610296 | F46: Cargo por cobrar con código QR | G46: Si | J46: 83.42 | K46: Pago | L46: QR | M46: 71465208 | N46: Cerveza Träctor | P46: MARUDRI58 | Q46: 8600 | T46: Ir al Detalle de la operación en Mercado Pago
A47: 124379914851 | B47: 0067A00377504 | C47: 45904 | D47: 49792081287 | E47: 2061592042197 | F47: Cargo por cobrar con código QR | G47: Si | J47: 41.71 | K47: Pago | L47: QR | M47: 71465208 | N47: Cerveza Träctor | P47: PREISZLUISINA20221102165907 | Q47: 4300 | T47: Ir al Detalle de la operación en Mercado Pago
A48: 124926524640 | B48: 0067A00377504 | C48: 45904 | D48: 49792637855 | E48: 2061602453263 | F48: Cargo por cobrar con código QR | G48: Si | J48: 794.43 | K48: Pago | L48: QR | M48: 71465208 | N48: Cerveza Träctor | P48: MAXIESORIA3 | Q48: 81900 | T48: Ir al Detalle de la operación en Mercado Pago
A49: 124926603568 | B49: 0067A00377504 | C49: 45904 | D49: 49792700266 | E49: 2061603893533 | F49: Cargo por cobrar con código QR | G49: Si | J49: 134.83 | K49: Pago | L49: QR | M49: 71465208 | N49: Cerveza Träctor | P49: DANGELOKEVIN164 | Q49: 13900 | T49: Ir al Detalle de la operación en Mercado Pago
A50: 124926894128 | B50: 0067A00377504 | C50: 45904 | D50: 49792760846 | E50: 2061604892151 | F50: Cargo por cobrar con código QR | G50: Si | J50: 33.95 | K50: Pago | L50: QR | M50: 71465208 | N50: Cerveza Träctor | P50: MALENACERRUDO | Q50: 3500 | T50: Ir al Detalle de la operación en Mercado Pago
A51: 124382131027 | B51: 0067A00377504 | C51: 45904 | D51: 49792917465 | E51: 2061607911975 | F51: Cargo por cobrar con código QR | G51: Si | J51: 272.57 | K51: Pago | L51: QR | M51: 71465208 | N51: Cerveza Träctor | P51: CHINELLATOALEX | Q51: 28100 | T51: Ir al Detalle de la operación en Mercado Pago
A52: 124382333979 | B52: 0067A00377504 | C52: 45904 | D52: 49793044524 | E52: 2061610463869 | F52: Cargo por cobrar con código QR | G52: Si | J52: 125.13 | K52: Pago | L52: QR | M52: 71465208 | N52: Cerveza Träctor | P52: MARUDRI58 | Q52: 12900 | T52: Ir al Detalle de la operación en Mercado Pago
A53: 124383268861 | B53: 0067A00377504 | C53: 45904 | D53: 49793375258 | E53: 2061616817383 | F53: Cargo por cobrar con código QR | G53: Si | J53: 41.71 | K53: Pago | L53: QR | M53: 71465208 | N53: Cerveza Träctor | P53: DANGELOKEVIN164 | Q53: 4300 | T53: Ir al Detalle de la operación en Mercado Pago
A54: 124383275693 | B54: 0067A00377504 | C54: 45904 | D54: 49793444127 | E54: 2061657642060 | F54: Cargo por cobrar con código QR | G54: Si | J54: 90.21 | K54: Pago | L54: QR | M54: 71465208 | N54: Cerveza Träctor | P54: SAYASRAMIRO20230202201557 | Q54: 9300 | T54: Ir al Detalle de la operación en Mercado Pago
A55: 124928647796 | B55: 0067A00377504 | C55: 45904 | D55: 49793470711 | E55: 2061619062465 | F55: Cargo por uso de QR - Pagos Interoperables | G55: Si | J55: 125.13 | K55: Pago | L55: QR | M55: 71465208 | N55: Cerveza Träctor | P55: @2489718921 | Q55: 12900
A56: 124929160694 | B56: 0067A00377504 | C56: 45904 | D56: 49793609477 | E56: 2061621903175 | F56: Cargo por cobrar con Point | G56: Si | J56: 2693.94 | K56: Pago | L56: Point | M56: 71465208 | N56: Cerveza Träctor | O56: Venta presencial | P56: VENTASPRESENCIAL | Q56: 35400 | T56: Ir al Detalle de la operación en Mercado Pago
A57: 124929201672 | B57: 0067A00377504 | C57: 45904 | D57: 49793689456 | E57: 2061662653282 | F57: Cargo por cobrar con código QR | G57: Si | J57: 125.13 | K57: Pago | L57: QR | M57: 71465208 | N57: Cerveza Träctor | P57: VALLEDEL20220829194050 | Q57: 12900 | T57: Ir al Detalle de la operación en Mercado Pago
A58: 124929525256 | B58: 0067A00377504 | C58: 45904 | D58: 49793799379 | E58: 2061665211084 | F58: Cargo por cobrar con código QR | G58: Si | J58: 33.95 | K58: Pago | L58: QR | M58: 71465208 | N58: Cerveza Träctor | P58: JVICINO | Q58: 3500 | T58: Ir al Detalle de la operación en Mercado Pago
A59: 124929549560 | B59: 0067A00377504 | C59: 45904 | D59: 49793841462 | E59: 2061626378599 | F59: Cargo por cobrar con código QR | G59: Si | J59: 131.92 | K59: Pago | L59: QR | M59: 71465208 | N59: Cerveza Träctor | P59: JURICEVICTOMAS20220531155059 | Q59: 13600 | T59: Ir al Detalle de la operación en Mercado Pago
A60: 124384575133 | B60: 0067A00377504 | C60: 45904 | D60: 49793859601 | E60: 2061666428428 | F60: Cargo por cobrar con código QR | G60: Si | J60: 105.73 | K60: Pago | L60: QR | M60: 71465208 | N60: Cerveza Träctor | P60: LAPALMAMELANIE | Q60: 10900 | T60: Ir al Detalle de la operación en Mercado Pago
A61: 124929877616 | B61: 0067A00377504 | C61: 45904 | D61: 49793991063 | E61: 2061668644620 | F61: Cargo por cobrar con código QR | G61: Si | J61: 37.83 | K61: Pago | L61: QR | M61: 71465208 | N61: Cerveza Träctor | P61: GOMA5659770 | Q61: 3900 | T61: Ir al Detalle de la operación en Mercado Pago
A62: 124929957960 | B62: 0067A00377504 | C62: 45904 | D62: 49794040978 | E62: 2061630112565 | F62: Cargo por cobrar con código QR | G62: Si | J62: 41.71 | K62: Pago | L62: QR | M62: 71465208 | N62: Cerveza Träctor | P62: LEZCANOSARTORIVALENTIN | Q62: 4300 | T62: Ir al Detalle de la operación en Mercado Pago
A63: 124385248819 | B63: 0067A00377504 | C63: 45904 | D63: 49794116789 | E63: 2061671104490 | F63: Cargo por cobrar con código QR | G63: Si | J63: 37.83 | K63: Pago | L63: QR | M63: 71465208 | N63: Cerveza Träctor | P63: CLARAPEYCHAUX | Q63: 3900 | T63: Ir al Detalle de la operación en Mercado Pago
A64: 124930281670 | B64: 0067A00377504 | C64: 45904 | D64: 49794139898 | E64: 2061632297205 | F64: Cargo por cobrar con Point | G64: Si | J64: 390.44 | K64: Pago | L64: Point | M64: 71465208 | N64: Cerveza Träctor | O64: Venta presencial | P64: VENTASPRESENCIAL | Q64: 8600 | T64: Ir al Detalle de la operación en Mercado Pago
A65: 124385652341 | B65: 0067A00377504 | C65: 45904 | D65: 49794283775 | E65: 2061634555225 | F65: Cargo por cobrar con código QR | G65: Si | J65: 138.71 | K65: Pago | L65: QR | M65: 71465208 | N65: Cerveza Träctor | P65: BALLESTERDELFINA20230225195118 | Q65: 14300 | T65: Ir al Detalle de la operación en Mercado Pago
A66: 124930920538 | B66: 0067A00377504 | C66: 45904 | D66: 49794316920 | E66: 2061635353667 | F66: Cargo por cobrar con Point | G66: Si | J66: 844.95 | K66: Pago | L66: Point | M66: 71465208 | N66: Cerveza Träctor | O66: Venta presencial | P66: VENTASPRESENCIAL | Q66: 21500 | T66: Ir al Detalle de la operación en Mercado Pago
A67: 124385743585 | B67: 0067A00377504 | C67: 45904 | D67: 49794395679 | E67: 2061676280606 | F67: Cargo por uso de QR - Pagos Interoperables | G67: Si | J67: 37.83 | K67: Pago | L67: QR | M67: 71465208 | N67: Cerveza Träctor | P67: @2489718921 | Q67: 3900
A68: 124386234575 | B68: 0067A00377504 | C68: 45904 | D68: 49794552129 | E68: 2061639832319 | F68: Cargo por cobrar con Point | G68: Si | J68: 518.76 | K68: Pago | L68: Point | M68: 71465208 | N68: Cerveza Träctor | O68: Venta presencial | P68: VENTASPRESENCIAL | Q68: 13200 | T68: Ir al Detalle de la operación en Mercado Pago
A69: 124386117715 | B69: 0067A00377504 | C69: 45904 | D69: 49794581546 | E69: 2061680142672 | F69: Cargo por uso de QR - Pagos Interoperables | G69: Si | J69: 183.33 | K69: Pago | L69: QR | M69: 71465208 | N69: Cerveza Träctor | P69: @2489718921 | Q69: 18900
A70: 124931688378 | B70: 0067A00377504 | C70: 45904 | D70: 49794617036 | E70: 2061641348221 | F70: Cargo por cobrar con código QR | G70: Si | J70: 93.12 | K70: Pago | L70: QR | M70: 71465208 | N70: Cerveza Träctor | P70: ALEJOGONZALEZ15 | Q70: 9600 | T70: Ir al Detalle de la operación en Mercado Pago
A71: 124931738646 | B71: 0067A00377504 | C71: 45904 | D71: 49794659850 | E71: 2061642096377 | F71: Cargo por cobrar con código QR | G71: Si | J71: 37.83 | K71: Pago | L71: QR | M71: 71465208 | N71: Cerveza Träctor | P71: CANDELAABIGAIL13 | Q71: 3900 | T71: Ir al Detalle de la operación en Mercado Pago
A72: 124931811338 | B72: 0025A03281832 | C72: 45905 | D72: 49794885923 | E72: 2061643191205 | F72: Cargo por cobrar con código QR | G72: Si | J72: 18.43 | K72: Pago | L72: QR | M72: 71465208 | N72: Cerveza Träctor | P72: RONI2707995 | Q72: 1900 | T72: Ir al Detalle de la operación en Mercado Pago
A73: 124386853415 | B73: 0025A03281832 | C73: 45905 | D73: 49794893171 | E73: 2061645541077 | F73: Cargo por cobrar con código QR | G73: Si | J73: 37.83 | K73: Pago | L73: QR | M73: 71465208 | N73: Cerveza Träctor | P73: ORMAECHEANICANOR20220831201709 | Q73: 3900 | T73: Ir al Detalle de la operación en Mercado Pago
A74: 124387202427 | B74: 0025A03281832 | C74: 45905 | D74: 49794920915 | E74: 2061646999929 | F74: Cargo por cobrar con código QR | G74: Si | J74: 79.54 | K74: Pago | L74: QR | M74: 71465208 | N74: Cerveza Träctor | P74: VALLEDEL20220829194050 | Q74: 8200 | T74: Ir al Detalle de la operación en Mercado Pago
A75: 124932013860 | B75: 0025A03281832 | C75: 45905 | D75: 49795072667 | E75: 2061685408208 | F75: Cargo por cobrar con Point | G75: Si | J75: 2869.28 | K75: Pago | L75: Point | M75: 71465208 | N75: Cerveza Träctor | O75: Venta presencial | P75: VENTASPRESENCIAL | Q75: 63200 | T75: Ir al Detalle de la operación en Mercado Pago
A76: 124387169897 | B76: 0025A03281832 | C76: 45905 | D76: 49795140539 | E76: 2061648494567 | F76: Cargo por uso de QR - Pagos Interoperables | G76: Si | J76: 90.21 | K76: Pago | L76: QR | M76: 71465208 | N76: Cerveza Träctor | P76: @2489718921 | Q76: 9300
A77: 124387263837 | B77: 0025A03281832 | C77: 45905 | D77: 49795171840 | E77: 2061689088790 | F77: Cargo por uso de QR - Pagos Interoperables | G77: Si | J77: 154.23 | K77: Pago | L77: QR | M77: 71465208 | N77: Cerveza Träctor | P77: @2489718921 | Q77: 15900
A78: 124388358883 | B78: 0025A03281832 | C78: 45905 | D78: 49795204416 | E78: 2061696860136 | F78: Cargo por cobrar con Point | G78: Si | J78: 168.99 | K78: Pago | L78: Point | M78: 71465208 | N78: Cerveza Träctor | O78: Venta presencial | P78: VENTASPRESENCIAL | Q78: 4300 | T78: Ir al Detalle de la operación en Mercado Pago
A79: 124933214738 | B79: 0025A03281832 | C79: 45905 | D79: 49795343672 | E79: 2061654856339 | F79: Cargo por cobrar con código QR | G79: Si | J79: 41.71 | K79: Pago | L79: QR | M79: 71465208 | N79: Cerveza Träctor | P79: MANUCHI2108 | Q79: 4300 | T79: Ir al Detalle de la operación en Mercado Pago
A80: 124933398996 | B80: 0025A03281832 | C80: 45905 | D80: 49795516517 | E80: 2061656422631 | F80: Cargo por uso de QR - Pagos Interoperables | G80: Si | J80: 41.71 | K80: Pago | L80: QR | M80: 71465208 | N80: Cerveza Träctor | P80: @2489718921 | Q80: 4300
A81: 124388466105 | B81: 0025A03281832 | C81: 45905 | D81: 49795561390 | E81: 2061697436492 | F81: Cargo por cobrar con código QR | G81: Si | J81: 1806.14 | K81: Pago | L81: QR | M81: 71465208 | N81: Cerveza Träctor | P81: RUDAZNICO20221024092610 | Q81: 186200 | T81: Ir al Detalle de la operación en Mercado Pago
A82: 124932672660 | B82: 0025A03281832 | C82: 45905 | D82: 49795804083 | E82: 2061690326872 | F82: Cargo por cobrar con código QR | G82: Si | J82: 48.5 | K82: Pago | L82: QR | M82: 71465208 | N82: Cerveza Träctor | P82: LAUTIGABIOUD | Q82: 5000 | T82: Ir al Detalle de la operación en Mercado Pago
A83: 124934432228 | B83: 0025A03281832 | C83: 45905 | D83: 49795806680 | E83: 2061704561998 | F83: Cargo por cobrar con código QR | G83: Si | J83: 41.71 | K83: Pago | L83: QR | M83: 71465208 | N83: Cerveza Träctor | P83: MOSO3793694 | Q83: 4300 | T83: Ir al Detalle de la operación en Mercado Pago
A84: 124932574010 | B84: 0025A03281832 | C84: 45905 | D84: 49795823203 | E84: 2061650878053 | F84: Cargo por cobrar con Point | G84: Si | J84: 380.5 | K84: Pago | L84: Point | M84: 71465208 | N84: Cerveza Träctor | O84: Venta presencial | P84: VENTASPRESENCIAL | Q84: 5000 | T84: Ir al Detalle de la operación en Mercado Pago
A85: 124387491809 | B85: 0025A03281832 | C85: 45905 | D85: 49795865712 | E85: 2061651352159 | F85: Cargo por uso de QR - Pagos Interoperables | G85: Si | J85: 686.76 | K85: Pago | L85: QR | M85: 71465208 | N85: Cerveza Träctor | P85: @2489718921 | Q85: 70800
A86: 124932738810 | B86: 0025A03281832 | C86: 45905 | D86: 49795926945 | E86: 2061651362337 | F86: Cargo por cobrar con código QR | G86: Si | J86: 21.34 | K86: Pago | L86: QR | M86: 71465208 | N86: Cerveza Träctor | P86: AD20250105170400 | Q86: 2200 | T86: Ir al Detalle de la operación en Mercado Pago
A87: 124933058374 | B87: 0025A03281832 | C87: 45905 | D87: 49796021886 | E87: 2061653127277 | F87: Cargo por cobrar con código QR | G87: Si | J87: 156.17 | K87: Pago | L87: QR | M87: 71465208 | N87: Cerveza Träctor | P87: KLOVEN | Q87: 16100 | T87: Ir al Detalle de la operación en Mercado Pago
A88: 124389389493 | B88: 0025A03281832 | C88: 45905 | D88: 49796024358 | E88: 2061666694317 | F88: Cargo por cobrar con código QR | G88: Si | J88: 41.71 | K88: Pago | L88: QR | M88: 71465208 | N88: Cerveza Träctor | P88: MAXIMOGOROSTEGUI4 | Q88: 4300 | T88: Ir al Detalle de la operación en Mercado Pago
A89: 124388057649 | B89: 0025A03281832 | C89: 45905 | D89: 49796082117 | E89: 2061655308027 | F89: Cargo por cobrar con código QR | G89: Si | J89: 41.71 | K89: Pago | L89: QR | M89: 71465208 | N89: Cerveza Träctor | P89: LEZCANOSARTORIVALENTIN | Q89: 4300 | T89: Ir al Detalle de la operación en Mercado Pago
A90: 124388706943 | B90: 0025A03281832 | C90: 45905 | D90: 49796236955 | E90: 2061661235031 | F90: Cargo por cobrar con código QR | G90: Si | J90: 37.83 | K90: Pago | L90: QR | M90: 71465208 | N90: Cerveza Träctor | P90: ORMAECHEANICANOR20220831201709 | Q90: 3900 | T90: Ir al Detalle de la operación en Mercado Pago
A91: 124389182075 | B91: 0025A03281832 | C91: 45905 | D91: 49796311721 | E91: 2061665794163 | F91: Cargo por uso de QR - Pagos Interoperables | G91: Si | J91: 41.71 | K91: Pago | L91: QR | M91: 71465208 | N91: Cerveza Träctor | P91: @2489718921 | Q91: 4300
A92: 124389369351 | B92: 0025A03281832 | C92: 45905 | D92: 49796347465 | E92: 2061666137237 | F92: Cargo por cobrar con código QR | G92: Si | J92: 582.97 | K92: Pago | L92: QR | M92: 71465208 | N92: Cerveza Träctor | P92: ELIANAVERSA | Q92: 60100 | T92: Ir al Detalle de la operación en Mercado Pago
A93: 124389390021 | B93: 0025A03281832 | C93: 45905 | D93: 49796386856 | E93: 2061706592168 | F93: Cargo por cobrar con Point | G93: Si | J93: 334.05 | K93: Pago | L93: Point | M93: 71465208 | N93: Cerveza Träctor | O93: Venta presencial | P93: VENTASPRESENCIAL | Q93: 8500 | T93: Ir al Detalle de la operación en Mercado Pago
A94: 124935015006 | B94: 0025A03281832 | C94: 45905 | D94: 49796439850 | E94: 2061709987112 | F94: Cargo por cobrar con código QR | G94: Si | J94: 41.71 | K94: Pago | L94: QR | M94: 71465208 | N94: Cerveza Träctor | P94: LEZCANOSARTORIVALENTIN | Q94: 4300 | T94: Ir al Detalle de la operación en Mercado Pago
A95: 124390277545 | B95: 0025A03281832 | C95: 45905 | D95: 49796620694 | E95: 2061675549333 | F95: Cargo por cobrar con código QR | G95: Si | J95: 41.71 | K95: Pago | L95: QR | M95: 71465208 | N95: Cerveza Träctor | P95: BENJAMIKROLLS | Q95: 4300 | T95: Ir al Detalle de la operación en Mercado Pago
A96: 124390468955 | B96: 0025A03281832 | C96: 45905 | D96: 49796683596 | E96: 2061676996727 | F96: Cargo por cobrar con código QR | G96: Si | J96: 138.71 | K96: Pago | L96: QR | M96: 71465208 | N96: Cerveza Träctor | P96: MAGDALENABALLESTERCARRIZO | Q96: 14300 | T96: Ir al Detalle de la operación en Mercado Pago
A97: 124390658789 | B97: 0025A03281832 | C97: 45905 | D97: 49796750176 | E97: 2061718145760 | F97: Cargo por cobrar con Point | G97: Si | J97: 1852.32 | K97: Pago | L97: Point | M97: 71465208 | N97: Cerveza Träctor | O97: Venta presencial | P97: VENTASPRESENCIAL | Q97: 40800 | T97: Ir al Detalle de la operación en Mercado Pago
A98: 124936306000 | B98: 0025A03281832 | C98: 45905 | D98: 49797055646 | E98: 2061723855152 | F98: Cargo por cobrar con código QR | G98: Si | J98: 83.42 | K98: Pago | L98: QR | M98: 71465208 | N98: Cerveza Träctor | P98: NOMA5886241 | Q98: 8600 | T98: Ir al Detalle de la operación en Mercado Pago
A99: 124936593136 | B99: 0025A03281832 | C99: 45905 | D99: 49797105852 | E99: 2061685435451 | F99: Cargo por cobrar con código QR | G99: Si | J99: 214.37 | K99: Pago | L99: QR | M99: 71465208 | N99: Cerveza Träctor | P99: COTOCARLA20220604112601 | Q99: 22100 | T99: Ir al Detalle de la operación en Mercado Pago
A100: 124391343749 | B100: 0025A03281832 | C100: 45905 | D100: 49797123812 | E100: 2061686464417 | F100: Cargo por uso de QR - Pagos Interoperables | G100: Si | J100: 90.21 | K100: Pago | L100: QR | M100: 71465208 | N100: Cerveza Träctor | P100: @2489718921 | Q100: 9300
A101: 124391696277 | B101: 0025A03281832 | C101: 45905 | D101: 49797196010 | E101: 2061687444727 | F101: Cargo por uso de QR - Pagos Interoperables | G101: Si | J101: 41.71 | K101: Pago | L101: QR | M101: 71465208 | N101: Cerveza Träctor | P101: @2489718921 | Q101: 4300
A102: 124391850585 | B102: 0025A03281832 | C102: 45905 | D102: 49797290210 | E102: 2061729250290 | F102: Cargo por cobrar con código QR | G102: Si | J102: 945.75 | K102: Pago | L102: QR | M102: 71465208 | N102: Cerveza Träctor | P102: MARUDRI58 | Q102: 97500 | T102: Ir al Detalle de la operación en Mercado Pago
A103: 124391938119 | B103: 0025A03281832 | C103: 45905 | D103: 49797292898 | E103: 2061729395074 | F103: Cargo por cobrar con código QR | G103: Si | J103: 41.71 | K103: Pago | L103: QR | M103: 71465208 | N103: Cerveza Träctor | P103: BENJAMIKROLLS | Q103: 4300 | T103: Ir al Detalle de la operación en Mercado Pago
A104: 124937292950 | B104: 0025A03281832 | C104: 45905 | D104: 49797404505 | E104: 2061731887100 | F104: Cargo por cobrar con código QR | G104: Si | J104: 347.26 | K104: Pago | L104: QR | M104: 71465208 | N104: Cerveza Träctor | P104: GONZALEZJUAN20210529211711 | Q104: 35800 | T104: Ir al Detalle de la operación en Mercado Pago
...

Sheet IDC
A1: Reporte-Retención-Impuesto-sobre-los-Créditos-y-Débitos-Septiembre-CC20250609171159-MercadoPago
A3: Usuario: | B3: CC20250609171159
A4: Impuesto: | B4: Impuesto sobre los Créditos y Débitos
A5: Fecha de descarga: | B5: 18/03/2026
A6: Intervalo de fechas consultadas: | B6: 01/09/2025 a 01/10/2025
A8: Total | B8: Monto
A9: Base imponible | B9: $67.169.289,38
A10: Importe retenido | B10: $403.015,73
A11: Importe devuelto | B11: $480,00
A13: Encuentra los movimientos de dinero en tu cuenta de Mercado Pago, en informes de balance.
A15: Este impuesto se aplica cada vez que hagas operaciones con terceros.
A16: Podrás conciliar la información con otros reportes de Mercado Libre. | D16: Podrás buscar el detalle de lo retenido en tu operación en la sección Actividad.
A18: Operación | E18: Impuesto
A19: Número de operación | B19: Número de venta - Referencia externa | C19: Fecha de operación | D19: Tipo | E19: Fecha de retención | F19: Alícuota | G19: Base imponible | H19: Importe retenido
A20: 124407749182 | C20: 31/08/2025 | D20: Transacción | E20: 01/09/2025 | F20: 0,60 % | G20: 24500 | H20: 147 | L20: =VLOOKUP(A20,$J$20:$K$1682,2,FALSE) -> #N/A | M20: =+H20+L20 -> #N/A | O20: =VLOOKUP(A20,[1]Detallado!$C$149:$G$1733,5,FALSE) -> #N/A | P20: #N/A
A21: 124407346652 | C21: 31/08/2025 | D21: Transacción | E21: 01/09/2025 | F21: 0,60 % | G21: 13200 | H21: 79.2 | L21: =VLOOKUP(A21,$J$20:$K$1682,2,FALSE) -> #N/A | M21: =+H21+L21 -> #N/A | O21: =VLOOKUP(A21,[1]Detallado!$C$149:$G$1733,5,FALSE) -> #N/A | P21: #N/A
A22: 123865265509 | B22: tips-124407346652 | C22: 31/08/2025 | D22: Transacción | E22: 01/09/2025 | F22: 0,60 % | G22: 660 | H22: 3.96 | L22: =VLOOKUP(A22,$J$20:$K$1682,2,FALSE) -> #N/A | M22: =+H22+L22 -> #N/A | O22: =VLOOKUP(A22,[1]Detallado!$C$149:$G$1733,5,FALSE) -> #N/A | P22: #N/A
A23: 123864645949 | C23: 31/08/2025 | D23: Transacción | E23: 01/09/2025 | F23: 0,60 % | G23: 17500 | H23: 105 | L23: =VLOOKUP(A23,$J$20:$K$1682,2,FALSE) -> #N/A | M23: =+H23+L23 -> #N/A | O23: =VLOOKUP(A23,[1]Detallado!$C$149:$G$1733,5,FALSE) -> #N/A | P23: #N/A
A24: 123864040285 | C24: 31/08/2025 | D24: Transacción | E24: 01/09/2025 | F24: 0,60 % | G24: 15000 | H24: 90 | L24: =VLOOKUP(A24,$J$20:$K$1682,2,FALSE) -> #N/A | M24: =+H24+L24 -> #N/A | O24: =VLOOKUP(A24,[1]Detallado!$C$149:$G$1733,5,FALSE) -> #N/A | P24: #N/A
A25: 123868184561 | C25: 01/09/2025 | D25: Transacción | E25: 01/09/2025 | F25: 0,60 % | G25: 10000 | H25: 60 | K25: =VLOOKUP(A25,Detallado!$C$5:$H$1570,6,FALSE) -> #N/A
A26: 123868170745 | C26: 01/09/2025 | D26: Transacción | E26: 01/09/2025 | F26: 0,60 % | G26: 13500 | H26: 81 | K26: =VLOOKUP(A26,Detallado!$C$5:$H$1570,6,FALSE) -> #N/A
A27: 124446003662 | C27: 01/09/2025 | D27: Transacción | E27: 01/09/2025 | F27: 0,60 % | G27: 91714.5 | H27: 550.29 | K27: =VLOOKUP(A27,Detallado!$C$5:$H$1570,6,FALSE) -> #N/A | M27: -547.00497 | N27: =+K27-M27 -> #N/A | O27: 01-09-2025 | P27: =+E27-O27 -> 0
A28: 0005biaiaj | C28: 01/09/2025 | D28: Transacción | E28: 01/09/2025 | F28: 0,60 % | G28: 160822 | H28: 964.93 | K28: =-H28 -> -964.93 | M28: -964.93199 | N28: =+K28-M28 -> 0.0019880716 | O28: 01-09-2025 | P28: =+E28-O28 -> 0
A29: 124489977054 | C29: 01/09/2025 | D29: Transacción | E29: 01/09/2025 | F29: 0,60 % | G29: 168677.75 | H29: 1012.07 | K29: =VLOOKUP(A29,Detallado!$C$5:$H$1570,6,FALSE) -> #N/A | M29: -1006.0303 | N29: =+K29-M29 -> #N/A | P29: =+E29-O29 -> 45901
A30: 0005b9gkza | C30: 01/09/2025 | D30: Transacción | E30: 01/09/2025 | F30: 0,60 % | G30: 236646 | H30: 1419.88 | K30: =-H30 -> -1419.88 | M30: -1419.876 | N30: =+K30-M30 -> -0.0039761431 | O30: 01-09-2025 | P30: =+E30-O30 -> 0
A31: 124454118654 | C31: 01/09/2025 | D31: Transacción | E31: 01/09/2025 | F31: 0,60 % | G31: 273665.16 | H31: 1641.99 | K31: =VLOOKUP(A31,Detallado!$C$5:$H$1570,6,FALSE) -> #N/A | M31: -1632.1978 | N31: =+K31-M31 -> #N/A | O31: 01-09-2025 | P31: =+E31-O31 -> 0
A32: 124618927966 | C32: 02/09/2025 | D32: Transacción | E32: 02/09/2025 | F32: 0,60 % | G32: 84294.94 | H32: 505.77 | K32: =VLOOKUP(A32,Detallado!$C$5:$H$1570,6,FALSE) -> #N/A | M32: -502.75312 | N32: =+K32-M32 -> #N/A | O32: 02-09-2025 | P32: =+E32-O32 -> 0
A33: 124624594370 | C33: 02/09/2025 | D33: Transacción | E33: 02/09/2025 | F33: 0,60 % | G33: 215724.16 | H33: 1294.34 | K33: =VLOOKUP(A33,Detallado!$C$5:$H$1570,6,FALSE) -> #N/A | M33: -1286.6252 | N33: =+K33-M33 -> #N/A | P33: =+E33-O33 -> 45902
A34: 0005c7ks8r | C34: 02/09/2025 | D34: Transacción | E34: 02/09/2025 | F34: 0,60 % | G34: 420647.38 | H34: 2523.88 | K34: =-H34 -> -2523.88 | M34: -2523.8843 | N34: =+K34-M34 -> 0.0042544731 | O34: 02-09-2025 | P34: =+E34-O34 -> 0
A35: 124031772669 | C35: 02/09/2025 | D35: Transacción | E35: 02/09/2025 | F35: 0,60 % | G35: 785165 | H35: 4710.99 | K35: =VLOOKUP(A35,Detallado!$C$5:$H$1570,6,FALSE) -> #N/A | M35: -4682.8926 | N35: =+K35-M35 -> #N/A | O35: 02-09-2025 | P35: =+E35-O35 -> 0
A36: 124014458903 | C36: 02/09/2025 | D36: Transacción | E36: 02/09/2025 | F36: 0,60 % | G36: 982084.1 | H36: 5892.5 | K36: =VLOOKUP(A36,Detallado!$C$5:$H$1570,6,FALSE) -> #N/A | M36: -5857.3604 | N36: =+K36-M36 -> #N/A | O36: 02-09-2025 | P36: =+E36-O36 -> 0
A37: 124795296394 | C37: 03/09/2025 | D37: Transacción | E37: 03/09/2025 | F37: 0,60 % | G37: 19999 | H37: 119.99 | K37: =VLOOKUP(A37,Detallado!$C$5:$H$1570,6,FALSE) -> #N/A
A38: 124788106000 | B38: Venta presencial | C38: 03/09/2025 | D38: Transacción | E38: 03/09/2025 | F38: 0,60 % | G38: 5300 | H38: 31.8 | K38: =VLOOKUP(A38,Detallado!$C$5:$H$1570,6,FALSE) -> #N/A
A39: 124784681512 | B39: Venta presencial | C39: 03/09/2025 | D39: Transacción | E39: 03/09/2025 | F39: 0,60 % | G39: 31000 | H39: 186 | K39: =VLOOKUP(A39,Detallado!$C$5:$H$1570,6,FALSE) -> #N/A
A40: 124781182650 | B40: Venta presencial | C40: 03/09/2025 | D40: Transacción | E40: 03/09/2025 | F40: 0,60 % | G40: 8600 | H40: 51.6 | K40: =VLOOKUP(A40,Detallado!$C$5:$H$1570,6,FALSE) -> #N/A
A41: 124251556927 | C41: 03/09/2025 | D41: Transacción | E41: 03/09/2025 | F41: 0,60 % | G41: 71000 | H41: 426 | K41: =VLOOKUP(A41,Detallado!$C$5:$H$1570,6,FALSE) -> #N/A
A42: 124251168101 | C42: 03/09/2025 | D42: Transacción | E42: 03/09/2025 | F42: 0,60 % | G42: 59896 | H42: 359.38 | K42: =VLOOKUP(A42,Detallado!$C$5:$H$1570,6,FALSE) -> #N/A
A43: 124247706111 | C43: 03/09/2025 | D43: Transacción | E43: 03/09/2025 | F43: 0,60 % | G43: 12300 | H43: 73.8 | K43: =VLOOKUP(A43,Detallado!$C$5:$H$1570,6,FALSE) -> #N/A
A44: 124245392201 | C44: 03/09/2025 | D44: Transacción | E44: 03/09/2025 | F44: 0,60 % | G44: 34100 | H44: 204.6 | K44: =VLOOKUP(A44,Detallado!$C$5:$H$1570,6,FALSE) -> #N/A
A45: 124245389515 | C45: 03/09/2025 | D45: Transacción | E45: 03/09/2025 | F45: 0,60 % | G45: 46000 | H45: 276 | K45: =VLOOKUP(A45,Detallado!$C$5:$H$1570,6,FALSE) -> #N/A
A46: 124236889607 | C46: 03/09/2025 | D46: Transacción | E46: 03/09/2025 | F46: 0,60 % | G46: 29300 | H46: 175.8 | K46: =VLOOKUP(A46,Detallado!$C$5:$H$1570,6,FALSE) -> #N/A
A47: 124236877691 | B47: tips-124236889607 | C47: 03/09/2025 | D47: Transacción | E47: 03/09/2025 | F47: 0,60 % | G47: 1465 | H47: 8.79 | K47: =VLOOKUP(A47,Detallado!$C$5:$H$1570,6,FALSE) -> #N/A
A48: 124234497707 | C48: 03/09/2025 | D48: Transacción | E48: 03/09/2025 | F48: 0,60 % | G48: 4900 | H48: 29.4 | K48: =VLOOKUP(A48,Detallado!$C$5:$H$1570,6,FALSE) -> #N/A
A49: 124774089426 | C49: 03/09/2025 | D49: Transacción | E49: 03/09/2025 | F49: 0,60 % | G49: 45239.61 | H49: 271.44 | K49: =VLOOKUP(A49,Detallado!$C$5:$H$1570,6,FALSE) -> #N/A | M49: -269.81875 | N49: =+K49-M49 -> #N/A | O49: 03-09-2025 | P49: =+E49-O49 -> 0
A50: 124167213727 | C50: 03/09/2025 | D50: Transacción | E50: 03/09/2025 | F50: 0,60 % | G50: 107615.09 | H50: 645.69 | K50: =VLOOKUP(A50,Detallado!$C$5:$H$1570,6,FALSE) -> #N/A | M50: -641.8395 | N50: =+K50-M50 -> #N/A | O50: 03-09-2025 | P50: =+E50-O50 -> 0
A51: 0005cngcpo | C51: 03/09/2025 | D51: Transacción | E51: 03/09/2025 | F51: 0,60 % | G51: 154335 | H51: 926.01 | K51: =-H51 -> -926.01 | M51: -926.01 | N51: =+K51-M51 -> 9.3223207e-12 | O51: 03-09-2025 | P51: =+E51-O51 -> 0
A52: 124761516066 | C52: 03/09/2025 | D52: Transacción | E52: 03/09/2025 | F52: 0,60 % | G52: 210343.29 | H52: 1262.06 | K52: =VLOOKUP(A52,Detallado!$C$5:$H$1570,6,FALSE) -> #N/A | M52: -1254.5325 | N52: =+K52-M52 -> #N/A | O52: 03-09-2025 | P52: =+E52-O52 -> 0
A53: 124798706468 | C53: 03/09/2025 | D53: Transacción | E53: 04/09/2025 | F53: 0,60 % | G53: 9800 | H53: 58.8 | K53: =VLOOKUP(A53,Detallado!$C$5:$H$1570,6,FALSE) -> #N/A
A54: 124798439032 | C54: 03/09/2025 | D54: Transacción | E54: 04/09/2025 | F54: 0,60 % | G54: 28200 | H54: 169.2 | K54: =VLOOKUP(A54,Detallado!$C$5:$H$1570,6,FALSE) -> #N/A
A55: 124797908608 | C55: 03/09/2025 | D55: Transacción | E55: 04/09/2025 | F55: 0,60 % | G55: 15500 | H55: 93 | K55: =VLOOKUP(A55,Detallado!$C$5:$H$1570,6,FALSE) -> #N/A
A56: 124797743380 | B56: Venta presencial | C56: 03/09/2025 | D56: Transacción | E56: 04/09/2025 | F56: 0,60 % | G56: 152793 | H56: 916.76 | K56: =VLOOKUP(A56,Detallado!$C$5:$H$1570,6,FALSE) -> #N/A
A57: 124797394520 | C57: 03/09/2025 | D57: Transacción | E57: 04/09/2025 | F57: 0,60 % | G57: 36700 | H57: 220.2 | K57: =VLOOKUP(A57,Detallado!$C$5:$H$1570,6,FALSE) -> #N/A
A58: 124797073790 | C58: 03/09/2025 | D58: Transacción | E58: 04/09/2025 | F58: 0,60 % | G58: 57200 | H58: 343.2 | K58: =VLOOKUP(A58,Detallado!$C$5:$H$1570,6,FALSE) -> #N/A
A59: 124254045511 | B59: tips-124798439032 | C59: 03/09/2025 | D59: Transacción | E59: 04/09/2025 | F59: 0,60 % | G59: 1410 | H59: 8.46 | K59: =VLOOKUP(A59,Detallado!$C$5:$H$1570,6,FALSE) -> #N/A
A60: 124253989611 | C60: 03/09/2025 | D60: Transacción | E60: 04/09/2025 | F60: 0,60 % | G60: 20900 | H60: 125.4 | K60: =VLOOKUP(A60,Detallado!$C$5:$H$1570,6,FALSE) -> #N/A
A61: 124253070499 | B61: tips-124797394520 | C61: 03/09/2025 | D61: Transacción | E61: 04/09/2025 | F61: 0,60 % | G61: 1835 | H61: 11.01 | K61: =VLOOKUP(A61,Detallado!$C$5:$H$1570,6,FALSE) -> #N/A
A62: 124931811338 | C62: 04/09/2025 | D62: Transacción | E62: 04/09/2025 | F62: 0,60 % | G62: 1900 | H62: 11.4 | K62: =VLOOKUP(A62,Detallado!$C$5:$H$1570,6,FALSE) -> #N/A
A63: 124931738646 | C63: 04/09/2025 | D63: Transacción | E63: 04/09/2025 | F63: 0,60 % | G63: 3900 | H63: 23.4 | K63: =VLOOKUP(A63,Detallado!$C$5:$H$1570,6,FALSE) -> #N/A
A64: 124931688378 | C64: 04/09/2025 | D64: Transacción | E64: 04/09/2025 | F64: 0,60 % | G64: 9600 | H64: 57.6 | K64: =VLOOKUP(A64,Detallado!$C$5:$H$1570,6,FALSE) -> #N/A
A65: 124930920538 | B65: Venta presencial | C65: 04/09/2025 | D65: Transacción | E65: 04/09/2025 | F65: 0,60 % | G65: 21500 | H65: 129 | K65: =VLOOKUP(A65,Detallado!$C$5:$H$1570,6,FALSE) -> #N/A
A66: 124930281670 | B66: Venta presencial | C66: 04/09/2025 | D66: Transacción | E66: 04/09/2025 | F66: 0,60 % | G66: 8600 | H66: 51.6 | K66: =VLOOKUP(A66,Detallado!$C$5:$H$1570,6,FALSE) -> #N/A
A67: 124929957960 | C67: 04/09/2025 | D67: Transacción | E67: 04/09/2025 | F67: 0,60 % | G67: 4300 | H67: 25.8 | K67: =VLOOKUP(A67,Detallado!$C$5:$H$1570,6,FALSE) -> #N/A
A68: 124929877616 | C68: 04/09/2025 | D68: Transacción | E68: 04/09/2025 | F68: 0,60 % | G68: 3900 | H68: 23.4 | K68: =VLOOKUP(A68,Detallado!$C$5:$H$1570,6,FALSE) -> #N/A
A69: 124929549560 | C69: 04/09/2025 | D69: Transacción | E69: 04/09/2025 | F69: 0,60 % | G69: 13600 | H69: 81.6 | K69: =VLOOKUP(A69,Detallado!$C$5:$H$1570,6,FALSE) -> #N/A
A70: 124929525256 | C70: 04/09/2025 | D70: Transacción | E70: 04/09/2025 | F70: 0,60 % | G70: 3500 | H70: 21 | K70: =VLOOKUP(A70,Detallado!$C$5:$H$1570,6,FALSE) -> #N/A
A71: 124929201672 | C71: 04/09/2025 | D71: Transacción | E71: 04/09/2025 | F71: 0,60 % | G71: 12900 | H71: 77.4 | K71: =VLOOKUP(A71,Detallado!$C$5:$H$1570,6,FALSE) -> #N/A
A72: 124929160694 | B72: Venta presencial | C72: 04/09/2025 | D72: Transacción | E72: 04/09/2025 | F72: 0,60 % | G72: 35400 | H72: 212.4 | K72: =VLOOKUP(A72,Detallado!$C$5:$H$1570,6,FALSE) -> #N/A
A73: 124928647796 | C73: 04/09/2025 | D73: Transacción | E73: 04/09/2025 | F73: 0,60 % | G73: 12900 | H73: 77.4 | K73: =VLOOKUP(A73,Detallado!$C$5:$H$1570,6,FALSE) -> #N/A
A74: 124926894128 | C74: 04/09/2025 | D74: Transacción | E74: 04/09/2025 | F74: 0,60 % | G74: 3500 | H74: 21 | K74: =VLOOKUP(A74,Detallado!$C$5:$H$1570,6,FALSE) -> #N/A
A75: 124926882200 | B75: tips-124926894128 | C75: 04/09/2025 | D75: Transacción | E75: 04/09/2025 | F75: 0,60 % | G75: 175 | H75: 1.05 | K75: =VLOOKUP(A75,Detallado!$C$5:$H$1570,6,FALSE) -> #N/A
A76: 124926603568 | C76: 04/09/2025 | D76: Transacción | E76: 04/09/2025 | F76: 0,60 % | G76: 13900 | H76: 83.4 | K76: =VLOOKUP(A76,Detallado!$C$5:$H$1570,6,FALSE) -> #N/A
A77: 124926524640 | C77: 04/09/2025 | D77: Transacción | E77: 04/09/2025 | F77: 0,60 % | G77: 81900 | H77: 491.4 | K77: =VLOOKUP(A77,Detallado!$C$5:$H$1570,6,FALSE) -> #N/A
A78: 124924939738 | C78: 04/09/2025 | D78: Transacción | E78: 04/09/2025 | F78: 0,60 % | G78: 8600 | H78: 51.6 | K78: =VLOOKUP(A78,Detallado!$C$5:$H$1570,6,FALSE) -> #N/A
A79: 124921656040 | B79: Venta presencial | C79: 04/09/2025 | D79: Transacción | E79: 04/09/2025 | F79: 0,60 % | G79: 39800 | H79: 238.8 | K79: =VLOOKUP(A79,Detallado!$C$5:$H$1570,6,FALSE) -> #N/A
A80: 124919880508 | C80: 04/09/2025 | D80: Transacción | E80: 04/09/2025 | F80: 0,60 % | G80: 23800 | H80: 142.8 | K80: =VLOOKUP(A80,Detallado!$C$5:$H$1570,6,FALSE) -> #N/A
A81: 124912912486 | C81: 04/09/2025 | D81: Transacción | E81: 04/09/2025 | F81: 0,60 % | G81: 30000 | H81: 180 | K81: =VLOOKUP(A81,Detallado!$C$5:$H$1570,6,FALSE) -> #N/A
A82: 124909138878 | B82: tips-124909134908 | C82: 04/09/2025 | D82: Transacción | E82: 04/09/2025 | F82: 0,60 % | G82: 390 | H82: 2.34 | K82: =VLOOKUP(A82,Detallado!$C$5:$H$1570,6,FALSE) -> #N/A
A83: 124909134908 | C83: 04/09/2025 | D83: Transacción | E83: 04/09/2025 | F83: 0,60 % | G83: 7800 | H83: 46.8 | K83: =VLOOKUP(A83,Detallado!$C$5:$H$1570,6,FALSE) -> #N/A
A84: 124908939322 | C84: 04/09/2025 | D84: Transacción | E84: 04/09/2025 | F84: 0,60 % | G84: 4300 | H84: 25.8 | K84: =VLOOKUP(A84,Detallado!$C$5:$H$1570,6,FALSE) -> #N/A
A85: 124907529624 | C85: 04/09/2025 | D85: Transacción | E85: 04/09/2025 | F85: 0,60 % | G85: 15900 | H85: 95.4 | K85: =VLOOKUP(A85,Detallado!$C$5:$H$1570,6,FALSE) -> #N/A
A86: 124800062204 | C86: 04/09/2025 | D86: Transacción | E86: 04/09/2025 | F86: 0,60 % | G86: 47197 | H86: 283.18 | K86: =VLOOKUP(A86,Detallado!$C$5:$H$1570,6,FALSE) -> #N/A
A87: 124386234575 | B87: Venta presencial | C87: 04/09/2025 | D87: Transacción | E87: 04/09/2025 | F87: 0,60 % | G87: 13200 | H87: 79.2 | K87: =VLOOKUP(A87,Detallado!$C$5:$H$1570,6,FALSE) -> #N/A
A88: 124386117715 | C88: 04/09/2025 | D88: Transacción | E88: 04/09/2025 | F88: 0,60 % | G88: 18900 | H88: 113.4 | K88: =VLOOKUP(A88,Detallado!$C$5:$H$1570,6,FALSE) -> #N/A
A89: 124385743585 | C89: 04/09/2025 | D89: Transacción | E89: 04/09/2025 | F89: 0,60 % | G89: 3900 | H89: 23.4 | K89: =VLOOKUP(A89,Detallado!$C$5:$H$1570,6,FALSE) -> #N/A
A90: 124385652341 | C90: 04/09/2025 | D90: Transacción | E90: 04/09/2025 | F90: 0,60 % | G90: 14300 | H90: 85.8 | K90: =VLOOKUP(A90,Detallado!$C$5:$H$1570,6,FALSE) -> #N/A
A91: 124385248819 | C91: 04/09/2025 | D91: Transacción | E91: 04/09/2025 | F91: 0,60 % | G91: 3900 | H91: 23.4 | K91: =VLOOKUP(A91,Detallado!$C$5:$H$1570,6,FALSE) -> #N/A
A92: 124384575133 | C92: 04/09/2025 | D92: Transacción | E92: 04/09/2025 | F92: 0,60 % | G92: 10900 | H92: 65.4 | K92: =VLOOKUP(A92,Detallado!$C$5:$H$1570,6,FALSE) -> #N/A
A93: 124383275693 | C93: 04/09/2025 | D93: Transacción | E93: 04/09/2025 | F93: 0,60 % | G93: 9300 | H93: 55.8 | K93: =VLOOKUP(A93,Detallado!$C$5:$H$1570,6,FALSE) -> #N/A
A94: 124383268861 | C94: 04/09/2025 | D94: Transacción | E94: 04/09/2025 | F94: 0,60 % | G94: 4300 | H94: 25.8 | K94: =VLOOKUP(A94,Detallado!$C$5:$H$1570,6,FALSE) -> #N/A
A95: 124382333979 | C95: 04/09/2025 | D95: Transacción | E95: 04/09/2025 | F95: 0,60 % | G95: 12900 | H95: 77.4 | K95: =VLOOKUP(A95,Detallado!$C$5:$H$1570,6,FALSE) -> #N/A
A96: 124382131027 | C96: 04/09/2025 | D96: Transacción | E96: 04/09/2025 | F96: 0,60 % | G96: 28100 | H96: 168.6 | K96: =VLOOKUP(A96,Detallado!$C$5:$H$1570,6,FALSE) -> #N/A
A97: 124382023949 | B97: tips-124382131027 | C97: 04/09/2025 | D97: Transacción | E97: 04/09/2025 | F97: 0,60 % | G97: 4215 | H97: 25.29 | K97: =VLOOKUP(A97,Detallado!$C$5:$H$1570,6,FALSE) -> #N/A
A98: 124379914851 | C98: 04/09/2025 | D98: Transacción | E98: 04/09/2025 | F98: 0,60 % | G98: 4300 | H98: 25.8 | K98: =VLOOKUP(A98,Detallado!$C$5:$H$1570,6,FALSE) -> #N/A
A99: 124379045323 | C99: 04/09/2025 | D99: Transacción | E99: 04/09/2025 | F99: 0,60 % | G99: 3900 | H99: 23.4 | K99: =VLOOKUP(A99,Detallado!$C$5:$H$1570,6,FALSE) -> #N/A
A100: 124375560999 | B100: Venta presencial | C100: 04/09/2025 | D100: Transacción | E100: 04/09/2025 | F100: 0,60 % | G100: 4300 | H100: 25.8 | K100: =VLOOKUP(A100,Detallado!$C$5:$H$1570,6,FALSE) -> #N/A
A101: 124370030581 | C101: 04/09/2025 | D101: Transacción | E101: 04/09/2025 | F101: 0,60 % | G101: 108900 | H101: 653.4 | K101: =VLOOKUP(A101,Detallado!$C$5:$H$1570,6,FALSE) -> #N/A
A102: 124368294535 | B102: Venta presencial | C102: 04/09/2025 | D102: Transacción | E102: 04/09/2025 | F102: 0,60 % | G102: 4300 | H102: 25.8 | K102: =VLOOKUP(A102,Detallado!$C$5:$H$1570,6,FALSE) -> #N/A
A103: 124362828291 | B103: tips-124362593953 | C103: 04/09/2025 | D103: Transacción | E103: 04/09/2025 | F103: 0,60 % | G103: 215 | H103: 1.29 | K103: =VLOOKUP(A103,Detallado!$C$5:$H$1570,6,FALSE) -> #N/A
A104: 124362593953 | C104: 04/09/2025 | D104: Transacción | E104: 04/09/2025 | F104: 0,60 % | G104: 4300 | H104: 25.8 | K104: =VLOOKUP(A104,Detallado!$C$5:$H$1570,6,FALSE) -> #N/A
A105: 124256095479 | C105: 04/09/2025 | D105: Transacción | E105: 04/09/2025 | F105: 0,60 % | G105: 19998 | H105: 119.99 | K105: =VLOOKUP(A105,Detallado!$C$5:$H$1570,6,FALSE) -> #N/A
...
