Workbook

Sheet sheet0
A1: INITIAL_BALANCE | B1: CREDITS | C1: DEBITS | D1: FINAL_BALANCE
A2: 20952879 | B2: 37229764 | C2: -46195595 | D2: 11987048
A4: RELEASE_DATE | B4: TRANSACTION_TYPE | C4: REFERENCE_ID | D4: TRANSACTION_NET_AMOUNT | E4: PARTIAL_BALANCE | F4: VARIOS | G4: TRANSACTION_TOTAL_AMOUNT | H4: IDC COMPRAS | I4: SIRCUPA | J4: SIRTAC | K4: Gastos | L4: IDC | M4: MOV TOTAL | O4: OBSERV
A5: 01-12-2025 | B5: Liquidación de dinero | C5: 135329078135 | D5: 19388.57 | E5: 20972268 | F5: COBRO | I5: =-IFERROR(VLOOKUP(C5,SIRCUPA!$A$21:$H$186,8,0),0) -> 0 | J5: =-IFERROR(VLOOKUP(C5,SIRTAC!$A$16:$H$1405,8,0),0) -> -199 | K5: =-IFERROR(VLOOKUP(C5,Gastos!$A$9:$J$1398,10,0),0) -> -193.03 | L5: =-IFERROR(VLOOKUP(C5,IDC!$A$20:$H$1596,8,0),0) -> -119.4 | M5: =+D5-I5-J5-K5-L5 -> 19900
A6: 01-12-2025 | B6: Liquidación de dinero | C6: 135329349869 | D6: 37599.06 | E6: 21009867 | F6: COBRO | I6: =-IFERROR(VLOOKUP(C6,SIRCUPA!$A$21:$H$186,8,0),0) -> 0 | J6: =-IFERROR(VLOOKUP(C6,SIRTAC!$A$16:$H$1405,8,0),0) -> -398 | K6: =-IFERROR(VLOOKUP(C6,Gastos!$A$9:$J$1398,10,0),0) -> -1564.14 | L6: =-IFERROR(VLOOKUP(C6,IDC!$A$20:$H$1596,8,0),0) -> -238.8 | M6: =+D6-I6-J6-K6-L6 -> 39800
A7: 01-12-2025 | B7: Liquidación de dinero | C7: 135945633656 | D7: 8184.12 | E7: 21018051 | F7: COBRO | I7: =-IFERROR(VLOOKUP(C7,SIRCUPA!$A$21:$H$186,8,0),0) -> 0 | J7: =-IFERROR(VLOOKUP(C7,SIRTAC!$A$16:$H$1405,8,0),0) -> -84 | K7: =-IFERROR(VLOOKUP(C7,Gastos!$A$9:$J$1398,10,0),0) -> -81.48 | L7: =-IFERROR(VLOOKUP(C7,IDC!$A$20:$H$1596,8,0),0) -> -50.4 | M7: =+D7-I7-J7-K7-L7 -> 8400
A8: 01-12-2025 | B8: Liquidación de dinero | C8: 135945997406 | D8: 12276.18 | E8: 21030327 | F8: COBRO | I8: =-IFERROR(VLOOKUP(C8,SIRCUPA!$A$21:$H$186,8,0),0) -> 0 | J8: =-IFERROR(VLOOKUP(C8,SIRTAC!$A$16:$H$1405,8,0),0) -> -126 | K8: =-IFERROR(VLOOKUP(C8,Gastos!$A$9:$J$1398,10,0),0) -> -122.22 | L8: =-IFERROR(VLOOKUP(C8,IDC!$A$20:$H$1596,8,0),0) -> -75.6 | M8: =+D8-I8-J8-K8-L8 -> 12600
A9: 01-12-2025 | B9: Liquidación de dinero | C9: 135330440377 | D9: 55242.81 | E9: 21085570 | F9: COBRO | I9: =-IFERROR(VLOOKUP(C9,SIRCUPA!$A$21:$H$186,8,0),0) -> 0 | J9: =-IFERROR(VLOOKUP(C9,SIRTAC!$A$16:$H$1405,8,0),0) -> -567 | K9: =-IFERROR(VLOOKUP(C9,Gastos!$A$9:$J$1398,10,0),0) -> -549.99 | L9: =-IFERROR(VLOOKUP(C9,IDC!$A$20:$H$1596,8,0),0) -> -340.2 | M9: =+D9-I9-J9-K9-L9 -> 56700
A10: 01-12-2025 | B10: Liquidación de dinero | C10: 135330988071 | D10: 47518.41 | E10: 21133088 | F10: COBRO | I10: =-IFERROR(VLOOKUP(C10,SIRCUPA!$A$21:$H$186,8,0),0) -> 0 | J10: =-IFERROR(VLOOKUP(C10,SIRTAC!$A$16:$H$1405,8,0),0) -> -503 | K10: =-IFERROR(VLOOKUP(C10,Gastos!$A$9:$J$1398,10,0),0) -> -1976.79 | L10: =-IFERROR(VLOOKUP(C10,IDC!$A$20:$H$1596,8,0),0) -> -301.8 | M10: =+D10-I10-J10-K10-L10 -> 50300
A11: 01-12-2025 | B11: Liquidación de dinero | C11: 135331302959 | D11: 16368.24 | E11: 21149456 | F11: COBRO | I11: =-IFERROR(VLOOKUP(C11,SIRCUPA!$A$21:$H$186,8,0),0) -> 0 | J11: =-IFERROR(VLOOKUP(C11,SIRTAC!$A$16:$H$1405,8,0),0) -> -168 | K11: =-IFERROR(VLOOKUP(C11,Gastos!$A$9:$J$1398,10,0),0) -> -162.96 | L11: =-IFERROR(VLOOKUP(C11,IDC!$A$20:$H$1596,8,0),0) -> -100.8 | M11: =+D11-I11-J11-K11-L11 -> 16800
A12: 01-12-2025 | B12: Liquidación de dinero | C12: 135949105672 | D12: 9840.43 | E12: 21159297 | F12: COBRO | I12: =-IFERROR(VLOOKUP(C12,SIRCUPA!$A$21:$H$186,8,0),0) -> 0 | J12: =-IFERROR(VLOOKUP(C12,SIRTAC!$A$16:$H$1405,8,0),0) -> -101 | K12: =-IFERROR(VLOOKUP(C12,Gastos!$A$9:$J$1398,10,0),0) -> -97.97 | L12: =-IFERROR(VLOOKUP(C12,IDC!$A$20:$H$1596,8,0),0) -> -60.6 | M12: =+D12-I12-J12-K12-L12 -> 10100
A13: 01-12-2025 | B13: Impuesto por extracción | C13: 135362543637 | D13: -3309.17 | E13: 20202059 | F13: IDC | G13: =+D13/0.006 -> -551528.33 | I13: =-IFERROR(VLOOKUP(C13,SIRCUPA!$A$21:$H$186,8,0),0) -> 0 | J13: =-IFERROR(VLOOKUP(C13,SIRTAC!$A$16:$H$1405,8,0),0) -> 0 | K13: =-IFERROR(VLOOKUP(C13,Gastos!$A$9:$J$1398,10,0),0) -> 0 | M13: =+D13 -> -3309.17
A14: 01-12-2025 | B14: Transferencia enviada BASSO REPRESENT SRL | C14: 135362543637 | D14: -551528.92 | E14: 20205368 | F14: PAGO PROVEEDOR | G14: =+D14/1.006 -> -548239.48 | I14: =-IFERROR(VLOOKUP(C14,SIRCUPA!$A$21:$H$186,8,0),0) -> 0 | J14: =-IFERROR(VLOOKUP(C14,SIRTAC!$A$16:$H$1405,8,0),0) -> 0 | K14: =-IFERROR(VLOOKUP(C14,Gastos!$A$9:$J$1398,10,0),0) -> 0 | L14: =-IFERROR(VLOOKUP(C14,IDC!$A$20:$H$1596,8,0),0) -> -3309.17 | M14: =+D14 -> -551528.92
A15: 01-12-2025 | B15: Impuesto por extracción | C15: 135979554276 | D15: -2400 | E15: 20756897 | F15: IDC | G15: =+D15/0.006 -> -400000 | I15: =-IFERROR(VLOOKUP(C15,SIRCUPA!$A$21:$H$186,8,0),0) -> 0 | J15: =-IFERROR(VLOOKUP(C15,SIRTAC!$A$16:$H$1405,8,0),0) -> 0 | K15: =-IFERROR(VLOOKUP(C15,Gastos!$A$9:$J$1398,10,0),0) -> 0 | M15: =+D15 -> -2400
A16: 01-12-2025 | B16: Transferencia enviada EMBOTELLADORA DEL ATLANTICO S.A. | C16: 135979554276 | D16: -400000 | E16: 20759297 | F16: PAGO PROVEEDOR | I16: =-IFERROR(VLOOKUP(C16,SIRCUPA!$A$21:$H$186,8,0),0) -> 0 | J16: =-IFERROR(VLOOKUP(C16,SIRTAC!$A$16:$H$1405,8,0),0) -> 0 | K16: =-IFERROR(VLOOKUP(C16,Gastos!$A$9:$J$1398,10,0),0) -> 0 | L16: =-IFERROR(VLOOKUP(C16,IDC!$A$20:$H$1596,8,0),0) -> -2400 | M16: =+D16 -> -400000
A17: 03-12-2025 | B17: Liquidación de dinero | C17: 135734903707 | D17: 11690.63 | E17: 20213749 | F17: COBRO | I17: =-IFERROR(VLOOKUP(C17,SIRCUPA!$A$21:$H$186,8,0),0) -> 0 | J17: =-IFERROR(VLOOKUP(C17,SIRTAC!$A$16:$H$1405,8,0),0) -> -119.99 | K17: =-IFERROR(VLOOKUP(C17,Gastos!$A$9:$J$1398,10,0),0) -> -116.39 | L17: =-IFERROR(VLOOKUP(C17,IDC!$A$20:$H$1596,8,0),0) -> -71.99 | M17: =+D17-I17-J17-K17-L17 -> 11999
A18: 03-12-2025 | B18: Liquidación de dinero | C18: 135738371583 | D18: 24467.73 | E18: 20238217 | F18: COBRO | I18: =-IFERROR(VLOOKUP(C18,SIRCUPA!$A$21:$H$186,8,0),0) -> 0 | J18: =-IFERROR(VLOOKUP(C18,SIRTAC!$A$16:$H$1405,8,0),0) -> -259 | K18: =-IFERROR(VLOOKUP(C18,Gastos!$A$9:$J$1398,10,0),0) -> -1017.87 | L18: =-IFERROR(VLOOKUP(C18,IDC!$A$20:$H$1596,8,0),0) -> -155.4 | M18: =+D18-I18-J18-K18-L18 -> 25900
A19: 03-12-2025 | B19: Liquidación de dinero | C19: 135739132419 | D19: 15681.08 | E19: 20253898 | F19: COBRO | I19: =-IFERROR(VLOOKUP(C19,SIRCUPA!$A$21:$H$186,8,0),0) -> 0 | J19: =-IFERROR(VLOOKUP(C19,SIRTAC!$A$16:$H$1405,8,0),0) -> -165.99 | K19: =-IFERROR(VLOOKUP(C19,Gastos!$A$9:$J$1398,10,0),0) -> -652.34 | L19: =-IFERROR(VLOOKUP(C19,IDC!$A$20:$H$1596,8,0),0) -> -99.59 | M19: =+D19-I19-J19-K19-L19 -> 16599
A20: 03-12-2025 | B20: Liquidación de dinero | C20: 136364441784 | D20: 4357.92 | E20: 20258256 | F20: COBRO | I20: =-IFERROR(VLOOKUP(C20,SIRCUPA!$A$21:$H$186,8,0),0) -> 0 | J20: =-IFERROR(VLOOKUP(C20,SIRTAC!$A$16:$H$1405,8,0),0) -> -48 | K20: =-IFERROR(VLOOKUP(C20,Gastos!$A$9:$J$1398,10,0),0) -> -365.28 | L20: =-IFERROR(VLOOKUP(C20,IDC!$A$20:$H$1596,8,0),0) -> -28.8 | M20: =+D20-I20-J20-K20-L20 -> 4800
A21: 03-12-2025 | B21: Transferencia recibida Juan Felipe Folmer Dondena | C21: 136364596558 | D21: 234.96 | E21: 20258491 | F21: COBRO | I21: =-IFERROR(VLOOKUP(C21,SIRCUPA!$A$21:$H$186,8,0),0) -> -3.6 | J21: =-IFERROR(VLOOKUP(C21,SIRTAC!$A$16:$H$1405,8,0),0) -> 0 | K21: =-IFERROR(VLOOKUP(C21,Gastos!$A$9:$J$1398,10,0),0) -> 0 | L21: =-IFERROR(VLOOKUP(C21,IDC!$A$20:$H$1596,8,0),0) -> -1.44 | M21: =+D21-I21-J21-K21-L21 -> 240
A22: 03-12-2025 | B22: Liquidación de dinero | C22: 136364614462 | D22: 9069.12 | E22: 20267560 | F22: COBRO | I22: =-IFERROR(VLOOKUP(C22,SIRCUPA!$A$21:$H$186,8,0),0) -> 0 | J22: =-IFERROR(VLOOKUP(C22,SIRTAC!$A$16:$H$1405,8,0),0) -> -96 | K22: =-IFERROR(VLOOKUP(C22,Gastos!$A$9:$J$1398,10,0),0) -> -377.28 | L22: =-IFERROR(VLOOKUP(C22,IDC!$A$20:$H$1596,8,0),0) -> -57.6 | M22: =+D22-I22-J22-K22-L22 -> 9600
A23: 03-12-2025 | B23: Liquidación de dinero | C23: 136366138324 | D23: 7989.26 | E23: 20275549 | F23: COBRO | I23: =-IFERROR(VLOOKUP(C23,SIRCUPA!$A$21:$H$186,8,0),0) -> 0 | J23: =-IFERROR(VLOOKUP(C23,SIRTAC!$A$16:$H$1405,8,0),0) -> -82 | K23: =-IFERROR(VLOOKUP(C23,Gastos!$A$9:$J$1398,10,0),0) -> -79.54 | L23: =-IFERROR(VLOOKUP(C23,IDC!$A$20:$H$1596,8,0),0) -> -49.2 | M23: =+D23-I23-J23-K23-L23 -> 8200
A24: 03-12-2025 | B24: Liquidación de dinero | C24: 135748062571 | D24: 45629.01 | E24: 20321178 | F24: COBRO | I24: =-IFERROR(VLOOKUP(C24,SIRCUPA!$A$21:$H$186,8,0),0) -> 0 | J24: =-IFERROR(VLOOKUP(C24,SIRTAC!$A$16:$H$1405,8,0),0) -> -483 | K24: =-IFERROR(VLOOKUP(C24,Gastos!$A$9:$J$1398,10,0),0) -> -1898.19 | L24: =-IFERROR(VLOOKUP(C24,IDC!$A$20:$H$1596,8,0),0) -> -289.8 | M24: =+D24-I24-J24-K24-L24 -> 48300
A25: 03-12-2025 | B25: Liquidación de dinero | C25: 136370129344 | D25: 23675.49 | E25: 20344854 | F25: COBRO | I25: =-IFERROR(VLOOKUP(C25,SIRCUPA!$A$21:$H$186,8,0),0) -> 0 | J25: =-IFERROR(VLOOKUP(C25,SIRTAC!$A$16:$H$1405,8,0),0) -> -243 | K25: =-IFERROR(VLOOKUP(C25,Gastos!$A$9:$J$1398,10,0),0) -> -235.71 | L25: =-IFERROR(VLOOKUP(C25,IDC!$A$20:$H$1596,8,0),0) -> -145.8 | M25: =+D25-I25-J25-K25-L25 -> 24300
A26: 03-12-2025 | B26: Liquidación de dinero | C26: 135749825345 | D26: 9069.12 | E26: 20353923 | F26: COBRO | I26: =-IFERROR(VLOOKUP(C26,SIRCUPA!$A$21:$H$186,8,0),0) -> 0 | J26: =-IFERROR(VLOOKUP(C26,SIRTAC!$A$16:$H$1405,8,0),0) -> -96 | K26: =-IFERROR(VLOOKUP(C26,Gastos!$A$9:$J$1398,10,0),0) -> -377.28 | L26: =-IFERROR(VLOOKUP(C26,IDC!$A$20:$H$1596,8,0),0) -> -57.6 | M26: =+D26-I26-J26-K26-L26 -> 9600
A27: 03-12-2025 | B27: Liquidación de dinero | C27: 136373560516 | D27: 30203.3 | E27: 20384126 | F27: COBRO | I27: =-IFERROR(VLOOKUP(C27,SIRCUPA!$A$21:$H$186,8,0),0) -> 0 | J27: =-IFERROR(VLOOKUP(C27,SIRTAC!$A$16:$H$1405,8,0),0) -> -310 | K27: =-IFERROR(VLOOKUP(C27,Gastos!$A$9:$J$1398,10,0),0) -> -300.7 | L27: =-IFERROR(VLOOKUP(C27,IDC!$A$20:$H$1596,8,0),0) -> -186 | M27: =+D27-I27-J27-K27-L27 -> 31000
A28: 03-12-2025 | B28: Liquidación de dinero | C28: 136374043234 | D28: 14127.35 | E28: 20398254 | F28: COBRO | I28: =-IFERROR(VLOOKUP(C28,SIRCUPA!$A$21:$H$186,8,0),0) -> 0 | J28: =-IFERROR(VLOOKUP(C28,SIRTAC!$A$16:$H$1405,8,0),0) -> -145 | K28: =-IFERROR(VLOOKUP(C28,Gastos!$A$9:$J$1398,10,0),0) -> -140.65 | L28: =-IFERROR(VLOOKUP(C28,IDC!$A$20:$H$1596,8,0),0) -> -87 | M28: =+D28-I28-J28-K28-L28 -> 14500
... A129: 05-12-2025 | B129: Liquidación de dinero | C129: 136539211002 | D129: 8525.12 | E129: 22850825 | F129: COBRO | I129: =-IFERROR(VLOOKUP(C129,SIRCUPA!$A$21:$H$186,8,0),0) -> 0 | J129: =-IFERROR(VLOOKUP(C129,SIRTAC!$A$16:$H$1405,8,0),0) -> -87.5 | K129: =-IFERROR(VLOOKUP(C129,Gastos!$A$9:$J$1398,10,0),0) -> -84.88 | L129: =-IFERROR(VLOOKUP(C129,IDC!$A$20:$H$1596,8,0),0) -> -52.5 | M129: =+D129-I129-J129-K129-L129 -> 8750
A130: 05-12-2025 | B130: Transferencia recibida Juan Lucas Presas | C130: 136582518616 | D130: 63145.5 | E130: 22913970 | F130: COBRO | I130: =-IFERROR(VLOOKUP(C130,SIRCUPA!$A$21:$H$186,8,0),0) -> -967.5 | J130: =-IFERROR(VLOOKUP(C130,SIRTAC!$A$16:$H$1405,8,0),0) -> 0 | K130: =-IFERROR(VLOOKUP(C130,Gastos!$A$9:$J$1398,10,0),0) -> 0 | L130: -387 | M130: =+D130-I130-J130-K130-L130 -> 64500 | Q130: =+I130/0.015 -> -64500 | R130: =+Q130*0.006 -> -387
A131: 05-12-2025 | B131: Liquidación de dinero | C131: 136675013138 | D131: 4092.06 | E131: 22918062 | F131: COBRO | I131: =-IFERROR(VLOOKUP(C131,SIRCUPA!$A$21:$H$186,8,0),0) -> 0 | J131: =-IFERROR(VLOOKUP(C131,SIRTAC!$A$16:$H$1405,8,0),0) -> -42 | K131: =-IFERROR(VLOOKUP(C131,Gastos!$A$9:$J$1398,10,0),0) -> -40.74 | L131: =-IFERROR(VLOOKUP(C131,IDC!$A$20:$H$1596,8,0),0) -> -25.2 | M131: =+D131-I131-J131-K131-L131 -> 4200
A132: 05-12-2025 | B132: Transferencia recibida Brian Ramon Coronel | C132: 136051543027 | D132: 205.59 | E132: 22918268 | F132: COBRO | I132: =-IFERROR(VLOOKUP(C132,SIRCUPA!$A$21:$H$186,8,0),0) -> -3.15 | J132: =-IFERROR(VLOOKUP(C132,SIRTAC!$A$16:$H$1405,8,0),0) -> 0 | K132: =-IFERROR(VLOOKUP(C132,Gastos!$A$9:$J$1398,10,0),0) -> 0 | L132: =-IFERROR(VLOOKUP(C132,IDC!$A$20:$H$1596,8,0),0) -> -1.26 | M132: =+D132-I132-J132-K132-L132 -> 210
A133: 05-12-2025 | B133: Liquidación de dinero | C133: 136052254573 | D133: 4534.56 | E133: 22922803 | F133: COBRO | I133: =-IFERROR(VLOOKUP(C133,SIRCUPA!$A$21:$H$186,8,0),0) -> 0 | J133: =-IFERROR(VLOOKUP(C133,SIRTAC!$A$16:$H$1405,8,0),0) -> -48 | K133: =-IFERROR(VLOOKUP(C133,Gastos!$A$9:$J$1398,10,0),0) -> -188.64 | L133: =-IFERROR(VLOOKUP(C133,IDC!$A$20:$H$1596,8,0),0) -> -28.8 | M133: =+D133-I133-J133-K133-L133 -> 4800
A134: 05-12-2025 | B134: Liquidación de dinero | C134: 136676483834 | D134: 23969 | E134: 22946772 | F134: COBRO | I134: =-IFERROR(VLOOKUP(C134,SIRCUPA!$A$21:$H$186,8,0),0) -> 0 | J134: =-IFERROR(VLOOKUP(C134,SIRTAC!$A$16:$H$1405,8,0),0) -> -275 | K134: =-IFERROR(VLOOKUP(C134,Gastos!$A$9:$J$1398,10,0),0) -> -3091 | L134: =-IFERROR(VLOOKUP(C134,IDC!$A$20:$H$1596,8,0),0) -> -165 | M134: =+D134-I134-J134-K134-L134 -> 27500
A135: 05-12-2025 | B135: Liquidación de dinero | C135: 136676932768 | D135: 15870.96 | E135: 22962643 | F135: COBRO | I135: =-IFERROR(VLOOKUP(C135,SIRCUPA!$A$21:$H$186,8,0),0) -> 0 | J135: =-IFERROR(VLOOKUP(C135,SIRTAC!$A$16:$H$1405,8,0),0) -> -168 | K135: =-IFERROR(VLOOKUP(C135,Gastos!$A$9:$J$1398,10,0),0) -> -660.24 | L135: =-IFERROR(VLOOKUP(C135,IDC!$A$20:$H$1596,8,0),0) -> -100.8 | M135: =+D135-I135-J135-K135-L135 -> 16800
A136: 05-12-2025 | B136: Liquidación de dinero | C136: 136677967596 | D136: 15296.51 | E136: 22977939 | F136: COBRO | I136: =-IFERROR(VLOOKUP(C136,SIRCUPA!$A$21:$H$186,8,0),0) -> 0 | J136: =-IFERROR(VLOOKUP(C136,SIRTAC!$A$16:$H$1405,8,0),0) -> -157 | K136: =-IFERROR(VLOOKUP(C136,Gastos!$A$9:$J$1398,10,0),0) -> -152.29 | L136: =-IFERROR(VLOOKUP(C136,IDC!$A$20:$H$1596,8,0),0) -> -94.2 | M136: =+D136-I136-J136-K136-L136 -> 15700
A137: 05-12-2025 | B137: Liquidación de dinero | C137: 136058124483 | D137: 8715.84 | E137: 22986655 | F137: COBRO | I137: =-IFERROR(VLOOKUP(C137,SIRCUPA!$A$21:$H$186,8,0),0) -> 0 | J137: =-IFERROR(VLOOKUP(C137,SIRTAC!$A$16:$H$1405,8,0),0) -> -96 | K137: =-IFERROR(VLOOKUP(C137,Gastos!$A$9:$J$1398,10,0),0) -> -730.56 | L137: =-IFERROR(VLOOKUP(C137,IDC!$A$20:$H$1596,8,0),0) -> -57.6 | M137: =+D137-I137-J137-K137-L137 -> 9600
A138: 05-12-2025 | B138: Liquidación de dinero | C138: 136684362466 | D138: 26793.25 | E138: 23013448 | F138: COBRO | I138: =-IFERROR(VLOOKUP(C138,SIRCUPA!$A$21:$H$186,8,0),0) -> 0 | J138: =-IFERROR(VLOOKUP(C138,SIRTAC!$A$16:$H$1405,8,0),0) -> -275 | K138: =-IFERROR(VLOOKUP(C138,Gastos!$A$9:$J$1398,10,0),0) -> -266.75 | L138: =-IFERROR(VLOOKUP(C138,IDC!$A$20:$H$1596,8,0),0) -> -165 | M138: =+D138-I138-J138-K138-L138 -> 27500
A139: 05-12-2025 | B139: Transferencia recibida Iván Atilano Fellay | C139: 136684356570 | D139: 1346.12 | E139: 23014794 | F139: COBRO | I139: =-IFERROR(VLOOKUP(C139,SIRCUPA!$A$21:$H$186,8,0),0) -> -20.63 | J139: =-IFERROR(VLOOKUP(C139,SIRTAC!$A$16:$H$1405,8,0),0) -> 0 | K139: =-IFERROR(VLOOKUP(C139,Gastos!$A$9:$J$1398,10,0),0) -> 0 | L139: =-IFERROR(VLOOKUP(C139,IDC!$A$20:$H$1596,8,0),0) -> -8.25 | M139: =+D139-I139-J139-K139-L139 -> 1375
A140: 05-12-2025 | B140: Liquidación de dinero | C140: 136684524618 | D140: 4629.03 | E140: 23019423 | F140: COBRO | I140: =-IFERROR(VLOOKUP(C140,SIRCUPA!$A$21:$H$186,8,0),0) -> 0 | J140: =-IFERROR(VLOOKUP(C140,SIRTAC!$A$16:$H$1405,8,0),0) -> -49 | K140: =-IFERROR(VLOOKUP(C140,Gastos!$A$9:$J$1398,10,0),0) -> -192.57 | L140: =-IFERROR(VLOOKUP(C140,IDC!$A$20:$H$1596,8,0),0) -> -29.4 | M140: =+D140-I140-J140-K140-L140 -> 4900
A141: 05-12-2025 | B141: Liquidación de dinero | C141: 136686063362 | D141: 9548.14 | E141: 23028971 | F141: COBRO | I141: =-IFERROR(VLOOKUP(C141,SIRCUPA!$A$21:$H$186,8,0),0) -> 0 | J141: =-IFERROR(VLOOKUP(C141,SIRTAC!$A$16:$H$1405,8,0),0) -> -98 | K141: =-IFERROR(VLOOKUP(C141,Gastos!$A$9:$J$1398,10,0),0) -> -95.06 | L141: =-IFERROR(VLOOKUP(C141,IDC!$A$20:$H$1596,8,0),0) -> -58.8 | M141: =+D141-I141-J141-K141-L141 -> 9800
A142: 05-12-2025 | B142: Liquidación de dinero | C142: 136689125144 | D142: 8768.7 | E142: 23037740 | F142: COBRO | I142: =-IFERROR(VLOOKUP(C142,SIRCUPA!$A$21:$H$186,8,0),0) -> 0 | J142: =-IFERROR(VLOOKUP(C142,SIRTAC!$A$16:$H$1405,8,0),0) -> -90 | K142: =-IFERROR(VLOOKUP(C142,Gastos!$A$9:$J$1398,10,0),0) -> -87.3 | L142: =-IFERROR(VLOOKUP(C142,IDC!$A$20:$H$1596,8,0),0) -> -54 | M142: =+D142-I142-J142-K142-L142 -> 9000
... A181: 06-12-2025 | B181: Liquidación de dinero | C181: 136086178973 | D181: 22896.05 | E181: 24251857 | F181: COBRO | I181: =-IFERROR(VLOOKUP(C181,SIRCUPA!$A$21:$H$186,8,0),0) -> 0 | J181: =-IFERROR(VLOOKUP(C181,SIRTAC!$A$16:$H$1405,8,0),0) -> -235 | K181: =-IFERROR(VLOOKUP(C181,Gastos!$A$9:$J$1398,10,0),0) -> -227.95 | L181: =-IFERROR(VLOOKUP(C181,IDC!$A$20:$H$1596,8,0),0) -> -141 | M181: =+D181-I181-J181-K181-L181 -> 23500
A182: 06-12-2025 | B182: Pago Mercado Libre S R L - MLA MP | C182: 136154630259 | D182: -30763.36 | E182: 24221093 | F182: PAGO PROVEEDOR | G182: =+D182/1.006 -> -30579.881 | I182: =-IFERROR(VLOOKUP(C182,SIRCUPA!$A$21:$H$186,8,0),0) -> 0 | J182: =-IFERROR(VLOOKUP(C182,SIRTAC!$A$16:$H$1405,8,0),0) -> 0 | K182: =-IFERROR(VLOOKUP(C182,Gastos!$A$9:$J$1398,10,0),0) -> 0 | L182: =+D182-G182 -> -183.47928 | M182: =+D182-I182-J182-K182-L182 -> -30579.881
A183: 06-12-2025 | B183: Liquidación de dinero | C183: 136182589345 | D183: 14.17 | E183: 24221108 | F183: COBRO | I183: =-IFERROR(VLOOKUP(C183,SIRCUPA!$A$21:$H$186,8,0),0) -> 0 | J183: =-IFERROR(VLOOKUP(C183,SIRTAC!$A$16:$H$1405,8,0),0) -> -0.15 | K183: =-IFERROR(VLOOKUP(C183,Gastos!$A$9:$J$1398,10,0),0) -> -0.59 | L183: =-IFERROR(VLOOKUP(C183,IDC!$A$20:$H$1596,8,0),0) -> -0.09 | M183: =+D183-I183-J183-K183-L183 -> 15
A184: 06-12-2025 | B184: Liquidación de dinero cancelada Venta cancelada | C184: 136182589345 | D184: -14.17 | E184: 24221093 | F184: COBRO | I184: =-IFERROR(VLOOKUP(C184,SIRCUPA!$A$21:$H$186,8,0),0) -> 0 | J184: 0.14 | K184: 0.59 | L184: 0.09 | M184: =+D184-I184-J184-K184-L184 -> -14.99
A185: 06-12-2025 | B185: Liquidación de dinero | C185: 136818536256 | D185: 7935.48 | E185: 24229029 | F185: COBRO | I185: =-IFERROR(VLOOKUP(C185,SIRCUPA!$A$21:$H$186,8,0),0) -> 0 | J185: =-IFERROR(VLOOKUP(C185,SIRTAC!$A$16:$H$1405,8,0),0) -> -84 | K185: =-IFERROR(VLOOKUP(C185,Gastos!$A$9:$J$1398,10,0),0) -> -330.12 | L185: =-IFERROR(VLOOKUP(C185,IDC!$A$20:$H$1596,8,0),0) -> -50.4 | M185: =+D185-I185-J185-K185-L185 -> 8400
A186: 06-12-2025 | B186: Liquidación de dinero | C186: 136197610809 | D186: 9353.28 | E186: 24238382 | F186: COBRO | I186: =-IFERROR(VLOOKUP(C186,SIRCUPA!$A$21:$H$186,8,0),0) -> 0 | J186: =-IFERROR(VLOOKUP(C186,SIRTAC!$A$16:$H$1405,8,0),0) -> -96 | K186: =-IFERROR(VLOOKUP(C186,Gastos!$A$9:$J$1398,10,0),0) -> -93.12 | L186: =-IFERROR(VLOOKUP(C186,IDC!$A$20:$H$1596,8,0),0) -> -57.6 | M186: =+D186-I186-J186-K186-L186 -> 9600
A187: 06-12-2025 | B187: Liquidación de dinero | C187: 136199301371 | D187: 12081.32 | E187: 24250463 | F187: COBRO | I187: =-IFERROR(VLOOKUP(C187,SIRCUPA!$A$21:$H$186,8,0),0) -> 0 | J187: =-IFERROR(VLOOKUP(C187,SIRTAC!$A$16:$H$1405,8,0),0) -> -124 | K187: =-IFERROR(VLOOKUP(C187,Gastos!$A$9:$J$1398,10,0),0) -> -120.28 | L187: =-IFERROR(VLOOKUP(C187,IDC!$A$20:$H$1596,8,0),0) -> -74.4 | M187: =+D187-I187-J187-K187-L187 -> 12400
A188: 06-12-2025 | B188: Liquidación de dinero | C188: 136825810056 | D188: 13225.8 | E188: 24263689 | F188: COBRO | I188: =-IFERROR(VLOOKUP(C188,SIRCUPA!$A$21:$H$186,8,0),0) -> 0 | J188: =-IFERROR(VLOOKUP(C188,SIRTAC!$A$16:$H$1405,8,0),0) -> -140 | K188: =-IFERROR(VLOOKUP(C188,Gastos!$A$9:$J$1398,10,0),0) -> -550.2 | L188: =-IFERROR(VLOOKUP(C188,IDC!$A$20:$H$1596,8,0),0) -> -84 | M188: =+D188-I188-J188-K188-L188 -> 14000
A189: 06-12-2025 | B189: Liquidación de dinero | C189: 136203880503 | D189: 22483.86 | E189: 24286173 | F189: COBRO | I189: =-IFERROR(VLOOKUP(C189,SIRCUPA!$A$21:$H$186,8,0),0) -> 0 | J189: =-IFERROR(VLOOKUP(C189,SIRTAC!$A$16:$H$1405,8,0),0) -> -238 | K189: =-IFERROR(VLOOKUP(C189,Gastos!$A$9:$J$1398,10,0),0) -> -935.34 | L189: =-IFERROR(VLOOKUP(C189,IDC!$A$20:$H$1596,8,0),0) -> -142.8 | M189: =+D189-I189-J189-K189-L189 -> 23800
A190: 06-12-2025 | B190: Liquidación de dinero | C190: 136204861051 | D190: 19778.29 | E190: 24305951 | F190: COBRO | I190: =-IFERROR(VLOOKUP(C190,SIRCUPA!$A$21:$H$186,8,0),0) -> 0 | J190: =-IFERROR(VLOOKUP(C190,SIRTAC!$A$16:$H$1405,8,0),0) -> -203 | K190: =-IFERROR(VLOOKUP(C190,Gastos!$A$9:$J$1398,10,0),0) -> -196.91 | L190: =-IFERROR(VLOOKUP(C190,IDC!$A$20:$H$1596,8,0),0) -> -121.8 | M190: =+D190-I190-J190-K190-L190 -> 20300
A191: 06-12-2025 | B191: Transferencia recibida Timoteo Nicolás Alcaraz | C191: 136829205946 | D191: 993.68 | E191: 24306945 | F191: COBRO | I191: =-IFERROR(VLOOKUP(C191,SIRCUPA!$A$21:$H$186,8,0),0) -> -15.23 | J191: =-IFERROR(VLOOKUP(C191,SIRTAC!$A$16:$H$1405,8,0),0) -> 0 | K191: =-IFERROR(VLOOKUP(C191,Gastos!$A$9:$J$1398,10,0),0) -> 0 | L191: =-IFERROR(VLOOKUP(C191,IDC!$A$20:$H$1596,8,0),0) -> -6.09 | M191: =+D191-I191-J191-K191-L191 -> 1015
A192: 06-12-2025 | B192: Liquidación de dinero | C192: 136206758325 | D192: 71905.68 | E192: 24378851 | F192: COBRO | I192: =-IFERROR(VLOOKUP(C192,SIRCUPA!$A$21:$H$186,8,0),0) -> 0 | J192: =-IFERROR(VLOOKUP(C192,SIRTAC!$A$16:$H$1405,8,0),0) -> -792 | K192: =-IFERROR(VLOOKUP(C192,Gastos!$A$9:$J$1398,10,0),0) -> -6027.12 | L192: =-IFERROR(VLOOKUP(C192,IDC!$A$20:$H$1596,8,0),0) -> -475.2 | M192: =+D192-I192-J192-K192-L192 -> 79200
A193: 06-12-2025 | B193: Liquidación de dinero | C193: 136206659707 | D193: 34879.94 | E193: 24413731 | F193: COBRO | I193: =-IFERROR(VLOOKUP(C193,SIRCUPA!$A$21:$H$186,8,0),0) -> 0 | J193: =-IFERROR(VLOOKUP(C193,SIRTAC!$A$16:$H$1405,8,0),0) -> -358 | K193: =-IFERROR(VLOOKUP(C193,Gastos!$A$9:$J$1398,10,0),0) -> -347.26 | L193: =-IFERROR(VLOOKUP(C193,IDC!$A$20:$H$1596,8,0),0) -> -214.8 | M193: =+D193-I193-J193-K193-L193 -> 35800
A194: 06-12-2025 | B194: Liquidación de dinero | C194: 136830857486 | D194: 9548.14 | E194: 24423279 | F194: COBRO | I194: =-IFERROR(VLOOKUP(C194,SIRCUPA!$A$21:$H$186,8,0),0) -> 0 | J194: =-IFERROR(VLOOKUP(C194,SIRTAC!$A$16:$H$1405,8,0),0) -> -98 | K194: =-IFERROR(VLOOKUP(C194,Gastos!$A$9:$J$1398,10,0),0) -> -95.06 | L194: =-IFERROR(VLOOKUP(C194,IDC!$A$20:$H$1596,8,0),0) -> -58.8 | M194: =+D194-I194-J194-K194-L194 -> 9800
A195: 06-12-2025 | B195: Liquidación de dinero | C195: 136831622152 | D195: 31536.96 | E195: 24454816 | F195: COBRO | I195: =-IFERROR(VLOOKUP(C195,SIRCUPA!$A$21:$H$186,8,0),0) -> 0 | J195: =-IFERROR(VLOOKUP(C195,SIRTAC!$A$16:$H$1405,8,0),0) -> -336 | K195: =-IFERROR(VLOOKUP(C195,Gastos!$A$9:$J$1398,10,0),0) -> -1525.44 | L195: =-IFERROR(VLOOKUP(C195,IDC!$A$20:$H$1596,8,0),0) -> -201.6 | M195: =+D195-I195-J195-K195-L195 -> 33600
A196: 06-12-2025 | B196: Liquidación de dinero | C196: 136832417604 | D196: 9258.06 | E196: 24464074 | F196: COBRO | I196: =-IFERROR(VLOOKUP(C196,SIRCUPA!$A$21:$H$186,8,0),0) -> 0 | J196: =-IFERROR(VLOOKUP(C196,SIRTAC!$A$16:$H$1405,8,0),0) -> -98 | K196: =-IFERROR(VLOOKUP(C196,Gastos!$A$9:$J$1398,10,0),0) -> -385.14 | L196: =-IFERROR(VLOOKUP(C196,IDC!$A$20:$H$1596,8,0),0) -> -58.8 | M196: =+D196-I196-J196-K196-L196 -> 9800
... A352: 08-12-2025 | B352: Liquidación de dinero | C352: 136959788742 | D352: 9986.9 | E352: 28672072 | F352: COBRO | I352: =-IFERROR(VLOOKUP(C352,SIRCUPA!$A$21:$H$186,8,0),0) -> 0 | J352: =-IFERROR(VLOOKUP(C352,SIRTAC!$A$16:$H$1405,8,0),0) -> -110 | K352: =-IFERROR(VLOOKUP(C352,Gastos!$A$9:$J$1398,10,0),0) -> -837.1 | L352: =-IFERROR(VLOOKUP(C352,IDC!$A$20:$H$1596,8,0),0) -> -66 | M352: =+D352-I352-J352-K352-L352 -> 11000
A353: 10-12-2025 | B353: Pago de servicio ARCA | C353: 136635567927 | D353: -2368604.7 | E353: 26303468 | F353: ARCA | G353: =+D353/1.006 -> -2354477.8 | I353: =-IFERROR(VLOOKUP(C353,SIRCUPA!$A$21:$H$186,8,0),0) -> 0 | J353: =-IFERROR(VLOOKUP(C353,SIRTAC!$A$16:$H$1405,8,0),0) -> 0 | K353: =-IFERROR(VLOOKUP(C353,Gastos!$A$9:$J$1398,10,0),0) -> 0 | L353: =+D353-G353 -> -14126.867 | M353: =+D353-I353-J353-K353-L353 -> -2354477.8
A354: 10-12-2025 | B354: Transferencia enviada Cerveza Tractor Sr | C354: 136642965749 | D354: -1000000 | E354: 22800468 | F354: RETIRO / PROV | G354: =+D354 -> -1000000 | I354: =-IFERROR(VLOOKUP(C354,SIRCUPA!$A$21:$H$186,8,0),0) -> 0 | J354: =-IFERROR(VLOOKUP(C354,SIRTAC!$A$16:$H$1405,8,0),0) -> 0 | K354: =-IFERROR(VLOOKUP(C354,Gastos!$A$9:$J$1398,10,0),0) -> 0 | L354: =-IFERROR(VLOOKUP(C354,IDC!$A$20:$H$1596,8,0),0) -> 0 | M354: =+D354 -> -1000000
A355: 10-12-2025 | B355: Transferencia enviada Cerveza Tractor Sr | C355: 136642967981 | D355: -1000000 | E355: 19800468 | F355: RETIRO / PROV | G355: =+D355 -> -1000000 | I355: =-IFERROR(VLOOKUP(C355,SIRCUPA!$A$21:$H$186,8,0),0) -> 0 | J355: =-IFERROR(VLOOKUP(C355,SIRTAC!$A$16:$H$1405,8,0),0) -> 0 | K355: =-IFERROR(VLOOKUP(C355,Gastos!$A$9:$J$1398,10,0),0) -> 0 | L355: =-IFERROR(VLOOKUP(C355,IDC!$A$20:$H$1596,8,0),0) -> 0 | M355: =+D355 -> -1000000
A356: 10-12-2025 | B356: Transferencia enviada Cerveza Tractor Sr | C356: 136643127123 | D356: -1000000 | E356: 24800468 | F356: RETIRO / PROV | G356: =+D356 -> -1000000 | I356: =-IFERROR(VLOOKUP(C356,SIRCUPA!$A$21:$H$186,8,0),0) -> 0 | J356: =-IFERROR(VLOOKUP(C356,SIRTAC!$A$16:$H$1405,8,0),0) -> 0 | K356: =-IFERROR(VLOOKUP(C356,Gastos!$A$9:$J$1398,10,0),0) -> 0 | L356: =-IFERROR(VLOOKUP(C356,IDC!$A$20:$H$1596,8,0),0) -> 0 | M356: =+D356 -> -1000000
A357: 10-12-2025 | B357: Transferencia enviada Cerveza Tractor Sr | C357: 136643473817 | D357: -1000000 | E357: 17800468 | F357: RETIRO / PROV | G357: =+D357 -> -1000000 | I357: =-IFERROR(VLOOKUP(C357,SIRCUPA!$A$21:$H$186,8,0),0) -> 0 | J357: =-IFERROR(VLOOKUP(C357,SIRTAC!$A$16:$H$1405,8,0),0) -> 0 | K357: =-IFERROR(VLOOKUP(C357,Gastos!$A$9:$J$1398,10,0),0) -> 0 | L357: =-IFERROR(VLOOKUP(C357,IDC!$A$20:$H$1596,8,0),0) -> 0 | M357: =+D357 -> -1000000
A358: 10-12-2025 | B358: Transferencia enviada Cerveza Tractor Sr | C358: 136643589881 | D358: -1000000 | E358: 16800468 | F358: RETIRO / PROV | G358: =+D358 -> -1000000 | I358: =-IFERROR(VLOOKUP(C358,SIRCUPA!$A$21:$H$186,8,0),0) -> 0 | J358: =-IFERROR(VLOOKUP(C358,SIRTAC!$A$16:$H$1405,8,0),0) -> 0 | K358: =-IFERROR(VLOOKUP(C358,Gastos!$A$9:$J$1398,10,0),0) -> 0 | L358: =-IFERROR(VLOOKUP(C358,IDC!$A$20:$H$1596,8,0),0) -> 0 | M358: =+D358 -> -1000000
A359: 10-12-2025 | B359: Transferencia enviada Cerveza Tractor Sr | C359: 136643619197 | D359: -1000000 | E359: 20800468 | F359: RETIRO / PROV | G359: =+D359 -> -1000000 | I359: =-IFERROR(VLOOKUP(C359,SIRCUPA!$A$21:$H$186,8,0),0) -> 0 | J359: =-IFERROR(VLOOKUP(C359,SIRTAC!$A$16:$H$1405,8,0),0) -> 0 | K359: =-IFERROR(VLOOKUP(C359,Gastos!$A$9:$J$1398,10,0),0) -> 0 | L359: =-IFERROR(VLOOKUP(C359,IDC!$A$20:$H$1596,8,0),0) -> 0 | M359: =+D359 -> -1000000
A360: 12-12-2025 | B360: Liquidación de dinero | C360: 137649717546 | D360: 9353.28 | E360: 12951149 | F360: COBRO | I360: =-IFERROR(VLOOKUP(C360,SIRCUPA!$A$21:$H$186,8,0),0) -> 0 | J360: =-IFERROR(VLOOKUP(C360,SIRTAC!$A$16:$H$1405,8,0),0) -> -96 | K360: =-IFERROR(VLOOKUP(C360,Gastos!$A$9:$J$1398,10,0),0) -> -93.12 | L360: =-IFERROR(VLOOKUP(C360,IDC!$A$20:$H$1596,8,0),0) -> -57.6 | M360: =+D360-I360-J360-K360-L360 -> 9600
A361: 12-12-2025 | B361: Liquidación de dinero | C361: 137035785219 | D361: 25721.52 | E361: 12976871 | F361: COBRO | I361: =-IFERROR(VLOOKUP(C361,SIRCUPA!$A$21:$H$186,8,0),0) -> 0 | J361: =-IFERROR(VLOOKUP(C361,SIRTAC!$A$16:$H$1405,8,0),0) -> -264 | K361: =-IFERROR(VLOOKUP(C361,Gastos!$A$9:$J$1398,10,0),0) -> -256.08 | L361: =-IFERROR(VLOOKUP(C361,IDC!$A$20:$H$1596,8,0),0) -> -158.4 | M361: =+D361-I361-J361-K361-L361 -> 26400
A362: 12-12-2025 | B362: Liquidación de dinero | C362: 137670538274 | D362: 3778.8 | E362: 12980650 | F362: COBRO | I362: =-IFERROR(VLOOKUP(C362,SIRCUPA!$A$21:$H$186,8,0),0) -> 0 | J362: =-IFERROR(VLOOKUP(C362,SIRTAC!$A$16:$H$1405,8,0),0) -> -40 | K362: =-IFERROR(VLOOKUP(C362,Gastos!$A$9:$J$1398,10,0),0) -> -157.2 | L362: =-IFERROR(VLOOKUP(C362,IDC!$A$20:$H$1596,8,0),0) -> -24 | M362: =+D362-I362-J362-K362-L362 -> 4000
A363: 12-12-2025 | B363: Liquidación de dinero | C363: 137671009436 | D363: 18339.58 | E363: 12998989 | F363: COBRO | I363: =-IFERROR(VLOOKUP(C363,SIRCUPA!$A$21:$H$186,8,0),0) -> 0 | J363: =-IFERROR(VLOOKUP(C363,SIRTAC!$A$16:$H$1405,8,0),0) -> -202 | K363: =-IFERROR(VLOOKUP(C363,Gastos!$A$9:$J$1398,10,0),0) -> -1537.22 | L363: =-IFERROR(VLOOKUP(C363,IDC!$A$20:$H$1596,8,0),0) -> -121.2 | M363: =+D363-I363-J363-K363-L363 -> 20200
A364: 12-12-2025 | B364: Liquidación de dinero | C364: 137040182521 | D364: 9548.14 | E364: 13008537 | F364: COBRO | I364: =-IFERROR(VLOOKUP(C364,SIRCUPA!$A$21:$H$186,8,0),0) -> 0 | J364: =-IFERROR(VLOOKUP(C364,SIRTAC!$A$16:$H$1405,8,0),0) -> -98 | K364: =-IFERROR(VLOOKUP(C364,Gastos!$A$9:$J$1398,10,0),0) -> -95.06 | L364: =-IFERROR(VLOOKUP(C364,IDC!$A$20:$H$1596,8,0),0) -> -58.8 | M364: =+D364-I364-J364-K364-L364 -> 9800
A365: 12-12-2025 | B365: Liquidación de dinero | C365: 137673449798 | D365: 9069.12 | E365: 13017607 | F365: COBRO | I365: =-IFERROR(VLOOKUP(C365,SIRCUPA!$A$21:$H$186,8,0),0) -> 0 | J365: =-IFERROR(VLOOKUP(C365,SIRTAC!$A$16:$H$1405,8,0),0) -> -96 | K365: =-IFERROR(VLOOKUP(C365,Gastos!$A$9:$J$1398,10,0),0) -> -377.28 | L365: =-IFERROR(VLOOKUP(C365,IDC!$A$20:$H$1596,8,0),0) -> -57.6 | M365: =+D365-I365-J365-K365-L365 -> 9600
A366: 12-12-2025 | B366: Liquidación de dinero | C366: 137042830597 | D366: 5265.82 | E366: 13022872 | F366: COBRO | I366: =-IFERROR(VLOOKUP(C366,SIRCUPA!$A$21:$H$186,8,0),0) -> 0 | J366: =-IFERROR(VLOOKUP(C366,SIRTAC!$A$16:$H$1405,8,0),0) -> -58 | K366: =-IFERROR(VLOOKUP(C366,Gastos!$A$9:$J$1398,10,0),0) -> -441.38 | L366: =-IFERROR(VLOOKUP(C366,IDC!$A$20:$H$1596,8,0),0) -> -34.8 | M366: =+D366-I366-J366-K366-L366 -> 5800
A367: 12-12-2025 | B367: Liquidación de dinero | C367: 137676231468 | D367: 4676.64 | E367: 13027549 | F367: COBRO | I367: =-IFERROR(VLOOKUP(C367,SIRCUPA!$A$21:$H$186,8,0),0) -> 0 | J367: =-IFERROR(VLOOKUP(C367,SIRTAC!$A$16:$H$1405,8,0),0) -> -48 | K367: =-IFERROR(VLOOKUP(C367,Gastos!$A$9:$J$1398,10,0),0) -> -46.56 | L367: =-IFERROR(VLOOKUP(C367,IDC!$A$20:$H$1596,8,0),0) -> -28.8 | M367: =+D367-I367-J367-K367-L367 -> 4800
A368: 12-12-2025 | B368: Liquidación de dinero | C368: 137677529088 | D368: 8897.42 | E368: 13036446 | F368: COBRO | I368: =-IFERROR(VLOOKUP(C368,SIRCUPA!$A$21:$H$186,8,0),0) -> 0 | J368: =-IFERROR(VLOOKUP(C368,SIRTAC!$A$16:$H$1405,8,0),0) -> -98 | K368: =-IFERROR(VLOOKUP(C368,Gastos!$A$9:$J$1398,10,0),0) -> -745.78 | L368: =-IFERROR(VLOOKUP(C368,IDC!$A$20:$H$1596,8,0),0) -> -58.8 | M368: =+D368-I368-J368-K368-L368 -> 9800
A369: 12-12-2025 | B369: Liquidación de dinero | C369: 137044469955 | D369: 85887.34 | E369: 13122334 | F369: COBRO | I369: =-IFERROR(VLOOKUP(C369,SIRCUPA!$A$21:$H$186,8,0),0) -> 0 | J369: =-IFERROR(VLOOKUP(C369,SIRTAC!$A$16:$H$1405,8,0),0) -> -946 | K369: =-IFERROR(VLOOKUP(C369,Gastos!$A$9:$J$1398,10,0),0) -> -7199.06 | L369: =-IFERROR(VLOOKUP(C369,IDC!$A$20:$H$1596,8,0),0) -> -567.6 | M369: =+D369-I369-J369-K369-L369 -> 94600
A370: 12-12-2025 | B370: Liquidación de dinero | C370: 137044959869 | D370: 62160.34 | E370: 13184494 | F370: COBRO | I370: =-IFERROR(VLOOKUP(C370,SIRCUPA!$A$21:$H$186,8,0),0) -> 0 | J370: =-IFERROR(VLOOKUP(C370,SIRTAC!$A$16:$H$1405,8,0),0) -> -638 | K370: =-IFERROR(VLOOKUP(C370,Gastos!$A$9:$J$1398,10,0),0) -> -618.86 | L370: =-IFERROR(VLOOKUP(C370,IDC!$A$20:$H$1596,8,0),0) -> -382.8 | M370: =+D370-I370-J370-K370-L370 -> 63800
A371: 12-12-2025 | B371: Liquidación de dinero | C371: 137678741226 | D371: 7557.6 | E371: 13192052 | F371: COBRO | I371: =-IFERROR(VLOOKUP(C371,SIRCUPA!$A$21:$H$186,8,0),0) -> 0 | J371: =-IFERROR(VLOOKUP(C371,SIRTAC!$A$16:$H$1405,8,0),0) -> -80 | K371: =-IFERROR(VLOOKUP(C371,Gastos!$A$9:$J$1398,10,0),0) -> -314.4 | L371: =-IFERROR(VLOOKUP(C371,IDC!$A$20:$H$1596,8,0),0) -> -48 | M371: =+D371-I371-J371-K371-L371 -> 8000
A372: 12-12-2025 | B372: Liquidación de dinero | C372: 137680175054 | D372: 4357.92 | E372: 13196410 | F372: COBRO | I372: =-IFERROR(VLOOKUP(C372,SIRCUPA!$A$21:$H$186,8,0),0) -> 0 | J372: =-IFERROR(VLOOKUP(C372,SIRTAC!$A$16:$H$1405,8,0),0) -> -48 | K372: =-IFERROR(VLOOKUP(C372,Gastos!$A$9:$J$1398,10,0),0) -> -365.28 | L372: =-IFERROR(VLOOKUP(C372,IDC!$A$20:$H$1596,8,0),0) -> -28.8 | M372: =+D372-I372-J372-K372-L372 -> 4800
A373: 10-12-2025 | B373: Transferencia recibida Rodrigo Ezequiel Anaratone | C373: 137371068462 | D373: 30739.62 | E373: 9631207.2 | F373: COBRO | I373: =-IFERROR(VLOOKUP(C373,SIRCUPA!$A$21:$H$186,8,0),0) -> -470.99 | J373: =-IFERROR(VLOOKUP(C373,SIRTAC!$A$16:$H$1405,8,0),0) -> 0 | K373: =-IFERROR(VLOOKUP(C373,Gastos!$A$9:$J$1398,10,0),0) -> 0 | L373: -188.396 | M373: =+D373-I373-J373-K373-L373 -> 31399.006 | Q373: =+I373/0.015 -> -31399.333 | R373: =+Q373*0.006 -> -188.396
A374: 10-12-2025 | B374: Liquidación de dinero | C374: 136740668549 | D374: 4092.06 | E374: 9635299.3 | F374: COBRO | I374: =-IFERROR(VLOOKUP(C374,SIRCUPA!$A$21:$H$186,8,0),0) -> 0 | J374: =-IFERROR(VLOOKUP(C374,SIRTAC!$A$16:$H$1405,8,0),0) -> -42 | K374: =-IFERROR(VLOOKUP(C374,Gastos!$A$9:$J$1398,10,0),0) -> -40.74 | L374: =-IFERROR(VLOOKUP(C374,IDC!$A$20:$H$1596,8,0),0) -> -25.2 | M374: =+D374-I374-J374-K374-L374 -> 4200
A375: 10-12-2025 | B375: Liquidación de dinero | C375: 137373870662 | D375: 29380.17 | E375: 9664679.4 | F375: COBRO | I375: =-IFERROR(VLOOKUP(C375,SIRCUPA!$A$21:$H$186,8,0),0) -> 0 | J375: =-IFERROR(VLOOKUP(C375,SIRTAC!$A$16:$H$1405,8,0),0) -> -311 | K375: =-IFERROR(VLOOKUP(C375,Gastos!$A$9:$J$1398,10,0),0) -> -1222.23 | L375: =-IFERROR(VLOOKUP(C375,IDC!$A$20:$H$1596,8,0),0) -> -186.6 | M375: =+D375-I375-J375-K375-L375 -> 31100
A376: 10-12-2025 | B376: Liquidación de dinero | C376: 136743127343 | D376: 9450.71 | E376: 9674130.2 | F376: COBRO | I376: =-IFERROR(VLOOKUP(C376,SIRCUPA!$A$21:$H$186,8,0),0) -> 0 | J376: =-IFERROR(VLOOKUP(C376,SIRTAC!$A$16:$H$1405,8,0),0) -> -97 | K376: =-IFERROR(VLOOKUP(C376,Gastos!$A$9:$J$1398,10,0),0) -> -94.09 | L376: =-IFERROR(VLOOKUP(C376,IDC!$A$20:$H$1596,8,0),0) -> -58.2 | M376: =+D376-I376-J376-K376-L376 -> 9700
A377: 10-12-2025 | B377: Liquidación de dinero | C377: 136743612291 | D377: 37168.56 | E377: 9711298.7 | F377: COBRO | I377: =-IFERROR(VLOOKUP(C377,SIRCUPA!$A$21:$H$186,8,0),0) -> 0 | J377: =-IFERROR(VLOOKUP(C377,SIRTAC!$A$16:$H$1405,8,0),0) -> -396 | K377: =-IFERROR(VLOOKUP(C377,Gastos!$A$9:$J$1398,10,0),0) -> -1797.84 | L377: =-IFERROR(VLOOKUP(C377,IDC!$A$20:$H$1596,8,0),0) -> -237.6 | M377: =+D377-I377-J377-K377-L377 -> 39600
A378: 10-12-2025 | B378: Transferencia recibida REBORD FACUNDO | C378: 137375738068 | D378: 37985.2 | E378: 9749283.9 | F378: COBRO | I378: =-IFERROR(VLOOKUP(C378,SIRCUPA!$A$21:$H$186,8,0),0) -> -582 | J378: =-IFERROR(VLOOKUP(C378,SIRTAC!$A$16:$H$1405,8,0),0) -> 0 | K378: =-IFERROR(VLOOKUP(C378,Gastos!$A$9:$J$1398,10,0),0) -> 0 | L378: =-IFERROR(VLOOKUP(C378,IDC!$A$20:$H$1596,8,0),0) -> -232.8 | M378: =+D378-I378-J378-K378-L378 -> 38800
A379: 10-12-2025 | B379: Transferencia recibida Martin Totorica | C379: 137380209516 | D379: 208331.2 | E379: 9957615.1 | F379: COBRO | I379: =-IFERROR(VLOOKUP(C379,SIRCUPA!$A$21:$H$186,8,0),0) -> -3192 | J379: =-IFERROR(VLOOKUP(C379,SIRTAC!$A$16:$H$1405,8,0),0) -> 0 | K379: =-IFERROR(VLOOKUP(C379,Gastos!$A$9:$J$1398,10,0),0) -> 0 | L379: -1276.8 | M379: =+D379-I379-J379-K379-L379 -> 212800 | Q379: =+I379/0.015 -> -212800 | R379: =+Q379*0.006 -> -1276.8
A380: 10-12-2025 | B380: Liquidación de dinero | C380: 136750250721 | D380: 25233.4 | E380: 9982848.5 | F380: COBRO | I380: =-IFERROR(VLOOKUP(C380,SIRCUPA!$A$21:$H$186,8,0),0) -> 0 | J380: =-IFERROR(VLOOKUP(C380,SIRTAC!$A$16:$H$1405,8,0),0) -> -258.99 | K380: =-IFERROR(VLOOKUP(C380,Gastos!$A$9:$J$1398,10,0),0) -> -251.22 | L380: =-IFERROR(VLOOKUP(C380,IDC!$A$20:$H$1596,8,0),0) -> -155.39 | M380: =+D380-I380-J380-K380-L380 -> 25899
A381: 10-12-2025 | B381: Transferencia recibida Sergio Daniel Gareca | C381: 137381180222 | D381: 1266.83 | E381: 9984115.3 | F381: COBRO | I381: =-IFERROR(VLOOKUP(C381,SIRCUPA!$A$21:$H$186,8,0),0) -> -19.41 | J381: =-IFERROR(VLOOKUP(C381,SIRTAC!$A$16:$H$1405,8,0),0) -> 0 | K381: =-IFERROR(VLOOKUP(C381,Gastos!$A$9:$J$1398,10,0),0) -> 0 | L381: =-IFERROR(VLOOKUP(C381,IDC!$A$20:$H$1596,8,0),0) -> -7.76 | M381: =+D381-I381-J381-K381-L381 -> 1294
A382: 10-12-2025 | B382: Liquidación de dinero | C382: 137381613934 | D382: 40334.07 | E382: 10024449 | F382: COBRO | I382: =-IFERROR(VLOOKUP(C382,SIRCUPA!$A$21:$H$186,8,0),0) -> 0 | J382: =-IFERROR(VLOOKUP(C382,SIRTAC!$A$16:$H$1405,8,0),0) -> -413.98 | K382: =-IFERROR(VLOOKUP(C382,Gastos!$A$9:$J$1398,10,0),0) -> -401.56 | L382: =-IFERROR(VLOOKUP(C382,IDC!$A$20:$H$1596,8,0),0) -> -248.39 | M382: =+D382-I382-J382-K382-L382 -> 41398
A383: 10-12-2025 | B383: Liquidación de dinero | C383: 136751051819 | D383: 119574.83 | E383: 10144024 | F383: COBRO | I383: =-IFERROR(VLOOKUP(C383,SIRCUPA!$A$21:$H$186,8,0),0) -> 0 | J383: =-IFERROR(VLOOKUP(C383,SIRTAC!$A$16:$H$1405,8,0),0) -> -1273.97 | K383: =-IFERROR(VLOOKUP(C383,Gastos!$A$9:$J$1398,10,0),0) -> -5783.82 | L383: =-IFERROR(VLOOKUP(C383,IDC!$A$20:$H$1596,8,0),0) -> -764.38 | M383: =+D383-I383-J383-K383-L383 -> 127397
A384: 10-12-2025 | B384: Liquidación de dinero | C384: 136751554233 | D384: 55535.1 | E384: 10199559 | F384: COBRO | I384: =-IFERROR(VLOOKUP(C384,SIRCUPA!$A$21:$H$186,8,0),0) -> 0 | J384: =-IFERROR(VLOOKUP(C384,SIRTAC!$A$16:$H$1405,8,0),0) -> -570 | K384: =-IFERROR(VLOOKUP(C384,Gastos!$A$9:$J$1398,10,0),0) -> -552.9 | L384: =-IFERROR(VLOOKUP(C384,IDC!$A$20:$H$1596,8,0),0) -> -342 | M384: =+D384-I384-J384-K384-L384 -> 57000
A385: 10-12-2025 | B385: Liquidación de dinero | C385: 137382793626 | D385: 58287.99 | E385: 10257847 | F385: COBRO | I385: =-IFERROR(VLOOKUP(C385,SIRCUPA!$A$21:$H$186,8,0),0) -> 0 | J385: =-IFERROR(VLOOKUP(C385,SIRTAC!$A$16:$H$1405,8,0),0) -> -617 | K385: =-IFERROR(VLOOKUP(C385,Gastos!$A$9:$J$1398,10,0),0) -> -2424.81 | L385: =-IFERROR(VLOOKUP(C385,IDC!$A$20:$H$1596,8,0),0) -> -370.2 | M385: =+D385-I385-J385-K385-L385 -> 61700
A386: 10-12-2025 | B386: Liquidación de dinero | C386: 136752846325 | D386: 49970.85 | E386: 10307818 | F386: COBRO | I386: =-IFERROR(VLOOKUP(C386,SIRCUPA!$A$21:$H$186,8,0),0) -> 0 | J386: =-IFERROR(VLOOKUP(C386,SIRTAC!$A$16:$H$1405,8,0),0) -> -528.96 | K386: =-IFERROR(VLOOKUP(C386,Gastos!$A$9:$J$1398,10,0),0) -> -2078.81 | L386: =-IFERROR(VLOOKUP(C386,IDC!$A$20:$H$1596,8,0),0) -> -317.38 | M386: =+D386-I386-J386-K386-L386 -> 52896
A387: 10-12-2025 | B387: Liquidación de dinero | C387: 136754028045 | D387: 37597.17 | E387: 10345415 | F387: COBRO | I387: =-IFERROR(VLOOKUP(C387,SIRCUPA!$A$21:$H$186,8,0),0) -> 0 | J387: =-IFERROR(VLOOKUP(C387,SIRTAC!$A$16:$H$1405,8,0),0) -> -397.98 | K387: =-IFERROR(VLOOKUP(C387,Gastos!$A$9:$J$1398,10,0),0) -> -1564.06 | L387: =-IFERROR(VLOOKUP(C387,IDC!$A$20:$H$1596,8,0),0) -> -238.79 | M387: =+D387-I387-J387-K387-L387 -> 39798
A388: 10-12-2025 | B388: Liquidación de dinero | C388: 136754376295 | D388: 9069.12 | E388: 10354484 | F388: COBRO | I388: =-IFERROR(VLOOKUP(C388,SIRCUPA!$A$21:$H$186,8,0),0) -> 0 | J388: =-IFERROR(VLOOKUP(C388,SIRTAC!$A$16:$H$1405,8,0),0) -> -96 | K388: =-IFERROR(VLOOKUP(C388,Gastos!$A$9:$J$1398,10,0),0) -> -377.28 | L388: =-IFERROR(VLOOKUP(C388,IDC!$A$20:$H$1596,8,0),0) -> -57.6 | M388: =+D388-I388-J388-K388-L388 -> 9600
A389: 10-12-2025 | B389: Liquidación de dinero | C389: 136754357781 | D389: 36049.1 | E389: 10390534 | F389: COBRO | I389: =-IFERROR(VLOOKUP(C389,SIRCUPA!$A$21:$H$186,8,0),0) -> 0 | J389: =-IFERROR(VLOOKUP(C389,SIRTAC!$A$16:$H$1405,8,0),0) -> -370 | K389: =-IFERROR(VLOOKUP(C389,Gastos!$A$9:$J$1398,10,0),0) -> -358.9 | L389: =-IFERROR(VLOOKUP(C389,IDC!$A$20:$H$1596,8,0),0) -> -222 | M389: =+D389-I389-J389-K389-L389 -> 37000
A390: 10-12-2025 | B390: Liquidación de dinero | C390: 136756050703 | D390: 39556.58 | E390: 10430090 | F390: COBRO | I390: =-IFERROR(VLOOKUP(C390,SIRCUPA!$A$21:$H$186,8,0),0) -> 0 | J390: =-IFERROR(VLOOKUP(C390,SIRTAC!$A$16:$H$1405,8,0),0) -> -406 | K390: =-IFERROR(VLOOKUP(C390,Gastos!$A$9:$J$1398,10,0),0) -> -393.82 | L390: =-IFERROR(VLOOKUP(C390,IDC!$A$20:$H$1596,8,0),0) -> -243.6 | M390: =+D390-I390-J390-K390-L390 -> 40600
A391: 10-12-2025 | B391: Liquidación de dinero | C391: 137387028658 | D391: 52027.62 | E391: 10482118 | F391: COBRO | I391: =-IFERROR(VLOOKUP(C391,SIRCUPA!$A$21:$H$186,8,0),0) -> 0 | J391: =-IFERROR(VLOOKUP(C391,SIRTAC!$A$16:$H$1405,8,0),0) -> -534 | K391: =-IFERROR(VLOOKUP(C391,Gastos!$A$9:$J$1398,10,0),0) -> -517.98 | L391: =-IFERROR(VLOOKUP(C391,IDC!$A$20:$H$1596,8,0),0) -> -320.4 | M391: =+D391-I391-J391-K391-L391 -> 53400
A392: 11-12-2025 | B392: Transferencia recibida Lucia Paola Sachinelli | C392: 137387927580 | D392: 26922.5 | E392: 10509040 | F392: COBRO | I392: =-IFERROR(VLOOKUP(C392,SIRCUPA!$A$21:$H$186,8,0),0) -> -412.5 | J392: =-IFERROR(VLOOKUP(C392,SIRTAC!$A$16:$H$1405,8,0),0) -> 0 | K392: =-IFERROR(VLOOKUP(C392,Gastos!$A$9:$J$1398,10,0),0) -> 0 | L392: -165 | M392: =+D392-I392-J392-K392-L392 -> 27500 | Q392: =+I392/0.015 -> -27500 | R392: =+Q392*0.006 -> -165
A393: 11-12-2025 | B393: Liquidación de dinero | C393: 137388651946 | D393: 22257.1 | E393: 10531297 | F393: COBRO | I393: =-IFERROR(VLOOKUP(C393,SIRCUPA!$A$21:$H$186,8,0),0) -> 0 | J393: =-IFERROR(VLOOKUP(C393,SIRTAC!$A$16:$H$1405,8,0),0) -> -230 | K393: =-IFERROR(VLOOKUP(C393,Gastos!$A$9:$J$1398,10,0),0) -> -374.9 | L393: =-IFERROR(VLOOKUP(C393,IDC!$A$20:$H$1596,8,0),0) -> -138 | M393: =+D393-I393-J393-K393-L393 -> 23000
A394: 11-12-2025 | B394: Liquidación de dinero | C394: 136758090307 | D394: 8184.12 | E394: 10539481 | F394: COBRO | I394: =-IFERROR(VLOOKUP(C394,SIRCUPA!$A$21:$H$186,8,0),0) -> 0 | J394: =-IFERROR(VLOOKUP(C394,SIRTAC!$A$16:$H$1405,8,0),0) -> -84 | K394: =-IFERROR(VLOOKUP(C394,Gastos!$A$9:$J$1398,10,0),0) -> -81.48 | L394: =-IFERROR(VLOOKUP(C394,IDC!$A$20:$H$1596,8,0),0) -> -50.4 | M394: =+D394-I394-J394-K394-L394 -> 8400
...

Sheet TR
A3: Suma de MOV TOTAL | B3: Etiquetas de columna
A4: Etiquetas de fila | B4: ARCA | C4: COBRO | D4: IDC | E4: PAGO PROVEEDOR | F4: RETIRO / PROV | G4: Total general
A5: Compra de Epitrónica Pack 100 Rollos Papel Térmico 80x50 48grs Ticket, Comandera, ... | E5: -118000 | G5: -118000 | H5: C | I5: ASIENTO 105
A6: Compra de Kit De Internet Via Satélite Starlink Mini Mercado Libre | E6: -143789.59 | G6: -143789.59 | H6: C | I6: ASIENTO 103
A7: Compra Mercado Libre | E7: -88974 | G7: -88974 | H7: C | I7: ASIENTO 104
A8: Impuesto por extracción | D8: -20029.75 | G8: -20029.75
A9: Liquidación de dinero | C9: 38030271 | G9: 38030271
A10: Liquidación de dinero cancelada Venta cancelada | C10: -84314.99 | G10: -84314.99 | I10: ASIENTO 100 B | J10: COBRO DS X VENTA | K10: =SUM(G9:G10,G23:G171) -> 38717734 | L10: modificado
A11: Pago ADAPTO FUNGTASTIC S.R.L. | E11: -86285.7 | G11: -86285.7 | H11: C | I11: ASIENTO 101 B | J11: PAGO PROVEEDORES | K11: =SUM(G11,G13,G17,G19,G21:G22) -> -3634778 | L11: modificado
A12: Pago de servicio ARCA | B12: -8991759.4 | G12: -8991759.4 | H12: C | J12: VER SI HAY COMPRA
A13: Pago de servicio Federación Patronal | E13: -168233.36 | G13: -168233.36 | H13: C | J13: IMPUESTOS | K13: =SUM(G12,G20) -> -9505829.2
A14: Pago Mercado Libre S R L - MLA MP | E14: -30579.881 | G14: -30579.881 | J14: IDYC - GASTO
A15: Pago MERCADOPAGO POINT AR | E15: -44999 | G15: -44999 | H15: C | J15: CERVEZA TRACTOR | K15: =+GETPIVOTDATA("MOV TOTAL",$A$3,"TRANSACTION_TYPE","Transferencia enviada Cerveza Tractor Sr") -> -32400000
A16: Pago RIO URUGUAY SEGUROS | E16: -66429 | G16: -66429 | H16: C | I16: ASIENTO 102 B | J16: CAJA | K16: =SUM(GETPIVOTDATA("MOV TOTAL",$A$3,"TRANSACTION_TYPE","Pago RIO URUGUAY SEGUROS")) -> -66429 | L16: modificado
A17: Transferencia enviada BASSO REPRESENT SRL | E17: -551528.92 | G17: -551528.92 | H17: C
A18: Transferencia enviada Cerveza Tractor Sr | F18: -32400000 | G18: -32400000 | H18: C
A19: Transferencia enviada EMBOTELLADORA DEL ATLANTICO S.A. | E19: -2100000 | G19: -2100000 | H19: C
A20: Transferencia enviada Municipalidad De Concepcion Del Uru | E20: -514069.75 | G20: -514069.75 | H20: C
A21: Transferencia enviada Norberto David Dolcet | E21: -556037.69 | G21: -556037.69 | H21: C
A22: Transferencia enviada Sucesion De Satto | E22: -172692.29 | G22: -172692.29 | H22: C
A23: Transferencia recibida Aaron Facundo Alarcon | C23: 2200 | G23: 2200
A24: Transferencia recibida Abigail Ayelen Del Valle | C24: 1010 | G24: 1010
A25: Transferencia recibida Agustin Daniel Bastian Alvarez | C25: 1790 | G25: 1790
A26: Transferencia recibida Ailen Micaela Trabichet | C26: 3620 | G26: 3620
A27: Transferencia recibida Alan Nicolas Opez | C27: 240 | G27: 240
A28: Transferencia recibida Alexis Maximiliano Dominguez | C28: 2415 | G28: 2415
A29: Transferencia recibida Amina Alfonso | C29: 500 | G29: 500
A30: Transferencia recibida Andreina De Los Angeles Canchi | C30: 1315 | G30: 1315
A31: Transferencia recibida Angela Justina Cicchitti | C31: 4245 | G31: 4245
A32: Transferencia recibida ANGELINA/BELEN HARDT | C32: 40000 | G32: 40000
A33: Transferencia recibida Ariel Damian Fiorenza | C33: 1340 | G33: 1340
A34: Transferencia recibida Balon 5 Pizza Libre | C34: 2350 | G34: 2350
... A171: Transferencia recibida Yamila Lujan Bel | C171: 3190 | G171: 3190
A172: Total general | B172: -8991759.4 | C172: 38717734 | D172: -20029.75 | E172: -4641619.2 | F172: -32400000 | G172: -7335674.4
G173: =-GETPIVOTDATA("MOV TOTAL",$A$3,"TRANSACTION_TYPE","Pago MERCADOPAGO POINT AR") -> 44999
G174: =+GETPIVOTDATA("MOV TOTAL",$A$3)+G173 -> -7290675.4
G175: =+sheet0!M1583 -> -45268.99
G176: =+G174+G175 -> -7335944.3

Sheet Hoja1
A3: Etiquetas de fila | B3: Suma de TRANSACTION_NET_AMOUNT
A4: Compra de Epitrónica Pack 100 Rollos Papel Térmico 80x50 48grs Ticket, Comandera, ... | B4: -118708 | C4: Contab. | D4: FIRST LABEL S.R.L. x $143789,49 | E4: ASIENTO 100 B | F4: COBRO DS X VENTA | G4: =SUM(B8:B9,B22:B170) -> 37149348
A5: Compra de Kit De Internet Via Satélite Starlink Mini Mercado Libre | B5: -144652.33 | C5: Contab. | D5: GALANSINO JORGE ALBERTO x $ 88974 | E5: ASIENTO 101 B | F5: PAGO PROVEEDORES | G5: =SUM(B10,B12,B14,B16,B18,B20,B21) -> -3684910.3
A6: Compra Mercado Libre | B6: -89507.84 | C6: Contab. | D6: NOY TOMAS AGUSTIN x $ 118000 | F6: VER SI HAY COMPRA
A7: Impuesto por extracción | B7: -20029.75 | C7: Contab. | D7: Corresponde IDyC ya contabilizados globalmente | E7: ASINTO DE PAGO | F7: VER SI CONCILIA CON IMPUESTOS | G7: =+GETPIVOTDATA("TRANSACTION_NET_AMOUNT",$A$3,"TRANSACTION_TYPE","Pago de servicio ARCA")+GETPIVOTDATA("TRANSACTION_NET_AMOUNT",$A$3,"TRANSACTION_TYPE","Transferencia enviada Municipalidad De Concepcion Del Uru") -> -9559779.7
A8: Liquidación de dinero | B8: 36474194 | C8: Contab. | F8: VER QUE ES
A9: Liquidación de dinero cancelada Venta cancelada | B9: -80416.06 | C9: Contab. | F9: CERVEZA TRACTOR
A10: Pago ADAPTO FUNGTASTIC S.R.L. | B10: -86803.41 | C10: Contab. | E10: ASIENTO 102 B | F10: CAJA | G10: =+GETPIVOTDATA("TRANSACTION_NET_AMOUNT",$A$3,"TRANSACTION_TYPE","Pago RIO URUGUAY SEGUROS") -> -66827.57
A11: Pago de servicio ARCA | B11: -9045710 | C11: Contab.
A12: Pago de servicio Federación Patronal | B12: -169242.76 | C12: Contab.
A13: Pago Mercado Libre S R L - MLA MP | B13: -30763.36 | C13: Contab. | D13: Percepción factura MP + IDyC (contab. Globalmente)
A14: Pago MERCADOPAGO POINT AR | B14: -45268.99 | C14: Contab.
A15: Pago RIO URUGUAY SEGUROS | B15: -66827.57 | C15: Contab.
A16: Transferencia enviada BASSO REPRESENT SRL | B16: -551528.92 | C16: Contab.
A17: Transferencia enviada Cerveza Tractor Sr | B17: -32400000 | C17: Contab. | D17: DEPOSITO ENTRE CUENTAS
A18: Transferencia enviada EMBOTELLADORA DEL ATLANTICO S.A. | B18: -2100000 | C18: Contab.
A19: Transferencia enviada Municipalidad De Concepcion Del Uru | B19: -514069.75 | C19: Contab.
A20: Transferencia enviada Norberto David Dolcet | B20: -559373.92 | C20: Contab.
A21: Transferencia enviada Sucesion De Satto | B21: -172692.29 | C21: Contab.
A22: Transferencia recibida Aaron Facundo Alarcon | B22: 2153.8 | C22: Contab.
A23: Transferencia recibida Abigail Ayelen Del Valle | B23: 988.79 | C23: Contab.
A24: Transferencia recibida Agustin Daniel Bastian Alvarez | B24: 1752.41 | C24: Contab.
A25: Transferencia recibida Ailen Micaela Trabichet | B25: 3543.98 | C25: Contab.
A26: Transferencia recibida Alan Nicolas Opez | B26: 234.96 | C26: Contab.
A27: Transferencia recibida Alexis Maximiliano Dominguez | B27: 2364.28 | C27: Contab.
A28: Transferencia recibida Amina Alfonso | B28: 489.5 | C28: Contab.
A29: Transferencia recibida Andreina De Los Angeles Canchi | B29: 1287.38 | C29: Contab.
... A170: Transferencia recibida Yamila Lujan Bel | B170: 3123.01 | C170: Contab.
A171: Total general | B171: -8965831

Sheet SIRCUPA
A1: Reporte-Retención-SIRCUPA-Diciembre-CC20250609171159-MercadoPago
A3: Usuario: | B3: CC20250609171159
A4: Impuesto: | B4: Retención SIRCUPA
A5: Fecha de descarga: | B5: 18/03/2026
A6: Intervalo de fechas consultadas: | B6: 01/12/2025 a 01/01/2026
A8: Total | B8: Monto
A9: Base imponible | B9: $771.778,00
A10: Tramo 1 - retenido del 01/12 al 10/12 | B10: $6.354,32
A11: Tramo 2 - retenido del 11/12 al 20/12 | B11: $2.442,92
A12: Tramo 3 - retenido del 21/12 al 31/12 | B12: $2.779,68
A13: Importe retenido | B13: $11.576,92
A14: Importe devuelto | B14: $0,00
A16: Podrás utilizar este reporte para conciliar lo que retuvimos.
A17: Podrás buscar el detalle de lo retenido en tu operación en la sección Actividad.
A19: Operación | E19: Impuesto
A20: Número de operación | B20: Fecha de operación | C20: Tipo | D20: Monto de transferencia | E20: Fecha de retención | F20: Alícuota | G20: Base imponible | H20: Importe retenido
A21: 135759329655 | B21: 03/12/2025 | C21: Transferencia | D21: 1199 | E21: 03/12/2025 | F21: 1,50 % | G21: 1199 | H21: 17.99
A22: 136364596558 | B22: 03/12/2025 | C22: Transferencia | D22: 240 | E22: 03/12/2025 | F22: 1,50 % | G22: 240 | H22: 3.6
A23: 135762846725 | B23: 03/12/2025 | C23: Transferencia | D23: 1530 | E23: 04/12/2025 | F23: 1,50 % | G23: 1530 | H23: 22.95
A24: 136374922986 | B24: 03/12/2025 | C24: Transferencia | D24: 2889 | E24: 03/12/2025 | F24: 1,50 % | G24: 2889 | H24: 43.34
A25: 136505473782 | B25: 04/12/2025 | C25: Transferencia | D25: 2820 | E25: 04/12/2025 | F25: 1,50 % | G25: 2820 | H25: 42.3
A26: 135903889629 | B26: 04/12/2025 | C26: Transferencia | D26: 200 | E26: 04/12/2025 | F26: 1,50 % | G26: 200 | H26: 3
A27: 135888975597 | B27: 04/12/2025 | C27: Transferencia | D27: 495 | E27: 04/12/2025 | F27: 1,50 % | G27: 495 | H27: 7.43
A28: 136531346928 | B28: 04/12/2025 | C28: Transferencia | D28: 2350 | E28: 05/12/2025 | F28: 1,50 % | G28: 2350 | H28: 35.25
A29: 135900601361 | B29: 04/12/2025 | C29: Transferencia | D29: 210 | E29: 04/12/2025 | F29: 1,50 % | G29: 210 | H29: 3.15
A30: 135904259461 | B30: 04/12/2025 | C30: Transferencia | D30: 240 | E30: 04/12/2025 | F30: 1,50 % | G30: 240 | H30: 3.6
A31: 136582518616 | B31: 05/12/2025 | C31: Transferencia | D31: 64500 | E31: 05/12/2025 | F31: 1,50 % | G31: 64500 | H31: 967.5
A32: 136051543027 | B32: 05/12/2025 | C32: Transferencia | D32: 210 | E32: 05/12/2025 | F32: 1,50 % | G32: 210 | H32: 3.15
... A186: 139485730265 | B186: 31/12/2025 | C186: Transferencia | D186: 740 | E186: 31/12/2025 | F186: 1,50 % | G186: 740 | H186: 11.1
G188: =SUM(G21:G187) -> 771778 | H188: =SUM(H21:H187) -> 11576.92

Sheet SIRTAC
A1: Reporte-Retención-SIRTAC-inscripto-1ra-quincena-Diciembre-CC20250609171159-MercadoPago
A3: Usuario: | B3: CC20250609171159
A4: Impuesto: | B4: Retención SIRTAC
A5: Fecha de descarga: | B5: 18/03/2026
A6: Intervalo de fechas consultadas: | B6: 01/12/2025 a 16/12/2025
A8: Total | B8: Monto
A9: Base imponible | B9: $17.115.463,00
A10: Importe retenido | B10: $171.154,63
A11: Importe devuelto | B11: $0,15
A12: Podrás conciliar la información con otros reportes de Mercado Libre. | D12: Podrás buscar el detalle de lo retenido en tu operación en la sección Actividad.
A14: Operación | E14: Impuesto
A15: Número de operación | B15: Número de venta - Referencia externa | C15: Fecha de operación | D15: Tipo | E15: Fecha de retención | F15: Alícuota | G15: Base imponible | H15: Importe retenido
A16: 135329078135 | C16: 30/11/2025 | D16: Venta | E16: 01/12/2025 | F16: 1,00 % | G16: 19900 | H16: 199
A17: 135329349869 | B17: Venta presencial | C17: 30/11/2025 | D17: Venta | E17: 01/12/2025 | F17: 1,00 % | G17: 39800 | H17: 398
A18: 135945633656 | C18: 30/11/2025 | D18: Venta | E18: 01/12/2025 | F18: 1,00 % | G18: 8400 | H18: 84
A19: 135330988071 | B19: Venta presencial | C19: 30/11/2025 | D19: Venta | E19: 01/12/2025 | F19: 1,00 % | G19: 50300 | H19: 503
A20: 135949105672 | C20: 01/12/2025 | D20: Venta | E20: 01/12/2025 | F20: 1,00 % | G20: 10100 | H20: 101
A21: 135945997406 | C21: 30/11/2025 | D21: Venta | E21: 01/12/2025 | F21: 1,00 % | G21: 12600 | H21: 126
A22: 135330440377 | C22: 30/11/2025 | D22: Venta | E22: 01/12/2025 | F22: 1,00 % | G22: 56700 | H22: 567
A23: 135331302959 | C23: 30/11/2025 | D23: Venta | E23: 01/12/2025 | F23: 1,00 % | G23: 16800 | H23: 168
A24: 135734903707 | C24: 03/12/2025 | D24: Venta | E24: 03/12/2025 | F24: 1,00 % | G24: 11999 | H24: 119.99
A25: 136364441784 | C25: 03/12/2025 | D25: Venta | E25: 03/12/2025 | F25: 1,00 % | G25: 4800 | H25: 48
A26: 136366138324 | C26: 03/12/2025 | D26: Venta | E26: 03/12/2025 | F26: 1,00 % | G26: 8200 | H26: 82
A27: 135748062571 | B27: Venta presencial | C27: 03/12/2025 | D27: Venta | E27: 03/12/2025 | F27: 1,00 % | G27: 48300 | H27: 483
A28: 136373560516 | C28: 03/12/2025 | D28: Venta | E28: 03/12/2025 | F28: 1,00 % | G28: 31000 | H28: 310
A29: 136374478166 | C29: 03/12/2025 | D29: Venta | E29: 03/12/2025 | F29: 1,00 % | G29: 29800 | H29: 298
A30: 135754447275 | B30: Venta presencial | C30: 03/12/2025 | D30: Venta | E30: 03/12/2025 | F30: 1,00 % | G30: 11999 | H30: 119.99
A31: 135754874311 | B31: Venta presencial | C31: 03/12/2025 | D31: Venta | E31: 03/12/2025 | F31: 1,00 % | G31: 50500 | H31: 505
A32: 135738371583 | B32: Venta presencial | C32: 03/12/2025 | D32: Venta | E32: 03/12/2025 | F32: 1,00 % | G32: 25900 | H32: 259
A33: 135739132419 | B33: Venta presencial | C33: 03/12/2025 | D33: Venta | E33: 03/12/2025 | F33: 1,00 % | G33: 16599 | H33: 165.99
A34: 135757364099 | C34: 03/12/2025 | D34: Venta | E34: 03/12/2025 | F34: 1,00 % | G34: 14600 | H34: 146
A35: 136379529420 | B35: Venta presencial | C35: 03/12/2025 | D35: Venta | E35: 03/12/2025 | F35: 1,00 % | G35: 73500 | H35: 735
A36: 136380032928 | B36: Venta presencial | C36: 03/12/2025 | D36: Venta | E36: 03/12/2025 | F36: 1,00 % | G36: 154897 | H36: 1548.97
A37: 136380185164 | C37: 03/12/2025 | D37: Venta | E37: 03/12/2025 | F37: 1,00 % | G37: 50400 | H37: 504
A38: 135759480719 | C38: 03/12/2025 | D38: Venta | E38: 03/12/2025 | F38: 1,00 % | G38: 23998 | H38: 239.98
A39: 135759894119 | C39: 03/12/2025 | D39: Venta | E39: 03/12/2025 | F39: 1,00 % | G39: 35997 | H39: 359.97
A40: 135759931927 | C40: 03/12/2025 | D40: Venta | E40: 04/12/2025 | F40: 1,00 % | G40: 8400 | H40: 84
A41: 135760275699 | C41: 03/12/2025 | D41: Venta | E41: 04/12/2025 | F41: 1,00 % | G41: 63500 | H41: 635
A42: 136364614462 | B42: Venta presencial | C42: 03/12/2025 | D42: Venta | E42: 03/12/2025 | F42: 1,00 % | G42: 9600 | H42: 96
A43: 135762331375 | C43: 03/12/2025 | D43: Venta | E43: 04/12/2025 | F43: 1,00 % | G43: 4900 | H43: 49
A44: 136383695972 | B44: Venta presencial | C44: 03/12/2025 | D44: Venta | E44: 04/12/2025 | F44: 1,00 % | G44: 34498 | H44: 344.98
A45: 136384024660 | C45: 03/12/2025 | D45: Venta | E45: 04/12/2025 | F45: 1,00 % | G45: 19400 | H45: 194
A46: 136384104070 | B46: Venta presencial | C46: 03/12/2025 | D46: Venta | E46: 04/12/2025 | F46: 1,00 % | G46: 47600 | H46: 476
A47: 136370129344 | C47: 03/12/2025 | D47: Venta | E47: 03/12/2025 | F47: 1,00 % | G47: 24300 | H47: 243
A48: 135749825345 | B48: Venta presencial | C48: 03/12/2025 | D48: Venta | E48: 03/12/2025 | F48: 1,00 % | G48: 9600 | H48: 96
A49: 136374043234 | C49: 03/12/2025 | D49: Venta | E49: 03/12/2025 | F49: 1,00 % | G49: 14500 | H49: 145
A50: 135753489523 | C50: 03/12/2025 | D50: Venta | E50: 03/12/2025 | F50: 1,00 % | G50: 8800 | H50: 88
A51: 136374909026 | C51: 03/12/2025 | D51: Venta | E51: 03/12/2025 | F51: 1,00 % | G51: 28898 | H51: 288.98
A52: 136376223468 | C52: 03/12/2025 | D52: Venta | E52: 03/12/2025 | F52: 1,00 % | G52: 23998 | H52: 239.98
A53: 136377026240 | B53: Venta presencial | C53: 03/12/2025 | D53: Venta | E53: 03/12/2025 | F53: 1,00 % | G53: 33900 | H53: 339
A54: 135757136427 | C54: 03/12/2025 | D54: Venta | E54: 03/12/2025 | F54: 1,00 % | G54: 4800 | H54: 48
A55: 135757391225 | C55: 03/12/2025 | D55: Venta | E55: 03/12/2025 | F55: 1,00 % | G55: 109000 | H55: 1090
A56: 136380675948 | C56: 03/12/2025 | D56: Venta | E56: 03/12/2025 | F56: 1,00 % | G56: 69399 | H56: 693.99
A57: 136381321286 | C57: 03/12/2025 | D57: Venta | E57: 04/12/2025 | F57: 1,00 % | G57: 10100 | H57: 101
A58: 135760346847 | C58: 03/12/2025 | D58: Venta | E58: 04/12/2025 | F58: 1,00 % | G58: 11999 | H58: 119.99
A59: 136382002426 | C59: 03/12/2025 | D59: Venta | E59: 04/12/2025 | F59: 1,00 % | G59: 53700 | H59: 537
A60: 136383829954 | C60: 03/12/2025 | D60: Venta | E60: 04/12/2025 | F60: 1,00 % | G60: 30600 | H60: 306
A61: 135763446201 | C61: 03/12/2025 | D61: Venta | E61: 04/12/2025 | F61: 1,00 % | G61: 21200 | H61: 212
A62: 135877734691 | B62: Venta presencial | C62: 04/12/2025 | D62: Venta | E62: 04/12/2025 | F62: 1,00 % | G62: 14700 | H62: 147
A63: 136507926506 | B63: Venta presencial | C63: 04/12/2025 | D63: Venta | E63: 04/12/2025 | F63: 1,00 % | G63: 9800 | H63: 98
A64: 135887589531 | B64: Venta presencial | C64: 04/12/2025 | D64: Venta | E64: 04/12/2025 | F64: 1,00 % | G64: 8400 | H64: 84
A65: 136521246224 | B65: Venta presencial | C65: 04/12/2025 | D65: Venta | E65: 04/12/2025 | F65: 1,00 % | G65: 22700 | H65: 227
A66: 135899858747 | B66: Venta presencial | C66: 04/12/2025 | D66: Venta | E66: 04/12/2025 | F66: 1,00 % | G66: 13600 | H66: 136
A67: 136505580672 | C67: 04/12/2025 | D67: Venta | E67: 04/12/2025 | F67: 1,00 % | G67: 28200 | H67: 282
A68: 135884884887 | B68: Venta presencial | C68: 04/12/2025 | D68: Venta | E68: 04/12/2025 | F68: 1,00 % | G68: 30700 | H68: 307
A69: 135902991043 | C69: 04/12/2025 | D69: Venta | E69: 04/12/2025 | F69: 1,00 % | G69: 14400 | H69: 144
A70: 135903079939 | C70: 04/12/2025 | D70: Venta | E70: 04/12/2025 | F70: 1,00 % | G70: 42300 | H70: 423
A71: 135903824609 | C71: 04/12/2025 | D71: Venta | E71: 04/12/2025 | F71: 1,00 % | G71: 32000 | H71: 320
A72: 135903962267 | C72: 04/12/2025 | D72: Venta | E72: 04/12/2025 | F72: 1,00 % | G72: 4000 | H72: 40
A73: 135903977575 | C73: 04/12/2025 | D73: Venta | E73: 04/12/2025 | F73: 1,00 % | G73: 11000 | H73: 110
A74: 135904176073 | C74: 04/12/2025 | D74: Venta | E74: 04/12/2025 | F74: 1,00 % | G74: 4800 | H74: 48
A75: 136527051650 | C75: 04/12/2025 | D75: Venta | E75: 04/12/2025 | F75: 1,00 % | G75: 9600 | H75: 96
A76: 136528092580 | C76: 04/12/2025 | D76: Venta | E76: 04/12/2025 | F76: 1,00 % | G76: 23000 | H76: 230
A77: 136528753792 | C77: 04/12/2025 | D77: Venta | E77: 04/12/2025 | F77: 1,00 % | G77: 14900 | H77: 149
A78: 135889088143 | C78: 04/12/2025 | D78: Venta | E78: 04/12/2025 | F78: 1,00 % | G78: 9900 | H78: 99
A79: 136529368322 | C79: 04/12/2025 | D79: Venta | E79: 04/12/2025 | F79: 1,00 % | G79: 16500 | H79: 165
A80: 136512148984 | C80: 04/12/2025 | D80: Venta | E80: 04/12/2025 | F80: 1,00 % | G80: 9800 | H80: 98
... A83: 135909210549 | C83: 04/12/2025 | D83: Venta | E83: 05/12/2025 | F83: 1,00 % | G83: 42800 | H83: 428
A84: 136532271696 | B84: Venta presencial | C84: 04/12/2025 | D84: Venta | E84: 05/12/2025 | F84: 1,00 % | G84: 28400 | H84: 284
A85: 135909801847 | C85: 04/12/2025 | D85: Venta | E85: 05/12/2025 | F85: 1,00 % | G85: 24400 | H85: 244
A86: 136532968476 | B86: Venta presencial | C86: 04/12/2025 | D86: Venta | E86: 05/12/2025 | F86: 1,00 % | G86: 185650 | H86: 1856.5
A87: 135910779181 | B87: Venta presencial | C87: 04/12/2025 | D87: Venta | E87: 05/12/2025 | F87: 1,00 % | G87: 6100 | H87: 61
A88: 135910838031 | C88: 04/12/2025 | D88: Venta | E88: 05/12/2025 | F88: 1,00 % | G88: 4500 | H88: 45
A89: 135911230541 | B89: Venta presencial | C89: 04/12/2025 | D89: Venta | E89: 05/12/2025 | F89: 1,00 % | G89: 49900 | H89: 499
A90: 136535032914 | C90: 04/12/2025 | D90: Venta | E90: 05/12/2025 | F90: 1,00 % | G90: 4900 | H90: 49
A91: 136535221070 | C91: 05/12/2025 | D91: Venta | E91: 05/12/2025 | F91: 1,00 % | G91: 63800 | H91: 638
A92: 135897982183 | B92: Venta presencial | C92: 04/12/2025 | D92: Venta | E92: 04/12/2025 | F92: 1,00 % | G92: 4700 | H92: 47
A93: 136520889392 | C93: 04/12/2025 | D93: Venta | E93: 04/12/2025 | F93: 1,00 % | G93: 4800 | H93: 48
A94: 135898239819 | C94: 04/12/2025 | D94: Venta | E94: 04/12/2025 | F94: 1,00 % | G94: 4200 | H94: 42
A95: 135915566345 | C95: 05/12/2025 | D95: Venta | E95: 05/12/2025 | F95: 1,00 % | G95: 24100 | H95: 241
A96: 136539211002 | C96: 05/12/2025 | D96: Venta | E96: 05/12/2025 | F96: 1,00 % | G96: 8750 | H96: 87.5
A97: 136522852030 | C97: 04/12/2025 | D97: Venta | E97: 04/12/2025 | F97: 1,00 % | G97: 27700 | H97: 277
A98: 135900371775 | B98: Venta presencial | C98: 04/12/2025 | D98: Venta | E98: 04/12/2025 | F98: 1,00 % | G98: 15800 | H98: 158
A99: 135900611305 | C99: 04/12/2025 | D99: Venta | E99: 04/12/2025 | F99: 1,00 % | G99: 4200 | H99: 42
A100: 136523721252 | C100: 04/12/2025 | D100: Venta | E100: 04/12/2025 | F100: 1,00 % | G100: 5500 | H100: 55
A101: 136523955074 | C101: 04/12/2025 | D101: Venta | E101: 04/12/2025 | F101: 1,00 % | G101: 4100 | H101: 41
A102: 136524590174 | B102: Venta presencial | C102: 04/12/2025 | D102: Venta | E102: 04/12/2025 | F102: 1,00 % | G102: 33000 | H102: 330
A103: 135902300611 | B103: Venta presencial | C103: 04/12/2025 | D103: Venta | E103: 04/12/2025 | F103: 1,00 % | G103: 12100 | H103: 121
A104: 135903488753 | C104: 04/12/2025 | D104: Venta | E104: 04/12/2025 | F104: 1,00 % | G104: 4800 | H104: 48
A105: 136525966018 | C105: 04/12/2025 | D105: Venta | E105: 04/12/2025 | F105: 1,00 % | G105: 5500 | H105: 55
...

Sheet Gastos
A1: Fecha de actualización | C1: 46125.407
A3: Sumamos nuevas columnas a tu reporte: Trabajamos para brindarte más detalle sobre los cargos por utilizar Mercado Pago. Por eso, a partir de ahora, en "Información sobre cargos" incluiremos las siguientes columnas: - Número del cargo: para que puedas cruzar la información con otros reportes. - Cobrado en la operación: para saber si un cargo fue cobrado en la operación o no. - Estado del cargo y Cargo que anula: para entender más sobre los cargos anulados.
A7: Información sobre cargos | J7: Información de la operación sobre la que se aplica | R7: Información sobre percepciones | T7: Accesos
A8: Operación relacionada | B8: N° de factura fiscal | C8: Fecha del cargo | D8: Número del cargo | E8: Número del movimiento | F8: Detalle | G8: Cobrado en la operacion | H8: Estado del cargo | I8: Cargo que anula | J8: Valor del cargo | K8: Tipo de operación | L8: Tipo de pago | M8: Número de sucursal | N8: Nombre de sucursal | O8: Referencia externa | P8: Cliente | Q8: Valor de la operación | R8: Alícuota | S8: Base imponible | T8: Sección de Mercado libre y de Mercado Pago
A9: 136529790482 | B9: 0067A00479529 | C9: 45995 | D9: 54262533771 | E9: 2139452011366 | F9: Cargo por cobrar con código QR | G9: Si | J9: 38.8 | K9: Pago | L9: QR | M9: 71465208 | N9: Cerveza Träctor | P9: SD20241024210552 | Q9: 4000 | T9: Ir al Detalle de la operación en Mercado Pago
A10: 136529601672 | B10: 0067A00479529 | C10: 45995 | D10: 54262527242 | E10: 2139451505618 | F10: Cargo por cobrar con código QR | G10: Si | J10: 46.56 | K10: Pago | L10: QR | M10: 71465208 | N10: Cerveza Träctor | P10: LOTO173795 | Q10: 4800 | T10: Ir al Detalle de la operación en Mercado Pago
A11: 135906555589 | B11: 0067A00479529 | C11: 45995 | D11: 54262330931 | E11: 2139448763672 | F11: Cargo por cobrar con código QR | G11: Si | J11: 139.68 | K11: Pago | L11: QR | M11: 71465208 | N11: Cerveza Träctor | P11: MANUCHI2108 | Q11: 14400 | T11: Ir al Detalle de la operación en Mercado Pago
A12: 136529368322 | B12: 0067A00479529 | C12: 45995 | D12: 54262393350 | E12: 2139318558791 | F12: Cargo por cobrar con código QR | G12: Si | J12: 160.05 | K12: Pago | L12: QR | M12: 71465208 | N12: Cerveza Träctor | P12: ROLLALUIS20230306203252 | Q12: 16500 | T12: Ir al Detalle de la operación en Mercado Pago
A13: 136530047680 | B13: 0067A00479529 | C13: 45995 | D13: 54262696987 | E13: 2139322693087 | F13: Cargo por cobrar con Mercado Pago | G13: Si | J13: 913.62 | K13: Pago | L13: QR | M13: 71465208 | N13: Cerveza Träctor | P13: @2113574232 | Q13: 56050 | T13: Ir al Detalle de la operación en Mercado Pago
A14: 135329078135 | B14: 0067A00479529 | C14: 45992 | D14: 54034149131 | E14: 2135329555249 | F14: Cargo por uso de QR - Pagos Interoperables | G14: Si | J14: 193.03 | K14: Pago | L14: QR | M14: 71465208 | N14: Cerveza Träctor | P14: @2489718921 | Q14: 19900
A15: 135329349869 | B15: 0067A00479529 | C15: 45992 | D15: 54034429224 | E15: 2135333114143 | F15: Cargo por cobrar con Point | G15: Si | J15: 1564.14 | K15: Pago | L15: Point | M15: 71465208 | N15: Cerveza Träctor | O15: Venta presencial | P15: VENTASPRESENCIAL | Q15: 39800 | T15: Ir al Detalle de la operación en Mercado Pago
A16: 135945633656 | B16: 0067A00479529 | C16: 45992 | D16: 54034458051 | E16: 2135333274985 | F16: Cargo por uso de QR - Pagos Interoperables | G16: Si | J16: 81.48 | K16: Pago | L16: QR | M16: 71465208 | N16: Cerveza Träctor | P16: @2489718921 | Q16: 8400
A17: 135945997406 | B17: 0067A00479529 | C17: 45992 | D17: 54034599783 | E17: 2135455471882 | F17: Cargo por cobrar con código QR | G17: Si | J17: 122.22 | K17: Pago | L17: QR | M17: 71465208 | N17: Cerveza Träctor | P17: SOFISILVA8 | Q17: 12600 | T17: Ir al Detalle de la operación en Mercado Pago
A18: 135330440377 | B18: 0067A00479529 | C18: 45992 | D18: 54034882974 | E18: 2135458984858 | F18: Cargo por uso de QR - Pagos Interoperables | G18: Si | J18: 549.99 | K18: Pago | L18: QR | M18: 71465208 | N18: Cerveza Träctor | P18: @2489718921 | Q18: 56700
A19: 135330988071 | B19: 0067A00479529 | C19: 45992 | D19: 54035372586 | E19: 2135345218453 | F19: Cargo por cobrar con Point | G19: Si | J19: 1976.79 | K19: Pago | L19: Point | M19: 71465208 | N19: Cerveza Träctor | O19: Venta presencial | P19: VENTASPRESENCIAL | Q19: 50300 | T19: Ir al Detalle de la operación en Mercado Pago
A20: 135331302959 | B20: 0067A00479529 | C20: 45992 | D20: 54035431321 | E20: 2135465869442 | F20: Cargo por cobrar con código QR | G20: Si | J20: 162.96 | K20: Pago | L20: QR | M20: 71465208 | N20: Cerveza Träctor | P20: JUSTINAGUELACHE | Q20: 16800 | T20: Ir al Detalle de la operación en Mercado Pago
A21: 135949105672 | B21: 0067A00479529 | C21: 45992 | D21: 54036750107 | E21: 2135361385667 | F21: Cargo por cobrar con código QR | G21: Si | J21: 97.97 | K21: Pago | L21: QR | M21: 71465208 | N21: Cerveza Träctor | P21: MICAMELLO15 | Q21: 10100 | T21: Ir al Detalle de la operación en Mercado Pago
A22: 135734903707 | B22: 0067A00479529 | C22: 45994 | D22: 54196345298 | E22: 2138128209819 | F22: Cargo por uso de QR - Pagos Interoperables | G22: Si | J22: 116.39 | K22: Pago | L22: QR | M22: 71465208 | N22: Cerveza Träctor | P22: @2489718921 | Q22: 11999
A23: 135738371583 | B23: 0067A00479529 | C23: 45994 | D23: 54197630941 | E23: 2138278186896 | F23: Cargo por cobrar con Point | G23: Si | J23: 1017.87 | K23: Pago | L23: Point | M23: 71465208 | N23: Cerveza Träctor | O23: Venta presencial | P23: VENTASPRESENCIAL | Q23: 25900 | T23: Ir al Detalle de la operación en Mercado Pago
A24: 135739132419 | B24: 0067A00479529 | C24: 45994 | D24: 54197864029 | E24: 2138282073128 | F24: Cargo por cobrar con Point | G24: Si | J24: 652.34 | K24: Pago | L24: Point | M24: 71465208 | N24: Cerveza Träctor | O24: Venta presencial | P24: VENTASPRESENCIAL | Q24: 16599 | T24: Ir al Detalle de la operación en Mercado Pago
A25: 136364614462 | B25: 0067A00479529 | C25: 45994 | D25: 54199590496 | E25: 2138313729844 | F25: Cargo por cobrar con Point | G25: Si | J25: 377.28 | K25: Pago | L25: Point | M25: 71465208 | N25: Cerveza Träctor | O25: Venta presencial | P25: VENTASPRESENCIAL | Q25: 9600 | T25: Ir al Detalle de la operación en Mercado Pago
A26: 136364441784 | B26: 0067A00479529 | C26: 45994 | D26: 54199605104 | E26: 2138185132615 | F26: Cargo por cobrar con código QR | G26: Si | J26: 365.28 | K26: Pago | L26: QR | M26: 71465208 | N26: Cerveza Träctor | P26: JUANFOLMERD1 | Q26: 4800 | T26: Ir al Detalle de la operación en Mercado Pago
A27: 136366138324 | B27: 0067A00479529 | C27: 45994 | D27: 54200200216 | E27: 2138196950733 | F27: Cargo por cobrar con código QR | G27: Si | J27: 79.54 | K27: Pago | L27: QR | M27: 71465208 | N27: Cerveza Träctor | P27: VICTORIAMASSARDI | Q27: 8200 | T27: Ir al Detalle de la operación en Mercado Pago
A28: 135748062571 | B28: 0067A00479529 | C28: 45994 | D28: 54201321613 | E28: 2138219548965 | F28: Cargo por cobrar con Point | G28: Si | J28: 1898.19 | K28: Pago | L28: Point | M28: 71465208 | N28: Cerveza Träctor | O28: Venta presencial | P28: VENTASPRESENCIAL | Q28: 48300 | T28: Ir al Detalle de la operación en Mercado Pago
A29: 136370129344 | B29: 0067A00479529 | C29: 45994 | D29: 54201766843 | E29: 2138356554706 | F29: Cargo por cobrar con código QR | G29: Si | J29: 235.71 | K29: Pago | L29: QR | M29: 71465208 | N29: Cerveza Träctor | P29: ALECOLO68 | Q29: 24300 | T29: Ir al Detalle de la operación en Mercado Pago
A30: 135749825345 | B30: 0067A00479529 | C30: 45994 | D30: 54202008317 | E30: 2138361467184 | F30: Cargo por cobrar con Point | G30: Si | J30: 377.28 | K30: Pago | L30: Point | M30: 71465208 | N30: Cerveza Träctor | O30: Venta presencial | P30: VENTASPRESENCIAL | Q30: 9600 | T30: Ir al Detalle de la operación en Mercado Pago
A31: 136373560516 | B31: 0067A00479529 | C31: 45994 | D31: 54203082239 | E31: 2138254069743 | F31: Cargo por cobrar con código QR | G31: Si | J31: 300.7 | K31: Pago | L31: QR | M31: 71465208 | N31: Cerveza Träctor | P31: CRISTIANVALDEZPUENTE | Q31: 31000 | T31: Ir al Detalle de la operación en Mercado Pago
A32: 136374043234 | B32: 0067A00479529 | C32: 45994 | D32: 54203336275 | E32: 2138387480544 | F32: Cargo por cobrar con código QR | G32: Si | J32: 140.65 | K32: Pago | L32: QR | M32: 71465208 | N32: Cerveza Träctor | P32: MATIASRACIGH20211027154052 | Q32: 14500 | T32: Ir al Detalle de la operación en Mercado Pago
A33: 136374478166 | B33: 0067A00479529 | C33: 45994 | D33: 54203459444 | E33: 2138261522843 | F33: Cargo por uso de QR - Pagos Interoperables | G33: Si | J33: 289.06 | K33: Pago | L33: QR | M33: 71465208 | N33: Cerveza Träctor | P33: @2489718921 | Q33: 29800
A34: 135753489523 | B34: 0067A00479529 | C34: 45994 | D34: 54203525086 | E34: 2138390866130 | F34: Cargo por cobrar con código QR | G34: Si | J34: 85.36 | K34: Pago | L34: QR | M34: 71465208 | N34: Cerveza Träctor | P34: FLORINOIR | Q34: 8800 | T34: Ir al Detalle de la operación en Mercado Pago
A35: 136374909026 | B35: 0067A00479529 | C35: 45994 | D35: 54203679974 | E35: 2138394366030 | F35: Cargo por cobrar con código QR | G35: Si | J35: 280.31 | K35: Pago | L35: QR | M35: 71465208 | N35: Cerveza Träctor | P35: CINTHIAJANETBRUCHEZ | Q35: 28898 | T35: Ir al Detalle de la operación en Mercado Pago
A36: 135754447275 | B36: 0067A00479529 | C36: 45994 | D36: 54203916166 | E36: 2138270561355 | F36: Cargo por cobrar con Point | G36: Si | J36: 471.56 | K36: Pago | L36: Point | M36: 71465208 | N36: Cerveza Träctor | O36: Venta presencial | P36: VENTASPRESENCIAL | Q36: 11999 | T36: Ir al Detalle de la operación en Mercado Pago
A37: 135754874311 | B37: 0067A00479529 | C37: 45994 | D37: 54204036365 | E37: 2138272977715 | F37: Cargo por cobrar con Point | G37: Si | J37: 3843.05 | K37: Pago | L37: Point | M37: 71465208 | N37: Cerveza Träctor | O37: Venta presencial | P37: VENTASPRESENCIAL | Q37: 50500 | T37: Ir al Detalle de la operación en Mercado Pago
A38: 136376223468 | B38: 0067A00479529 | C38: 45994 | D38: 54204228599 | E38: 2138405064126 | F38: Cargo por cobrar con Mercado Pago | G38: Si | J38: 1826.25 | K38: Pago | L38: QR | M38: 71465208 | N38: Cerveza Träctor | P38: @1785701758 | Q38: 23998 | T38: Ir al Detalle de la operación en Mercado Pago
A39: 136377026240 | B39: 0067A00479529 | C39: 45994 | D39: 54204441507 | E39: 2138409355852 | F39: Cargo por cobrar con Point | G39: Si | J39: 1332.27 | K39: Pago | L39: Point | M39: 71465208 | N39: Cerveza Träctor | O39: Venta presencial | P39: VENTASPRESENCIAL | Q39: 33900 | T39: Ir al Detalle de la operación en Mercado Pago
A40: 135757136427 | B40: 0067A00479529 | C40: 45994 | D40: 54204995808 | E40: 2138418857124 | F40: Cargo por cobrar con código QR | G40: Si | J40: 46.56 | K40: Pago | L40: QR | M40: 71465208 | N40: Cerveza Träctor | P40: MARAFOLLONIER97 | Q40: 4800 | T40: Ir al Detalle de la operación en Mercado Pago
A41: 135757391225 | B41: 0067A00479529 | C41: 45994 | D41: 54205129122 | E41: 2138421164640 | F41: Cargo por cobrar con código QR | G41: Si | J41: 1057.3 | K41: Pago | L41: QR | M41: 71465208 | N41: Cerveza Träctor | P41: LUCALUGRIN | Q41: 109000 | T41: Ir al Detalle de la operación en Mercado Pago
A42: 135757364099 | B42: 0067A00479529 | C42: 45994 | D42: 54205151337 | E42: 2138292566305 | F42: Cargo por cobrar con código QR | G42: Si | J42: 141.62 | K42: Pago | L42: QR | M42: 71465208 | N42: Cerveza Träctor | P42: MATIASRACIGH20211027154052 | Q42: 14600 | T42: Ir al Detalle de la operación en Mercado Pago
A43: 136379529420 | B43: 0067A00479529 | C43: 45994 | D43: 54205610330 | E43: 2138299226623 | F43: Cargo por cobrar con Point | G43: Si | J43: 2888.55 | K43: Pago | L43: Point | M43: 71465208 | N43: Cerveza Träctor | O43: Venta presencial | P43: VENTASPRESENCIAL | Q43: 73500 | T43: Ir al Detalle de la operación en Mercado Pago
A44: 136380032928 | B44: 0067A00479529 | C44: 45994 | D44: 54205773905 | E44: 2138301936037 | F44: Cargo por cobrar con Point | G44: Si | J44: 6087.45 | K44: Pago | L44: Point | M44: 71465208 | N44: Cerveza Träctor | O44: Venta presencial | P44: VENTASPRESENCIAL | Q44: 154897 | T44: Ir al Detalle de la operación en Mercado Pago
A45: 136380185164 | B45: 0067A00479529 | C45: 45994 | D45: 54205841364 | E45: 2138302453357 | F45: Cargo por cobrar con código QR | G45: Si | J45: 821.52 | K45: Pago | L45: QR | M45: 71465208 | N45: Cerveza Träctor | P45: GONZA.ROMERO11 | Q45: 50400 | T45: Ir al Detalle de la operación en Mercado Pago
A46: 135759480719 | B46: 0067A00479529 | C46: 45994 | D46: 54206008055 | E46: 2138304836889 | F46: Cargo por cobrar con código QR | G46: Si | J46: 232.78 | K46: Pago | L46: QR | M46: 71465208 | N46: Cerveza Träctor | P46: NAHUELDEPARDON | Q46: 23998 | T46: Ir al Detalle de la operación en Mercado Pago
A47: 136380675948 | B47: 0067A00479529 | C47: 45994 | D47: 54206130691 | E47: 2138435526624 | F47: Cargo por cobrar con código QR | G47: Si | J47: 673.17 | K47: Pago | L47: QR | M47: 71465208 | N47: Cerveza Träctor | P47: SILDEPRO | Q47: 69399 | T47: Ir al Detalle de la operación en Mercado Pago
A48: 135759894119 | B48: 0067A00479529 | C48: 45994 | D48: 54206160206 | E48: 2138306879839 | F48: Cargo por cobrar con código QR | G48: Si | J48: 349.17 | K48: Pago | L48: QR | M48: 71465208 | N48: Cerveza Träctor | P48: EZEQUIELBONNIN | Q48: 35997 | T48: Ir al Detalle de la operación en Mercado Pago
A49: 135759931927 | B49: 0067A00479529 | C49: 45995 | D49: 54206307187 | E49: 2138308836093 | F49: Cargo por uso de QR - Pagos Interoperables | G49: Si | J49: 81.48 | K49: Pago | L49: QR | M49: 71465208 | N49: Cerveza Träctor | P49: @2489718921 | Q49: 8400
A50: 136381321286 | B50: 0067A00479529 | C50: 45995 | D50: 54206407970 | E50: 2138439287148 | F50: Cargo por cobrar con código QR | G50: Si | J50: 97.97 | K50: Pago | L50: QR | M50: 71465208 | N50: Cerveza Träctor | P50: LOJU4214196 | Q50: 10100 | T50: Ir al Detalle de la operación en Mercado Pago
A51: 135760346847 | B51: 0067A00479529 | C51: 45995 | D51: 54206430316 | E51: 2138439838072 | F51: Cargo por cobrar con código QR | G51: Si | J51: 116.39 | K51: Pago | L51: QR | M51: 71465208 | N51: Cerveza Träctor | P51: JUANFIDELBENITEZ | Q51: 11999 | T51: Ir al Detalle de la operación en Mercado Pago
A52: 135760275699 | B52: 0067A00479529 | C52: 45995 | D52: 54206453607 | E52: 2138311153723 | F52: Cargo por cobrar con código QR | G52: Si | J52: 615.95 | K52: Pago | L52: QR | M52: 71465208 | N52: Cerveza Träctor | P52: MOFE8073706 | Q52: 63500 | T52: Ir al Detalle de la operación en Mercado Pago
A53: 136382002426 | B53: 0067A00479529 | C53: 45995 | D53: 54206671476 | E53: 2138443421074 | F53: Cargo por cobrar con código QR | G53: Si | J53: 520.89 | K53: Pago | L53: QR | M53: 71465208 | N53: Cerveza Träctor | P53: MENTILMARALUCIANA | Q53: 53700 | T53: Ir al Detalle de la operación en Mercado Pago
A54: 135762331375 | B54: 0067A00479529 | C54: 45995 | D54: 54207267695 | E54: 2138325159669 | F54: Cargo por cobrar con código QR | G54: Si | J54: 47.53 | K54: Pago | L54: QR | M54: 71465208 | N54: Cerveza Träctor | P54: MATIASRACIGH20211027154052 | Q54: 4900 | T54: Ir al Detalle de la operación en Mercado Pago
A55: 136383695972 | B55: 0067A00479529 | C55: 45995 | D55: 54207406619 | E55: 2138327987765 | F55: Cargo por cobrar con Point | G55: Si | J55: 2625.3 | K55: Pago | L55: Point | M55: 71465208 | N55: Cerveza Träctor | O55: Venta presencial | P55: VENTASPRESENCIAL | Q55: 34498 | T55: Ir al Detalle de la operación en Mercado Pago
A56: 136384024660 | B56: 0067A00479529 | C56: 45995 | D56: 54207424212 | E56: 2138328839867 | F56: Cargo por cobrar con código QR | G56: Si | J56: 188.18 | K56: Pago | L56: QR | M56: 71465208 | N56: Cerveza Träctor | P56: QUIROZAYELEN | Q56: 19400 | T56: Ir al Detalle de la operación en Mercado Pago
A57: 136383829954 | B57: 0067A00479529 | C57: 45995 | D57: 54207431777 | E57: 2138458518430 | F57: Cargo por cobrar con código QR | G57: Si | J57: 296.82 | K57: Pago | L57: QR | M57: 71465208 | N57: Cerveza Träctor | P57: MARADELFINAGAGGIETTA | Q57: 30600 | T57: Ir al Detalle de la operación en Mercado Pago
A58: 136384104070 | B58: 0067A00479529 | C58: 45995 | D58: 54207573633 | E58: 2138331962073 | F58: Cargo por cobrar con Point | G58: Si | J58: 1870.68 | K58: Pago | L58: Point | M58: 71465208 | N58: Cerveza Träctor | O58: Venta presencial | P58: VENTASPRESENCIAL | Q58: 47600 | T58: Ir al Detalle de la operación en Mercado Pago
A59: 135763446201 | B59: 0067A00479529 | C59: 45995 | D59: 54207622616 | E59: 2138462459972 | F59: Cargo por uso de QR - Pagos Interoperables | G59: Si | J59: 205.64 | K59: Pago | L59: QR | M59: 71465208 | N59: Cerveza Träctor | P59: @2489718921 | Q59: 21200
A60: 135877734691 | B60: 0067A00479529 | C60: 45995 | D60: 54251251227 | E60: 2139111916003 | F60: Cargo por cobrar con Point | G60: Si | J60: 667.38 | K60: Pago | L60: Point | M60: 71465208 | N60: Cerveza Träctor | O60: Venta presencial | P60: VENTASPRESENCIAL | Q60: 14700 | T60: Ir al Detalle de la operación en Mercado Pago
A61: 136505580672 | B61: 0067A00479529 | C61: 45995 | D61: 54253200155 | E61: 2139275437070 | F61: Cargo por cobrar con código QR | G61: Si | J61: 2146.02 | K61: Pago | L61: QR | M61: 71465208 | N61: Cerveza Träctor | P61: JOAQUINSCHENONE | Q61: 28200 | T61: Ir al Detalle de la operación en Mercado Pago
A62: 135884884887 | B62: 0067A00479529 | C62: 45995 | D62: 54253921768 | E62: 2139288150684 | F62: Cargo por cobrar con Point | G62: Si | J62: 1206.51 | K62: Pago | L62: Point | M62: 71465208 | N62: Cerveza Träctor | O62: Venta presencial | P62: VENTASPRESENCIAL | Q62: 30700 | T62: Ir al Detalle de la operación en Mercado Pago
A63: 136507926506 | B63: 0067A00479529 | C63: 45995 | D63: 54254113616 | E63: 2139159899315 | F63: Cargo por cobrar con Point | G63: Si | J63: 385.14 | K63: Pago | L63: Point | M63: 71465208 | N63: Cerveza Träctor | O63: Venta presencial | P63: VENTASPRESENCIAL | Q63: 9800 | T63: Ir al Detalle de la operación en Mercado Pago
A64: 135887589531 | B64: 0067A00479529 | C64: 45995 | D64: 54255011630 | E64: 2139176280701 | F64: Cargo por cobrar con Point | G64: Si | J64: 330.12 | K64: Pago | L64: Point | M64: 71465208 | N64: Cerveza Träctor | O64: Venta presencial | P64: VENTASPRESENCIAL | Q64: 8400 | T64: Ir al Detalle de la operación en Mercado Pago
A65: 135889088143 | B65: 0067A00479529 | C65: 45995 | D65: 54255504773 | E65: 2139317073022 | F65: Cargo por cobrar con código QR | G65: Si | J65: 96.03 | K65: Pago | L65: QR | M65: 71465208 | N65: Cerveza Träctor | P65: MATIASSENSIMATIASSENSI | Q65: 9900 | T65: Ir al Detalle de la operación en Mercado Pago
A66: 136512148984 | B66: 0067A00479529 | C66: 45995 | D66: 54255713912 | E66: 2139321350566 | F66: Cargo por uso de QR - Pagos Interoperables | G66: Si | J66: 95.06 | K66: Pago | L66: QR | M66: 71465208 | N66: Cerveza Träctor | P66: @2489718921 | Q66: 9800
A67: 135897982183 | B67: 0067A00479529 | C67: 45995 | D67: 54258971062 | E67: 2139384049160 | F67: Cargo por cobrar con Point | G67: Si | J67: 184.71 | K67: Pago | L67: Point | M67: 71465208 | N67: Cerveza Träctor | O67: Venta presencial | P67: VENTASPRESENCIAL | Q67: 4700 | T67: Ir al Detalle de la operación en Mercado Pago
A68: 136520889392 | B68: 0067A00479529 | C68: 45995 | D68: 54259052989 | E68: 2139385615814 | F68: Cargo por cobrar con código QR | G68: Si | J68: 46.56 | K68: Pago | L68: QR | M68: 71465208 | N68: Cerveza Träctor | P68: ABRILSOTTO | Q68: 4800 | T68: Ir al Detalle de la operación en Mercado Pago
A69: 135898239819 | B69: 0067A00479529 | C69: 45995 | D69: 54259100498 | E69: 2139386708412 | F69: Cargo por uso de QR - Pagos Interoperables | G69: Si | J69: 40.74 | K69: Pago | L69: QR | M69: 71465208 | N69: Cerveza Träctor | P69: @2489718921 | Q69: 4200
A70: 136521246224 | B70: 0067A00479529 | C70: 45995 | D70: 54259178746 | E70: 2139256374183 | F70: Cargo por cobrar con Point | G70: Si | J70: 1030.58 | K70: Pago | L70: Point | M70: 71465208 | N70: Cerveza Träctor | O70: Venta presencial | P70: VENTASPRESENCIAL | Q70: 22700 | T70: Ir al Detalle de la operación en Mercado Pago
A71: 135899858747 | B71: 0067A00479529 | C71: 45995 | D71: 54259670543 | E71: 2139265905985 | F71: Cargo por cobrar con Point | G71: Si | J71: 617.44 | K71: Pago | L71: Point | M71: 71465208 | N71: Cerveza Träctor | O71: Venta presencial | P71: VENTASPRESENCIAL | Q71: 13600 | T71: Ir al Detalle de la operación en Mercado Pago
A72: 136522852030 | B72: 0067A00479529 | C72: 45995 | D72: 54259885111 | E72: 2139402060908 | F72: Cargo por cobrar con código QR | G72: Si | J72: 268.69 | K72: Pago | L72: QR | M72: 71465208 | N72: Cerveza Träctor | P72: BETIANA_RODRIGUEZ_ENTRERIOS | Q72: 27700 | T72: Ir al Detalle de la operación en Mercado Pago
A73: 135900371775 | B73: 0067A00479529 | C73: 45995 | D73: 54259899294 | E73: 2139402267422 | F73: Cargo por cobrar con Point | G73: Si | J73: 620.94 | K73: Pago | L73: Point | M73: 71465208 | N73: Cerveza Träctor | O73: Venta presencial | P73: VENTASPRESENCIAL | Q73: 15800 | T73: Ir al Detalle de la operación en Mercado Pago
A74: 135900611305 | B74: 0067A00479529 | C74: 45995 | D74: 54260005469 | E74: 2139404140102 | F74: Cargo por cobrar con código QR | G74: Si | J74: 40.74 | K74: Pago | L74: QR | M74: 71465208 | N74: Cerveza Träctor | P74: LARAVITTON | Q74: 4200 | T74: Ir al Detalle de la operación en Mercado Pago
A75: 136523721252 | B75: 0067A00479529 | C75: 45995 | D75: 54260185164 | E75: 2139408071206 | F75: Cargo por cobrar con código QR | G75: Si | J75: 53.35 | K75: Pago | L75: QR | M75: 71465208 | N75: Cerveza Träctor | P75: TRONCOSOMELISA97 | Q75: 5500 | T75: Ir al Detalle de la operación en Mercado Pago
A76: 136523955074 | B76: 0067A00479529 | C76: 45995 | D76: 54260238790 | E76: 2139409436046 | F76: Cargo por cobrar con código QR | G76: Si | J76: 39.77 | K76: Pago | L76: QR | M76: 71465208 | N76: Cerveza Träctor | P76: CAMILAGERMANIER | Q76: 4100 | T76: Ir al Detalle de la operación en Mercado Pago
A77: 136524590174 | B77: 0067A00479529 | C77: 45995 | D77: 54260443945 | E77: 2139413759518 | F77: Cargo por cobrar con Point | G77: Si | J77: 1296.9 | K77: Pago | L77: Point | M77: 71465208 | N77: Cerveza Träctor | O77: Venta presencial | P77: VENTASPRESENCIAL | Q77: 33000 | T77: Ir al Detalle de la operación en Mercado Pago
A78: 135902300611 | B78: 0067A00479529 | C78: 45995 | D78: 54260665463 | E78: 2139417590044 | F78: Cargo por cobrar con Point | G78: Si | J78: 920.81 | K78: Pago | L78: Point | M78: 71465208 | N78: Cerveza Träctor | O78: Venta presencial | P78: VENTASPRESENCIAL | Q78: 12100 | T78: Ir al Detalle de la operación en Mercado Pago
A79: 135902991043 | B79: 0067A00479529 | C79: 45995 | D79: 54260889584 | E79: 2139290802927 | F79: Cargo por cobrar con código QR | G79: Si | J79: 234.72 | K79: Pago | L79: QR | M79: 71465208 | N79: Cerveza Träctor | P79: MORENDAIANA20210706000336 | Q79: 14400 | T79: Ir al Detalle de la operación en Mercado Pago
A80: 135903079939 | B80: 0067A00479529 | C80: 45995 | D80: 54260929882 | E80: 2139291812949 | F80: Cargo por cobrar con código QR | G80: Si | J80: 410.31 | K80: Pago | L80: QR | M80: 71465208 | N80: Cerveza Träctor | P80: GRI_83 | Q80: 42300 | T80: Ir al Detalle de la operación en Mercado Pago
A81: 135903488753 | B81: 0067A00479529 | C81: 45995 | D81: 54261086056 | E81: 2139426224594 | F81: Cargo por cobrar con código QR | G81: Si | J81: 46.56 | K81: Pago | L81: QR | M81: 71465208 | N81: Cerveza Träctor | P81: ESLU6384315 | Q81: 4800 | T81: Ir al Detalle de la operación en Mercado Pago
A82: 136525966018 | B82: 0067A00479529 | C82: 45995 | D82: 54261094086 | E82: 2139426879750 | F82: Cargo por cobrar con código QR | G82: Si | J82: 53.35 | K82: Pago | L82: QR | M82: 71465208 | N82: Cerveza Träctor | P82: SCALESEJUANI | Q82: 5500 | T82: Ir al Detalle de la operación en Mercado Pago
A83: 135903704321 | B83: 0067A00479529 | C83: 45995 | D83: 54261164794 | E83: 2139428136436 | F83: Cargo por uso de QR - Pagos Interoperables | G83: Si | J83: 43.65 | K83: Pago | L83: QR | M83: 71465208 | N83: Cerveza Träctor | P83: @2489718921 | Q83: 4500
A84: 135903824609 | B84: 0067A00479529 | C84: 45995 | D84: 54261231530 | E84: 2139297648701 | F84: Cargo por cobrar con código QR | G84: Si | J84: 310.4 | K84: Pago | L84: QR | M84: 71465208 | N84: Cerveza Träctor | P84: BASO144203 | Q84: 32000 | T84: Ir al Detalle de la operación en Mercado Pago
A85: 135903962267 | B85: 0067A00479529 | C85: 45995 | D85: 54261279096 | E85: 2139298590595 | F85: Cargo por cobrar con código QR | G85: Si | J85: 38.8 | K85: Pago | L85: QR | M85: 71465208 | N85: Cerveza Träctor | P85: MATIASNAHUELBOUCHET | Q85: 4000 | T85: Ir al Detalle de la operación en Mercado Pago
A86: 135903977575 | B86: 0067A00479529 | C86: 45995 | D86: 54261317198 | E86: 2139299370035 | F86: Cargo por cobrar con código QR | G86: Si | J86: 106.7 | K86: Pago | L86: QR | M86: 71465208 | N86: Cerveza Träctor | P86: QUIIMEY | Q86: 11000 | T86: Ir al Detalle de la operación en Mercado Pago
A87: 135904176073 | B87: 0067A00479529 | C87: 45995 | D87: 54261429470 | E87: 2139301202283 | F87: Cargo por cobrar con Mercado Pago | G87: Si | J87: 78.24 | K87: Pago | L87: QR | M87: 71465208 | N87: Cerveza Träctor | P87: @2027641910 | Q87: 4800 | T87: Ir al Detalle de la operación en Mercado Pago
A88: 136526927868 | B88: 0067A00479529 | C88: 45995 | D88: 54261455892 | E88: 2139433239762 | F88: Cargo por cobrar con código QR | G88: Si | J88: 46.56 | K88: Pago | L88: QR | M88: 71465208 | N88: Cerveza Träctor | P88: GALVANFEDERIO20221225121930 | Q88: 4800 | T88: Ir al Detalle de la operación en Mercado Pago
A89: 136527051650 | B89: 0067A00479529 | C89: 45995 | D89: 54261498134 | E89: 2139302658089 | F89: Cargo por uso de QR - Pagos Interoperables | G89: Si | J89: 93.12 | K89: Pago | L89: QR | M89: 71465208 | N89: Cerveza Träctor | P89: @2489718921 | Q89: 9600
A90: 136527375236 | B90: 0067A00479529 | C90: 45995 | D90: 54261581815 | E90: 2139436010066 | F90: Cargo por cobrar con código QR | G90: Si | J90: 93.12 | K90: Pago | L90: QR | M90: 71465208 | N90: Cerveza Träctor | P90: CACERESLUZ25 | Q90: 9600 | T90: Ir al Detalle de la operación en Mercado Pago
A91: 135904784987 | B91: 0067A00479529 | C91: 45995 | D91: 54261633376 | E91: 2139436914476 | F91: Cargo por cobrar con Mercado Pago | G91: Si | J91: 89.65 | K91: Pago | L91: QR | M91: 71465208 | N91: Cerveza Träctor | P91: @2027641910 | Q91: 5500 | T91: Ir al Detalle de la operación en Mercado Pago
A92: 136527796466 | B92: 0067A00479529 | C92: 45995 | D92: 54261744086 | E92: 2139438867086 | F92: Cargo por cobrar con código QR | G92: Si | J92: 39.77 | K92: Pago | L92: QR | M92: 71465208 | N92: Cerveza Träctor | P92: ML20241218213212 | Q92: 4100 | T92: Ir al Detalle de la operación en Mercado Pago
A93: 136527826814 | B93: 0067A00479529 | C93: 45995 | D93: 54261788251 | E93: 2139439433696 | F93: Cargo por cobrar con código QR | G93: Si | J93: 42.68 | K93: Pago | L93: QR | M93: 71465208 | N93: Cerveza Träctor | P93: ELMA7548284 | Q93: 4400 | T93: Ir al Detalle de la operación en Mercado Pago
A94: 136528092580 | B94: 0067A00479529 | C94: 45995 | D94: 54261896606 | E94: 2139309593961 | F94: Cargo por cobrar con código QR | G94: Si | J94: 223.1 | K94: Pago | L94: QR | M94: 71465208 | N94: Cerveza Träctor | P94: ISGLEASVICTORIA20230319120404 | Q94: 23000 | T94: Ir al Detalle de la operación en Mercado Pago
A95: 136528512600 | B95: 0067A00479529 | C95: 45995 | D95: 54262072400 | E95: 2139444229490 | F95: Cargo por cobrar con código QR | G95: Si | J95: 53.35 | K95: Pago | L95: QR | M95: 71465208 | N95: Cerveza Träctor | P95: DE20241124220647 | Q95: 5500 | T95: Ir al Detalle de la operación en Mercado Pago
A96: 136528753792 | B96: 0067A00479529 | C96: 45995 | D96: 54262209481 | E96: 2139315123645 | F96: Cargo por cobrar con Mercado Pago | G96: Si | J96: 242.87 | K96: Pago | L96: QR | M96: 71465208 | N96: Cerveza Träctor | P96: @2113574232 | Q96: 14900 | T96: Ir al Detalle de la operación en Mercado Pago
A97: 136528767468 | B97: 0067A00479529 | C97: 45995 | D97: 54262243931 | E97: 2139446694054 | F97: Cargo por uso de QR - Pagos Interoperables | G97: Si | J97: 42.68 | K97: Pago | L97: QR | M97: 71465208 | N97: Cerveza Träctor | P97: @2489718921 | Q97: 4400
A98: 135908897041 | B98: 0071A00512168 | C98: 45996 | D98: 54263290267 | E98: 2139331270697 | F98: Cargo por cobrar con código QR | G98: Si | J98: 455.9 | K98: Pago | L98: QR | M98: 71465208 | N98: Cerveza Träctor | P98: MAX_PID | Q98: 47000 | T98: Ir al Detalle de la operación en Mercado Pago
A99: 135909210549 | B99: 0071A00512168 | C99: 45996 | D99: 54263448761 | E99: 2139333221569 | F99: Cargo por uso de QR - Pagos Interoperables | G99: Si | J99: 415.16 | K99: Pago | L99: QR | M99: 71465208 | N99: Cerveza Träctor | P99: @2489718921 | Q99: 42800
A100: 135909548389 | B100: 0071A00512168 | C100: 45996 | D100: 54263626796 | E100: 2139467327648 | F100: Cargo por cobrar con código QR | G100: Si | J100: 187.21 | K100: Pago | L100: QR | M100: 71465208 | N100: Cerveza Träctor | P100: PARLATTOCAMILA20220515111643 | Q100: 19300 | T100: Ir al Detalle de la operación en Mercado Pago
A101: 136532314330 | B101: 0071A00512168 | C101: 45996 | D101: 54263677011 | E101: 2139467862424 | F101: Cargo por cobrar con Point | G101: Si | J101: 821.37 | K101: Pago | L101: Point | M101: 71465208 | N101: Cerveza Träctor | O101: Venta presencial | P101: VENTASPRESENCIAL | Q101: 20900 | T101: Ir al Detalle de la operación en Mercado Pago
A102: 136532271696 | B102: 0071A00512168 | C102: 45996 | D102: 54263716381 | E102: 2139336836733 | F102: Cargo por cobrar con Point | G102: Si | J102: 1116.12 | K102: Pago | L102: Point | M102: 71465208 | N102: Cerveza Träctor | O102: Venta presencial | P102: VENTASPRESENCIAL | Q102: 28400 | T102: Ir al Detalle de la operación en Mercado Pago
A103: 135909801847 | B103: 0071A00512168 | C103: 45996 | D103: 54263825185 | E103: 2139338634733 | F103: Cargo por cobrar con código QR | G103: Si | J103: 236.68 | K103: Pago | L103: QR | M103: 71465208 | N103: Cerveza Träctor | P103: DANIELEMARIA20220215211222 | Q103: 24400 | T103: Ir al Detalle de la operación en Mercado Pago
A104: 135910347159 | B104: 0071A00512168 | C104: 45996 | D104: 54263993507 | E104: 2139473005720 | F104: Cargo por cobrar con código QR | G104: Si | J104: 443.29 | K104: Pago | L104: QR | M104: 71465208 | N104: Cerveza Träctor | P104: PALYMASSERA | Q104: 45700 | T104: Ir al Detalle de la operación en Mercado Pago
...

Sheet IDC
A1: Reporte-Retención-Impuesto-sobre-los-Créditos-y-Débitos-Diciembre-CC20250609171159-MercadoPago
A3: Usuario: | B3: CC20250609171159
A4: Impuesto: | B4: Impuesto sobre los Créditos y Débitos
A5: Fecha de descarga: | B5: 18/03/2026
A6: Intervalo de fechas consultadas: | B6: 01/12/2025 a 01/01/2026
A8: Total | B8: Monto
A9: Base imponible | B9: $52.351.112,61
A10: Importe retenido | B10: $314.106,65
A11: Importe devuelto | B11: $505,89
A13: Encuentra los movimientos de dinero en tu cuenta de Mercado Pago, en informes de balance.
A15: Este impuesto se aplica cada vez que hagas operaciones con terceros.
A16: Podrás conciliar la información con otros reportes de Mercado Libre. | D16: Podrás buscar el detalle de lo retenido en tu operación en la sección Actividad.
A18: Operación | E18: Impuesto
A19: Número de operación | B19: Número de venta - Referencia externa | C19: Fecha de operación | D19: Tipo | E19: Fecha de retención | F19: Alícuota | G19: Base imponible | H19: Importe retenido
A20: 135329078135 | C20: 30/11/2025 | D20: Transacción | E20: 01/12/2025 | F20: 0,60 % | G20: 19900 | H20: 119.4
A21: 135329349869 | B21: Venta presencial | C21: 30/11/2025 | D21: Transacción | E21: 01/12/2025 | F21: 0,60 % | G21: 39800 | H21: 238.8
A22: 135945633656 | C22: 30/11/2025 | D22: Transacción | E22: 01/12/2025 | F22: 0,60 % | G22: 8400 | H22: 50.4
A23: 135330988071 | B23: Venta presencial | C23: 30/11/2025 | D23: Transacción | E23: 01/12/2025 | F23: 0,60 % | G23: 50300 | H23: 301.8
A24: 135949105672 | C24: 01/12/2025 | D24: Transacción | E24: 01/12/2025 | F24: 0,60 % | G24: 10100 | H24: 60.6
A25: 135945997406 | C25: 30/11/2025 | D25: Transacción | E25: 01/12/2025 | F25: 0,60 % | G25: 12600 | H25: 75.6
A26: 135330440377 | C26: 30/11/2025 | D26: Transacción | E26: 01/12/2025 | F26: 0,60 % | G26: 56700 | H26: 340.2
A27: 135331302959 | C27: 30/11/2025 | D27: Transacción | E27: 01/12/2025 | F27: 0,60 % | G27: 16800 | H27: 100.8
A28: 135979554276 | C28: 01/12/2025 | D28: Transacción | E28: 01/12/2025 | F28: 0,60 % | G28: 400000 | H28: 2400
A29: 135362543637 | C29: 01/12/2025 | D29: Transacción | E29: 01/12/2025 | F29: 0,60 % | G29: 551528.92 | H29: 3309.17
A30: 135734903707 | C30: 03/12/2025 | D30: Transacción | E30: 03/12/2025 | F30: 0,60 % | G30: 11999 | H30: 71.99
A31: 136364441784 | C31: 03/12/2025 | D31: Transacción | E31: 03/12/2025 | F31: 0,60 % | G31: 4800 | H31: 28.8
A32: 136366138324 | C32: 03/12/2025 | D32: Transacción | E32: 03/12/2025 | F32: 0,60 % | G32: 8200 | H32: 49.2
A33: 135748062571 | B33: Venta presencial | C33: 03/12/2025 | D33: Transacción | E33: 03/12/2025 | F33: 0,60 % | G33: 48300 | H33: 289.8
A34: 136373560516 | C34: 03/12/2025 | D34: Transacción | E34: 03/12/2025 | F34: 0,60 % | G34: 31000 | H34: 186
A35: 136374478166 | C35: 03/12/2025 | D35: Transacción | E35: 03/12/2025 | F35: 0,60 % | G35: 29800 | H35: 178.8
A36: 135754447275 | B36: Venta presencial | C36: 03/12/2025 | D36: Transacción | E36: 03/12/2025 | F36: 0,60 % | G36: 11999 | H36: 71.99
A37: 135754874311 | B37: Venta presencial | C37: 03/12/2025 | D37: Transacción | E37: 03/12/2025 | F37: 0,60 % | G37: 50500 | H37: 303
A38: 135738371583 | B38: Venta presencial | C38: 03/12/2025 | D38: Transacción | E38: 03/12/2025 | F38: 0,60 % | G38: 25900 | H38: 155.4
A39: 135739132419 | B39: Venta presencial | C39: 03/12/2025 | D39: Transacción | E39: 03/12/2025 | F39: 0,60 % | G39: 16599 | H39: 99.59
A40: 135757364099 | C40: 03/12/2025 | D40: Transacción | E40: 03/12/2025 | F40: 0,60 % | G40: 14600 | H40: 87.6
A41: 136379529420 | B41: Venta presencial | C41: 03/12/2025 | D41: Transacción | E41: 03/12/2025 | F41: 0,60 % | G41: 73500 | H41: 441
A42: 136380032928 | B42: Venta presencial | C42: 03/12/2025 | D42: Transacción | E42: 03/12/2025 | F42: 0,60 % | G42: 154897 | H42: 929.38
A43: 136380185164 | C43: 03/12/2025 | D43: Transacción | E43: 03/12/2025 | F43: 0,60 % | G43: 50400 | H43: 302.4
A44: 135759480719 | C44: 03/12/2025 | D44: Transacción | E44: 03/12/2025 | F44: 0,60 % | G44: 23998 | H44: 143.99
A45: 135759329655 | B45: tips-135759480719 | C45: 03/12/2025 | D45: Transacción | E45: 03/12/2025 | F45: 0,60 % | G45: 1199 | H45: 7.19
A46: 135759894119 | C46: 03/12/2025 | D46: Transacción | E46: 03/12/2025 | F46: 0,60 % | G46: 35997 | H46: 215.98
A47: 135759931927 | C47: 03/12/2025 | D47: Transacción | E47: 04/12/2025 | F47: 0,60 % | G47: 8400 | H47: 50.4
A48: 135760275699 | C48: 03/12/2025 | D48: Transacción | E48: 04/12/2025 | F48: 0,60 % | G48: 63500 | H48: 381
A49: 136364596558 | B49: tips-136364441784 | C49: 03/12/2025 | D49: Transacción | E49: 03/12/2025 | F49: 0,60 % | G49: 240 | H49: 1.44
A50: 136364614462 | B50: Venta presencial | C50: 03/12/2025 | D50: Transacción | E50: 03/12/2025 | F50: 0,60 % | G50: 9600 | H50: 57.6
A51: 135762331375 | C51: 03/12/2025 | D51: Transacción | E51: 04/12/2025 | F51: 0,60 % | G51: 4900 | H51: 29.4
A52: 136383695972 | B52: Venta presencial | C52: 03/12/2025 | D52: Transacción | E52: 04/12/2025 | F52: 0,60 % | G52: 34498 | H52: 206.99
A53: 135762846725 | B53: tips-136383829954 | C53: 03/12/2025 | D53: Transacción | E53: 04/12/2025 | F53: 0,60 % | G53: 1530 | H53: 9.18
A54: 136384024660 | C54: 03/12/2025 | D54: Transacción | E54: 04/12/2025 | F54: 0,60 % | G54: 19400 | H54: 116.4
A55: 136384104070 | B55: Venta presencial | C55: 03/12/2025 | D55: Transacción | E55: 04/12/2025 | F55: 0,60 % | G55: 47600 | H55: 285.6
A56: 136370129344 | C56: 03/12/2025 | D56: Transacción | E56: 03/12/2025 | F56: 0,60 % | G56: 24300 | H56: 145.8
A57: 135749825345 | B57: Venta presencial | C57: 03/12/2025 | D57: Transacción | E57: 03/12/2025 | F57: 0,60 % | G57: 9600 | H57: 57.6
A58: 136374043234 | C58: 03/12/2025 | D58: Transacción | E58: 03/12/2025 | F58: 0,60 % | G58: 14500 | H58: 87
A59: 135753489523 | C59: 03/12/2025 | D59: Transacción | E59: 03/12/2025 | F59: 0,60 % | G59: 8800 | H59: 52.8
A60: 136374922986 | B60: tips-136374909026 | C60: 03/12/2025 | D60: Transacción | E60: 03/12/2025 | F60: 0,60 % | G60: 2889 | H60: 17.33
A61: 136374909026 | C61: 03/12/2025 | D61: Transacción | E61: 03/12/2025 | F61: 0,60 % | G61: 28898 | H61: 173.39
A62: 136376223468 | C62: 03/12/2025 | D62: Transacción | E62: 03/12/2025 | F62: 0,60 % | G62: 23998 | H62: 143.99
A63: 136377026240 | B63: Venta presencial | C63: 03/12/2025 | D63: Transacción | E63: 03/12/2025 | F63: 0,60 % | G63: 33900 | H63: 203.4
A64: 135757136427 | C64: 03/12/2025 | D64: Transacción | E64: 03/12/2025 | F64: 0,60 % | G64: 4800 | H64: 28.8
A65: 135757391225 | C65: 03/12/2025 | D65: Transacción | E65: 03/12/2025 | F65: 0,60 % | G65: 109000 | H65: 654
A66: 136380675948 | C66: 03/12/2025 | D66: Transacción | E66: 03/12/2025 | F66: 0,60 % | G66: 69399 | H66: 416.39
A67: 136381321286 | C67: 03/12/2025 | D67: Transacción | E67: 04/12/2025 | F67: 0,60 % | G67: 10100 | H67: 60.6
A68: 135760346847 | C68: 03/12/2025 | D68: Transacción | E68: 04/12/2025 | F68: 0,60 % | G68: 11999 | H68: 71.99
A69: 136382002426 | C69: 03/12/2025 | D69: Transacción | E69: 04/12/2025 | F69: 0,60 % | G69: 53700 | H69: 322.2
A70: 136383829954 | C70: 03/12/2025 | D70: Transacción | E70: 04/12/2025 | F70: 0,60 % | G70: 30600 | H70: 183.6
A71: 135763446201 | C71: 03/12/2025 | D71: Transacción | E71: 04/12/2025 | F71: 0,60 % | G71: 21200 | H71: 127.2
A72: 135877734691 | B72: Venta presencial | C72: 04/12/2025 | D72: Transacción | E72: 04/12/2025 | F72: 0,60 % | G72: 14700 | H72: 88.2
A73: 136505473782 | B73: tips-136505580672 | C73: 04/12/2025 | D73: Transacción | E73: 04/12/2025 | F73: 0,60 % | G73: 2820 | H73: 16.92
A74: 136507926506 | B74: Venta presencial | C74: 04/12/2025 | D74: Transacción | E74: 04/12/2025 | F74: 0,60 % | G74: 9800 | H74: 58.8
A75: 135887589531 | B75: Venta presencial | C75: 04/12/2025 | D75: Transacción | E75: 04/12/2025 | F75: 0,60 % | G75: 8400 | H75: 50.4
A76: 136521246224 | B76: Venta presencial | C76: 04/12/2025 | D76: Transacción | E76: 04/12/2025 | F76: 0,60 % | G76: 22700 | H76: 136.2
A77: 135899858747 | B77: Venta presencial | C77: 04/12/2025 | D77: Transacción | E77: 04/12/2025 | F77: 0,60 % | G77: 13600 | H77: 81.6
A78: 136505580672 | C78: 04/12/2025 | D78: Transacción | E78: 04/12/2025 | F78: 0,60 % | G78: 28200 | H78: 169.2
A79: 135884884887 | B79: Venta presencial | C79: 04/12/2025 | D79: Transacción | E79: 04/12/2025 | F79: 0,60 % | G79: 30700 | H79: 184.2
A80: 135902991043 | C80: 04/12/2025 | D80: Transacción | E80: 04/12/2025 | F80: 0,60 % | G80: 14400 | H80: 86.4
A81: 135903079939 | C81: 04/12/2025 | D81: Transacción | E81: 04/12/2025 | F81: 0,60 % | G81: 42300 | H81: 253.8
A82: 135903824609 | C82: 04/12/2025 | D82: Transacción | E82: 04/12/2025 | F82: 0,60 % | G82: 32000 | H82: 192
A83: 135903962267 | C83: 04/12/2025 | D83: Transacción | E83: 04/12/2025 | F83: 0,60 % | G83: 4000 | H83: 24
A84: 135903889629 | B84: tips-135903962267 | C84: 04/12/2025 | D84: Transacción | E84: 04/12/2025 | F84: 0,60 % | G84: 200 | H84: 1.2
A85: 135903977575 | C85: 04/12/2025 | D85: Transacción | E85: 04/12/2025 | F85: 0,60 % | G85: 11000 | H85: 66
A86: 135904176073 | C86: 04/12/2025 | D86: Transacción | E86: 04/12/2025 | F86: 0,60 % | G86: 4800 | H86: 28.8
A87: 136527051650 | C87: 04/12/2025 | D87: Transacción | E87: 04/12/2025 | F87: 0,60 % | G87: 9600 | H87: 57.6
A88: 136528092580 | C88: 04/12/2025 | D88: Transacción | E88: 04/12/2025 | F88: 0,60 % | G88: 23000 | H88: 138
A89: 136528753792 | C89: 04/12/2025 | D89: Transacción | E89: 04/12/2025 | F89: 0,60 % | G89: 14900 | H89: 89.4
A90: 135889088143 | C90: 04/12/2025 | D90: Transacción | E90: 04/12/2025 | F90: 0,60 % | G90: 9900 | H90: 59.4
A91: 135888975597 | B91: tips-135889088143 | C91: 04/12/2025 | D91: Transacción | E91: 04/12/2025 | F91: 0,60 % | G91: 495 | H91: 2.97
A92: 136529368322 | C92: 04/12/2025 | D92: Transacción | E92: 04/12/2025 | F92: 0,60 % | G92: 16500 | H92: 99
A93: 136512148984 | C93: 04/12/2025 | D93: Transacción | E93: 04/12/2025 | F93: 0,60 % | G93: 9800 | H93: 58.8
A94: 136530047680 | C94: 04/12/2025 | D94: Transacción | E94: 04/12/2025 | F94: 0,60 % | G94: 56050 | H94: 336.3
A95: 135908897041 | C95: 04/12/2025 | D95: Transacción | E95: 05/12/2025 | F95: 0,60 % | G95: 47000 | H95: 282
A96: 136531346928 | B96: tips-135908897041 | C96: 04/12/2025 | D96: Transacción | E96: 05/12/2025 | F96: 0,60 % | G96: 2350 | H96: 14.1
A97: 135909210549 | C97: 04/12/2025 | D97: Transacción | E97: 05/12/2025 | F97: 0,60 % | G97: 42800 | H97: 256.8
A98: 136532271696 | B98: Venta presencial | C98: 04/12/2025 | D98: Transacción | E98: 05/12/2025 | F98: 0,60 % | G98: 28400 | H98: 170.4
A99: 135909801847 | C99: 04/12/2025 | D99: Transacción | E99: 05/12/2025 | F99: 0,60 % | G99: 24400 | H99: 146.4
A100: 136532968476 | B100: Venta presencial | C100: 04/12/2025 | D100: Transacción | E100: 05/12/2025 | F100: 0,60 % | G100: 185650 | H100: 1113.9
A101: 135910779181 | B101: Venta presencial | C101: 04/12/2025 | D101: Transacción | E101: 05/12/2025 | F101: 0,60 % | G101: 6100 | H101: 36.6
A102: 135910838031 | C102: 04/12/2025 | D102: Transacción | E102: 05/12/2025 | F102: 0,60 % | G102: 4500 | H102: 27
A103: 135911230541 | B103: Venta presencial | C103: 04/12/2025 | D103: Transacción | E103: 05/12/2025 | F103: 0,60 % | G103: 49900 | H103: 299.4
A104: 136535032914 | C104: 04/12/2025 | D104: Transacción | E104: 05/12/2025 | F104: 0,60 % | G104: 4900 | H104: 29.4
A105: 136535221070 | C105: 05/12/2025 | D105: Transacción | E105: 05/12/2025 | F105: 0,60 % | G105: 63800 | H105: 382.8
...

Sheet TP
A1: INITIAL_BALANCE | B1: CREDITS | C1: DEBITS | D1: FINAL_BALANCE
A2: 20952879 | B2: 37229764 | C2: -46195595 | D2: 11987048
A4: RELEASE_DATE | B4: TRANSACTION_TYPE | C4: REFERENCE_ID | D4: TRANSACTION_NET_AMOUNT | E4: PARTIAL_BALANCE | F4: VARIOS | G4: TRANSACTION_TOTAL_AMOUNT | H4: IDC COMPRAS | I4: SIRCUPA | J4: SIRTAC | K4: Gastos | L4: IDC | M4: MOV TOTAL
A5: 01-12-2025 | B5: Liquidación de dinero | C5: 135329078135 | D5: 19388.57 | E5: 20972268 | F5: COBRO | M5: =+D5-I5-J5-K5-L5 -> 19388.57
A6: 01-12-2025 | B6: Liquidación de dinero | C6: 135329349869 | D6: 37599.06 | E6: 21009867 | F6: COBRO | M6: =+D6-I6-J6-K6-L6 -> 37599.06
A7: 01-12-2025 | B7: Liquidación de dinero | C7: 135945633656 | D7: 8184.12 | E7: 21018051 | F7: COBRO | M7: =+D7-I7-J7-K7-L7 -> 8184.12
A8: 01-12-2025 | B8: Liquidación de dinero | C8: 135945997406 | D8: 12276.18 | E8: 21030327 | F8: COBRO | M8: =+D8-I8-J8-K8-L8 -> 12276.18
A9: 01-12-2025 | B9: Liquidación de dinero | C9: 135330440377 | D9: 55242.81 | E9: 21085570 | F9: COBRO | M9: =+D9-I9-J9-K9-L9 -> 55242.81
A10: 01-12-2025 | B10: Liquidación de dinero | C10: 135330988071 | D10: 47518.41 | E10: 21133088 | F10: COBRO | M10: =+D10-I10-J10-K10-L10 -> 47518.41
A11: 01-12-2025 | B11: Liquidación de dinero | C11: 135331302959 | D11: 16368.24 | E11: 21149456 | F11: COBRO | M11: =+D11-I11-J11-K11-L11 -> 16368.24
A12: 01-12-2025 | B12: Liquidación de dinero | C12: 135949105672 | D12: 9840.43 | E12: 21159297 | F12: COBRO | M12: =+D12-I12-J12-K12-L12 -> 9840.43
A13: 01-12-2025 | B13: Impuesto por extracción | C13: 135362543637 | D13: -3309.17 | E13: 20202059 | F13: IDC | G13: =+D13/0.006 -> -551528.33 | M13: =+D13 -> -3309.17
A14: 01-12-2025 | B14: Transferencia enviada BASSO REPRESENT SRL | C14: 135362543637 | D14: -551528.92 | E14: 20205368 | F14: PAGO PROVEEDOR | G14: =+D14/1.006 -> -548239.48 | M14: =+D14 -> -551528.92
A15: 01-12-2025 | B15: Impuesto por extracción | C15: 135979554276 | D15: -2400 | E15: 20756897 | F15: IDC | G15: =+D15/0.006 -> -400000 | M15: =+D15 -> -2400
A16: 01-12-2025 | B16: Transferencia enviada EMBOTELLADORA DEL ATLANTICO S.A. | C16: 135979554276 | D16: -400000 | E16: 20759297 | F16: PAGO PROVEEDOR | M16: =+D16 -> -400000
A17: 03-12-2025 | B17: Liquidación de dinero | C17: 135734903707 | D17: 11690.63 | E17: 20213749 | F17: COBRO | M17: =+D17-I17-J17-K17-L17 -> 11690.63
A18: 03-12-2025 | B18: Liquidación de dinero | C18: 135738371583 | D18: 24467.73 | E18: 20238217 | F18: COBRO | M18: =+D18-I18-J18-K18-L18 -> 24467.73
A19: 03-12-2025 | B19: Liquidación de dinero | C19: 135739132419 | D19: 15681.08 | E19: 20253898 | F19: COBRO | M19: =+D19-I19-J19-K19-L19 -> 15681.08
A20: 03-12-2025 | B20: Liquidación de dinero | C20: 136364441784 | D20: 4357.92 | E20: 20258256 | F20: COBRO | M20: =+D20-I20-J20-K20-L20 -> 4357.92
A21: 03-12-2025 | B21: Transferencia recibida Juan Felipe Folmer Dondena | C21: 136364596558 | D21: 234.96 | E21: 20258491 | F21: COBRO | M21: =+D21-I21-J21-K21-L21 -> 234.96
A22: 03-12-2025 | B22: Liquidación de dinero | C22: 136364614462 | D22: 9069.12 | E22: 20267560 | F22: COBRO | M22: =+D22-I22-J22-K22-L22 -> 9069.12
A23: 03-12-2025 | B23: Liquidación de dinero | C23: 136366138324 | D23: 7989.26 | E23: 20275549 | F23: COBRO | M23: =+D23-I23-J23-K23-L23 -> 7989.26
A24: 03-12-2025 | B24: Liquidación de dinero | C24: 135748062571 | D24: 45629.01 | E24: 20321178 | F24: COBRO | M24: =+D24-I24-J24-K24-L24 -> 45629.01
A25: 03-12-2025 | B25: Liquidación de dinero | C25: 136370129344 | D25: 23675.49 | E25: 20344854 | F25: COBRO | M25: =+D25-I25-J25-K25-L25 -> 23675.49
A26: 03-12-2025 | B26: Liquidación de dinero | C26: 135749825345 | D26: 9069.12 | E26: 20353923 | F26: COBRO | M26: =+D26-I26-J26-K26-L26 -> 9069.12
A27: 03-12-2025 | B27: Liquidación de dinero | C27: 136373560516 | D27: 30203.3 | E27: 20384126 | F27: COBRO | M27: =+D27-I27-J27-K27-L27 -> 30203.3
A28: 03-12-2025 | B28: Liquidación de dinero | C28: 136374043234 | D28: 14127.35 | E28: 20398254 | F28: COBRO | M28: =+D28-I28-J28-K28-L28 -> 14127.35
... A181: 06-12-2025 | B181: Liquidación de dinero | C181: 136086178973 | D181: 22896.05 | E181: 24251857 | F181: COBRO | M181: =+D181-I181-J181-K181-L181 -> 22896.05
A182: 06-12-2025 | B182: Pago Mercado Libre S R L - MLA MP | C182: 136154630259 | D182: -30763.36 | E182: 24221093 | F182: PAGO PROVEEDOR | G182: =+D182/1.006 -> -30579.881 | M182: =+D182-I182-J182-K182-L182 -> -30763.36
A183: 06-12-2025 | B183: Liquidación de dinero | C183: 136182589345 | D183: 14.17 | E183: 24221108 | F183: COBRO | M183: =+D183-I183-J183-K183-L183 -> 14.17
A184: 06-12-2025 | B184: Liquidación de dinero cancelada Venta cancelada | C184: 136182589345 | D184: -14.17 | E184: 24221093 | F184: COBRO | M184: =+D184-I184-J184-K184-L184 -> -14.17
A185: 06-12-2025 | B185: Liquidación de dinero | C185: 136818536256 | D185: 7935.48 | E185: 24229029 | F185: COBRO | M185: =+D185-I185-J185-K185-L185 -> 7935.48
A186: 06-12-2025 | B186: Liquidación de dinero | C186: 136197610809 | D186: 9353.28 | E186: 24238382 | F186: COBRO | M186: =+D186-I186-J186-K186-L186 -> 9353.28
A187: 06-12-2025 | B187: Liquidación de dinero | C187: 136199301371 | D187: 12081.32 | E187: 24250463 | F187: COBRO | M187: =+D187-I187-J187-K187-L187 -> 12081.32
A188: 06-12-2025 | B188: Liquidación de dinero | C188: 136825810056 | D188: 13225.8 | E188: 24263689 | F188: COBRO | M188: =+D188-I188-J188-K188-L188 -> 13225.8
A189: 06-12-2025 | B189: Liquidación de dinero | C189: 136203880503 | D189: 22483.86 | E189: 24286173 | F189: COBRO | M189: =+D189-I189-J189-K189-L189 -> 22483.86
A190: 06-12-2025 | B190: Liquidación de dinero | C190: 136204861051 | D190: 19778.29 | E190: 24305951 | F190: COBRO | M190: =+D190-I190-J190-K190-L190 -> 19778.29
A191: 06-12-2025 | B191: Transferencia recibida Timoteo Nicolás Alcaraz | C191: 136829205946 | D191: 993.68 | E191: 24306945 | F191: COBRO | M191: =+D191-I191-J191-K191-L191 -> 993.68
A192: 06-12-2025 | B192: Liquidación de dinero | C192: 136206758325 | D192: 71905.68 | E192: 24378851 | F192: COBRO | M192: =+D192-I192-J192-K192-L192 -> 71905.68
A193: 06-12-2025 | B193: Liquidación de dinero | C193: 136206659707 | D193: 34879.94 | E193: 24413731 | F193: COBRO | M193: =+D193-I193-J193-K193-L193 -> 34879.94
A194: 06-12-2025 | B194: Liquidación de dinero | C194: 136830857486 | D194: 9548.14 | E194: 24423279 | F194: COBRO | M194: =+D194-I194-J194-K194-L194 -> 9548.14
... A352: 08-12-2025 | B352: Liquidación de dinero | C352: 136959788742 | D352: 9986.9 | E352: 28672072 | F352: COBRO | M352: =+D352-I352-J352-K352-L352 -> 9986.9
A353: 10-12-2025 | B353: Pago de servicio ARCA | C353: 136635567927 | D353: -2368604.7 | E353: 26303468 | F353: ARCA | G353: =+D353/1.006 -> -2354477.8 | M353: =+D353-I353-J353-K353-L353 -> -2368604.7
A354: 10-12-2025 | B354: Transferencia enviada Cerveza Tractor Sr | C354: 136642965749 | D354: -1000000 | E354: 22800468 | F354: RETIRO / PROV | G354: =+D354 -> -1000000 | M354: =+D354 -> -1000000
A355: 10-12-2025 | B355: Transferencia enviada Cerveza Tractor Sr | C355: 136642967981 | D355: -1000000 | E355: 19800468 | F355: RETIRO / PROV | G355: =+D355 -> -1000000 | M355: =+D355 -> -1000000
A356: 10-12-2025 | B356: Transferencia enviada Cerveza Tractor Sr | C356: 136643127123 | D356: -1000000 | E356: 24800468 | F356: RETIRO / PROV | G356: =+D356 -> -1000000 | M356: =+D356 -> -1000000
A357: 10-12-2025 | B357: Transferencia enviada Cerveza Tractor Sr | C357: 136643473817 | D357: -1000000 | E357: 17800468 | F357: RETIRO / PROV | G357: =+D357 -> -1000000 | M357: =+D357 -> -1000000
A358: 10-12-2025 | B358: Transferencia enviada Cerveza Tractor Sr | C358: 136643589881 | D358: -1000000 | E358: 16800468 | F358: RETIRO / PROV | G358: =+D358 -> -1000000 | M358: =+D358 -> -1000000
A359: 10-12-2025 | B359: Transferencia enviada Cerveza Tractor Sr | C359: 136643619197 | D359: -1000000 | E359: 20800468 | F359: RETIRO / PROV | G359: =+D359 -> -1000000 | M359: =+D359 -> -1000000
A360: 12-12-2025 | B360: Liquidación de dinero | C360: 137649717546 | D360: 9353.28 | E360: 12951149 | F360: COBRO | M360: =+D360-I360-J360-K360-L360 -> 9353.28
A361: 12-12-2025 | B361: Liquidación de dinero | C361: 137035785219 | D361: 25721.52 | E361: 12976871 | F361: COBRO | M361: =+D361-I361-J361-K361-L361 -> 25721.52
A362: 12-12-2025 | B362: Liquidación de dinero | C362: 137670538274 | D362: 3778.8 | E362: 12980650 | F362: COBRO | M362: =+D362-I362-J362-K362-L362 -> 3778.8
A363: 12-12-2025 | B363: Liquidación de dinero | C363: 137671009436 | D363: 18339.58 | E363: 12998989 | F363: COBRO | M363: =+D363-I363-J363-K363-L363 -> 18339.58
A364: 12-12-2025 | B364: Liquidación de dinero | C364: 137040182521 | D364: 9548.14 | E364: 13008537 | F364: COBRO | M364: =+D364-I364-J364-K364-L364 -> 9548.14
A365: 12-12-2025 | B365: Liquidación de dinero | C365: 137673449798 | D365: 9069.12 | E365: 13017607 | F365: COBRO | M365: =+D365-I365-J365-K365-L365 -> 9069.12
A366: 12-12-2025 | B366: Liquidación de dinero | C366: 137042830597 | D366: 5265.82 | E366: 13022872 | F366: COBRO | M366: =+D366-I366-J366-K366-L366 -> 5265.82
A367: 12-12-2025 | B367: Liquidación de dinero | C367: 137676231468 | D367: 4676.64 | E367: 13027549 | F367: COBRO | M367: =+D367-I367-J367-K367-L367 -> 4676.64
A368: 12-12-2025 | B368: Liquidación de dinero | C368: 137677529088 | D368: 8897.42 | E368: 13036446 | F368: COBRO | M368: =+D368-I368-J368-K368-L368 -> 8897.42
A369: 12-12-2025 | B369: Liquidación de dinero | C369: 137044469955 | D369: 85887.34 | E369: 13122334 | F369: COBRO | M369: =+D369-I369-J369-K369-L369 -> 85887.34
A370: 12-12-2025 | B370: Liquidación de dinero | C370: 137044959869 | D370: 62160.34 | E370: 13184494 | F370: COBRO | M370: =+D370-I370-J370-K370-L370 -> 62160.34
A371: 12-12-2025 | B371: Liquidación de dinero | C371: 137678741226 | D371: 7557.6 | E371: 13192052 | F371: COBRO | M371: =+D371-I371-J371-K371-L371 -> 7557.6
... A1565: 23-12-2025 | B1565: Liquidación de dinero cancelada Venta cancelada | C1565: 139273670082 | D1565: -37032.24 | E1565: 16076637 | F1565: COBRO | M1565: =+D1565-I1565-J1565-K1565-L1565 -> -37032.24
A1566: 10-12-2025 | B1566: Transferencia enviada Cerveza Tractor Sr | C1566: 136643701755 | D1566: -1000000 | E1566: 15800468 | F1566: RETIRO / PROV | G1566: =+D1566 -> -1000000 | M1566: =+D1566 -> -1000000
A1567: 10-12-2025 | B1567: Transferencia enviada Cerveza Tractor Sr | C1567: 136644102125 | D1567: -1000000 | E1567: 23800468 | F1567: RETIRO / PROV | G1567: =+D1567 -> -1000000 | M1567: =+D1567 -> -1000000
A1568: 31-12-2025 | B1568: Transferencia recibida Franco Nicolas Moreno Bordet | C1568: 139480876737 | D1568: 489.5 | E1568: 10930874 | F1568: COBRO | M1568: =+D1568-I1568-J1568-K1568-L1568 -> 489.5
A1569: 10-12-2025 | B1569: Transferencia enviada Cerveza Tractor Sr | C1569: 136644141961 | D1569: -1000000 | E1569: 11800468 | F1569: RETIRO / PROV | G1569: =+D1569 -> -1000000 | M1569: =+D1569 -> -1000000
A1570: 10-12-2025 | B1570: Transferencia enviada Cerveza Tractor Sr | C1570: 136645101177 | D1570: -200000 | E1570: 9600467.6 | F1570: RETIRO / PROV | G1570: =+D1570 -> -200000 | M1570: =+D1570 -> -200000
A1571: 10-12-2025 | B1571: Impuesto por extracción | C1571: 137266249568 | D1571: -3000 | E1571: 25800468 | F1571: IDC | G1571: =+D1571/0.006 -> -500000 | M1571: =+D1571 -> -3000
A1572: 10-12-2025 | B1572: Transferencia enviada Embotelladora Del Atlantico S.a. | C1572: 137266249568 | D1572: -500000 | E1572: 25803468 | F1572: PAGO PROVEEDOR | M1572: =+D1572 -> -500000
A1573: 31-12-2025 | B1573: Transferencia recibida Nair Ayelen Chiappella Zarini | C1573: 140129960332 | D1573: 386.7 | E1573: 10958796 | F1573: COBRO | M1573: =+D1573-I1573-J1573-K1573-L1573 -> 386.7
A1574: 10-12-2025 | B1574: Transferencia enviada Cerveza Tractor Sr | C1574: 137272037684 | D1574: -1000000 | E1574: 21800468 | F1574: RETIRO / PROV | G1574: =+D1574 -> -1000000 | M1574: =+D1574 -> -1000000
A1575: 10-12-2025 | B1575: Transferencia enviada Cerveza Tractor Sr | C1575: 137272199862 | D1575: -1000000 | E1575: 18800468 | F1575: RETIRO / PROV | G1575: =+D1575 -> -1000000 | M1575: =+D1575 -> -1000000
A1576: 10-12-2025 | B1576: Transferencia enviada Cerveza Tractor Sr | C1576: 137272959812 | D1576: -1000000 | E1576: 14800468 | F1576: RETIRO / PROV | G1576: =+D1576 -> -1000000 | M1576: =+D1576 -> -1000000
A1577: 10-12-2025 | B1577: Transferencia enviada Cerveza Tractor Sr | C1577: 137273297958 | D1577: -1000000 | E1577: 10800468 | F1577: RETIRO / PROV | G1577: =+D1577 -> -1000000 | M1577: =+D1577 -> -1000000
A1578: 10-12-2025 | B1578: Transferencia enviada Cerveza Tractor Sr | C1578: 137273876874 | D1578: -1000000 | E1578: 12800468 | F1578: RETIRO / PROV | G1578: =+D1578 -> -1000000 | M1578: =+D1578 -> -1000000
A1579: 31-12-2025 | B1579: Transferencia recibida Alexis Maximiliano Dominguez | C1579: 140131190404 | D1579: 2364.28 | E1579: 11046274 | F1579: COBRO | M1579: =+D1579-I1579-J1579-K1579-L1579 -> 2364.28
A1580: 10-12-2025 | B1580: Transferencia enviada Cerveza Tractor Sr | C1580: 137273884824 | D1580: -1000000 | E1580: 13800468 | F1580: RETIRO / PROV | G1580: =+D1580 -> -1000000 | M1580: =+D1580 -> -1000000
A1581: 10-12-2025 | B1581: Transferencia enviada Cerveza Tractor Sr | C1581: 137273929588 | D1581: -1000000 | E1581: 9800467.6 | F1581: RETIRO / PROV | G1581: =+D1581 -> -1000000 | M1581: =+D1581 -> -1000000
A1582: 12-12-2025 | B1582: Compra de Kit De Internet Via Satélite Starlink Mini Mercado Libre | C1582: 137611435372 | D1582: -144652.33 | E1582: 12987065 | F1582: PAGO PROVEEDOR | G1582: =+D1582/1.006 -> -143789.59 | M1582: =+D1582-I1582-J1582-K1582-L1582 -> -144652.33
A1583: 12-12-2025 | B1583: Pago MERCADOPAGO POINT AR | C1583: 137621114436 | D1583: -45268.99 | E1583: 12941796 | F1583: PAGO PROVEEDOR | G1583: =+D1583/1.006 -> -44998.996 | M1583: =+D1583-I1583-J1583-K1583-L1583 -> -45268.99
A1584: 17-12-2025 | B1584: Impuesto por extracción | C1584: 137625617225 | D1584: -1800 | E1584: 17348924 | F1584: IDC | G1584: =+D1584/0.006 -> -300000 | M1584: =+D1584 -> -1800
A1585: 17-12-2025 | B1585: Transferencia enviada Embotelladora Del Atlantico S.a. | C1585: 137625617225 | D1585: -300000 | E1585: 17350724 | F1585: PAGO PROVEEDOR | M1585: =+D1585 -> -300000
A1586: 17-12-2025 | B1586: Transferencia enviada Norberto David Dolcet | C1586: 137628567805 | D1586: -366988.8 | E1586: 16981935 | F1586: PAGO PROVEEDOR | G1586: =+D1586/1.006 -> -364800 | M1586: =+D1586-I1586-J1586-K1586-L1586 -> -366988.8
A1587: 17-12-2025 | B1587: Transferencia enviada Cerveza Tractor Sr | C1587: 137647504691 | D1587: -3200000 | E1587: 13781935 | F1587: RETIRO / PROV | G1587: =+D1587 -> -3200000 | M1587: =+D1587 -> -3200000
A1588: 17-12-2025 | B1588: Compra Mercado Libre | C1588: 137676769397 | D1588: -89507.84 | E1588: 13692428 | F1588: PAGO PROVEEDOR | G1588: =+D1588/1.006 -> -88973.996 | M1588: =+D1588-I1588-J1588-K1588-L1588 -> -89507.84
A1589: 19-12-2025 | B1589: Impuesto por extracción | C1589: 137934058475 | D1589: -3084.42 | E1589: 16851886 | F1589: IDC | G1589: =+D1589/0.006 -> -514070 | M1589: =+D1589 -> -3084.42
A1590: 19-12-2025 | B1590: Transferencia enviada Municipalidad De Concepcion Del Uru | C1590: 137934058475 | D1590: -514069.75 | E1590: 16854971 | F1590: PAGO PROVEEDOR | M1590: =+D1590 -> -514069.75
A1591: 31-12-2025 | B1591: Transferencia recibida Nair Ayelen Chiappella Zarini | C1591: 139485224387 | D1591: 773.41 | E1591: 11211936 | F1591: COBRO | M1591: =+D1591-I1591-J1591-K1591-L1591 -> 773.41
A1592: 19-12-2025 | B1592: Transferencia enviada Cerveza Tractor Sr | C1592: 137938761795 | D1592: -2000000 | E1592: 10851886 | F1592: RETIRO / PROV | G1592: =+D1592 -> -2000000 | M1592: =+D1592 -> -2000000
A1593: 19-12-2025 | B1593: Impuesto por extracción | C1593: 138016711113 | D1593: -2400 | E1593: 10449486 | F1593: IDC | G1593: =+D1593/0.006 -> -400000 | M1593: =+D1593 -> -2400
A1594: 19-12-2025 | B1594: Transferencia enviada Embotelladora Del Atlantico S.a. | C1594: 138016711113 | D1594: -400000 | E1594: 10451886 | F1594: PAGO PROVEEDOR | M1594: =+D1594 -> -400000
A1595: 17-12-2025 | B1595: Compra de Epitrónica Pack 100 Rollos Papel Térmico 80x50 48grs Ticket, Comandera, ... | C1595: 138355746802 | D1595: -118708 | E1595: 13573720 | F1595: PAGO PROVEEDOR | G1595: =+D1595/1.006 -> -118000 | M1595: =+D1595-I1595-J1595-K1595-L1595 -> -118708
A1596: 31-12-2025 | B1596: Transferencia recibida Franco Nicolas Moreno Bordet | C1596: 139485730265 | D1596: 724.46 | E1596: 11273338 | F1596: COBRO | M1596: =+D1596-I1596-J1596-K1596-L1596 -> 724.46
A1597: 22-12-2025 | B1597: Pago de servicio ARCA | C1597: 138371810153 | D1597: -716612.4 | E1597: 16030590 | F1597: ARCA | G1597: =+D1597/1.006 -> -712338.37 | M1597: =+D1597-I1597-J1597-K1597-L1597 -> -716612.4
A1598: 19-12-2025 | B1598: Transferencia enviada Cerveza Tractor Sr | C1598: 138579078470 | D1598: -2000000 | E1598: 12851886 | F1598: RETIRO / PROV | G1598: =+D1598 -> -2000000 | M1598: =+D1598 -> -2000000
A1599: 19-12-2025 | B1599: Transferencia enviada Cerveza Tractor Sr | C1599: 138579090174 | D1599: -2000000 | E1599: 14851886 | F1599: RETIRO / PROV | G1599: =+D1599 -> -2000000 | M1599: =+D1599 -> -2000000
A1600: 20-12-2025 | B1600: Pago RIO URUGUAY SEGUROS | C1600: 138781228844 | D1600: -66827.57 | E1600: 12611533 | F1600: PAGO PROVEEDOR | G1600: =+D1600/1.006 -> -66428.996 | M1600: =+D1600-I1600-J1600-K1600-L1600 -> -66827.57
A1601: 31-12-2025 | B1601: Transferencia recibida Micaela Benitez CM | C1601: 140133811442 | D1601: 719.56 | E1601: 11440750 | F1601: COBRO | M1601: =+D1601-I1601-J1601-K1601-L1601 -> 719.56
A1602: 26-12-2025 | B1602: Pago de servicio ARCA | C1602: 138873529219 | D1602: -5960492.9 | E1602: 12063893 | F1602: ARCA | G1602: =+D1602/1.006 -> -5924943.3 | M1602: =+D1602-I1602-J1602-K1602-L1602 -> -5960492.9
A1603: 22-12-2025 | B1603: Impuesto por extracción | C1603: 139008795034 | D1603: -3000 | E1603: 16747202 | F1603: IDC | G1603: =+D1603/0.006 -> -500000 | M1603: =+D1603 -> -3000
...
