Workbook

Sheet sheet0
A1: INITIAL_BALANCE | B1: CREDITS | C1: DEBITS | D1: FINAL_BALANCE
A2: 10882609 | B2: 36455185 | C2: -36709248 | D2: 10628546
A4: RELEASE_DATE | B4: TRANSACTION_TYPE | C4: REFERENCE_ID | D4: TRANSACTION_NET_AMOUNT | E4: PARTIAL_BALANCE | F4: VARIOS | G4: TRANSACTION_TOTAL_AMOUNT | H4: IDC COMPRAS | I4: SIRCUPA | J4: SIRTAC | K4: Gastos | L4: IDC | M4: MOV TOTAL | O4: OBSERV
A5: 01-10-2025 | B5: Liquidación de dinero | C5: 127694553001 | D5: 8502.3 | E5: 10891111 | F5: COBRO | I5: =-IFERROR(VLOOKUP(C5,SIRCUPA!$A$21:$H$221,8,0),0) -> 0 | J5: =-IFERROR(VLOOKUP(C5,SIRTAC!$A$16:$H$1458,8,0),0) -> -90 | K5: =-IFERROR(VLOOKUP(C5,Gastos!$A$9:$J$1451,10,0),0) -> -353.7 | L5: =-IFERROR(VLOOKUP(C5,IDC!$A$20:$H$1763,8,0),0) -> -54 | M5: =+D5-I5-J5-K5-L5 -> 9000
A6: 01-10-2025 | B6: Liquidación de dinero | C6: 127706300651 | D6: 7794.4 | E6: 10898905 | F6: COBRO | I6: =-IFERROR(VLOOKUP(C6,SIRCUPA!$A$21:$H$221,8,0),0) -> 0 | J6: =-IFERROR(VLOOKUP(C6,SIRTAC!$A$16:$H$1458,8,0),0) -> -80 | K6: =-IFERROR(VLOOKUP(C6,Gastos!$A$9:$J$1451,10,0),0) -> -77.6 | L6: =-IFERROR(VLOOKUP(C6,IDC!$A$20:$H$1763,8,0),0) -> -48 | M6: =+D6-I6-J6-K6-L6 -> 8000
A7: 01-10-2025 | B7: Liquidación de dinero | C7: 127707346037 | D7: 8768.7 | E7: 10907674 | F7: COBRO | I7: =-IFERROR(VLOOKUP(C7,SIRCUPA!$A$21:$H$221,8,0),0) -> 0 | J7: =-IFERROR(VLOOKUP(C7,SIRTAC!$A$16:$H$1458,8,0),0) -> -90 | K7: =-IFERROR(VLOOKUP(C7,Gastos!$A$9:$J$1451,10,0),0) -> -87.3 | L7: =-IFERROR(VLOOKUP(C7,IDC!$A$20:$H$1763,8,0),0) -> -54 | M7: =+D7-I7-J7-K7-L7 -> 9000
A8: 01-10-2025 | B8: Liquidación de dinero | C8: 128274716662 | D8: 10912.16 | E8: 10918586 | F8: COBRO | I8: =-IFERROR(VLOOKUP(C8,SIRCUPA!$A$21:$H$221,8,0),0) -> 0 | J8: =-IFERROR(VLOOKUP(C8,SIRTAC!$A$16:$H$1458,8,0),0) -> -112 | K8: =-IFERROR(VLOOKUP(C8,Gastos!$A$9:$J$1451,10,0),0) -> -108.64 | L8: =-IFERROR(VLOOKUP(C8,IDC!$A$20:$H$1763,8,0),0) -> -67.2 | M8: =+D8-I8-J8-K8-L8 -> 11200
A9: 01-10-2025 | B9: Liquidación de dinero | C9: 128275855374 | D9: 44131.89 | E9: 10962718 | F9: COBRO | I9: =-IFERROR(VLOOKUP(C9,SIRCUPA!$A$21:$H$221,8,0),0) -> 0 | J9: =-IFERROR(VLOOKUP(C9,SIRTAC!$A$16:$H$1458,8,0),0) -> -452.96 | K9: =-IFERROR(VLOOKUP(C9,Gastos!$A$9:$J$1451,10,0),0) -> -439.37 | L9: =-IFERROR(VLOOKUP(C9,IDC!$A$20:$H$1763,8,0),0) -> -271.78 | M9: =+D9-I9-J9-K9-L9 -> 45296
A10: 01-10-2025 | B10: Transferencia recibida Rodolfo Juan Saldarelli | C10: 128275829832 | D10: 2216.46 | E10: 10964934 | F10: COBRO | I10: =-IFERROR(VLOOKUP(C10,SIRCUPA!$A$21:$H$221,8,0),0) -> -33.96 | J10: =-IFERROR(VLOOKUP(C10,SIRTAC!$A$16:$H$1458,8,0),0) -> 0 | K10: =-IFERROR(VLOOKUP(C10,Gastos!$A$9:$J$1451,10,0),0) -> 0 | L10: =-IFERROR(VLOOKUP(C10,IDC!$A$20:$H$1763,8,0),0) -> -13.58 | M10: =+D10-I10-J10-K10-L10 -> 2264
A11: 01-10-2025 | B11: Liquidación de dinero | C11: 127713602167 | D11: 487.15 | E11: 10965422 | F11: COBRO | I11: =-IFERROR(VLOOKUP(C11,SIRCUPA!$A$21:$H$221,8,0),0) -> 0 | J11: =-IFERROR(VLOOKUP(C11,SIRTAC!$A$16:$H$1458,8,0),0) -> -5 | K11: =-IFERROR(VLOOKUP(C11,Gastos!$A$9:$J$1451,10,0),0) -> -4.85 | L11: =-IFERROR(VLOOKUP(C11,IDC!$A$20:$H$1763,8,0),0) -> -3 | M11: =+D11-I11-J11-K11-L11 -> 500
A12: 01-10-2025 | B12: Liquidación de dinero | C12: 127715107443 | D12: 30103.92 | E12: 10995525 | F12: COBRO | I12: =-IFERROR(VLOOKUP(C12,SIRCUPA!$A$21:$H$221,8,0),0) -> 0 | J12: =-IFERROR(VLOOKUP(C12,SIRTAC!$A$16:$H$1458,8,0),0) -> -308.98 | K12: =-IFERROR(VLOOKUP(C12,Gastos!$A$9:$J$1451,10,0),0) -> -299.71 | L12: =-IFERROR(VLOOKUP(C12,IDC!$A$20:$H$1763,8,0),0) -> -185.39 | M12: =+D12-I12-J12-K12-L12 -> 30898
A13: 01-10-2025 | B13: Liquidación de dinero | C13: 127715769581 | D13: 38704.13 | E13: 11034230 | F13: COBRO | I13: =-IFERROR(VLOOKUP(C13,SIRCUPA!$A$21:$H$221,8,0),0) -> 0 | J13: =-IFERROR(VLOOKUP(C13,SIRTAC!$A$16:$H$1458,8,0),0) -> -399.96 | K13: =-IFERROR(VLOOKUP(C13,Gastos!$A$9:$J$1451,10,0),0) -> -651.93 | L13: =-IFERROR(VLOOKUP(C13,IDC!$A$20:$H$1763,8,0),0) -> -239.98 | M13: =+D13-I13-J13-K13-L13 -> 39996
A14: 01-10-2025 | B14: Liquidación de dinero | C14: 128281546618 | D14: 25721.52 | E14: 11059951 | F14: COBRO | I14: =-IFERROR(VLOOKUP(C14,SIRCUPA!$A$21:$H$221,8,0),0) -> 0 | J14: =-IFERROR(VLOOKUP(C14,SIRTAC!$A$16:$H$1458,8,0),0) -> -264 | K14: =-IFERROR(VLOOKUP(C14,Gastos!$A$9:$J$1451,10,0),0) -> -256.08 | L14: =-IFERROR(VLOOKUP(C14,IDC!$A$20:$H$1763,8,0),0) -> -158.4 | M14: =+D14-I14-J14-K14-L14 -> 26400
A15: 01-10-2025 | B15: Transferencia recibida Nahuel Zalazar Miño | C15: 128281517156 | D15: 2584.56 | E15: 11062536 | F15: COBRO | I15: =-IFERROR(VLOOKUP(C15,SIRCUPA!$A$21:$H$221,8,0),0) -> -39.6 | J15: =-IFERROR(VLOOKUP(C15,SIRTAC!$A$16:$H$1458,8,0),0) -> 0 | K15: =-IFERROR(VLOOKUP(C15,Gastos!$A$9:$J$1451,10,0),0) -> 0 | L15: =-IFERROR(VLOOKUP(C15,IDC!$A$20:$H$1763,8,0),0) -> -15.84 | M15: =+D15-I15-J15-K15-L15 -> 2640
A16: 01-10-2025 | B16: Liquidación de dinero | C16: 128281806306 | D16: 12665.9 | E16: 11075202 | F16: COBRO | I16: =-IFERROR(VLOOKUP(C16,SIRCUPA!$A$21:$H$221,8,0),0) -> 0 | J16: =-IFERROR(VLOOKUP(C16,SIRTAC!$A$16:$H$1458,8,0),0) -> -130 | K16: =-IFERROR(VLOOKUP(C16,Gastos!$A$9:$J$1451,10,0),0) -> -126.1 | L16: =-IFERROR(VLOOKUP(C16,IDC!$A$20:$H$1763,8,0),0) -> -78 | M16: =+D16-I16-J16-K16-L16 -> 13000
... A32: 02-10-2025 | B32: Liquidación de dinero | C32: 127724766231 | D32: 4354.65 | E32: 11437556 | F32: COBRO | I32: =-IFERROR(VLOOKUP(C32,SIRCUPA!$A$21:$H$221,8,0),0) -> 0 | J32: =-IFERROR(VLOOKUP(C32,SIRTAC!$A$16:$H$1458,8,0),0) -> -45 | K32: =-IFERROR(VLOOKUP(C32,Gastos!$A$9:$J$1451,10,0),0) -> -73.35 | L32: =-IFERROR(VLOOKUP(C32,IDC!$A$20:$H$1763,8,0),0) -> -27 | M32: =+D32-I32-J32-K32-L32 -> 4500
A33: 11-10-2025 | B33: Débito por deuda Facturas vencidas de Mercado Libre | C33: 2430883946 | D33: -30049.69 | E33: 11485499 | F33: PAGO PROVEEDOR | G33: =+D33/1.006 -> -29870.467 | H33: =+D33-G33 -> -179.2228 | I33: =-IFERROR(VLOOKUP(C33,SIRCUPA!$A$21:$H$221,8,0),0) -> 0 | J33: =-IFERROR(VLOOKUP(C33,SIRTAC!$A$16:$H$1458,8,0),0) -> 0 | K33: =-IFERROR(VLOOKUP(C33,Gastos!$A$9:$J$1451,10,0),0) -> 0 | L33: =+D33-G33 -> -179.2228 | M33: =+D33-I33-J33-K33-L33 -> -29870.467
A34: 02-10-2025 | B34: Impuesto por extracción | C34: 127751261829 | D34: -1759.76 | E34: 10947597 | F34: IDC | G34: =+D34/0.006 -> -293293.33 | I34: =-IFERROR(VLOOKUP(C34,SIRCUPA!$A$21:$H$221,8,0),0) -> 0 | J34: =-IFERROR(VLOOKUP(C34,SIRTAC!$A$16:$H$1458,8,0),0) -> 0 | K34: =-IFERROR(VLOOKUP(C34,Gastos!$A$9:$J$1451,10,0),0) -> 0 | M34: =+D34 -> -1759.76
A35: 02-10-2025 | B35: Transferencia enviada EMBOTELLADORA DEL ATLANTICO SA | C35: 127751261829 | D35: -293293.89 | E35: 10949357 | F35: PAGO PROVEEDOR | G35: =+D35/1.006 -> -291544.62 | H35: =+D35-G35 -> -1749.2677 | I35: =-IFERROR(VLOOKUP(C35,SIRCUPA!$A$21:$H$221,8,0),0) -> 0 | J35: =-IFERROR(VLOOKUP(C35,SIRTAC!$A$16:$H$1458,8,0),0) -> 0 | K35: =-IFERROR(VLOOKUP(C35,Gastos!$A$9:$J$1451,10,0),0) -> 0 | L35: =-IFERROR(VLOOKUP(C35,IDC!$A$20:$H$1763,8,0),0) -> -1759.76 | M35: =+D35 -> -293293.89
A36: 02-10-2025 | B36: Compra Mercado Libre | C36: 127758769693 | D36: -84292.74 | E36: 10863304 | F36: PAGO PROVEEDOR | G36: =+D36/1.006 -> -83790 | H36: =+D36-G36 -> -502.74 | I36: =-IFERROR(VLOOKUP(C36,SIRCUPA!$A$21:$H$221,8,0),0) -> 0 | J36: =-IFERROR(VLOOKUP(C36,SIRTAC!$A$16:$H$1458,8,0),0) -> 0 | K36: =-IFERROR(VLOOKUP(C36,Gastos!$A$9:$J$1451,10,0),0) -> 0 | L36: =-IFERROR(VLOOKUP(C36,IDC!$A$20:$H$1763,8,0),0) -> -502.74 | M36: =+D36-I36-J36-K36-L36 -> -83790 | O36: GALANSINO JORGE ALBERTO X $ 88200
A37: 02-10-2025 | B37: Impuesto por extracción | C37: 127775080827 | D37: -1306.01 | E37: 10385056 | F37: IDC | G37: =+D37/0.006 -> -217668.33 | I37: =-IFERROR(VLOOKUP(C37,SIRCUPA!$A$21:$H$221,8,0),0) -> 0 | J37: =-IFERROR(VLOOKUP(C37,SIRTAC!$A$16:$H$1458,8,0),0) -> 0 | K37: =-IFERROR(VLOOKUP(C37,Gastos!$A$9:$J$1451,10,0),0) -> 0 | M37: =+D37 -> -1306.01
A38: 02-10-2025 | B38: Transferencia enviada FRUVECO S R L | C38: 127775080827 | D38: -217667.97 | E38: 10386362 | F38: PAGO PROVEEDOR | G38: =+D38/1.006 -> -216369.75 | H38: =+D38-G38 -> -1298.2185 | I38: =-IFERROR(VLOOKUP(C38,SIRCUPA!$A$21:$H$221,8,0),0) -> 0 | J38: =-IFERROR(VLOOKUP(C38,SIRTAC!$A$16:$H$1458,8,0),0) -> 0 | K38: =-IFERROR(VLOOKUP(C38,Gastos!$A$9:$J$1451,10,0),0) -> 0 | L38: =-IFERROR(VLOOKUP(C38,IDC!$A$20:$H$1763,8,0),0) -> -1306.01 | M38: =+D38 -> -217667.97
A39: 02-10-2025 | B39: Impuesto por extracción | C39: 127775364243 | D39: -1222.16 | E39: 10658388 | F39: IDC | G39: =+D39/0.006 -> -203693.33 | I39: =-IFERROR(VLOOKUP(C39,SIRCUPA!$A$21:$H$221,8,0),0) -> 0 | J39: =-IFERROR(VLOOKUP(C39,SIRTAC!$A$16:$H$1458,8,0),0) -> 0 | K39: =-IFERROR(VLOOKUP(C39,Gastos!$A$9:$J$1451,10,0),0) -> 0 | M39: =+D39 -> -1222.16
A40: 02-10-2025 | B40: Transferencia enviada FRUVECO S R L | C40: 127775364243 | D40: -203693.9 | E40: 10659611 | F40: PAGO PROVEEDOR | G40: =+D40/1.006 -> -202479.03 | H40: =+D40-G40 -> -1214.8742 | I40: =-IFERROR(VLOOKUP(C40,SIRCUPA!$A$21:$H$221,8,0),0) -> 0 | J40: =-IFERROR(VLOOKUP(C40,SIRTAC!$A$16:$H$1458,8,0),0) -> 0 | K40: =-IFERROR(VLOOKUP(C40,Gastos!$A$9:$J$1451,10,0),0) -> 0 | L40: =-IFERROR(VLOOKUP(C40,IDC!$A$20:$H$1763,8,0),0) -> -1222.16 | M40: =+D40 -> -203693.9
A41: 06-10-2025 | B41: Transferencia enviada ERPEN JULIO C. Y PONZONI ANTONELLA P. SOCIEDAD SIMPLE | C41: 128258988637 | D41: -960111.31 | E41: 15917896 | F41: PAGO PROVEEDOR | G41: =+D41/1.006 -> -954385 | H41: =+D41-G41 -> -5726.31 | I41: =-IFERROR(VLOOKUP(C41,SIRCUPA!$A$21:$H$221,8,0),0) -> 0 | J41: =-IFERROR(VLOOKUP(C41,SIRTAC!$A$16:$H$1458,8,0),0) -> 0 | K41: =-IFERROR(VLOOKUP(C41,Gastos!$A$9:$J$1451,10,0),0) -> 0 | L41: =+D41-G41 -> -5726.31 | M41: =+D41-I41-J41-K41-L41 -> -954385
A42: 06-10-2025 | B42: Impuesto por extracción | C42: 128290347795 | D42: -9232.32 | E42: 13058558 | F42: IDC | G42: =+D42/0.006 -> -1538720 | I42: =-IFERROR(VLOOKUP(C42,SIRCUPA!$A$21:$H$221,8,0),0) -> 0 | J42: =-IFERROR(VLOOKUP(C42,SIRTAC!$A$16:$H$1458,8,0),0) -> 0 | K42: =-IFERROR(VLOOKUP(C42,Gastos!$A$9:$J$1451,10,0),0) -> 0 | M42: =+D42 -> -9232.32
A43: 06-10-2025 | B43: Transferencia enviada BACO DE LOS ANDES SA | C43: 128290347795 | D43: -1538720.7 | E43: 13067790 | F43: PAGO PROVEEDOR | G43: =+D43/1.006 -> -1529543.4 | H43: =+D43-G43 -> -9177.2606 | I43: =-IFERROR(VLOOKUP(C43,SIRCUPA!$A$21:$H$221,8,0),0) -> 0 | J43: =-IFERROR(VLOOKUP(C43,SIRTAC!$A$16:$H$1458,8,0),0) -> 0 | K43: =-IFERROR(VLOOKUP(C43,Gastos!$A$9:$J$1451,10,0),0) -> 0 | L43: =-IFERROR(VLOOKUP(C43,IDC!$A$20:$H$1763,8,0),0) -> -9232.32 | M43: =+D43 -> -1538720.7
A44: 02-10-2025 | B44: Liquidación de dinero | C44: 127826757701 | D44: 9548.14 | E44: 10394604 | F44: COBRO | I44: =-IFERROR(VLOOKUP(C44,SIRCUPA!$A$21:$H$221,8,0),0) -> 0 | J44: =-IFERROR(VLOOKUP(C44,SIRTAC!$A$16:$H$1458,8,0),0) -> -98 | K44: =-IFERROR(VLOOKUP(C44,Gastos!$A$9:$J$1451,10,0),0) -> -95.06 | L44: =-IFERROR(VLOOKUP(C44,IDC!$A$20:$H$1763,8,0),0) -> -58.8 | M44: =+D44-I44-J44-K44-L44 -> 9800
A45: 02-10-2025 | B45: Liquidación de dinero | C45: 128398739964 | D45: 9353.28 | E45: 10403957 | F45: COBRO | I45: =-IFERROR(VLOOKUP(C45,SIRCUPA!$A$21:$H$221,8,0),0) -> 0 | J45: =-IFERROR(VLOOKUP(C45,SIRTAC!$A$16:$H$1458,8,0),0) -> -96 | K45: =-IFERROR(VLOOKUP(C45,Gastos!$A$9:$J$1451,10,0),0) -> -93.12 | L45: =-IFERROR(VLOOKUP(C45,IDC!$A$20:$H$1763,8,0),0) -> -57.6 | M45: =+D45-I45-J45-K45-L45 -> 9600
A46: 02-10-2025 | B46: Liquidación de dinero | C46: 127834309851 | D46: 13932.49 | E46: 10417890 | F46: COBRO | I46: =-IFERROR(VLOOKUP(C46,SIRCUPA!$A$21:$H$221,8,0),0) -> 0 | J46: =-IFERROR(VLOOKUP(C46,SIRTAC!$A$16:$H$1458,8,0),0) -> -143 | K46: =-IFERROR(VLOOKUP(C46,Gastos!$A$9:$J$1451,10,0),0) -> -138.71 | L46: =-IFERROR(VLOOKUP(C46,IDC!$A$20:$H$1763,8,0),0) -> -85.8 | M46: =+D46-I46-J46-K46-L46 -> 14300
A47: 02-10-2025 | B47: Transferencia recibida Argentina Segura e Higienica | C47: 127834303877 | D47: 2099.95 | E47: 10419990 | F47: COBRO | I47: =-IFERROR(VLOOKUP(C47,SIRCUPA!$A$21:$H$221,8,0),0) -> -32.18 | J47: =-IFERROR(VLOOKUP(C47,SIRTAC!$A$16:$H$1458,8,0),0) -> 0 | K47: =-IFERROR(VLOOKUP(C47,Gastos!$A$9:$J$1451,10,0),0) -> 0 | L47: =-IFERROR(VLOOKUP(C47,IDC!$A$20:$H$1763,8,0),0) -> -12.87 | M47: =+D47-I47-J47-K47-L47 -> 2145
A48: 02-10-2025 | B48: Liquidación de dinero | C48: 128402388274 | D48: 12958.19 | E48: 10432948 | F48: COBRO | I48: =-IFERROR(VLOOKUP(C48,SIRCUPA!$A$21:$H$221,8,0),0) -> 0 | J48: =-IFERROR(VLOOKUP(C48,SIRTAC!$A$16:$H$1458,8,0),0) -> -133 | K48: =-IFERROR(VLOOKUP(C48,Gastos!$A$9:$J$1451,10,0),0) -> -129.01 | L48: =-IFERROR(VLOOKUP(C48,IDC!$A$20:$H$1763,8,0),0) -> -79.8 | M48: =+D48-I48-J48-K48-L48 -> 13300
A49: 02-10-2025 | B49: Transferencia recibida Facundo Lonardi | C49: 128402325040 | D49: 1302.07 | E49: 10434250 | F49: COBRO | I49: =-IFERROR(VLOOKUP(C49,SIRCUPA!$A$21:$H$221,8,0),0) -> -19.95 | J49: =-IFERROR(VLOOKUP(C49,SIRTAC!$A$16:$H$1458,8,0),0) -> 0 | K49: =-IFERROR(VLOOKUP(C49,Gastos!$A$9:$J$1451,10,0),0) -> 0 | L49: =-IFERROR(VLOOKUP(C49,IDC!$A$20:$H$1763,8,0),0) -> -7.98 | M49: =+D49-I49-J49-K49-L49 -> 1330
A50: 02-10-2025 | B50: Liquidación de dinero | C50: 127836305261 | D50: 30598.36 | E50: 10464848 | F50: COBRO | I50: =-IFERROR(VLOOKUP(C50,SIRCUPA!$A$21:$H$221,8,0),0) -> 0 | J50: =-IFERROR(VLOOKUP(C50,SIRTAC!$A$16:$H$1458,8,0),0) -> -326 | K50: =-IFERROR(VLOOKUP(C50,Gastos!$A$9:$J$1451,10,0),0) -> -1480.04 | L50: =-IFERROR(VLOOKUP(C50,IDC!$A$20:$H$1763,8,0),0) -> -195.6 | M50: =+D50-I50-J50-K50-L50 -> 32600
A51: 02-10-2025 | B51: Liquidación de dinero | C51: 128408491342 | D51: 4676.64 | E51: 10469525 | F51: COBRO | I51: =-IFERROR(VLOOKUP(C51,SIRCUPA!$A$21:$H$221,8,0),0) -> 0 | J51: =-IFERROR(VLOOKUP(C51,SIRTAC!$A$16:$H$1458,8,0),0) -> -48 | K51: =-IFERROR(VLOOKUP(C51,Gastos!$A$9:$J$1451,10,0),0) -> -46.56 | L51: =-IFERROR(VLOOKUP(C51,IDC!$A$20:$H$1763,8,0),0) -> -28.8 | M51: =+D51-I51-J51-K51-L51 -> 4800
A52: 02-10-2025 | B52: Liquidación de dinero | C52: 128408853332 | D52: 4534.56 | E52: 10474060 | F52: COBRO | I52: =-IFERROR(VLOOKUP(C52,SIRCUPA!$A$21:$H$221,8,0),0) -> 0 | J52: =-IFERROR(VLOOKUP(C52,SIRTAC!$A$16:$H$1458,8,0),0) -> -48 | K52: =-IFERROR(VLOOKUP(C52,Gastos!$A$9:$J$1451,10,0),0) -> -188.64 | L52: =-IFERROR(VLOOKUP(C52,IDC!$A$20:$H$1763,8,0),0) -> -28.8 | M52: =+D52-I52-J52-K52-L52 -> 4800
A53: 02-10-2025 | B53: Liquidación de dinero | C53: 127843829541 | D53: 37705.41 | E53: 10511765 | F53: COBRO | I53: =-IFERROR(VLOOKUP(C53,SIRCUPA!$A$21:$H$221,8,0),0) -> 0 | J53: =-IFERROR(VLOOKUP(C53,SIRTAC!$A$16:$H$1458,8,0),0) -> -387 | K53: =-IFERROR(VLOOKUP(C53,Gastos!$A$9:$J$1451,10,0),0) -> -375.39 | L53: =-IFERROR(VLOOKUP(C53,IDC!$A$20:$H$1763,8,0),0) -> -232.2 | M53: =+D53-I53-J53-K53-L53 -> 38700
A54: 02-10-2025 | B54: Transferencia recibida Pablo Oscar Ardaiz | C54: 128410134666 | D54: 1894.36 | E54: 10513659 | F54: COBRO | I54: =-IFERROR(VLOOKUP(C54,SIRCUPA!$A$21:$H$221,8,0),0) -> -29.03 | J54: =-IFERROR(VLOOKUP(C54,SIRTAC!$A$16:$H$1458,8,0),0) -> 0 | K54: =-IFERROR(VLOOKUP(C54,Gastos!$A$9:$J$1451,10,0),0) -> 0 | L54: =-IFERROR(VLOOKUP(C54,IDC!$A$20:$H$1763,8,0),0) -> -11.61 | M54: =+D54-I54-J54-K54-L54 -> 1935
A55: 02-10-2025 | B55: Liquidación de dinero | C55: 127845010923 | D55: 8768.7 | E55: 10522428 | F55: COBRO | I55: =-IFERROR(VLOOKUP(C55,SIRCUPA!$A$21:$H$221,8,0),0) -> 0 | J55: =-IFERROR(VLOOKUP(C55,SIRTAC!$A$16:$H$1458,8,0),0) -> -90 | K55: =-IFERROR(VLOOKUP(C55,Gastos!$A$9:$J$1451,10,0),0) -> -87.3 | L55: =-IFERROR(VLOOKUP(C55,IDC!$A$20:$H$1763,8,0),0) -> -54 | M55: =+D55-I55-J55-K55-L55 -> 9000
... A102: 03-10-2025 | B102: Liquidación de dinero | C102: 127854974679 | D102: 18316.84 | E102: 11354838 | F102: COBRO | I102: =-IFERROR(VLOOKUP(C102,SIRCUPA!$A$21:$H$221,8,0),0) -> 0 | J102: =-IFERROR(VLOOKUP(C102,SIRTAC!$A$16:$H$1458,8,0),0) -> -188 | K102: =-IFERROR(VLOOKUP(C102,Gastos!$A$9:$J$1451,10,0),0) -> -182.36 | L102: =-IFERROR(VLOOKUP(C102,IDC!$A$20:$H$1763,8,0),0) -> -112.8 | M102: =+D102-I102-J102-K102-L102 -> 18800
A103: 03-10-2025 | B103: Liquidación de dinero | C103: 128421075828 | D103: 106718.82 | E103: 11461557 | F103: COBRO | I103: =-IFERROR(VLOOKUP(C103,SIRCUPA!$A$21:$H$221,8,0),0) -> 0 | J103: -1137 | K103: =-IFERROR(VLOOKUP(C103,Gastos!$A$9:$J$1451,10,0),0) -> -5161.98 | L103: -682.2 | M103: =+D103-I103-J103-K103-L103 -> 113700
A104: 03-10-2025 | B104: Liquidación de dinero | C104: 128421266626 | D104: 4189.49 | E104: 11465747 | F104: COBRO | I104: =-IFERROR(VLOOKUP(C104,SIRCUPA!$A$21:$H$221,8,0),0) -> 0 | J104: =-IFERROR(VLOOKUP(C104,SIRTAC!$A$16:$H$1458,8,0),0) -> -43 | K104: =-IFERROR(VLOOKUP(C104,Gastos!$A$9:$J$1451,10,0),0) -> -41.71 | L104: =-IFERROR(VLOOKUP(C104,IDC!$A$20:$H$1763,8,0),0) -> -25.8 | M104: =+D104-I104-J104-K104-L104 -> 4300
A105: 03-10-2025 | B105: Liquidación de dinero | C105: 128421434434 | D105: 9353.28 | E105: 11475100 | F105: COBRO | I105: =-IFERROR(VLOOKUP(C105,SIRCUPA!$A$21:$H$221,8,0),0) -> 0 | J105: =-IFERROR(VLOOKUP(C105,SIRTAC!$A$16:$H$1458,8,0),0) -> -96 | K105: =-IFERROR(VLOOKUP(C105,Gastos!$A$9:$J$1451,10,0),0) -> -93.12 | L105: =-IFERROR(VLOOKUP(C105,IDC!$A$20:$H$1763,8,0),0) -> -57.6 | M105: =+D105-I105-J105-K105-L105 -> 9600
A106: 03-10-2025 | B106: Liquidación de dinero | C106: 128421490336 | D106: 13250.48 | E106: 11488350 | F106: COBRO | I106: =-IFERROR(VLOOKUP(C106,SIRCUPA!$A$21:$H$221,8,0),0) -> 0 | J106: =-IFERROR(VLOOKUP(C106,SIRTAC!$A$16:$H$1458,8,0),0) -> -136 | K106: =-IFERROR(VLOOKUP(C106,Gastos!$A$9:$J$1451,10,0),0) -> -131.92 | L106: =-IFERROR(VLOOKUP(C106,IDC!$A$20:$H$1763,8,0),0) -> -81.6 | M106: =+D106-I106-J106-K106-L106 -> 13600
A107: 03-10-2025 | B107: Liquidación de dinero | C107: 128421501412 | D107: 154252.21 | E107: 11642603 | F107: COBRO | I107: =-IFERROR(VLOOKUP(C107,SIRCUPA!$A$21:$H$221,8,0),0) -> 0 | J107: =-IFERROR(VLOOKUP(C107,SIRTAC!$A$16:$H$1458,8,0),0) -> -1699 | K107: =-IFERROR(VLOOKUP(C107,Gastos!$A$9:$J$1451,10,0),0) -> -12929.39 | L107: =-IFERROR(VLOOKUP(C107,IDC!$A$20:$H$1763,8,0),0) -> -1019.4 | M107: =+D107-I107-J107-K107-L107 -> 169900
A108: 03-10-2025 | B108: Liquidación de dinero | C108: 127855461023 | D108: 15209.67 | E108: 11657812 | F108: COBRO | I108: =-IFERROR(VLOOKUP(C108,SIRCUPA!$A$21:$H$221,8,0),0) -> 0 | J108: =-IFERROR(VLOOKUP(C108,SIRTAC!$A$16:$H$1458,8,0),0) -> -161 | K108: =-IFERROR(VLOOKUP(C108,Gastos!$A$9:$J$1451,10,0),0) -> -632.73 | L108: =-IFERROR(VLOOKUP(C108,IDC!$A$20:$H$1763,8,0),0) -> -96.6 | M108: =+D108-I108-J108-K108-L108 -> 16100
A109: 03-10-2025 | B109: Liquidación de dinero | C109: 127855560075 | D109: 25154.48 | E109: 11682967 | F109: COBRO | I109: =-IFERROR(VLOOKUP(C109,SIRCUPA!$A$21:$H$221,8,0),0) -> 0 | J109: =-IFERROR(VLOOKUP(C109,SIRTAC!$A$16:$H$1458,8,0),0) -> -268 | K109: =-IFERROR(VLOOKUP(C109,Gastos!$A$9:$J$1451,10,0),0) -> -1216.72 | L109: =-IFERROR(VLOOKUP(C109,IDC!$A$20:$H$1763,8,0),0) -> -160.8 | M109: =+D109-I109-J109-K109-L109 -> 26800
A110: 03-10-2025 | B110: Liquidación de dinero | C110: 127855916129 | D110: 7502.11 | E110: 11690469 | F110: COBRO | I110: =-IFERROR(VLOOKUP(C110,SIRCUPA!$A$21:$H$221,8,0),0) -> 0 | J110: =-IFERROR(VLOOKUP(C110,SIRTAC!$A$16:$H$1458,8,0),0) -> -77 | K110: =-IFERROR(VLOOKUP(C110,Gastos!$A$9:$J$1451,10,0),0) -> -74.69 | L110: =-IFERROR(VLOOKUP(C110,IDC!$A$20:$H$1763,8,0),0) -> -46.2 | M110: =+D110-I110-J110-K110-L110 -> 7700
A111: 03-10-2025 | B111: Liquidación de dinero | C111: 128422197004 | D111: 3897.2 | E111: 11694366 | F111: COBRO | I111: =-IFERROR(VLOOKUP(C111,SIRCUPA!$A$21:$H$221,8,0),0) -> 0 | J111: =-IFERROR(VLOOKUP(C111,SIRTAC!$A$16:$H$1458,8,0),0) -> -40 | K111: =-IFERROR(VLOOKUP(C111,Gastos!$A$9:$J$1451,10,0),0) -> -38.8 | L111: =-IFERROR(VLOOKUP(C111,IDC!$A$20:$H$1763,8,0),0) -> -24 | M111: =+D111-I111-J111-K111-L111 -> 4000
A112: 03-10-2025 | B112: Transferencia recibida Juan Angel Juvenal | C112: 128422276166 | D112: 587.4 | E112: 11694954 | F112: COBRO | I112: =-IFERROR(VLOOKUP(C112,SIRCUPA!$A$21:$H$221,8,0),0) -> -9 | J112: =-IFERROR(VLOOKUP(C112,SIRTAC!$A$16:$H$1458,8,0),0) -> 0 | K112: =-IFERROR(VLOOKUP(C112,Gastos!$A$9:$J$1451,10,0),0) -> 0 | L112: =-IFERROR(VLOOKUP(C112,IDC!$A$20:$H$1763,8,0),0) -> -3.6 | M112: =+D112-I112-J112-K112-L112 -> 600
A113: 03-10-2025 | B113: Liquidación de dinero cancelada Venta cancelada | C113: 128421075828 | D113: -106718.82 | E113: 11588235 | F113: COBRO | I113: =-IFERROR(VLOOKUP(C113,SIRCUPA!$A$21:$H$221,8,0),0) -> 0 | J113: =-IFERROR(VLOOKUP(C113,SIRTAC!$A$16:$H$1458,8,0),0) -> 1137 | K113: 5161.98 | L113: =-IFERROR(VLOOKUP(C113,IDC!$A$20:$H$1763,8,0),0) -> 682.2 | M113: =+D113-I113-J113-K113-L113 -> -113700
A114: 03-10-2025 | B114: Liquidación de dinero | C114: 127856005159 | D114: 9353.28 | E114: 11597588 | F114: COBRO | I114: =-IFERROR(VLOOKUP(C114,SIRCUPA!$A$21:$H$221,8,0),0) -> 0 | J114: =-IFERROR(VLOOKUP(C114,SIRTAC!$A$16:$H$1458,8,0),0) -> -96 | K114: =-IFERROR(VLOOKUP(C114,Gastos!$A$9:$J$1451,10,0),0) -> -93.12 | L114: =-IFERROR(VLOOKUP(C114,IDC!$A$20:$H$1763,8,0),0) -> -57.6 | M114: =+D114-I114-J114-K114-L114 -> 9600
A115: 03-10-2025 | B115: Liquidación de dinero | C115: 127856064757 | D115: 34352.76 | E115: 11631941 | F115: COBRO | I115: =-IFERROR(VLOOKUP(C115,SIRCUPA!$A$21:$H$221,8,0),0) -> 0 | J115: =-IFERROR(VLOOKUP(C115,SIRTAC!$A$16:$H$1458,8,0),0) -> -366 | K115: =-IFERROR(VLOOKUP(C115,Gastos!$A$9:$J$1451,10,0),0) -> -1661.64 | L115: =-IFERROR(VLOOKUP(C115,IDC!$A$20:$H$1763,8,0),0) -> -219.6 | M115: =+D115-I115-J115-K115-L115 -> 36600
A116: 03-10-2025 | B116: Liquidación de dinero | C116: 127856418189 | D116: 6820.1 | E116: 11638761 | F116: COBRO | I116: =-IFERROR(VLOOKUP(C116,SIRCUPA!$A$21:$H$221,8,0),0) -> 0 | J116: =-IFERROR(VLOOKUP(C116,SIRTAC!$A$16:$H$1458,8,0),0) -> -70 | K116: =-IFERROR(VLOOKUP(C116,Gastos!$A$9:$J$1451,10,0),0) -> -67.9 | L116: =-IFERROR(VLOOKUP(C116,IDC!$A$20:$H$1763,8,0),0) -> -42 | M116: =+D116-I116-J116-K116-L116 -> 7000
A117: 03-10-2025 | B117: Liquidación de dinero | C117: 127856497497 | D117: 4092.06 | E117: 11642853 | F117: COBRO | I117: =-IFERROR(VLOOKUP(C117,SIRCUPA!$A$21:$H$221,8,0),0) -> 0 | J117: =-IFERROR(VLOOKUP(C117,SIRTAC!$A$16:$H$1458,8,0),0) -> -42 | K117: =-IFERROR(VLOOKUP(C117,Gastos!$A$9:$J$1451,10,0),0) -> -40.74 | L117: =-IFERROR(VLOOKUP(C117,IDC!$A$20:$H$1763,8,0),0) -> -25.2 | M117: =+D117-I117-J117-K117-L117 -> 4200
A118: 03-10-2025 | B118: Liquidación de dinero | C118: 128422949584 | D118: 58263.14 | E118: 11701116 | F118: COBRO | I118: =-IFERROR(VLOOKUP(C118,SIRCUPA!$A$21:$H$221,8,0),0) -> 0 | J118: =-IFERROR(VLOOKUP(C118,SIRTAC!$A$16:$H$1458,8,0),0) -> -598 | K118: =-IFERROR(VLOOKUP(C118,Gastos!$A$9:$J$1451,10,0),0) -> -580.06 | L118: =-IFERROR(VLOOKUP(C118,IDC!$A$20:$H$1763,8,0),0) -> -358.8 | M118: =+D118-I118-J118-K118-L118 -> 59800
A119: 03-10-2025 | B119: Transferencia recibida Carolina Ailen Rodriguez | C119: 128423104492 | D119: 2927.21 | E119: 11704043 | F119: COBRO | I119: =-IFERROR(VLOOKUP(C119,SIRCUPA!$A$21:$H$221,8,0),0) -> -44.85 | J119: =-IFERROR(VLOOKUP(C119,SIRTAC!$A$16:$H$1458,8,0),0) -> 0 | K119: =-IFERROR(VLOOKUP(C119,Gastos!$A$9:$J$1451,10,0),0) -> 0 | L119: =-IFERROR(VLOOKUP(C119,IDC!$A$20:$H$1763,8,0),0) -> -17.94 | M119: =+D119-I119-J119-K119-L119 -> 2990
A120: 03-10-2025 | B120: Liquidación de dinero | C120: 127856899443 | D120: 8259.68 | E120: 11712303 | F120: COBRO | I120: =-IFERROR(VLOOKUP(C120,SIRCUPA!$A$21:$H$221,8,0),0) -> 0 | J120: =-IFERROR(VLOOKUP(C120,SIRTAC!$A$16:$H$1458,8,0),0) -> -88 | K120: =-IFERROR(VLOOKUP(C120,Gastos!$A$9:$J$1451,10,0),0) -> -399.52 | L120: =-IFERROR(VLOOKUP(C120,IDC!$A$20:$H$1763,8,0),0) -> -52.8 | M120: =+D120-I120-J120-K120-L120 -> 8800
A121: 03-10-2025 | B121: Liquidación de dinero | C121: 128423208738 | D121: 4534.56 | E121: 11716837 | F121: COBRO | I121: =-IFERROR(VLOOKUP(C121,SIRCUPA!$A$21:$H$221,8,0),0) -> 0 | J121: =-IFERROR(VLOOKUP(C121,SIRTAC!$A$16:$H$1458,8,0),0) -> -48 | K121: =-IFERROR(VLOOKUP(C121,Gastos!$A$9:$J$1451,10,0),0) -> -188.64 | L121: =-IFERROR(VLOOKUP(C121,IDC!$A$20:$H$1763,8,0),0) -> -28.8 | M121: =+D121-I121-J121-K121-L121 -> 4800
A122: 03-10-2025 | B122: Liquidación de dinero | C122: 128423356546 | D122: 12665.9 | E122: 11729503 | F122: COBRO | I122: =-IFERROR(VLOOKUP(C122,SIRCUPA!$A$21:$H$221,8,0),0) -> 0 | J122: =-IFERROR(VLOOKUP(C122,SIRTAC!$A$16:$H$1458,8,0),0) -> -130 | K122: =-IFERROR(VLOOKUP(C122,Gastos!$A$9:$J$1451,10,0),0) -> -126.1 | L122: =-IFERROR(VLOOKUP(C122,IDC!$A$20:$H$1763,8,0),0) -> -78 | M122: =+D122-I122-J122-K122-L122 -> 13000
A123: 03-10-2025 | B123: Liquidación de dinero | C123: 127857063969 | D123: 10035.29 | E123: 11739539 | F123: COBRO | I123: =-IFERROR(VLOOKUP(C123,SIRCUPA!$A$21:$H$221,8,0),0) -> 0 | J123: =-IFERROR(VLOOKUP(C123,SIRTAC!$A$16:$H$1458,8,0),0) -> -103 | K123: =-IFERROR(VLOOKUP(C123,Gastos!$A$9:$J$1451,10,0),0) -> -99.91 | L123: =-IFERROR(VLOOKUP(C123,IDC!$A$20:$H$1763,8,0),0) -> -61.8 | M123: =+D123-I123-J123-K123-L123 -> 10300
A124: 03-10-2025 | B124: Liquidación de dinero | C124: 127857363213 | D124: 5163.79 | E124: 11744702 | F124: COBRO | I124: =-IFERROR(VLOOKUP(C124,SIRCUPA!$A$21:$H$221,8,0),0) -> 0 | J124: =-IFERROR(VLOOKUP(C124,SIRTAC!$A$16:$H$1458,8,0),0) -> -53 | K124: =-IFERROR(VLOOKUP(C124,Gastos!$A$9:$J$1451,10,0),0) -> -51.41 | L124: =-IFERROR(VLOOKUP(C124,IDC!$A$20:$H$1763,8,0),0) -> -31.8 | M124: =+D124-I124-J124-K124-L124 -> 5300
A125: 03-10-2025 | B125: Liquidación de dinero | C125: 128423642872 | D125: 51248.18 | E125: 11795951 | F125: COBRO | I125: =-IFERROR(VLOOKUP(C125,SIRCUPA!$A$21:$H$221,8,0),0) -> 0 | J125: =-IFERROR(VLOOKUP(C125,SIRTAC!$A$16:$H$1458,8,0),0) -> -526 | K125: =-IFERROR(VLOOKUP(C125,Gastos!$A$9:$J$1451,10,0),0) -> -510.22 | L125: =-IFERROR(VLOOKUP(C125,IDC!$A$20:$H$1763,8,0),0) -> -315.6 | M125: =+D125-I125-J125-K125-L125 -> 52600
... A157: 03-10-2025 | B157: Liquidación de dinero | C157: 128427296372 | D157: 27280.4 | E157: 12386227 | F157: COBRO | I157: =-IFERROR(VLOOKUP(C157,SIRCUPA!$A$21:$H$221,8,0),0) -> 0 | J157: =-IFERROR(VLOOKUP(C157,SIRTAC!$A$16:$H$1458,8,0),0) -> -280 | K157: =-IFERROR(VLOOKUP(C157,Gastos!$A$9:$J$1451,10,0),0) -> -271.6 | L157: =-IFERROR(VLOOKUP(C157,IDC!$A$20:$H$1763,8,0),0) -> -168 | M157: =+D157-I157-J157-K157-L157 -> 28000
A158: 06-10-2025 | B158: Impuesto por extracción | C158: 128302630577 | D158: -7688.4 | E158: 11769469 | F158: IDC | G158: =+D158/0.006 -> -1281400 | I158: =-IFERROR(VLOOKUP(C158,SIRCUPA!$A$21:$H$221,8,0),0) -> 0 | J158: =-IFERROR(VLOOKUP(C158,SIRTAC!$A$16:$H$1458,8,0),0) -> 0 | K158: =-IFERROR(VLOOKUP(C158,Gastos!$A$9:$J$1451,10,0),0) -> 0 | M158: =+D158 -> -7688.4
A159: 06-10-2025 | B159: Transferencia enviada LAGUNA CAPRI SAS | C159: 128302630577 | D159: -1281400 | E159: 11777158 | F159: PAGO PROVEEDOR | G159: =+D159/1.006 -> -1273757.5 | H159: =+D159-G159 -> -7642.5449 | I159: =-IFERROR(VLOOKUP(C159,SIRCUPA!$A$21:$H$221,8,0),0) -> 0 | J159: =-IFERROR(VLOOKUP(C159,SIRTAC!$A$16:$H$1458,8,0),0) -> 0 | K159: =-IFERROR(VLOOKUP(C159,Gastos!$A$9:$J$1451,10,0),0) -> 0 | L159: =-IFERROR(VLOOKUP(C159,IDC!$A$20:$H$1763,8,0),0) -> -7688.4 | M159: =+D159 -> -1281400
A160: 03-10-2025 | B160: Liquidación de dinero | C160: 128532328060 | D160: 34953.9 | E160: 11663719 | F160: COBRO | I160: =-IFERROR(VLOOKUP(C160,SIRCUPA!$A$21:$H$221,8,0),0) -> 0 | J160: =-IFERROR(VLOOKUP(C160,SIRTAC!$A$16:$H$1458,8,0),0) -> -370 | K160: =-IFERROR(VLOOKUP(C160,Gastos!$A$9:$J$1451,10,0),0) -> -1454.1 | L160: =-IFERROR(VLOOKUP(C160,IDC!$A$20:$H$1763,8,0),0) -> -222 | M160: =+D160-I160-J160-K160-L160 -> 37000
A161: 03-10-2025 | B161: Liquidación de dinero | C161: 128538963780 | D161: 9353.28 | E161: 11673072 | F161: COBRO | I161: =-IFERROR(VLOOKUP(C161,SIRCUPA!$A$21:$H$221,8,0),0) -> 0 | J161: =-IFERROR(VLOOKUP(C161,SIRTAC!$A$16:$H$1458,8,0),0) -> -96 | K161: =-IFERROR(VLOOKUP(C161,Gastos!$A$9:$J$1451,10,0),0) -> -93.12 | L161: =-IFERROR(VLOOKUP(C161,IDC!$A$20:$H$1763,8,0),0) -> -57.6 | M161: =+D161-I161-J161-K161-L161 -> 9600
A162: 03-10-2025 | B162: Liquidación de dinero | C162: 128541606502 | D162: 38585.75 | E162: 11711658 | F162: COBRO | I162: =-IFERROR(VLOOKUP(C162,SIRCUPA!$A$21:$H$221,8,0),0) -> 0 | J162: =-IFERROR(VLOOKUP(C162,SIRTAC!$A$16:$H$1458,8,0),0) -> -425 | K162: =-IFERROR(VLOOKUP(C162,Gastos!$A$9:$J$1451,10,0),0) -> -3234.25 | L162: =-IFERROR(VLOOKUP(C162,IDC!$A$20:$H$1763,8,0),0) -> -255 | M162: =+D162-I162-J162-K162-L162 -> 42500
A163: 03-10-2025 | B163: Transferencia recibida Joaquin Pedro Schenone | C163: 127974511167 | D163: 2080.37 | E163: 11713738 | F163: COBRO | I163: =-IFERROR(VLOOKUP(C163,SIRCUPA!$A$21:$H$221,8,0),0) -> -31.88 | J163: =-IFERROR(VLOOKUP(C163,SIRTAC!$A$16:$H$1458,8,0),0) -> 0 | K163: =-IFERROR(VLOOKUP(C163,Gastos!$A$9:$J$1451,10,0),0) -> 0 | L163: =-IFERROR(VLOOKUP(C163,IDC!$A$20:$H$1763,8,0),0) -> -12.75 | M163: =+D163-I163-J163-K163-L163 -> 2125
A164: 03-10-2025 | B164: Liquidación de dinero | C164: 127975227343 | D164: 9548.14 | E164: 11723287 | F164: COBRO | I164: =-IFERROR(VLOOKUP(C164,SIRCUPA!$A$21:$H$221,8,0),0) -> 0 | J164: =-IFERROR(VLOOKUP(C164,SIRTAC!$A$16:$H$1458,8,0),0) -> -98 | K164: =-IFERROR(VLOOKUP(C164,Gastos!$A$9:$J$1451,10,0),0) -> -95.06 | L164: =-IFERROR(VLOOKUP(C164,IDC!$A$20:$H$1763,8,0),0) -> -58.8 | M164: =+D164-I164-J164-K164-L164 -> 9800
A165: 03-10-2025 | B165: Liquidación de dinero | C165: 127975543977 | D165: 12958.19 | E165: 11736245 | F165: COBRO | I165: =-IFERROR(VLOOKUP(C165,SIRCUPA!$A$21:$H$221,8,0),0) -> 0 | J165: =-IFERROR(VLOOKUP(C165,SIRTAC!$A$16:$H$1458,8,0),0) -> -133 | K165: =-IFERROR(VLOOKUP(C165,Gastos!$A$9:$J$1451,10,0),0) -> -129.01 | L165: =-IFERROR(VLOOKUP(C165,IDC!$A$20:$H$1763,8,0),0) -> -79.8 | M165: =+D165-I165-J165-K165-L165 -> 13300
A166: 03-10-2025 | B166: Transferencia recibida Agustin Rivero | C166: 128542794370 | D166: 1953.1 | E166: 11738198 | F166: COBRO | I166: =-IFERROR(VLOOKUP(C166,SIRCUPA!$A$21:$H$221,8,0),0) -> -29.93 | J166: =-IFERROR(VLOOKUP(C166,SIRTAC!$A$16:$H$1458,8,0),0) -> 0 | K166: =-IFERROR(VLOOKUP(C166,Gastos!$A$9:$J$1451,10,0),0) -> 0 | L166: =-IFERROR(VLOOKUP(C166,IDC!$A$20:$H$1763,8,0),0) -> -11.97 | M166: =+D166-I166-J166-K166-L166 -> 1995
A167: 03-10-2025 | B167: Liquidación de dinero | C167: 128544354086 | D167: 27112.89 | E167: 11765311 | F167: COBRO | I167: =-IFERROR(VLOOKUP(C167,SIRCUPA!$A$21:$H$221,8,0),0) -> 0 | J167: =-IFERROR(VLOOKUP(C167,SIRTAC!$A$16:$H$1458,8,0),0) -> -287 | K167: =-IFERROR(VLOOKUP(C167,Gastos!$A$9:$J$1451,10,0),0) -> -1127.91 | L167: =-IFERROR(VLOOKUP(C167,IDC!$A$20:$H$1763,8,0),0) -> -172.2 | M167: =+D167-I167-J167-K167-L167 -> 28700
A168: 03-10-2025 | B168: Liquidación de dinero | C168: 127978785635 | D168: 7794.4 | E168: 11773105 | F168: COBRO | I168: =-IFERROR(VLOOKUP(C168,SIRCUPA!$A$21:$H$221,8,0),0) -> 0 | J168: =-IFERROR(VLOOKUP(C168,SIRTAC!$A$16:$H$1458,8,0),0) -> -80 | K168: =-IFERROR(VLOOKUP(C168,Gastos!$A$9:$J$1451,10,0),0) -> -77.6 | L168: =-IFERROR(VLOOKUP(C168,IDC!$A$20:$H$1763,8,0),0) -> -48 | M168: =+D168-I168-J168-K168-L168 -> 8000
A169: 03-10-2025 | B169: Liquidación de dinero | C169: 127978952503 | D169: 15004.22 | E169: 11788109 | F169: COBRO | I169: =-IFERROR(VLOOKUP(C169,SIRCUPA!$A$21:$H$221,8,0),0) -> 0 | J169: =-IFERROR(VLOOKUP(C169,SIRTAC!$A$16:$H$1458,8,0),0) -> -154 | K169: =-IFERROR(VLOOKUP(C169,Gastos!$A$9:$J$1451,10,0),0) -> -149.38 | L169: =-IFERROR(VLOOKUP(C169,IDC!$A$20:$H$1763,8,0),0) -> -92.4 | M169: =+D169-I169-J169-K169-L169 -> 15400
A170: 03-10-2025 | B170: Liquidación de dinero | C170: 128546191150 | D170: 9353.28 | E170: 11797463 | F170: COBRO | I170: =-IFERROR(VLOOKUP(C170,SIRCUPA!$A$21:$H$221,8,0),0) -> 0 | J170: =-IFERROR(VLOOKUP(C170,SIRTAC!$A$16:$H$1458,8,0),0) -> -96 | K170: =-IFERROR(VLOOKUP(C170,Gastos!$A$9:$J$1451,10,0),0) -> -93.12 | L170: =-IFERROR(VLOOKUP(C170,IDC!$A$20:$H$1763,8,0),0) -> -57.6 | M170: =+D170-I170-J170-K170-L170 -> 9600
A171: 03-10-2025 | B171: Transferencia recibida Gala Store | C171: 128546254534 | D171: 469.92 | E171: 11797933 | F171: COBRO | I171: =-IFERROR(VLOOKUP(C171,SIRCUPA!$A$21:$H$221,8,0),0) -> -7.2 | J171: =-IFERROR(VLOOKUP(C171,SIRTAC!$A$16:$H$1458,8,0),0) -> 0 | K171: =-IFERROR(VLOOKUP(C171,Gastos!$A$9:$J$1451,10,0),0) -> 0 | L171: =-IFERROR(VLOOKUP(C171,IDC!$A$20:$H$1763,8,0),0) -> -2.88 | M171: =+D171-I171-J171-K171-L171 -> 480
... A195: 03-10-2025 | B195: Liquidación de dinero | C195: 127997252239 | D195: 9104.42 | E195: 12297730 | F195: COBRO | I195: =-IFERROR(VLOOKUP(C195,SIRCUPA!$A$21:$H$221,8,0),0) -> 0 | J195: =-IFERROR(VLOOKUP(C195,SIRTAC!$A$16:$H$1458,8,0),0) -> -97 | K195: =-IFERROR(VLOOKUP(C195,Gastos!$A$9:$J$1451,10,0),0) -> -440.38 | L195: =-IFERROR(VLOOKUP(C195,IDC!$A$20:$H$1763,8,0),0) -> -58.2 | M195: =+D195-I195-J195-K195-L195 -> 9700
A196: 03-10-2025 | B196: Liquidación de dinero cancelada Venta cancelada | C196: 128564070590 | D196: -42771.77 | E196: 12254958 | F196: COBRO | I196: =-IFERROR(VLOOKUP(C196,SIRCUPA!$A$21:$H$221,8,0),0) -> 0 | J196: 439 | K196: 425.83 | L196: 263.4 | M196: =+D196-I196-J196-K196-L196 -> -43900
A197: 03-10-2025 | B197: Liquidación de dinero | C197: 127997540269 | D197: 33808.21 | E197: 12288766 | F197: COBRO | I197: =-IFERROR(VLOOKUP(C197,SIRCUPA!$A$21:$H$221,8,0),0) -> 0 | J197: =-IFERROR(VLOOKUP(C197,SIRTAC!$A$16:$H$1458,8,0),0) -> -347 | K197: =-IFERROR(VLOOKUP(C197,Gastos!$A$9:$J$1451,10,0),0) -> -336.59 | L197: =-IFERROR(VLOOKUP(C197,IDC!$A$20:$H$1763,8,0),0) -> -208.2 | M197: =+D197-I197-J197-K197-L197 -> 34700
A198: 03-10-2025 | B198: Liquidación de dinero | C198: 128564579028 | D198: 29618.72 | E198: 12318385 | F198: COBRO | I198: =-IFERROR(VLOOKUP(C198,SIRCUPA!$A$21:$H$221,8,0),0) -> 0 | J198: =-IFERROR(VLOOKUP(C198,SIRTAC!$A$16:$H$1458,8,0),0) -> -304 | K198: =-IFERROR(VLOOKUP(C198,Gastos!$A$9:$J$1451,10,0),0) -> -294.88 | L198: =-IFERROR(VLOOKUP(C198,IDC!$A$20:$H$1763,8,0),0) -> -182.4 | M198: =+D198-I198-J198-K198-L198 -> 30400
A199: 03-10-2025 | B199: Liquidación de dinero | C199: 128564877302 | D199: 28839.28 | E199: 12347224 | F199: COBRO | I199: =-IFERROR(VLOOKUP(C199,SIRCUPA!$A$21:$H$221,8,0),0) -> 0 | J199: =-IFERROR(VLOOKUP(C199,SIRTAC!$A$16:$H$1458,8,0),0) -> -296 | K199: =-IFERROR(VLOOKUP(C199,Gastos!$A$9:$J$1451,10,0),0) -> -287.12 | L199: =-IFERROR(VLOOKUP(C199,IDC!$A$20:$H$1763,8,0),0) -> -177.6 | M199: =+D199-I199-J199-K199-L199 -> 29600
A200: 03-10-2025 | B200: Transferencia recibida Yamil Jose Ale | C200: 127997962901 | D200: 1448.92 | E200: 12348673 | F200: COBRO | I200: =-IFERROR(VLOOKUP(C200,SIRCUPA!$A$21:$H$221,8,0),0) -> -22.2 | J200: =-IFERROR(VLOOKUP(C200,SIRTAC!$A$16:$H$1458,8,0),0) -> 0 | K200: =-IFERROR(VLOOKUP(C200,Gastos!$A$9:$J$1451,10,0),0) -> 0 | L200: =-IFERROR(VLOOKUP(C200,IDC!$A$20:$H$1763,8,0),0) -> -8.88 | M200: =+D200-I200-J200-K200-L200 -> 1480
A201: 03-10-2025 | B201: Liquidación de dinero | C201: 127998034681 | D201: 31567.32 | E201: 12380240 | F201: COBRO | I201: =-IFERROR(VLOOKUP(C201,SIRCUPA!$A$21:$H$221,8,0),0) -> 0 | J201: =-IFERROR(VLOOKUP(C201,SIRTAC!$A$16:$H$1458,8,0),0) -> -324 | K201: =-IFERROR(VLOOKUP(C201,Gastos!$A$9:$J$1451,10,0),0) -> -314.28 | L201: =-IFERROR(VLOOKUP(C201,IDC!$A$20:$H$1763,8,0),0) -> -194.4 | M201: =+D201-I201-J201-K201-L201 -> 32400
A202: 03-10-2025 | B202: Liquidación de dinero | C202: 127998422719 | D202: 39848.87 | E202: 12420089 | F202: COBRO | I202: =-IFERROR(VLOOKUP(C202,SIRCUPA!$A$21:$H$221,8,0),0) -> 0 | J202: =-IFERROR(VLOOKUP(C202,SIRTAC!$A$16:$H$1458,8,0),0) -> -409 | K202: =-IFERROR(VLOOKUP(C202,Gastos!$A$9:$J$1451,10,0),0) -> -396.73 | L202: =-IFERROR(VLOOKUP(C202,IDC!$A$20:$H$1763,8,0),0) -> -245.4 | M202: =+D202-I202-J202-K202-L202 -> 40900
A203: 03-10-2025 | B203: Transferencia recibida Aldana Victoria Popov Lusardi | C203: 128565546884 | D203: 2002.05 | E203: 12422091 | F203: COBRO | I203: =-IFERROR(VLOOKUP(C203,SIRCUPA!$A$21:$H$221,8,0),0) -> -30.68 | J203: =-IFERROR(VLOOKUP(C203,SIRTAC!$A$16:$H$1458,8,0),0) -> 0 | K203: =-IFERROR(VLOOKUP(C203,Gastos!$A$9:$J$1451,10,0),0) -> 0 | L203: =-IFERROR(VLOOKUP(C203,IDC!$A$20:$H$1763,8,0),0) -> -12.27 | M203: =+D203-I203-J203-K203-L203 -> 2045
A204: 03-10-2025 | B204: Liquidación de dinero | C204: 127998530233 | D204: 23285.77 | E204: 12445377 | F204: COBRO | I204: =-IFERROR(VLOOKUP(C204,SIRCUPA!$A$21:$H$221,8,0),0) -> 0 | J204: =-IFERROR(VLOOKUP(C204,SIRTAC!$A$16:$H$1458,8,0),0) -> -239 | K204: =-IFERROR(VLOOKUP(C204,Gastos!$A$9:$J$1451,10,0),0) -> -231.83 | L204: =-IFERROR(VLOOKUP(C204,IDC!$A$20:$H$1763,8,0),0) -> -143.4 | M204: =+D204-I204-J204-K204-L204 -> 23900
A205: 03-10-2025 | B205: Liquidación de dinero | C205: 127998690249 | D205: 8573.84 | E205: 12453951 | F205: COBRO | I205: =-IFERROR(VLOOKUP(C205,SIRCUPA!$A$21:$H$221,8,0),0) -> 0 | J205: =-IFERROR(VLOOKUP(C205,SIRTAC!$A$16:$H$1458,8,0),0) -> -88 | K205: =-IFERROR(VLOOKUP(C205,Gastos!$A$9:$J$1451,10,0),0) -> -85.36 | L205: =-IFERROR(VLOOKUP(C205,IDC!$A$20:$H$1763,8,0),0) -> -52.8 | M205: =+D205-I205-J205-K205-L205 -> 8800
A206: 03-10-2025 | B206: Liquidación de dinero | C206: 127998715475 | D206: 86030.69 | E206: 12539981 | F206: COBRO | I206: =-IFERROR(VLOOKUP(C206,SIRCUPA!$A$21:$H$221,8,0),0) -> 0 | J206: =-IFERROR(VLOOKUP(C206,SIRTAC!$A$16:$H$1458,8,0),0) -> -883 | K206: =-IFERROR(VLOOKUP(C206,Gastos!$A$9:$J$1451,10,0),0) -> -856.51 | L206: =-IFERROR(VLOOKUP(C206,IDC!$A$20:$H$1763,8,0),0) -> -529.8 | M206: =+D206-I206-J206-K206-L206 -> 88300
A207: 03-10-2025 | B207: Liquidación de dinero | C207: 127998789467 | D207: 77559.87 | E207: 12617541 | F207: COBRO | I207: =-IFERROR(VLOOKUP(C207,SIRCUPA!$A$21:$H$221,8,0),0) -> 0 | J207: =-IFERROR(VLOOKUP(C207,SIRTAC!$A$16:$H$1458,8,0),0) -> -821 | K207: =-IFERROR(VLOOKUP(C207,Gastos!$A$9:$J$1451,10,0),0) -> -3226.53 | L207: =-IFERROR(VLOOKUP(C207,IDC!$A$20:$H$1763,8,0),0) -> -492.6 | M207: =+D207-I207-J207-K207-L207 -> 82100
A208: 03-10-2025 | B208: Liquidación de dinero | C208: 127998958295 | D208: 73267.36 | E208: 12690809 | F208: COBRO | I208: =-IFERROR(VLOOKUP(C208,SIRCUPA!$A$21:$H$221,8,0),0) -> 0 | J208: =-IFERROR(VLOOKUP(C208,SIRTAC!$A$16:$H$1458,8,0),0) -> -752 | K208: =-IFERROR(VLOOKUP(C208,Gastos!$A$9:$J$1451,10,0),0) -> -729.44 | L208: =-IFERROR(VLOOKUP(C208,IDC!$A$20:$H$1763,8,0),0) -> -451.2 | M208: =+D208-I208-J208-K208-L208 -> 75200
... A401: 06-10-2025 | B401: Liquidación de dinero | C401: 128222367735 | D401: 7989.52 | E401: 16878008 | F401: COBRO | I401: =-IFERROR(VLOOKUP(C401,SIRCUPA!$A$21:$H$221,8,0),0) -> 0 | J401: =-IFERROR(VLOOKUP(C401,SIRTAC!$A$16:$H$1458,8,0),0) -> -88 | K401: =-IFERROR(VLOOKUP(C401,Gastos!$A$9:$J$1451,10,0),0) -> -669.68 | L401: =-IFERROR(VLOOKUP(C401,IDC!$A$20:$H$1763,8,0),0) -> -52.8 | M401: =+D401-I401-J401-K401-L401 -> 8800
A402: 06-10-2025 | B402: Transferencia enviada | C402: 128307872905 | D402: -21729.59 | E402: 11747740 | F402: PAGO PROVEEDOR | G402: =+D402/1.006 -> -21599.99 | H402: =+D402-G402 -> -129.59994 | I402: =-IFERROR(VLOOKUP(C402,SIRCUPA!$A$21:$H$221,8,0),0) -> 0 | J402: =-IFERROR(VLOOKUP(C402,SIRTAC!$A$16:$H$1458,8,0),0) -> 0 | K402: =-IFERROR(VLOOKUP(C402,Gastos!$A$9:$J$1451,10,0),0) -> 0 | L402: =+D402-G402 -> -129.59994 | M402: =+D402-I402-J402-K402-L402 -> -21599.99 | O402: BRODE
A403: 02-10-2025 | B403: Impuesto por extracción | C403: 128313425810 | D403: -1162.45 | E403: 11242651 | F403: IDC | G403: =+D403/0.006 -> -193741.67 | I403: =-IFERROR(VLOOKUP(C403,SIRCUPA!$A$21:$H$221,8,0),0) -> 0 | J403: =-IFERROR(VLOOKUP(C403,SIRTAC!$A$16:$H$1458,8,0),0) -> 0 | K403: =-IFERROR(VLOOKUP(C403,Gastos!$A$9:$J$1451,10,0),0) -> 0 | M403: =+D403 -> -1162.45
A404: 02-10-2025 | B404: Transferencia enviada EMBOTELLADORA DEL ATLANTICO SA | C404: 128313425810 | D404: -193742.33 | E404: 11243813 | F404: PAGO PROVEEDOR | G404: =+D404/1.006 -> -192586.81 | H404: =+D404-G404 -> -1155.5209 | I404: =-IFERROR(VLOOKUP(C404,SIRCUPA!$A$21:$H$221,8,0),0) -> 0 | J404: =-IFERROR(VLOOKUP(C404,SIRTAC!$A$16:$H$1458,8,0),0) -> 0 | K404: =-IFERROR(VLOOKUP(C404,Gastos!$A$9:$J$1451,10,0),0) -> 0 | L404: =-IFERROR(VLOOKUP(C404,IDC!$A$20:$H$1763,8,0),0) -> -1162.45 | M404: =+D404 -> -193742.33
A405: 02-10-2025 | B405: Impuesto por extracción | C405: 128340094018 | D405: -324.21 | E405: 10604030 | F405: IDC | G405: =+D405/0.006 -> -54035 | I405: =-IFERROR(VLOOKUP(C405,SIRCUPA!$A$21:$H$221,8,0),0) -> 0 | J405: =-IFERROR(VLOOKUP(C405,SIRTAC!$A$16:$H$1458,8,0),0) -> 0 | K405: =-IFERROR(VLOOKUP(C405,Gastos!$A$9:$J$1451,10,0),0) -> 0 | M405: =+D405 -> -324.21
A406: 02-10-2025 | B406: Transferencia enviada FRUVECO S R L | C406: 128340094018 | D406: -54034.24 | E406: 10604354 | F406: PAGO PROVEEDOR | G406: =+D406/1.006 -> -53711.968 | H406: =+D406-G406 -> -322.27181 | I406: =-IFERROR(VLOOKUP(C406,SIRCUPA!$A$21:$H$221,8,0),0) -> 0 | J406: =-IFERROR(VLOOKUP(C406,SIRTAC!$A$16:$H$1458,8,0),0) -> 0 | K406: =-IFERROR(VLOOKUP(C406,Gastos!$A$9:$J$1451,10,0),0) -> 0 | L406: =-IFERROR(VLOOKUP(C406,IDC!$A$20:$H$1763,8,0),0) -> -324.21 | M406: =+D406 -> -54034.24
A407: 03-10-2025 | B407: Impuesto por extracción | C407: 128497382094 | D407: -4517.66 | E407: 11628765 | F407: IDC | G407: =+D407/0.006 -> -752943.33 | I407: =-IFERROR(VLOOKUP(C407,SIRCUPA!$A$21:$H$221,8,0),0) -> 0 | J407: =-IFERROR(VLOOKUP(C407,SIRTAC!$A$16:$H$1458,8,0),0) -> 0 | K407: =-IFERROR(VLOOKUP(C407,Gastos!$A$9:$J$1451,10,0),0) -> 0 | M407: =+D407 -> -4517.66
A408: 03-10-2025 | B408: Transferencia programada PORCOMAGRO SRL | C408: 128497382094 | D408: -752944 | E408: 11633283 | F408: PAGO PROVEEDOR | G408: =+D408/1.006 -> -748453.28 | H408: =+D408-G408 -> -4490.7197 | I408: =-IFERROR(VLOOKUP(C408,SIRCUPA!$A$21:$H$221,8,0),0) -> 0 | J408: =-IFERROR(VLOOKUP(C408,SIRTAC!$A$16:$H$1458,8,0),0) -> 0 | K408: =-IFERROR(VLOOKUP(C408,Gastos!$A$9:$J$1451,10,0),0) -> 0 | L408: =-IFERROR(VLOOKUP(C408,IDC!$A$20:$H$1763,8,0),0) -> -4517.66 | M408: =+D408 -> -752944
...

Sheet Detallado
A1: INITIAL_BALANCE | B1: CREDITS | C1: DEBITS | D1: FINAL_BALANCE
A2: 10.882.608,51 | B2: 36.455.184,88 | C2: -36.709.247,69 | D2: 10.628.545,70
A4: RELEASE_DATE | B4: TRANSACTION_TYPE | C4: REFERENCE_ID | D4: TRANSACTION_NET_AMOUNT | E4: PARTIAL_BALANCE | F4: VARIOS | G4: TRANSACTION_TOTAL_AMOUNT | H4: IDC COMPRAS | I4: OBSERVACION
A5: 01-10-2025 | B5: Liquidación de dinero | C5: 127694553001 | D5: 8502.3 | E5: 10891111 | F5: VENTA | G5: =+D5 -> 8502.3
A6: 01-10-2025 | B6: Liquidación de dinero | C6: 127706300651 | D6: 7794.4 | E6: 10898905 | F6: VENTA | G6: =+D6 -> 7794.4
A7: 01-10-2025 | B7: Liquidación de dinero | C7: 127707346037 | D7: 8768.7 | E7: 10907674 | F7: VENTA | G7: =+D7 -> 8768.7
A8: 01-10-2025 | B8: Liquidación de dinero | C8: 128274716662 | D8: 10912.16 | E8: 10918586 | F8: VENTA | G8: =+D8 -> 10912.16
A9: 01-10-2025 | B9: Liquidación de dinero | C9: 128275855374 | D9: 44131.89 | E9: 10962718 | F9: VENTA | G9: =+D9 -> 44131.89
A10: 02-10-2025 | B10: Compra Mercado Libre | C10: 127758769693 | D10: -84292.74 | E10: 10863304 | G10: =+D10/1.006 -> -83790 | H10: =+D10-G10 -> -502.74 | I10: GALANSINO JORGE ALBERTO X $ 88200 DESCUENTO DE 4410
A11: 01-10-2025 | B11: Liquidación de dinero | C11: 127713602167 | D11: 487.15 | E11: 10965422 | F11: VENTA | G11: =+D11 -> 487.15
A12: 01-10-2025 | B12: Liquidación de dinero | C12: 127715107443 | D12: 30103.92 | E12: 10995525 | F12: VENTA | G12: =+D12 -> 30103.92
A13: 01-10-2025 | B13: Liquidación de dinero | C13: 127715769581 | D13: 38704.13 | E13: 11034230 | F13: VENTA | G13: =+D13 -> 38704.13
A14: 01-10-2025 | B14: Liquidación de dinero | C14: 128281546618 | D14: 25721.52 | E14: 11059951 | F14: VENTA | G14: =+D14 -> 25721.52
A15: 14-10-2025 | B15: Compra Mercado Libre | C15: 129327674841 | D15: -51378.43 | E15: 14229475 | G15: =+D15/1.006 -> -51071.998 | H15: =+D15-G15 -> -306.43199 | I15: CAJA NO IDENTIFIQUE FACTURA - 51072
A16: 01-10-2025 | B16: Liquidación de dinero | C16: 128281806306 | D16: 12665.9 | E16: 11075202 | F16: VENTA | G16: =+D16 -> 12665.9
A17: 16-10-2025 | B17: Compra Mercado Libre | C17: 130176556044 | D17: -165601.68 | E17: 11005033 | G17: =+D17/1.006 -> -164614 | H17: =+D17-G17 -> -987.68398 | I17: se devolvio / SIN FACTURA
A18: 01-10-2025 | B18: Liquidación de dinero | C18: 128282615258 | D18: 20215.64 | E18: 11096054 | F18: VENTA | G18: =+D18 -> 20215.64
A19: 01-10-2025 | B19: Liquidación de dinero | C19: 127717828761 | D19: 28761.05 | E19: 11124815 | F19: VENTA | G19: =+D19 -> 28761.05
A20: 01-10-2025 | B20: Liquidación de dinero | C20: 127719464653 | D20: 13160.72 | E20: 11137975 | F20: VENTA | G20: =+D20 -> 13160.72
A21: 01-10-2025 | B21: Liquidación de dinero | C21: 127719431701 | D21: 19484.05 | E21: 11157459 | F21: VENTA | G21: =+D21 -> 19484.05
A22: 01-10-2025 | B22: Liquidación de dinero | C22: 128285003346 | D22: 24747.22 | E22: 11182207 | F22: VENTA | G22: =+D22 -> 24747.22
A23: 01-10-2025 | B23: Liquidación de dinero | C23: 127719758089 | D23: 73459.3 | E23: 11255666 | F23: VENTA | G23: =+D23 -> 73459.3
A24: 01-10-2025 | B24: Liquidación de dinero | C24: 128285683510 | D24: 38972 | E24: 11294638 | F24: VENTA | G24: =+D24 -> 38972
A25: 01-10-2025 | B25: Liquidación de dinero | C25: 127720557799 | D25: 29226.08 | E25: 11323864 | F25: VENTA | G25: =+D25 -> 29226.08
A26: 01-10-2025 | B26: Liquidación de dinero | C26: 128286715036 | D26: 17050.25 | E26: 11340914 | F26: VENTA | G26: =+D26 -> 17050.25
A27: 02-10-2025 | B27: Liquidación de dinero | C27: 128287489024 | D27: 9645.57 | E27: 11350560 | F27: VENTA | G27: =+D27 -> 9645.57
A28: 02-10-2025 | B28: Liquidación de dinero | C28: 128287673862 | D28: 14321.24 | E28: 11364881 | F28: VENTA | G28: =+D28 -> 14321.24
A29: 16-10-2025 | B29: Compra Mercado Libre | C29: 129600289573 | D29: -82800.84 | E29: 10922232 | G29: =+D29/1.006 -> -82306.998 | H29: =+D29-G29 -> -493.84199 | I29: se devolvio / SIN FACTURA
A30: 02-10-2025 | B30: Liquidación de dinero | C30: 127722493817 | D30: 32970.03 | E30: 11400009 | F30: VENTA | G30: =+D30 -> 32970.03
A31: 02-10-2025 | B31: Liquidación de dinero | C31: 128288249068 | D31: 33192.11 | E31: 11433201 | F31: VENTA | G31: =+D31 -> 33192.11
A32: 02-10-2025 | B32: Liquidación de dinero | C32: 127724766231 | D32: 4354.65 | E32: 11437556 | F32: VENTA | G32: =+D32 -> 4354.65
A33: 02-10-2025 | B33: Transferencia enviada EMBOTELLADORA DEL ATLANTICO SA | C33: 128313425810 | D33: -193742.33 | E33: 11243813 | G33: =+D33/1.006 -> -192586.81 | H33: =+D33-G33 -> -1155.5209
A34: 16-10-2025 | B34: Compra Mercado Libre | C34: 130177050648 | D34: -367900.24 | E34: 10554332 | G34: =+D34/1.006 -> -365706 | H34: =+D34-G34 -> -2194.236 | I34: EMELINT SRL. - 365706
A35: 02-10-2025 | B35: Transferencia enviada EMBOTELLADORA DEL ATLANTICO SA | C35: 127751261829 | D35: -293293.89 | E35: 10949357 | G35: =+D35/1.006 -> -291544.62 | H35: =+D35-G35 -> -1749.2677
A36: 22-10-2025 | B36: Compra Mercado Libre | C36: 130909261908 | D36: -36832.06 | E36: 10918996 | G36: =+D36/1.006 -> -36612.386 | H36: =+D36-G36 -> -219.67431 | I36: BARONETTI ALEJANDRO DARIO x$22000 + envio x $ 14612,39
A37: 23-10-2025 | B37: Compra Mercado Libre | C37: 131021496516 | D37: -374232 | E37: 10487140 | G37: =+D37/1.006 -> -372000 | H37: =+D37-G37 -> -2232 | I37: FILOVALEN SRL - 372000
A38: 02-10-2025 | B38: Transferencia enviada FRUVECO S R L | C38: 127775364243 | D38: -203693.9 | E38: 10659611 | G38: =+D38/1.006 -> -202479.03 | H38: =+D38-G38 -> -1214.8742
A39: 11-10-2025 | B39: Débito por deuda Facturas vencidas de Mercado Libre | C39: 2430883946 | D39: -30049.69 | E39: 11485499 | G39: =+D39/1.006 -> -29870.467 | H39: =+D39-G39 -> -179.2228
A40: 02-10-2025 | B40: Transferencia enviada FRUVECO S R L | C40: 128340094018 | D40: -54034.24 | E40: 10604354 | G40: =+D40/1.006 -> -53711.968 | H40: =+D40-G40 -> -322.27181
A41: 16-10-2025 | B41: Devolución de dinero Compra de Lampara Led Classic Filamento 6w Cálida Glowlux - E... | C41: 129600289573 | D41: 82800.84 | E41: 10436268 | G41: =+D41/1.006 -> 82306.998 | H41: =+D41-G41 -> 493.84199 | I41: DEVOLUCION DEL DINERO
A42: 02-10-2025 | B42: Transferencia enviada FRUVECO S R L | C42: 127775080827 | D42: -217667.97 | E42: 10386362 | G42: =+D42/1.006 -> -216369.75 | H42: =+D42-G42 -> -1298.2185
A43: 16-10-2025 | B43: Devolución de dinero Compra de Lampara Led Classic Filamento 6w Cálida Glowlux - E... | C43: 130176556044 | D43: 165601.68 | E43: 10601870 | G43: =+D43/1.006 -> 164614 | H43: =+D43-G43 -> 987.68398 | I43: DEVOLUCION DEL DINERO
A44: 02-10-2025 | B44: Liquidación de dinero | C44: 127826757701 | D44: 9548.14 | E44: 10394604 | F44: VENTA | G44: =+D44 -> 9548.14
A45: 02-10-2025 | B45: Liquidación de dinero | C45: 128398739964 | D45: 9353.28 | E45: 10403957 | F45: VENTA | G45: =+D45 -> 9353.28
A46: 02-10-2025 | B46: Liquidación de dinero | C46: 127834309851 | D46: 13932.49 | E46: 10417890 | F46: VENTA | G46: =+D46 -> 13932.49
A47: 20-10-2025 | B47: Devolución de dinero FEPASA | C47: 130619610184 | D47: 349480.54 | E47: 15392584 | G47: =+D47/1.006 -> 347396.16 | H47: =+D47-G47 -> 2084.377 | I47: DEVOLUCION DEL DINERO
A48: 02-10-2025 | B48: Liquidación de dinero | C48: 128402388274 | D48: 12958.19 | E48: 10432948 | F48: VENTA | G48: =+D48 -> 12958.19
A49: 20-10-2025 | B49: Devolución de dinero FEPASA | C49: 130619613726 | D49: 349480.54 | E49: 14047039 | G49: =+D49/1.006 -> 347396.16 | H49: =+D49-G49 -> 2084.377 | I49: DEVOLUCION DEL DINERO
A50: 02-10-2025 | B50: Liquidación de dinero | C50: 127836305261 | D50: 30598.36 | E50: 10464848 | F50: VENTA | G50: =+D50 -> 30598.36
A51: 02-10-2025 | B51: Liquidación de dinero | C51: 128408491342 | D51: 4676.64 | E51: 10469525 | F51: VENTA | G51: =+D51 -> 4676.64
A52: 02-10-2025 | B52: Liquidación de dinero | C52: 128408853332 | D52: 4534.56 | E52: 10474060 | F52: VENTA | G52: =+D52 -> 4534.56
A53: 02-10-2025 | B53: Liquidación de dinero | C53: 127843829541 | D53: 37705.41 | E53: 10511765 | F53: VENTA | G53: =+D53 -> 37705.41
A54: 02-10-2025 | B54: Impuesto por extracción | C54: 128313425810 | D54: -1162.45 | E54: 11242651 | G54: =+D54 -> -1162.45 | H54: =+D54-G54 -> 0
A55: 02-10-2025 | B55: Liquidación de dinero | C55: 127845010923 | D55: 8768.7 | E55: 10522428 | F55: VENTA | G55: =+D55 -> 8768.7
A56: 02-10-2025 | B56: Liquidación de dinero | C56: 127845412065 | D56: 4676.64 | E56: 10527105 | F56: VENTA | G56: =+D56 -> 4676.64
A57: 02-10-2025 | B57: Impuesto por extracción | C57: 127751261829 | D57: -1759.76 | E57: 10947597 | G57: =+D57 -> -1759.76 | H57: =+D57-G57 -> 0
A58: 02-10-2025 | B58: Liquidación de dinero | C58: 127845621093 | D58: 4286.92 | E58: 10531862 | F58: VENTA | G58: =+D58 -> 4286.92
A59: 02-10-2025 | B59: Liquidación de dinero | C59: 127846108405 | D59: 3967.74 | E59: 10535829 | F59: VENTA | G59: =+D59 -> 3967.74
A60: 02-10-2025 | B60: Liquidación de dinero | C60: 127846250789 | D60: 3967.74 | E60: 10539797 | F60: VENTA | G60: =+D60 -> 3967.74
A61: 02-10-2025 | B61: Liquidación de dinero | C61: 128412427806 | D61: 25342.2 | E61: 10565139 | F61: VENTA | G61: =+D61 -> 25342.2
A62: 02-10-2025 | B62: Liquidación de dinero | C62: 127847014705 | D62: 14322.21 | E62: 10579461 | F62: VENTA | G62: =+D62 -> 14322.21
A63: 02-10-2025 | B63: Liquidación de dinero | C63: 128413285526 | D63: 4534.56 | E63: 10583996 | F63: VENTA | G63: =+D63 -> 4534.56
A64: 02-10-2025 | B64: Liquidación de dinero | C64: 127847143045 | D64: 4676.64 | E64: 10588673 | F64: VENTA | G64: =+D64 -> 4676.64
A65: 02-10-2025 | B65: Liquidación de dinero | C65: 128413748622 | D65: 9743 | E65: 10598416 | F65: VENTA | G65: =+D65 -> 9743
A66: 02-10-2025 | B66: Liquidación de dinero | C66: 127847979869 | D66: 29234.38 | E66: 10627650 | F66: VENTA | G66: =+D66 -> 29234.38
A67: 02-10-2025 | B67: Liquidación de dinero | C67: 127848195943 | D67: 33905.64 | E67: 10661556 | F67: VENTA | G67: =+D67 -> 33905.64
A68: 02-10-2025 | B68: Impuesto por extracción | C68: 127775364243 | D68: -1222.16 | E68: 10658388 | G68: =+D68 -> -1222.16 | H68: =+D68-G68 -> 0
A69: 02-10-2025 | B69: Liquidación de dinero | C69: 128414602122 | D69: 5628.98 | E69: 10672295 | F69: VENTA | G69: =+D69 -> 5628.98
A70: 02-10-2025 | B70: Liquidación de dinero | C70: 127848730441 | D70: 8768.7 | E70: 10681064 | F70: VENTA | G70: =+D70 -> 8768.7
A71: 02-10-2025 | B71: Liquidación de dinero | C71: 127849129705 | D71: 4676.64 | E71: 10685740 | F71: VENTA | G71: =+D71 -> 4676.64
A72: 02-10-2025 | B72: Liquidación de dinero | C72: 128415782272 | D72: 3897.2 | E72: 10689638 | F72: VENTA | G72: =+D72 -> 3897.2
A73: 02-10-2025 | B73: Liquidación de dinero | C73: 127850379377 | D73: 11301.88 | E73: 10700939 | F73: VENTA | G73: =+D73 -> 11301.88
A74: 02-10-2025 | B74: Liquidación de dinero | C74: 127850602909 | D74: 3897.2 | E74: 10704837 | F74: VENTA | G74: =+D74 -> 3897.2
A75: 02-10-2025 | B75: Liquidación de dinero | C75: 127850717607 | D75: 11169.34 | E75: 10716006 | F75: VENTA | G75: =+D75 -> 11169.34
A76: 02-10-2025 | B76: Liquidación de dinero | C76: 128416983560 | D76: 7404.68 | E76: 10723411 | F76: VENTA | G76: =+D76 -> 7404.68
A77: 02-10-2025 | B77: Liquidación de dinero | C77: 128417090472 | D77: 33955.46 | E77: 10757366 | F77: VENTA | G77: =+D77 -> 33955.46
A78: 02-10-2025 | B78: Impuesto por extracción | C78: 128340094018 | D78: -324.21 | E78: 10604030 | G78: =+D78 -> -324.21 | H78: =+D78-G78 -> 0
A79: 02-10-2025 | B79: Liquidación de dinero | C79: 128417478168 | D79: 4384.35 | E79: 10765412 | F79: VENTA | G79: =+D79 -> 4384.35
A80: 02-10-2025 | B80: Liquidación de dinero | C80: 127851297553 | D80: 3967.74 | E80: 10769380 | F80: VENTA | G80: =+D80 -> 3967.74
A81: 02-10-2025 | B81: Liquidación de dinero | C81: 127851529137 | D81: 9743 | E81: 10779123 | F81: VENTA | G81: =+D81 -> 9743
A82: 02-10-2025 | B82: Liquidación de dinero | C82: 127852042311 | D82: 2338.32 | E82: 10781461 | F82: VENTA | G82: =+D82 -> 2338.32
A83: 02-10-2025 | B83: Liquidación de dinero | C83: 127852662327 | D83: 29911.01 | E83: 10811372 | F83: VENTA | G83: =+D83 -> 29911.01
A84: 02-10-2025 | B84: Liquidación de dinero | C84: 128418794938 | D84: 3897.2 | E84: 10815269 | F84: VENTA | G84: =+D84 -> 3897.2
A85: 02-10-2025 | B85: Liquidación de dinero | C85: 127852972373 | D85: 4676.64 | E85: 10819946 | F85: VENTA | G85: =+D85 -> 4676.64
A86: 02-10-2025 | B86: Liquidación de dinero | C86: 128419226662 | D86: 3967.74 | E86: 10823914 | F86: VENTA | G86: =+D86 -> 3967.74
A87: 02-10-2025 | B87: Liquidación de dinero | C87: 128419350310 | D87: 93825.09 | E87: 10917739 | F87: VENTA | G87: =+D87 -> 93825.09
A88: 02-10-2025 | B88: Liquidación de dinero | C88: 128419431770 | D88: 23772.92 | E88: 10941512 | F88: VENTA | G88: =+D88 -> 23772.92
A89: 02-10-2025 | B89: Liquidación de dinero | C89: 128419732970 | D89: 4676.64 | E89: 10946188 | F89: VENTA | G89: =+D89 -> 4676.64
A90: 02-10-2025 | B90: Liquidación de dinero | C90: 127853704713 | D90: 9743 | E90: 10955931 | F90: VENTA | G90: =+D90 -> 9743
A91: 02-10-2025 | B91: Impuesto por extracción | C91: 127775080827 | D91: -1306.01 | E91: 10385056 | G91: =+D91 -> -1306.01 | H91: =+D91-G91 -> 0
A92: 02-10-2025 | B92: Liquidación de dinero | C92: 127853815447 | D92: 18121.98 | E92: 10974543 | F92: VENTA | G92: =+D92 -> 18121.98
A93: 02-10-2025 | B93: Liquidación de dinero | C93: 128420232980 | D93: 41661.27 | E93: 11016204 | F93: VENTA | G93: =+D93 -> 41661.27
A94: 02-10-2025 | B94: Liquidación de dinero | C94: 127854076319 | D94: 6138.09 | E94: 11022342 | F94: VENTA | G94: =+D94 -> 6138.09
A95: 02-10-2025 | B95: Liquidación de dinero | C95: 128420407042 | D95: 210340.26 | E95: 11232682 | F95: VENTA | G95: =+D95 -> 210340.26
A96: 02-10-2025 | B96: Liquidación de dinero | C96: 127854278121 | D96: 6138.09 | E96: 11238820 | F96: VENTA | G96: =+D96 -> 6138.09
A97: 02-10-2025 | B97: Liquidación de dinero | C97: 128420454022 | D97: 9743 | E97: 11248563 | F97: VENTA | G97: =+D97 -> 9743
A98: 02-10-2025 | B98: Liquidación de dinero | C98: 127854437157 | D98: 46376.68 | E98: 11294940 | F98: VENTA | G98: =+D98 -> 46376.68
A99: 02-10-2025 | B99: Liquidación de dinero | C99: 128420793726 | D99: 7112.39 | E99: 11302052 | F99: VENTA | G99: =+D99 -> 7112.39
A100: 03-10-2025 | B100: Liquidación de dinero | C100: 127854884711 | D100: 4871.5 | E100: 11306924 | F100: VENTA | G100: =+D100 -> 4871.5
A101: 03-10-2025 | B101: Liquidación de dinero | C101: 127854922579 | D101: 29597.54 | E101: 11336522 | F101: VENTA | G101: =+D101 -> 29597.54
...

Sheet TR
A3: Suma de MOV TOTAL | B3: Etiquetas de columna
A4: Etiquetas de fila | B4: ARCA | C4: COBRO | D4: IDC | E4: PAGO PROVEEDOR | F4: PAGO PROVEEDOR / DEVOL | G4: RETIRO / PROV | H4: Total general
A5: Compra Mercado Libre | E5: -1156101.4 | H5: -1156101.4 | I5: C
A6: Débito por deuda Facturas vencidas de Mercado Libre | E6: -29870.467 | H6: -29870.467
A7: Devolución de dinero Compra de Lampara Led Classic Filamento 6w Cálida Glowlux - E... | F7: 246921 | H7: 246921 | I7: C
A8: Devolución de dinero FEPASA | F8: 698961.08 | H8: 698961.08 | I8: C | J8: ASIENTO 90 B | K8: COBRO DS X VENTA | L8: =SUM(H10:H11,H42:H213) -> 36859803 | M8: modificado
A9: Impuesto por extracción | D9: -106666.96 | H9: -106666.96 | J9: ASIENTO 91 B | K9: PAGO PROVEEDORES | L9: =SUM(H8,H12,H13,H15:H37,H39:H41) -> -31612498 | M9: modificado
A10: Liquidación de dinero | C10: 36647384 | H10: 36647384 | K10: VER SI HAY COMPRA
A11: Liquidación de dinero cancelada Venta cancelada | C11: -170000 | H11: -170000 | K11: IMPUESTOS | L11: =+GETPIVOTDATA("MOV TOTAL",$A$3,"TRANSACTION_TYPE","Pago de servicios ARCA") -> -2632600.8 | M11: modificado
A12: Pago con QR Coca-Cola ANDINA | E12: -1256978.2 | H12: -1256978.2 | I12: C | K12: VER QUE ES
A13: Pago con QR FEPASA | E13: -952861.53 | H13: -952861.53 | I13: C | J13: ASIENTO 91 B | K13: CERVEZA TRACTOR
A14: Pago de servicios ARCA | B14: -2632600.8 | H14: -2632600.8 | I14: C | J14: ASIENTO 92 B | K14: CAJA | L14: =+GETPIVOTDATA("MOV TOTAL",$A$3,"TRANSACTION_TYPE","Transferencia enviada SUCESION LAPORTA FRANCISCO AN") -> -199666.29 | M14: modificado
A15: Transferencia enviada | E15: -110400.01 | H15: -110400.01 | I15: C
A16: Transferencia enviada ACERO JEKLO SAS | E16: -1201400 | H16: -1201400 | I16: C
A17: Transferencia enviada BACO DE LOS ANDES SA | E17: -3648174.2 | H17: -3648174.2 | I17: C
A18: Transferencia enviada BASSO REPRESENT SRL | E18: -1062148.8 | H18: -1062148.8 | I18: C
A19: Transferencia enviada CAMILA SCARDINO | E19: -195300 | H19: -195300 | I19: C
A20: Transferencia enviada CDG SRL | E20: -291947 | H20: -291947 | I20: C
A21: Transferencia enviada Cerveza Tractor | G21: -5062000 | H21: -5062000 | I21: C
A22: Transferencia enviada DE BRABAND AGUSTIN | E22: -752812.33 | H22: -752812.33 | I22: C
A23: Transferencia enviada Distribuidora Doña Dora | E23: -1574854.8 | H23: -1574854.8 | I23: C
A24: Transferencia enviada DOÑA DORA | E24: -437569.01 | H24: -437569.01 | I24: C
A25: Transferencia enviada EMBOTELLADORA DEL ATLANTICO SA | E25: -827759.92 | H25: -827759.92 | I25: C
A26: Transferencia enviada ERPEN JULIO C. Y PONZONI ANTONELLA P. SOCIEDAD SIMPLE | E26: -5025324 | H26: -5025324 | I26: C
A27: Transferencia enviada FRUVECO S R L | E27: -2186142.8 | H27: -2186142.8 | I27: C
A28: Transferencia enviada GONZALES SILVIA NOEMI | E28: -575000 | H28: -575000 | I28: C
A29: Transferencia enviada Gustavo Eugenio Gatter | E29: -155300.02 | H29: -155300.02 | I29: C
A30: Transferencia enviada LAGUNA CAPRI SAS | E30: -1281400 | H30: -1281400 | I30: C
A31: Transferencia enviada LOS DOS HERMANOS SH | E31: -25668 | H31: -25668 | I31: C
A32: Transferencia enviada Mariano Pedro Rebord Palazzo | E32: -1014382.6 | H32: -1014382.6 | I32: C
A33: Transferencia enviada Norberto David Dolcet | E33: -375842.94 | H33: -375842.94 | I33: C
... A41: Transferencia programada PORCOMAGRO SRL | E41: -752944 | H41: -752944 | I41: C
A42: Transferencia recibida Abigail Burguez | C42: 930 | H42: 930
A43: Transferencia recibida Adrian Nicolas Arroyo | C43: 600 | H43: 600
A44: Transferencia recibida Agustin Ferrari | C44: 1925 | H44: 1925
A45: Transferencia recibida Agustin Manuel Ortolani | C45: 4700 | H45: 4700
A46: Transferencia recibida Agustin Rivero | C46: 1995 | H46: 1995
A47: Transferencia recibida Agustina Lorena Aste | C47: 420 | H47: 420
A48: Transferencia recibida Alan Bochatay | C48: 915 | H48: 915
A49: Transferencia recibida Alberto Jesus Lucarni | C49: 1235 | H49: 1235
A50: Transferencia recibida Aldana Victoria Popov Lusardi | C50: 2045 | H50: 2045
A51: Transferencia recibida Alexis Maximiliano Dominguez | C51: 2399 | H51: 2399
A52: Transferencia recibida Amina Alfonso | C52: 480 | H52: 480
A53: Transferencia recibida Ana Paula Orsingher | C53: 1000 | H53: 1000
... A213: Transferencia recibida Yo | C213: 3740 | H213: 3740
A214: Total general | B214: -2632600.8 | C214: 36859803 | D214: -106666.96 | E214: -28635097 | F214: 945882.08 | G214: -5062000 | H214: 1369320.5

Sheet Tabla Resumen
A3: Etiquetas de fila | B3: Suma de TRANSACTION_NET_AMOUNT
A4: Compra Mercado Libre | B4: -1163038 | C4: Contab. | F4: ASIENTO 90 B | G4: COBRO DS X VENTA | H4: =SUM(B41:B212,B9,B10) -> 35342056
A5: Débito por deuda Facturas vencidas de Mercado Libre | B5: -30049.69 | C5: Contab. | D5: Percepción factura MP + IDyC (contab. Globalmente) | F5: ASIENTO 91 B | G5: PAGO PROVEEDORES | H5: =SUM(B11,B15:B36,B38:B40)-110400-253900.45 -> -31696041
A6: Devolución de dinero Compra de Lampara Led Classic Filamento 6w Cálida Glowlux - E... | B6: 248402.52 | C6: Contab. | D6: devolución compra mercado libre | G6: VER SI HAY COMPRA
A7: Devolución de dinero FEPASA | B7: 698961.08 | C7: Contab. | G7: VER SI CONCILIA CON IMPUESTOS | H7: =+GETPIVOTDATA("TRANSACTION_NET_AMOUNT",$A$3,"TRANSACTION_TYPE","Pago de servicios ARCA") -> -2648396.4
A8: Impuesto por extracción | B8: -106666.96 | C8: Contab. | D8: Corresponde IDyC ya contabilizados globalmente | G8: VER QUE ES
A9: Liquidación de dinero | B9: 35129240 | C9: Contab. | F9: ASIENTO 91 B | G9: CERVEZA TRACTOR
A10: Liquidación de dinero cancelada Venta cancelada | B10: -161571.91 | C10: Contab. | F10: ASIENTO 92 B | G10: CAJA
A11: Pago con QR Coca-Cola ANDINA | B11: -1256978.2 | C11: Contab.
A12: Pago con QR FEPASA | B12: -952861.53 | C12: Contab. | D12: PROVEEDORES X $253900,45 - DEVOLUCION DEL DINERO POR LA DIFERENCIA $698961,08
A13: Pago de servicios ARCA | B13: -2648396.4 | C13: Contab.
A14: Transferencia enviada | B14: -111062.41 | C14: Contab. | D14: PROVEEDORES / Brode Hermanos x $110400 + IDyC (contabilizado globalmente)
A15: Transferencia enviada ACERO JEKLO SAS | B15: -1201400 | C15: Contab.
A16: Transferencia enviada BACO DE LOS ANDES SA | B16: -3648174.2 | C16: Contab.
A17: Transferencia enviada BASSO REPRESENT SRL | B17: -1062148.8 | C17: Contab.
A18: Transferencia enviada CAMILA SCARDINO | B18: -195300 | C18: Contab.
A19: Transferencia enviada CDG SRL | B19: -291947 | C19: Contab.
A20: Transferencia enviada Cerveza Tractor | B20: -5091172 | C20: Contab. | D20: Va a proveedores / Hay facturas
A21: Transferencia enviada DE BRABAND AGUSTIN | B21: -752812.33 | C21: Contab.
A22: Transferencia enviada Distribuidora Doña Dora | B22: -1584304 | C22: Contab.
A23: Transferencia enviada DOÑA DORA | B23: -440194.42 | C23: Contab.
A24: Transferencia enviada EMBOTELLADORA DEL ATLANTICO SA | B24: -827759.92 | C24: Contab.
A25: Transferencia enviada ERPEN JULIO C. Y PONZONI ANTONELLA P. SOCIEDAD SIMPLE | B25: -5055475.9 | C25: Contab.
A26: Transferencia enviada FRUVECO S R L | B26: -2186142.8 | C26: Contab.
A27: Transferencia enviada GONZALES SILVIA NOEMI | B27: -575000 | C27: Contab.
A28: Transferencia enviada Gustavo Eugenio Gatter | B28: -156231.82 | C28: Contab.
A29: Transferencia enviada LAGUNA CAPRI SAS | B29: -1281400 | C29: Contab.
A30: Transferencia enviada LOS DOS HERMANOS SH | B30: -25668 | C30: Contab.
A31: Transferencia enviada Mariano Pedro Rebord Palazzo | B31: -1020468.9 | C31: Contab.
A32: Transferencia enviada Norberto David Dolcet | B32: -378098 | C32: Contab.
... A36: Transferencia enviada SUCESION DE SATTO | B36: -246159.3 | C36: Contab.
A37: Transferencia enviada SUCESION LAPORTA FRANCISCO AN | B37: -199666.29 | C37: Contab. | D37: NO HAY FACTURA / CAJA
A38: Transferencia enviada TICKET BAND SRL | B38: -1167650 | C38: Contab.
A39: Transferencia enviada TRES ORILLAS SRL | B39: -1049664 | C39: Contab.
A40: Transferencia programada PORCOMAGRO SRL | B40: -752944 | C40: Contab.
A41: Transferencia recibida Abigail Burguez | B41: 910.47 | C41: Contab.
A42: Transferencia recibida Adrian Nicolas Arroyo | B42: 587.4 | C42: Contab.
A43: Transferencia recibida Agustin Ferrari | B43: 1884.57 | C43: Contab.
A44: Transferencia recibida Agustin Manuel Ortolani | B44: 4601.3 | C44: Contab.
A45: Transferencia recibida Agustin Rivero | B45: 1953.1 | C45: Contab.
A46: Transferencia recibida Agustina Lorena Aste | B46: 411.18 | C46: Contab.
A47: Transferencia recibida Alan Bochatay | B47: 895.78 | C47: Contab.
A48: Transferencia recibida Alberto Jesus Lucarni | B48: 1209.06 | C48: Contab.
A49: Transferencia recibida Aldana Victoria Popov Lusardi | B49: 2002.05 | C49: Contab.
... A212: Transferencia recibida Yo | B212: 3661.46 | C212: Contab.
A213: Total general | B213: -254062.81

Sheet SIRCUPA
A1: Reporte-Retención-SIRCUPA-Octubre-CC20250609171159-MercadoPago
A3: Usuario: | B3: CC20250609171159
A4: Impuesto: | B4: Retención SIRCUPA
A5: Fecha de descarga: | B5: 18/03/2026
A6: Intervalo de fechas consultadas: | B6: 01/10/2025 a 01/11/2025
A8: Total | B8: Monto
A9: Base imponible | B9: $382.419,00
A10: Tramo 1 - retenido del 01/10 al 10/10 | B10: $2.320,83
A11: Tramo 2 - retenido del 11/10 al 20/10 | B11: $2.161,32
A12: Tramo 3 - retenido del 21/10 al 31/10 | B12: $1.254,38
A13: Importe retenido | B13: $5.736,53
A14: Importe devuelto | B14: $0,00
A16: Podrás utilizar este reporte para conciliar lo que retuvimos.
A17: Podrás buscar el detalle de lo retenido en tu operación en la sección Actividad.
A19: Operación | E19: Impuesto
A20: Número de operación | B20: Fecha de operación | C20: Tipo | D20: Monto de transferencia | E20: Fecha de retención | F20: Alícuota | G20: Base imponible | H20: Importe retenido
A21: 128275829832 | B21: 01/10/2025 | C21: Transferencia | D21: 2264 | E21: 01/10/2025 | F21: 1,50 % | G21: 2264 | H21: 33.96
A22: 128287834208 | B22: 01/10/2025 | C22: Transferencia | D22: 2204 | E22: 02/10/2025 | F22: 1,50 % | G22: 2204 | H22: 33.06
A23: 128281517156 | B23: 01/10/2025 | C23: Transferencia | D23: 2640 | E23: 01/10/2025 | F23: 1,50 % | G23: 2640 | H23: 39.6
A24: 128281760842 | B24: 01/10/2025 | C24: Transferencia | D24: 650 | E24: 01/10/2025 | F24: 1,50 % | G24: 650 | H24: 9.75
A25: 127834303877 | B25: 02/10/2025 | C25: Transferencia | D25: 2145 | E25: 02/10/2025 | F25: 1,50 % | G25: 2145 | H25: 32.18
A26: 128402325040 | B26: 02/10/2025 | C26: Transferencia | D26: 1330 | E26: 02/10/2025 | F26: 1,50 % | G26: 1330 | H26: 19.95
A27: 128414396282 | B27: 02/10/2025 | C27: Transferencia | D27: 5220 | E27: 02/10/2025 | F27: 1,50 % | G27: 5220 | H27: 78.3
A28: 128410134666 | B28: 02/10/2025 | C28: Transferencia | D28: 1935 | E28: 02/10/2025 | F28: 1,50 % | G28: 1935 | H28: 29.03
A29: 127853669293 | B29: 02/10/2025 | C29: Transferencia | D29: 500 | E29: 02/10/2025 | F29: 1,50 % | G29: 500 | H29: 7.5
A30: 128411521730 | B30: 02/10/2025 | C30: Transferencia | D30: 480 | E30: 02/10/2025 | F30: 1,50 % | G30: 480 | H30: 7.2
A31: 128422276166 | B31: 02/10/2025 | C31: Transferencia | D31: 600 | E31: 03/10/2025 | F31: 1,50 % | G31: 600 | H31: 9
A32: 128423104492 | B32: 02/10/2025 | C32: Transferencia | D32: 2990 | E32: 03/10/2025 | F32: 1,50 % | G32: 2990 | H32: 44.85
... A221: 131426410673 | B221: 31/10/2025 | C221: Transferencia | D221: 480 | E221: 31/10/2025 | F221: 1,50 % | G221: 480 | H221: 7.2
G223: =SUM(G21:G222) -> 382419 | H223: =SUM(H21:H222) -> 5736.53

Sheet SIRTAC
A1: Reporte-Retención-SIRTAC-inscripto-1ra-quincena-Octubre-CC20250609171159-MercadoPago
A3: Usuario: | B3: CC20250609171159
A4: Impuesto: | B4: Retención SIRTAC
A5: Fecha de descarga: | B5: 18/03/2026
A6: Intervalo de fechas consultadas: | B6: 01/10/2025 a 16/10/2025
A8: Total | B8: Monto
A9: Base imponible | B9: $19.033.940,00
A10: Importe retenido | B10: $190.339,40
A11: Importe devuelto | B11: $1.576,00
A12: Podrás conciliar la información con otros reportes de Mercado Libre. | D12: Podrás buscar el detalle de lo retenido en tu operación en la sección Actividad.
A14: Operación | E14: Impuesto
A15: Número de operación | B15: Número de venta - Referencia externa | C15: Fecha de operación | D15: Tipo | E15: Fecha de retención | F15: Alícuota | G15: Base imponible | H15: Importe retenido
A16: 127694553001 | B16: Venta presencial | C16: 01/10/2025 | D16: Venta | E16: 01/10/2025 | F16: 1,00 % | G16: 9000 | H16: 90
A17: 127706300651 | C17: 01/10/2025 | D17: Venta | E17: 01/10/2025 | F17: 1,00 % | G17: 8000 | H17: 80
A18: 127707346037 | C18: 01/10/2025 | D18: Venta | E18: 01/10/2025 | F18: 1,00 % | G18: 9000 | H18: 90
A19: 128274716662 | C19: 01/10/2025 | D19: Venta | E19: 01/10/2025 | F19: 1,00 % | G19: 11200 | H19: 112
A20: 128275855374 | C20: 01/10/2025 | D20: Venta | E20: 01/10/2025 | F20: 1,00 % | G20: 45296 | H20: 452.96
A21: 127715107443 | C21: 01/10/2025 | D21: Venta | E21: 01/10/2025 | F21: 1,00 % | G21: 30898 | H21: 308.98
A22: 128281806306 | C22: 01/10/2025 | D22: Venta | E22: 01/10/2025 | F22: 1,00 % | G22: 13000 | H22: 130
A23: 127719431701 | C23: 01/10/2025 | D23: Venta | E23: 01/10/2025 | F23: 1,00 % | G23: 19998 | H23: 199.98
A24: 127719758089 | C24: 01/10/2025 | D24: Venta | E24: 01/10/2025 | F24: 1,00 % | G24: 75397 | H24: 753.97
A25: 128285683510 | C25: 01/10/2025 | D25: Venta | E25: 01/10/2025 | F25: 1,00 % | G25: 40000 | H25: 400
A26: 128286715036 | C26: 01/10/2025 | D26: Venta | E26: 01/10/2025 | F26: 1,00 % | G26: 17500 | H26: 175
A27: 127713602167 | C27: 01/10/2025 | D27: Venta | E27: 01/10/2025 | F27: 1,00 % | G27: 500 | H27: 5
A28: 128287489024 | C28: 01/10/2025 | D28: Venta | E28: 02/10/2025 | F28: 1,00 % | G28: 9900 | H28: 99
A29: 127722493817 | B29: Venta presencial | C29: 01/10/2025 | D29: Venta | E29: 02/10/2025 | F29: 1,00 % | G29: 34900 | H29: 349
A30: 128288249068 | C30: 01/10/2025 | D30: Venta | E30: 02/10/2025 | F30: 1,00 % | G30: 34300 | H30: 343
A31: 127715769581 | C31: 01/10/2025 | D31: Venta | E31: 01/10/2025 | F31: 1,00 % | G31: 39996 | H31: 399.96
A32: 128281546618 | C32: 01/10/2025 | D32: Venta | E32: 01/10/2025 | F32: 1,00 % | G32: 26400 | H32: 264
A33: 127724766231 | C33: 02/10/2025 | D33: Venta | E33: 02/10/2025 | F33: 1,00 % | G33: 4500 | H33: 45
A34: 128282615258 | B34: Venta presencial | C34: 01/10/2025 | D34: Venta | E34: 01/10/2025 | F34: 1,00 % | G34: 21399 | H34: 213.99
A35: 127717828761 | B35: Venta presencial | C35: 01/10/2025 | D35: Venta | E35: 01/10/2025 | F35: 1,00 % | G35: 32998 | H35: 329.98
A36: 127719464653 | C36: 01/10/2025 | D36: Venta | E36: 01/10/2025 | F36: 1,00 % | G36: 13600 | H36: 136
A37: 128285003346 | C37: 01/10/2025 | D37: Venta | E37: 01/10/2025 | F37: 1,00 % | G37: 25400 | H37: 254
A38: 127720557799 | C38: 01/10/2025 | D38: Venta | E38: 01/10/2025 | F38: 1,00 % | G38: 29997 | H38: 299.97
A39: 128287673862 | C39: 01/10/2025 | D39: Venta | E39: 02/10/2025 | F39: 1,00 % | G39: 14699 | H39: 146.99
A40: 128398739964 | C40: 02/10/2025 | D40: Venta | E40: 02/10/2025 | F40: 1,00 % | G40: 9600 | H40: 96
A41: 128402388274 | C41: 02/10/2025 | D41: Venta | E41: 02/10/2025 | F41: 1,00 % | G41: 13300 | H41: 133
A42: 127836305261 | B42: Venta presencial | C42: 02/10/2025 | D42: Venta | E42: 02/10/2025 | F42: 1,00 % | G42: 32600 | H42: 326
A43: 127826757701 | C43: 02/10/2025 | D43: Venta | E43: 02/10/2025 | F43: 1,00 % | G43: 9800 | H43: 98
A44: 128408853332 | B44: Venta presencial | C44: 02/10/2025 | D44: Venta | E44: 02/10/2025 | F44: 1,00 % | G44: 4800 | H44: 48
A45: 127834309851 | C45: 02/10/2025 | D45: Venta | E45: 02/10/2025 | F45: 1,00 % | G45: 14300 | H45: 143
A46: 127845412065 | C46: 02/10/2025 | D46: Venta | E46: 02/10/2025 | F46: 1,00 % | G46: 4800 | H46: 48
A47: 127846108405 | B47: Venta presencial | C47: 02/10/2025 | D47: Venta | E47: 02/10/2025 | F47: 1,00 % | G47: 4200 | H47: 42
A48: 127846250789 | B48: Venta presencial | C48: 02/10/2025 | D48: Venta | E48: 02/10/2025 | F48: 1,00 % | G48: 4200 | H48: 42
A49: 128412427806 | B49: Venta presencial | C49: 02/10/2025 | D49: Venta | E49: 02/10/2025 | F49: 1,00 % | G49: 27000 | H49: 270
A50: 128413285526 | B50: Venta presencial | C50: 02/10/2025 | D50: Venta | E50: 02/10/2025 | F50: 1,00 % | G50: 4800 | H50: 48
A51: 127847143045 | C51: 02/10/2025 | D51: Venta | E51: 02/10/2025 | F51: 1,00 % | G51: 4800 | H51: 48
A52: 127848195943 | C52: 02/10/2025 | D52: Venta | E52: 02/10/2025 | F52: 1,00 % | G52: 34800 | H52: 348
A53: 127848730441 | C53: 02/10/2025 | D53: Venta | E53: 02/10/2025 | F53: 1,00 % | G53: 9000 | H53: 90
A54: 127850602909 | C54: 02/10/2025 | D54: Venta | E54: 02/10/2025 | F54: 1,00 % | G54: 4000 | H54: 40
A55: 128408491342 | C55: 02/10/2025 | D55: Venta | E55: 02/10/2025 | F55: 1,00 % | G55: 4800 | H55: 48
A56: 128417090472 | C56: 02/10/2025 | D56: Venta | E56: 02/10/2025 | F56: 1,00 % | G56: 37400 | H56: 374
A57: 127851297553 | B57: Venta presencial | C57: 02/10/2025 | D57: Venta | E57: 02/10/2025 | F57: 1,00 % | G57: 4200 | H57: 42
A58: 127851529137 | C58: 02/10/2025 | D58: Venta | E58: 02/10/2025 | F58: 1,00 % | G58: 10000 | H58: 100
A59: 127843829541 | C59: 02/10/2025 | D59: Venta | E59: 02/10/2025 | F59: 1,00 % | G59: 38700 | H59: 387
A60: 127852662327 | C60: 02/10/2025 | D60: Venta | E60: 02/10/2025 | F60: 1,00 % | G60: 30700 | H60: 307
A61: 128418794938 | C61: 02/10/2025 | D61: Venta | E61: 02/10/2025 | F61: 1,00 % | G61: 4000 | H61: 40
A62: 128419350310 | C62: 02/10/2025 | D62: Venta | E62: 02/10/2025 | F62: 1,00 % | G62: 96300 | H62: 963
A63: 127845010923 | C63: 02/10/2025 | D63: Venta | E63: 02/10/2025 | F63: 1,00 % | G63: 9000 | H63: 90
A64: 128419431770 | C64: 02/10/2025 | D64: Venta | E64: 02/10/2025 | F64: 1,00 % | G64: 24400 | H64: 244
A65: 127853704713 | C65: 02/10/2025 | D65: Venta | E65: 02/10/2025 | F65: 1,00 % | G65: 10000 | H65: 100
A66: 127845621093 | C66: 02/10/2025 | D66: Venta | E66: 02/10/2025 | F66: 1,00 % | G66: 4400 | H66: 44
A67: 127853815447 | C67: 02/10/2025 | D67: Venta | E67: 02/10/2025 | F67: 1,00 % | G67: 18600 | H67: 186
A68: 128420232980 | B68: Venta presencial | C68: 02/10/2025 | D68: Venta | E68: 02/10/2025 | F68: 1,00 % | G68: 44100 | H68: 441
A69: 127854278121 | C69: 02/10/2025 | D69: Venta | E69: 02/10/2025 | F69: 1,00 % | G69: 6300 | H69: 63
A70: 128420454022 | C70: 02/10/2025 | D70: Venta | E70: 02/10/2025 | F70: 1,00 % | G70: 10000 | H70: 100
A71: 128420793726 | C71: 02/10/2025 | D71: Venta | E71: 02/10/2025 | F71: 1,00 % | G71: 7300 | H71: 73
A72: 127854922579 | C72: 02/10/2025 | D72: Venta | E72: 03/10/2025 | F72: 1,00 % | G72: 32600 | H72: 326
A73: 128421266626 | C73: 02/10/2025 | D73: Venta | E73: 03/10/2025 | F73: 1,00 % | G73: 4300 | H73: 43
A74: 128421434434 | C74: 02/10/2025 | D74: Venta | E74: 03/10/2025 | F74: 1,00 % | G74: 9600 | H74: 96
A75: 128421490336 | C75: 02/10/2025 | D75: Venta | E75: 03/10/2025 | F75: 1,00 % | G75: 13600 | H75: 136
A76: 127847014705 | C76: 02/10/2025 | D76: Venta | E76: 02/10/2025 | F76: 1,00 % | G76: 14700 | H76: 147
A77: 127855461023 | B77: Venta presencial | C77: 02/10/2025 | D77: Venta | E77: 03/10/2025 | F77: 1,00 % | G77: 16100 | H77: 161
A78: 128413748622 | C78: 02/10/2025 | D78: Venta | E78: 02/10/2025 | F78: 1,00 % | G78: 10000 | H78: 100
A79: 128422197004 | C79: 02/10/2025 | D79: Venta | E79: 03/10/2025 | F79: 1,00 % | G79: 4000 | H79: 40
A80: 128421075828 | B80: Venta presencial | C80: 02/10/2025 | D80: Devolución | E80: 03/10/2025 | F80: 1,00 % | G80: -113700 | H80: -1137
A81: 127856064757 | B81: Venta presencial | C81: 02/10/2025 | D81: Venta | E81: 03/10/2025 | F81: 1,00 % | G81: 36600 | H81: 366
A82: 127856418189 | C82: 02/10/2025 | D82: Venta | E82: 03/10/2025 | F82: 1,00 % | G82: 7000 | H82: 70
A83: 127847979869 | C83: 02/10/2025 | D83: Venta | E83: 02/10/2025 | F83: 1,00 % | G83: 32200 | H83: 322
A84: 128414602122 | B84: Venta presencial | C84: 02/10/2025 | D84: Venta | E84: 02/10/2025 | F84: 1,00 % | G84: 6200 | H84: 62
A85: 128423208738 | B85: Venta presencial | C85: 02/10/2025 | D85: Venta | E85: 03/10/2025 | F85: 1,00 % | G85: 4800 | H85: 48
A86: 128423356546 | C86: 02/10/2025 | D86: Venta | E86: 03/10/2025 | F86: 1,00 % | G86: 13000 | H86: 130
A87: 127857063969 | C87: 02/10/2025 | D87: Venta | E87: 03/10/2025 | F87: 1,00 % | G87: 10300 | H87: 103
A88: 128423642872 | C88: 02/10/2025 | D88: Venta | E88: 03/10/2025 | F88: 1,00 % | G88: 52600 | H88: 526
A89: 127849129705 | C89: 02/10/2025 | D89: Venta | E89: 02/10/2025 | F89: 1,00 % | G89: 4800 | H89: 48
A90: 127857712847 | C90: 02/10/2025 | D90: Venta | E90: 03/10/2025 | F90: 1,00 % | G90: 4800 | H90: 48
A91: 128415782272 | C91: 02/10/2025 | D91: Venta | E91: 02/10/2025 | F91: 1,00 % | G91: 4000 | H91: 40
A92: 127857973671 | C92: 03/10/2025 | D92: Venta | E92: 03/10/2025 | F92: 1,00 % | G92: 10000 | H92: 100
A93: 127858454489 | C93: 03/10/2025 | D93: Venta | E93: 03/10/2025 | F93: 1,00 % | G93: 4800 | H93: 48
A94: 127850379377 | C94: 02/10/2025 | D94: Venta | E94: 02/10/2025 | F94: 1,00 % | G94: 11600 | H94: 116
A95: 128424874738 | C95: 03/10/2025 | D95: Venta | E95: 03/10/2025 | F95: 1,00 % | G95: 20700 | H95: 207
A96: 127850717607 | B96: Venta presencial | C96: 02/10/2025 | D96: Venta | E96: 02/10/2025 | F96: 1,00 % | G96: 11900 | H96: 119
A97: 128416983560 | C97: 02/10/2025 | D97: Venta | E97: 02/10/2025 | F97: 1,00 % | G97: 7600 | H97: 76
A98: 128417478168 | C98: 02/10/2025 | D98: Venta | E98: 02/10/2025 | F98: 1,00 % | G98: 4500 | H98: 45
A99: 128425421186 | C99: 03/10/2025 | D99: Venta | E99: 03/10/2025 | F99: 1,00 % | G99: 2400 | H99: 24
A100: 128425586550 | B100: Venta presencial | C100: 03/10/2025 | D100: Venta | E100: 03/10/2025 | F100: 1,00 % | G100: 34700 | H100: 347
A101: 127859588493 | C101: 03/10/2025 | D101: Venta | E101: 03/10/2025 | F101: 1,00 % | G101: 160500 | H101: 1605
A102: 127852042311 | C102: 02/10/2025 | D102: Venta | E102: 02/10/2025 | F102: 1,00 % | G102: 2400 | H102: 24
A103: 128425855926 | B103: Venta presencial | C103: 03/10/2025 | D103: Venta | E103: 03/10/2025 | F103: 1,00 % | G103: 4500 | H103: 45
...

Sheet Gastos
A1: Fecha de actualización | C1: 46125.405
A3: Sumamos nuevas columnas a tu reporte: Trabajamos para brindarte más detalle sobre los cargos por utilizar Mercado Pago. Por eso, a partir de ahora, en "Información sobre cargos" incluiremos las siguientes columnas: - Número del cargo: para que puedas cruzar la información con otros reportes. - Cobrado en la operación: para saber si un cargo fue cobrado en la operación o no. - Estado del cargo y Cargo que anula: para entender más sobre los cargos anulados.
A7: Información sobre cargos | J7: Información de la operación sobre la que se aplica | R7: Información sobre percepciones | T7: Accesos
A8: Operación relacionada | B8: N° de factura fiscal | C8: Fecha del cargo | D8: Número del cargo | E8: Número del movimiento | F8: Detalle | G8: Cobrado en la operacion | H8: Estado del cargo | I8: Cargo que anula | J8: Valor del cargo | K8: Tipo de operación | L8: Tipo de pago | M8: Número de sucursal | N8: Nombre de sucursal | O8: Referencia externa | P8: Cliente | Q8: Valor de la operación | R8: Alícuota | S8: Base imponible | T8: Sección de Mercado libre y de Mercado Pago
A9: 127694553001 | B9: 0025A03281832 | C9: 45931 | D9: 51014460439 | E9: 2084126327393 | F9: Cargo por cobrar con Point | G9: Si | J9: 353.7 | K9: Pago | L9: Point | M9: 71465208 | N9: Cerveza Träctor | O9: Venta presencial | P9: VENTASPRESENCIAL | Q9: 9000 | T9: Ir al Detalle de la operación en Mercado Pago
A10: 127706300651 | B10: 0025A03281832 | C10: 45931 | D10: 51018944973 | E10: 2084203218691 | F10: Cargo por cobrar con código QR | G10: Si | J10: 77.6 | K10: Pago | L10: QR | M10: 71465208 | N10: Cerveza Träctor | P10: SOLANGEHAGEDORN | Q10: 8000 | T10: Ir al Detalle de la operación en Mercado Pago
A11: 127707346037 | B11: 0025A03281832 | C11: 45931 | D11: 51019339506 | E11: 2084211208519 | F11: Cargo por cobrar con código QR | G11: Si | J11: 87.3 | K11: Pago | L11: QR | M11: 71465208 | N11: Cerveza Träctor | P11: GONZALOGON2000 | Q11: 9000 | T11: Ir al Detalle de la operación en Mercado Pago
A12: 128274716662 | B12: 0025A03281832 | C12: 45931 | D12: 51020088068 | E12: 2084225283917 | F12: Cargo por cobrar con código QR | G12: Si | J12: 108.64 | K12: Pago | L12: QR | M12: 71465208 | N12: Cerveza Träctor | P12: SOFIAFORNASARI | Q12: 11200 | T12: Ir al Detalle de la operación en Mercado Pago
A13: 128275855374 | B13: 0025A03281832 | C13: 45931 | D13: 51020539495 | E13: 2084233597469 | F13: Cargo por cobrar con código QR | G13: Si | J13: 439.37 | K13: Pago | L13: QR | M13: 71465208 | N13: Cerveza Träctor | P13: SALDARELLIRODOLFO | Q13: 45296 | T13: Ir al Detalle de la operación en Mercado Pago
A14: 127713602167 | B14: 0025A03281832 | C14: 45931 | D14: 51021737062 | E14: 2084315133774 | F14: Cargo por cobrar con código QR | G14: Si | J14: 4.85 | K14: Pago | L14: QR | M14: 71465208 | N14: Cerveza Träctor | P14: AGUSTINAFORNASARI | Q14: 500 | T14: Ir al Detalle de la operación en Mercado Pago
A15: 127715107443 | B15: 0025A03281832 | C15: 45931 | D15: 51022393777 | E15: 2084266151099 | F15: Cargo por cobrar con código QR | G15: Si | J15: 299.71 | K15: Pago | L15: QR | M15: 71465208 | N15: Cerveza Träctor | P15: JONIIANTUNEZ | Q15: 30898 | T15: Ir al Detalle de la operación en Mercado Pago
A16: 127715769581 | B16: 0025A03281832 | C16: 45931 | D16: 51022672306 | E16: 2084331355744 | F16: Cargo por cobrar con código QR | G16: Si | J16: 651.93 | K16: Pago | L16: QR | M16: 71465208 | N16: Cerveza Träctor | P16: ESTEFANIARENIERO20220811162002 | Q16: 39996 | T16: Ir al Detalle de la operación en Mercado Pago
A17: 128281546618 | B17: 0025A03281832 | C17: 45931 | D17: 51022869175 | E17: 2084334575916 | F17: Cargo por cobrar con código QR | G17: Si | J17: 256.08 | K17: Pago | L17: QR | M17: 71465208 | N17: Cerveza Träctor | P17: ZANA617907 | Q17: 26400 | T17: Ir al Detalle de la operación en Mercado Pago
A18: 128281806306 | B18: 0025A03281832 | C18: 45931 | D18: 51022961871 | E18: 2084275970685 | F18: Cargo por cobrar con código QR | G18: Si | J18: 126.1 | K18: Pago | L18: QR | M18: 71465208 | N18: Cerveza Träctor | P18: LALY.M | Q18: 13000 | T18: Ir al Detalle de la operación en Mercado Pago
A19: 128282615258 | B19: 0025A03281832 | C19: 45931 | D19: 51023319638 | E19: 2084342831756 | F19: Cargo por cobrar con Point | G19: Si | J19: 840.98 | K19: Pago | L19: Point | M19: 71465208 | N19: Cerveza Träctor | O19: Venta presencial | P19: VENTASPRESENCIAL | Q19: 21399 | T19: Ir al Detalle de la operación en Mercado Pago
A20: 127717828761 | B20: 0025A03281832 | C20: 45931 | D20: 51023567216 | E20: 2084346996672 | F20: Cargo por cobrar con Point | G20: Si | J20: 3708.98 | K20: Pago | L20: Point | M20: 71465208 | N20: Cerveza Träctor | O20: Venta presencial | P20: VENTASPRESENCIAL | Q20: 32998 | T20: Ir al Detalle de la operación en Mercado Pago
A21: 127719464653 | B21: 0025A03281832 | C21: 45931 | D21: 51024212327 | E21: 2084358274976 | F21: Cargo por cobrar con código QR | G21: Si | J21: 221.68 | K21: Pago | L21: QR | M21: 71465208 | N21: Cerveza Träctor | P21: SANCHEZCARMIN2 | Q21: 13600 | T21: Ir al Detalle de la operación en Mercado Pago
A22: 127719431701 | B22: 0025A03281832 | C22: 45931 | D22: 51024243433 | E22: 2084297895527 | F22: Cargo por cobrar con código QR | G22: Si | J22: 193.98 | K22: Pago | L22: QR | M22: 71465208 | N22: Cerveza Träctor | P22: SANTIAGOPEREIRAMAGUNA | Q22: 19998 | T22: Ir al Detalle de la operación en Mercado Pago
A23: 128285003346 | B23: 0025A03281832 | C23: 45931 | D23: 51024343281 | E23: 2084360435996 | F23: Cargo por uso de QR - Pagos Interoperables | G23: Si | J23: 246.38 | K23: Pago | L23: QR | M23: 71465208 | N23: Cerveza Träctor | P23: @2489718921 | Q23: 25400
A24: 127719758089 | B24: 0025A03281832 | C24: 45931 | D24: 51024399946 | E24: 2084300414123 | F24: Cargo por cobrar con código QR | G24: Si | J24: 731.35 | K24: Pago | L24: QR | M24: 71465208 | N24: Cerveza Träctor | P24: MARIALUZALMADA | Q24: 75397 | T24: Ir al Detalle de la operación en Mercado Pago
A25: 128285683510 | B25: 0025A03281832 | C25: 45931 | D25: 51024686385 | E25: 2084304513879 | F25: Cargo por cobrar con código QR | G25: Si | J25: 388 | K25: Pago | L25: QR | M25: 71465208 | N25: Cerveza Träctor | P25: VALI4649926 | Q25: 40000 | T25: Ir al Detalle de la operación en Mercado Pago
A26: 127720557799 | B26: 0025A03281832 | C26: 45931 | D26: 51024777311 | E26: 2084366779882 | F26: Cargo por uso de QR - Pagos Interoperables | G26: Si | J26: 290.97 | K26: Pago | L26: QR | M26: 71465208 | N26: Cerveza Träctor | P26: @2489718921 | Q26: 29997
A27: 128286715036 | B27: 0025A03281832 | C27: 45931 | D27: 51025120194 | E27: 2084311552191 | F27: Cargo por uso de QR - Pagos Interoperables | G27: Si | J27: 169.75 | K27: Pago | L27: QR | M27: 71465208 | N27: Cerveza Träctor | P27: @2489718921 | Q27: 17500
A28: 128287489024 | B28: 0025A03281832 | C28: 45932 | D28: 51025508118 | E28: 2084317078519 | F28: Cargo por cobrar con código QR | G28: Si | J28: 96.03 | K28: Pago | L28: QR | M28: 71465208 | N28: Cerveza Träctor | P28: ERZEKIEL | Q28: 9900 | T28: Ir al Detalle de la operación en Mercado Pago
A29: 128287673862 | B29: 0025A03281832 | C29: 45932 | D29: 51025630028 | E29: 2084379150672 | F29: Cargo por cobrar con código QR | G29: Si | J29: 142.58 | K29: Pago | L29: QR | M29: 71465208 | N29: Cerveza Träctor | P29: MARIOELBARBA | Q29: 14699 | T29: Ir al Detalle de la operación en Mercado Pago
A30: 127722493817 | B30: 0025A03281832 | C30: 45932 | D30: 51025769014 | E30: 2084320044239 | F30: Cargo por cobrar con Point | G30: Si | J30: 1371.57 | K30: Pago | L30: Point | M30: 71465208 | N30: Cerveza Träctor | O30: Venta presencial | P30: VENTASPRESENCIAL | Q30: 34900 | T30: Ir al Detalle de la operación en Mercado Pago
A31: 128288249068 | B31: 0025A03281832 | C31: 45932 | D31: 51025888777 | E31: 2084322046705 | F31: Cargo por cobrar con Mercado Pago | G31: Si | J31: 559.09 | K31: Pago | L31: QR | M31: 71465208 | N31: Cerveza Träctor | P31: @2027641910 | Q31: 34300 | T31: Ir al Detalle de la operación en Mercado Pago
A32: 127724766231 | B32: 0025A03281832 | C32: 45932 | D32: 51026805316 | E32: 2084336458985 | F32: Cargo por cobrar con código QR | G32: Si | J32: 73.35 | K32: Pago | L32: QR | M32: 71465208 | N32: Cerveza Träctor | P32: JUANFOLMERD1 | Q32: 4500 | T32: Ir al Detalle de la operación en Mercado Pago
A33: 127826757701 | B33: 0025A03281832 | C33: 45932 | D33: 51065013549 | E33: 2085097455188 | F33: Cargo por cobrar con código QR | G33: Si | J33: 95.06 | K33: Pago | L33: QR | M33: 71465208 | N33: Cerveza Träctor | P33: DIEGOOLIVER75 | Q33: 9800 | T33: Ir al Detalle de la operación en Mercado Pago
A34: 128398739964 | B34: 0025A03281832 | C34: 45932 | D34: 51067161325 | E34: 2085072197011 | F34: Cargo por cobrar con código QR | G34: Si | J34: 93.12 | K34: Pago | L34: QR | M34: 71465208 | N34: Cerveza Träctor | P34: GRASFACUNDO1999 | Q34: 9600 | T34: Ir al Detalle de la operación en Mercado Pago
A35: 127834309851 | B35: 0025A03281832 | C35: 45932 | D35: 51067798581 | E35: 2085144795666 | F35: Cargo por cobrar con código QR | G35: Si | J35: 138.71 | K35: Pago | L35: QR | M35: 71465208 | N35: Cerveza Träctor | P35: FELIXMARCELONAVARRO | Q35: 14300 | T35: Ir al Detalle de la operación en Mercado Pago
A36: 128402388274 | B36: 0025A03281832 | C36: 45932 | D36: 51068449111 | E36: 2085094938511 | F36: Cargo por cobrar con código QR | G36: Si | J36: 129.01 | K36: Pago | L36: QR | M36: 71465208 | N36: Cerveza Träctor | P36: LONFACU | Q36: 13300 | T36: Ir al Detalle de la operación en Mercado Pago
A37: 127836305261 | B37: 0025A03281832 | C37: 45932 | D37: 51068461860 | E37: 2085095314531 | F37: Cargo por cobrar con Point | G37: Si | J37: 1480.04 | K37: Pago | L37: Point | M37: 71465208 | N37: Cerveza Träctor | O37: Venta presencial | P37: VENTASPRESENCIAL | Q37: 32600 | T37: Ir al Detalle de la operación en Mercado Pago
A38: 128408491342 | B38: 0025A03281832 | C38: 45932 | D38: 51070698024 | E38: 2085199834342 | F38: Cargo por cobrar con código QR | G38: Si | J38: 46.56 | K38: Pago | L38: QR | M38: 71465208 | N38: Cerveza Träctor | P38: IRINAMEICHTRY | Q38: 4800 | T38: Ir al Detalle de la operación en Mercado Pago
A39: 128408853332 | B39: 0025A03281832 | C39: 45932 | D39: 51070854546 | E39: 2085140680053 | F39: Cargo por cobrar con Point | G39: Si | J39: 188.64 | K39: Pago | L39: Point | M39: 71465208 | N39: Cerveza Träctor | O39: Venta presencial | P39: VENTASPRESENCIAL | Q39: 4800 | T39: Ir al Detalle de la operación en Mercado Pago
A40: 127843829541 | B40: 0025A03281832 | C40: 45932 | D40: 51071274580 | E40: 2085210592958 | F40: Cargo por cobrar con código QR | G40: Si | J40: 375.39 | K40: Pago | L40: QR | M40: 71465208 | N40: Cerveza Träctor | P40: ARDAIZPABLO | Q40: 38700 | T40: Ir al Detalle de la operación en Mercado Pago
A41: 127845010923 | B41: 0025A03281832 | C41: 45932 | D41: 51071698369 | E41: 2085218923540 | F41: Cargo por cobrar con código QR | G41: Si | J41: 87.3 | K41: Pago | L41: QR | M41: 71465208 | N41: Cerveza Träctor | P41: CARLSSONLAUTARO20221224163039 | Q41: 9000 | T41: Ir al Detalle de la operación en Mercado Pago
A42: 127845412065 | B42: 0025A03281832 | C42: 45932 | D42: 51071840848 | E42: 2085160334591 | F42: Cargo por cobrar con código QR | G42: Si | J42: 46.56 | K42: Pago | L42: QR | M42: 71465208 | N42: Cerveza Träctor | P42: MERIANOIRIS20220126150046 | Q42: 4800 | T42: Ir al Detalle de la operación en Mercado Pago
A43: 127845621093 | B43: 0025A03281832 | C43: 45932 | D43: 51071924758 | E43: 2085223062718 | F43: Cargo por cobrar con código QR | G43: Si | J43: 42.68 | K43: Pago | L43: QR | M43: 71465208 | N43: Cerveza Träctor | P43: JOACKOFELLAY | Q43: 4400 | T43: Ir al Detalle de la operación en Mercado Pago
A44: 127846108405 | B44: 0025A03281832 | C44: 45932 | D44: 51072099422 | E44: 2085165091419 | F44: Cargo por cobrar con Point | G44: Si | J44: 165.06 | K44: Pago | L44: Point | M44: 71465208 | N44: Cerveza Träctor | O44: Venta presencial | P44: VENTASPRESENCIAL | Q44: 4200 | T44: Ir al Detalle de la operación en Mercado Pago
A45: 127846250789 | B45: 0025A03281832 | C45: 45932 | D45: 51072196991 | E45: 2085166593759 | F45: Cargo por cobrar con Point | G45: Si | J45: 165.06 | K45: Pago | L45: Point | M45: 71465208 | N45: Cerveza Träctor | O45: Venta presencial | P45: VENTASPRESENCIAL | Q45: 4200 | T45: Ir al Detalle de la operación en Mercado Pago
A46: 128412427806 | B46: 0025A03281832 | C46: 45932 | D46: 51072236357 | E46: 2085167340209 | F46: Cargo por cobrar con Point | G46: Si | J46: 1225.8 | K46: Pago | L46: Point | M46: 71465208 | N46: Cerveza Träctor | O46: Venta presencial | P46: VENTASPRESENCIAL | Q46: 27000 | T46: Ir al Detalle de la operación en Mercado Pago
A47: 127847014705 | B47: 0025A03281832 | C47: 45932 | D47: 51072515266 | E47: 2085234008940 | F47: Cargo por cobrar con código QR | G47: Si | J47: 142.59 | K47: Pago | L47: QR | M47: 71465208 | N47: Cerveza Träctor | P47: VICKYMARTEN | Q47: 14700 | T47: Ir al Detalle de la operación en Mercado Pago
A48: 128413285526 | B48: 0025A03281832 | C48: 45932 | D48: 51072555831 | E48: 2085172947327 | F48: Cargo por cobrar con Point | G48: Si | J48: 188.64 | K48: Pago | L48: Point | M48: 71465208 | N48: Cerveza Träctor | O48: Venta presencial | P48: VENTASPRESENCIAL | Q48: 4800 | T48: Ir al Detalle de la operación en Mercado Pago
A49: 127847143045 | B49: 0025A03281832 | C49: 45932 | D49: 51072586350 | E49: 2085173844383 | F49: Cargo por cobrar con código QR | G49: Si | J49: 46.56 | K49: Pago | L49: QR | M49: 71465208 | N49: Cerveza Träctor | P49: LUCIORAPALLO | Q49: 4800 | T49: Ir al Detalle de la operación en Mercado Pago
A50: 128413748622 | B50: 0025A03281832 | C50: 45932 | D50: 51072713993 | E50: 2085238000716 | F50: Cargo por cobrar con código QR | G50: Si | J50: 97 | K50: Pago | L50: QR | M50: 71465208 | N50: Cerveza Träctor | P50: QUIIMEY | Q50: 10000 | T50: Ir al Detalle de la operación en Mercado Pago
A51: 127847979869 | B51: 0025A03281832 | C51: 45932 | D51: 51072893244 | E51: 2085241422152 | F51: Cargo por cobrar con Mercado Pago | G51: Si | J51: 2450.42 | K51: Pago | L51: QR | M51: 71465208 | N51: Cerveza Träctor | P51: @1785701758 | Q51: 32200 | T51: Ir al Detalle de la operación en Mercado Pago
A52: 127848195943 | B52: 0025A03281832 | C52: 45932 | D52: 51072976223 | E52: 2085181177151 | F52: Cargo por cobrar con código QR | G52: Si | J52: 337.56 | K52: Pago | L52: QR | M52: 71465208 | N52: Cerveza Träctor | P52: MARIOELBARBA | Q52: 34800 | T52: Ir al Detalle de la operación en Mercado Pago
A53: 128414602122 | B53: 0025A03281832 | C53: 45932 | D53: 51073043510 | E53: 2085244589088 | F53: Cargo por cobrar con Point | G53: Si | J53: 471.82 | K53: Pago | L53: Point | M53: 71465208 | N53: Cerveza Träctor | O53: Venta presencial | P53: VENTASPRESENCIAL | Q53: 6200 | T53: Ir al Detalle de la operación en Mercado Pago
A54: 127848730441 | B54: 0025A03281832 | C54: 45932 | D54: 51073144177 | E54: 2085185132833 | F54: Cargo por cobrar con código QR | G54: Si | J54: 87.3 | K54: Pago | L54: QR | M54: 71465208 | N54: Cerveza Träctor | P54: CARLSSONLAUTARO20221224163039 | Q54: 9000 | T54: Ir al Detalle de la operación en Mercado Pago
A55: 127849129705 | B55: 0025A03281832 | C55: 45932 | D55: 51073369185 | E55: 2085250679430 | F55: Cargo por cobrar con código QR | G55: Si | J55: 46.56 | K55: Pago | L55: QR | M55: 71465208 | N55: Cerveza Träctor | P55: MERIANOIRIS20220126150046 | Q55: 4800 | T55: Ir al Detalle de la operación en Mercado Pago
A56: 128415782272 | B56: 0025A03281832 | C56: 45932 | D56: 51073486283 | E56: 2085252678710 | F56: Cargo por cobrar con código QR | G56: Si | J56: 38.8 | K56: Pago | L56: QR | M56: 71465208 | N56: Cerveza Träctor | P56: PRIPARLATTO | Q56: 4000 | T56: Ir al Detalle de la operación en Mercado Pago
A57: 127850379377 | B57: 0025A03281832 | C57: 45932 | D57: 51073845232 | E57: 2085260059778 | F57: Cargo por uso de QR - Pagos Interoperables | G57: Si | J57: 112.52 | K57: Pago | L57: QR | M57: 71465208 | N57: Cerveza Träctor | P57: @2489718921 | Q57: 11600
A58: 127850602909 | B58: 0025A03281832 | C58: 45932 | D58: 51073905240 | E58: 2085199414377 | F58: Cargo por cobrar con código QR | G58: Si | J58: 38.8 | K58: Pago | L58: QR | M58: 71465208 | N58: Cerveza Träctor | P58: DELFINAIZAURRALDE | Q58: 4000 | T58: Ir al Detalle de la operación en Mercado Pago
A59: 127850717607 | B59: 0025A03281832 | C59: 45932 | D59: 51073958760 | E59: 2085262323988 | F59: Cargo por cobrar con Point | G59: Si | J59: 540.26 | K59: Pago | L59: Point | M59: 71465208 | N59: Cerveza Träctor | O59: Venta presencial | P59: VENTASPRESENCIAL | Q59: 11900 | T59: Ir al Detalle de la operación en Mercado Pago
A60: 128416983560 | B60: 0025A03281832 | C60: 45932 | D60: 51074044454 | E60: 2085263792080 | F60: Cargo por cobrar con código QR | G60: Si | J60: 73.72 | K60: Pago | L60: QR | M60: 71465208 | N60: Cerveza Träctor | P60: CAMILATERENZIO | Q60: 7600 | T60: Ir al Detalle de la operación en Mercado Pago
A61: 128417090472 | B61: 0025A03281832 | C61: 45932 | D61: 51074051714 | E61: 2085202513559 | F61: Cargo por cobrar con código QR | G61: Si | J61: 2846.14 | K61: Pago | L61: QR | M61: 71465208 | N61: Cerveza Träctor | P61: RODRI_ESP | Q61: 37400 | T61: Ir al Detalle de la operación en Mercado Pago
A62: 128417478168 | B62: 0025A03281832 | C62: 45932 | D62: 51074215056 | E62: 2085266862062 | F62: Cargo por cobrar con código QR | G62: Si | J62: 43.65 | K62: Pago | L62: QR | M62: 71465208 | N62: Cerveza Träctor | P62: VALENRABOSTO | Q62: 4500 | T62: Ir al Detalle de la operación en Mercado Pago
A63: 127851297553 | B63: 0025A03281832 | C63: 45932 | D63: 51074220836 | E63: 2085205412193 | F63: Cargo por cobrar con Point | G63: Si | J63: 165.06 | K63: Pago | L63: Point | M63: 71465208 | N63: Cerveza Träctor | O63: Venta presencial | P63: VENTASPRESENCIAL | Q63: 4200 | T63: Ir al Detalle de la operación en Mercado Pago
A64: 127851529137 | B64: 0025A03281832 | C64: 45932 | D64: 51074283341 | E64: 2085207128339 | F64: Cargo por cobrar con código QR | G64: Si | J64: 97 | K64: Pago | L64: QR | M64: 71465208 | N64: Cerveza Träctor | P64: QUIIMEY | Q64: 10000 | T64: Ir al Detalle de la operación en Mercado Pago
A65: 127852042311 | B65: 0025A03281832 | C65: 45932 | D65: 51074498467 | E65: 2085271773062 | F65: Cargo por cobrar con código QR | G65: Si | J65: 23.28 | K65: Pago | L65: QR | M65: 71465208 | N65: Cerveza Träctor | P65: WOOFIE.MANEE | Q65: 2400 | T65: Ir al Detalle de la operación en Mercado Pago
A66: 127852662327 | B66: 0025A03281832 | C66: 45932 | D66: 51074740234 | E66: 2085214164687 | F66: Cargo por cobrar con código QR | G66: Si | J66: 297.79 | K66: Pago | L66: QR | M66: 71465208 | N66: Cerveza Träctor | P66: DEGANOSOFIA1 | Q66: 30700 | T66: Ir al Detalle de la operación en Mercado Pago
A67: 128418794938 | B67: 0025A03281832 | C67: 45932 | D67: 51074769774 | E67: 2085214695545 | F67: Cargo por cobrar con código QR | G67: Si | J67: 38.8 | K67: Pago | L67: QR | M67: 71465208 | N67: Cerveza Träctor | P67: CARLSSONLAUTARO20221224163039 | Q67: 4000 | T67: Ir al Detalle de la operación en Mercado Pago
A68: 127852972373 | B68: 0025A03281832 | C68: 45932 | D68: 51074839610 | E68: 2085277787734 | F68: Cargo por uso de QR - Pagos Interoperables | G68: Si | J68: 46.56 | K68: Pago | L68: QR | M68: 71465208 | N68: Cerveza Träctor | P68: @2489718921 | Q68: 4800
A69: 128419226662 | B69: 0025A03281832 | C69: 45932 | D69: 51074929612 | E69: 2085279175928 | F69: Cargo por cobrar con Point | G69: Si | J69: 165.06 | K69: Pago | L69: Point | M69: 71465208 | N69: Cerveza Träctor | O69: Venta presencial | P69: VENTASPRESENCIAL | Q69: 4200 | T69: Ir al Detalle de la operación en Mercado Pago
A70: 128419350310 | B70: 0025A03281832 | C70: 45932 | D70: 51074996784 | E70: 2085218218651 | F70: Cargo por cobrar con código QR | G70: Si | J70: 934.11 | K70: Pago | L70: QR | M70: 71465208 | N70: Cerveza Träctor | P70: GP20240729142131 | Q70: 96300 | T70: Ir al Detalle de la operación en Mercado Pago
A71: 128419431770 | B71: 0025A03281832 | C71: 45932 | D71: 51075078022 | E71: 2085219650395 | F71: Cargo por cobrar con código QR | G71: Si | J71: 236.68 | K71: Pago | L71: QR | M71: 71465208 | N71: Cerveza Träctor | P71: MARA.V | Q71: 24400 | T71: Ir al Detalle de la operación en Mercado Pago
A72: 128419732970 | B72: 0025A03281832 | C72: 45932 | D72: 51075195068 | E72: 2085282955246 | F72: Cargo por cobrar con código QR | G72: Si | J72: 46.56 | K72: Pago | L72: QR | M72: 71465208 | N72: Cerveza Träctor | P72: MARIANOEBARRETO | Q72: 4800 | T72: Ir al Detalle de la operación en Mercado Pago
A73: 127853704713 | B73: 0025A03281832 | C73: 45932 | D73: 51075232500 | E73: 2085222175109 | F73: Cargo por cobrar con código QR | G73: Si | J73: 97 | K73: Pago | L73: QR | M73: 71465208 | N73: Cerveza Träctor | P73: DOMINGUEZVALENTINA202205031321 | Q73: 10000 | T73: Ir al Detalle de la operación en Mercado Pago
A74: 127853815447 | B74: 0025A03281832 | C74: 45932 | D74: 51075281569 | E74: 2085223146617 | F74: Cargo por cobrar con código QR | G74: Si | J74: 180.42 | K74: Pago | L74: QR | M74: 71465208 | N74: Cerveza Träctor | P74: NACHOBOUJON07 | Q74: 18600 | T74: Ir al Detalle de la operación en Mercado Pago
A75: 128420232980 | B75: 0025A03281832 | C75: 45932 | D75: 51075365368 | E75: 2085224164907 | F75: Cargo por cobrar con Point | G75: Si | J75: 1733.13 | K75: Pago | L75: Point | M75: 71465208 | N75: Cerveza Träctor | O75: Venta presencial | P75: VENTASPRESENCIAL | Q75: 44100 | T75: Ir al Detalle de la operación en Mercado Pago
A76: 127854076319 | B76: 0025A03281832 | C76: 45932 | D76: 51075386088 | E76: 2085286173518 | F76: Cargo por cobrar con código QR | G76: Si | J76: 61.11 | K76: Pago | L76: QR | M76: 71465208 | N76: Cerveza Träctor | P76: RESPAUDMARIA20230106123150 | Q76: 6300 | T76: Ir al Detalle de la operación en Mercado Pago
A77: 128420407042 | B77: 0025A03281832 | C77: 45932 | D77: 51075465472 | E77: 2085287326594 | F77: Cargo por cobrar con Point | G77: Si | J77: 10174.14 | K77: Pago | L77: Point | M77: 71465208 | N77: Cerveza Träctor | O77: Venta presencial | P77: VENTASPRESENCIAL | Q77: 224100 | T77: Ir al Detalle de la operación en Mercado Pago
A78: 127854278121 | B78: 0025A03281832 | C78: 45932 | D78: 51075495766 | E78: 2085226017327 | F78: Cargo por cobrar con código QR | G78: Si | J78: 61.11 | K78: Pago | L78: QR | M78: 71465208 | N78: Cerveza Träctor | P78: RESPAUDMARIA20230106123150 | Q78: 6300 | T78: Ir al Detalle de la operación en Mercado Pago
A79: 128420454022 | B79: 0025A03281832 | C79: 45932 | D79: 51075502755 | E79: 2085226497795 | F79: Cargo por uso de QR - Pagos Interoperables | G79: Si | J79: 97 | K79: Pago | L79: QR | M79: 71465208 | N79: Cerveza Träctor | P79: @2489718921 | Q79: 10000
A80: 127854437157 | B80: 0025A03281832 | C80: 45932 | D80: 51075573186 | E80: 2085289416098 | F80: Cargo por uso de QR - Pagos Interoperables | G80: Si | J80: 461.72 | K80: Pago | L80: QR | M80: 71465208 | N80: Cerveza Träctor | P80: @2489718921 | Q80: 47600
A81: 128420793726 | B81: 0025A03281832 | C81: 45932 | D81: 51075694431 | E81: 2085228926727 | F81: Cargo por cobrar con código QR | G81: Si | J81: 70.81 | K81: Pago | L81: QR | M81: 71465208 | N81: Cerveza Träctor | P81: LIKAYBENJAMIN20220310013105 | Q81: 7300 | T81: Ir al Detalle de la operación en Mercado Pago
A82: 127854884711 | B82: 0025A03281832 | C82: 45933 | D82: 51075722797 | E82: 2085291534300 | F82: Cargo por cobrar con código QR | G82: Si | J82: 48.5 | K82: Pago | L82: QR | M82: 71465208 | N82: Cerveza Träctor | P82: ALLAUDGONZALO20220827192154 | Q82: 5000 | T82: Ir al Detalle de la operación en Mercado Pago
A83: 127854922579 | B83: 0025A03281832 | C83: 45933 | D83: 51075756052 | E83: 2085230249263 | F83: Cargo por cobrar con código QR | G83: Si | J83: 2480.86 | K83: Pago | L83: QR | M83: 71465208 | N83: Cerveza Träctor | P83: BOAL2059999 | Q83: 32600 | T83: Ir al Detalle de la operación en Mercado Pago
A84: 127854974679 | B84: 0025A03281832 | C84: 45933 | D84: 51075797540 | E84: 2085292620384 | F84: Cargo por uso de QR - Pagos Interoperables | G84: Si | J84: 182.36 | K84: Pago | L84: QR | M84: 71465208 | N84: Cerveza Träctor | P84: @2489718921 | Q84: 18800
A85: 128421075828 | B85: 0025A03281832 | C85: 45933 | D85: 51075823571 | E85: 2085292833910 | F85: Cargo por cobrar con Point | G85: No aplica | H85: Anulado en factura | J85: 5161.98 | K85: Pago | L85: Point | M85: 71465208 | N85: Cerveza Träctor | O85: Venta presencial | P85: VENTASPRESENCIAL | Q85: 113700 | T85: Ir al Detalle de la operación en Mercado Pago
A86: 128421266626 | B86: 0025A03281832 | C86: 45933 | D86: 51075897848 | E86: 2085232092175 | F86: Cargo por uso de QR - Pagos Interoperables | G86: Si | J86: 41.71 | K86: Pago | L86: QR | M86: 71465208 | N86: Cerveza Träctor | P86: @2489718921 | Q86: 4300
A87: 128421434434 | B87: 0025A03281832 | C87: 45933 | D87: 51075972722 | E87: 2085233390737 | F87: Cargo por cobrar con código QR | G87: Si | J87: 93.12 | K87: Pago | L87: QR | M87: 71465208 | N87: Cerveza Träctor | P87: ZURMUHLEIGNACIO20210611014735 | Q87: 9600 | T87: Ir al Detalle de la operación en Mercado Pago
A88: 128421490336 | B88: 0025A03281832 | C88: 45933 | D88: 51075994138 | E88: 2085233728069 | F88: Cargo por cobrar con código QR | G88: Si | J88: 131.92 | K88: Pago | L88: QR | M88: 71465208 | N88: Cerveza Träctor | P88: EMI_KPO_ROJO | Q88: 13600 | T88: Ir al Detalle de la operación en Mercado Pago
A89: 128421501412 | B89: 0025A03281832 | C89: 45933 | D89: 51076067301 | E89: 2085296128556 | F89: Cargo por cobrar con Point | G89: Si | J89: 12929.39 | K89: Pago | L89: Point | M89: 71465208 | N89: Cerveza Träctor | O89: Venta presencial | P89: VENTASPRESENCIAL | Q89: 169900 | T89: Ir al Detalle de la operación en Mercado Pago
A90: 127855461023 | B90: 0025A03281832 | C90: 45933 | D90: 51076097235 | E90: 2085234669479 | F90: Cargo por cobrar con Point | G90: Si | J90: 632.73 | K90: Pago | L90: Point | M90: 71465208 | N90: Cerveza Träctor | O90: Venta presencial | P90: VENTASPRESENCIAL | Q90: 16100 | T90: Ir al Detalle de la operación en Mercado Pago
A91: 127855560075 | B91: 0025A03281832 | C91: 45933 | D91: 51076184214 | E91: 2085297929572 | F91: Cargo por cobrar con Point | G91: Si | J91: 1216.72 | K91: Pago | L91: Point | M91: 71465208 | N91: Cerveza Träctor | O91: Venta presencial | P91: VENTASPRESENCIAL | Q91: 26800 | T91: Ir al Detalle de la operación en Mercado Pago
A92: 127855916129 | B92: 0025A03281832 | C92: 45933 | D92: 51076271763 | E92: 2085299269916 | F92: Cargo por cobrar con código QR | G92: Si | J92: 74.69 | K92: Pago | L92: QR | M92: 71465208 | N92: Cerveza Träctor | P92: IZJO3961013 | Q92: 7700 | T92: Ir al Detalle de la operación en Mercado Pago
A93: 128422197004 | B93: 0025A03281832 | C93: 45933 | D93: 51076333606 | E93: 2085238650807 | F93: Cargo por cobrar con código QR | G93: Si | J93: 38.8 | K93: Pago | L93: QR | M93: 71465208 | N93: Cerveza Träctor | P93: JUVENALJUAN20230708121409 | Q93: 4000 | T93: Ir al Detalle de la operación en Mercado Pago
A94: 128421075828 | B94: 0025A03281832 | C94: 45933 | D94: 51076343582 | E94: 2085238848693 | F94: Anulación del cargo por cobrar con Point | G94: No aplica | I94: 51075823571 | J94: -5161.98 | K94: Pago | L94: Point | M94: 71465208 | N94: Cerveza Träctor | O94: Venta presencial | P94: VENTASPRESENCIAL | Q94: 113700
A95: 127856005159 | B95: 0025A03281832 | C95: 45933 | D95: 51076371296 | E95: 2085300884234 | F95: Cargo por uso de QR - Pagos Interoperables | G95: Si | J95: 93.12 | K95: Pago | L95: QR | M95: 71465208 | N95: Cerveza Träctor | P95: @2489718921 | Q95: 9600
A96: 127856064757 | B96: 0025A03281832 | C96: 45933 | D96: 51076415056 | E96: 2085239238421 | F96: Cargo por cobrar con Point | G96: Si | J96: 1661.64 | K96: Pago | L96: Point | M96: 71465208 | N96: Cerveza Träctor | O96: Venta presencial | P96: VENTASPRESENCIAL | Q96: 36600 | T96: Ir al Detalle de la operación en Mercado Pago
A97: 127856418189 | B97: 0025A03281832 | C97: 45933 | D97: 51076504649 | E97: 2085240981129 | F97: Cargo por cobrar con código QR | G97: Si | J97: 67.9 | K97: Pago | L97: QR | M97: 71465208 | N97: Cerveza Träctor | P97: G20250813211951 | Q97: 7000 | T97: Ir al Detalle de la operación en Mercado Pago
A98: 127856497497 | B98: 0025A03281832 | C98: 45933 | D98: 51076548535 | E98: 2085303889488 | F98: Cargo por cobrar con código QR | G98: Si | J98: 40.74 | K98: Pago | L98: QR | M98: 71465208 | N98: Cerveza Träctor | P98: JOAQUINBORTAGARAY | Q98: 4200 | T98: Ir al Detalle de la operación en Mercado Pago
A99: 128422949584 | B99: 0025A03281832 | C99: 45933 | D99: 51076716350 | E99: 2085307029798 | F99: Cargo por cobrar con código QR | G99: Si | J99: 580.06 | K99: Pago | L99: QR | M99: 71465208 | N99: Cerveza Träctor | P99: CAROOR16 | Q99: 59800 | T99: Ir al Detalle de la operación en Mercado Pago
A100: 127856899443 | B100: 0025A03281832 | C100: 45933 | D100: 51076756213 | E100: 2085308111738 | F100: Cargo por cobrar con Point | G100: Si | J100: 399.52 | K100: Pago | L100: Point | M100: 71465208 | N100: Cerveza Träctor | O100: Venta presencial | P100: VENTASPRESENCIAL | Q100: 8800 | T100: Ir al Detalle de la operación en Mercado Pago
A101: 128423208738 | B101: 0025A03281832 | C101: 45933 | D101: 51076766921 | E101: 2085246316743 | F101: Cargo por cobrar con Point | G101: Si | J101: 188.64 | K101: Pago | L101: Point | M101: 71465208 | N101: Cerveza Träctor | O101: Venta presencial | P101: VENTASPRESENCIAL | Q101: 4800 | T101: Ir al Detalle de la operación en Mercado Pago
A102: 127857063969 | B102: 0025A03281832 | C102: 45933 | D102: 51076813741 | E102: 2085247875641 | F102: Cargo por cobrar con código QR | G102: Si | J102: 99.91 | K102: Pago | L102: QR | M102: 71465208 | N102: Cerveza Träctor | P102: JARACANDELA20230112195954 | Q102: 10300 | T102: Ir al Detalle de la operación en Mercado Pago
A103: 128423356546 | B103: 0025A03281832 | C103: 45933 | D103: 51076818857 | E103: 2085247523599 | F103: Cargo por uso de QR - Pagos Interoperables | G103: Si | J103: 126.1 | K103: Pago | L103: QR | M103: 71465208 | N103: Cerveza Träctor | P103: @2489718921 | Q103: 13000
A104: 127857363213 | B104: 0025A03281832 | C104: 45933 | D104: 51076893577 | E104: 2085311513972 | F104: Cargo por uso de QR - Pagos Interoperables | G104: Si | J104: 51.41 | K104: Pago | L104: QR | M104: 71465208 | N104: Cerveza Träctor | P104: @2489718921 | Q104: 5300
...

Sheet IDC
A1: Reporte-Retención-Impuesto-sobre-los-Créditos-y-Débitos-Octubre-CC20250609171159-MercadoPago
A3: Usuario: | B3: CC20250609171159
A4: Impuesto: | B4: Impuesto sobre los Créditos y Débitos
A5: Fecha de descarga: | B5: 18/03/2026
A6: Intervalo de fechas consultadas: | B6: 01/10/2025 a 01/11/2025
A8: Total | B8: Monto
A9: Base imponible | B9: $72.256.708,51
A10: Importe retenido | B10: $433.540,21
A11: Importe devuelto | B11: $2.501,52
A13: Encuentra los movimientos de dinero en tu cuenta de Mercado Pago, en informes de balance.
A15: Este impuesto se aplica cada vez que hagas operaciones con terceros.
A16: Podrás conciliar la información con otros reportes de Mercado Libre. | D16: Podrás buscar el detalle de lo retenido en tu operación en la sección Actividad.
A18: Operación | E18: Impuesto
A19: Número de operación | B19: Número de venta - Referencia externa | C19: Fecha de operación | D19: Tipo | E19: Fecha de retención | F19: Alícuota | G19: Base imponible | H19: Importe retenido
A20: 127694553001 | B20: Venta presencial | C20: 01/10/2025 | D20: Transacción | E20: 01/10/2025 | F20: 0,60 % | G20: 9000 | H20: 54 | K20: =VLOOKUP(B20,Detallado!$C$5:$H$1570,6,FALSE) -> #N/A
A21: 127706300651 | C21: 01/10/2025 | D21: Transacción | E21: 01/10/2025 | F21: 0,60 % | G21: 8000 | H21: 48
A22: 127707346037 | C22: 01/10/2025 | D22: Transacción | E22: 01/10/2025 | F22: 0,60 % | G22: 9000 | H22: 54
A23: 128274716662 | C23: 01/10/2025 | D23: Transacción | E23: 01/10/2025 | F23: 0,60 % | G23: 11200 | H23: 67.2
A24: 128275855374 | C24: 01/10/2025 | D24: Transacción | E24: 01/10/2025 | F24: 0,60 % | G24: 45296 | H24: 271.78
A25: 127715107443 | C25: 01/10/2025 | D25: Transacción | E25: 01/10/2025 | F25: 0,60 % | G25: 30898 | H25: 185.39
A26: 128281806306 | C26: 01/10/2025 | D26: Transacción | E26: 01/10/2025 | F26: 0,60 % | G26: 13000 | H26: 78
A27: 128275829832 | B27: tips-128275855374 | C27: 01/10/2025 | D27: Transacción | E27: 01/10/2025 | F27: 0,60 % | G27: 2264 | H27: 13.58
A28: 127719431701 | C28: 01/10/2025 | D28: Transacción | E28: 01/10/2025 | F28: 0,60 % | G28: 19998 | H28: 119.99
A29: 127719758089 | C29: 01/10/2025 | D29: Transacción | E29: 01/10/2025 | F29: 0,60 % | G29: 75397 | H29: 452.38
A30: 128285683510 | C30: 01/10/2025 | D30: Transacción | E30: 01/10/2025 | F30: 0,60 % | G30: 40000 | H30: 240
A31: 128286715036 | C31: 01/10/2025 | D31: Transacción | E31: 01/10/2025 | F31: 0,60 % | G31: 17500 | H31: 105
A32: 127713602167 | C32: 01/10/2025 | D32: Transacción | E32: 01/10/2025 | F32: 0,60 % | G32: 500 | H32: 3
A33: 128287489024 | C33: 01/10/2025 | D33: Transacción | E33: 02/10/2025 | F33: 0,60 % | G33: 9900 | H33: 59.4
A34: 128287834208 | B34: tips-128287673862 | C34: 01/10/2025 | D34: Transacción | E34: 02/10/2025 | F34: 0,60 % | G34: 2204 | H34: 13.22
A35: 127722493817 | B35: Venta presencial | C35: 01/10/2025 | D35: Transacción | E35: 02/10/2025 | F35: 0,60 % | G35: 34900 | H35: 209.4
A36: 128288249068 | C36: 01/10/2025 | D36: Transacción | E36: 02/10/2025 | F36: 0,60 % | G36: 34300 | H36: 205.8
A37: 127715769581 | C37: 01/10/2025 | D37: Transacción | E37: 01/10/2025 | F37: 0,60 % | G37: 39996 | H37: 239.98
A38: 128281546618 | C38: 01/10/2025 | D38: Transacción | E38: 01/10/2025 | F38: 0,60 % | G38: 26400 | H38: 158.4
A39: 128281517156 | B39: tips-128281546618 | C39: 01/10/2025 | D39: Transacción | E39: 01/10/2025 | F39: 0,60 % | G39: 2640 | H39: 15.84
A40: 128281760842 | B40: tips-128281806306 | C40: 01/10/2025 | D40: Transacción | E40: 01/10/2025 | F40: 0,60 % | G40: 650 | H40: 3.9
A41: 127724766231 | C41: 02/10/2025 | D41: Transacción | E41: 02/10/2025 | F41: 0,60 % | G41: 4500 | H41: 27
A42: 128282615258 | B42: Venta presencial | C42: 01/10/2025 | D42: Transacción | E42: 01/10/2025 | F42: 0,60 % | G42: 21399 | H42: 128.39
A43: 127717828761 | B43: Venta presencial | C43: 01/10/2025 | D43: Transacción | E43: 01/10/2025 | F43: 0,60 % | G43: 32998 | H43: 197.99
A44: 127719464653 | C44: 01/10/2025 | D44: Transacción | E44: 01/10/2025 | F44: 0,60 % | G44: 13600 | H44: 81.6
A45: 128285003346 | C45: 01/10/2025 | D45: Transacción | E45: 01/10/2025 | F45: 0,60 % | G45: 25400 | H45: 152.4
A46: 127720557799 | C46: 01/10/2025 | D46: Transacción | E46: 01/10/2025 | F46: 0,60 % | G46: 29997 | H46: 179.98
A47: 128287673862 | C47: 01/10/2025 | D47: Transacción | E47: 02/10/2025 | F47: 0,60 % | G47: 14699 | H47: 88.19
A48: 127751261829 | C48: 02/10/2025 | D48: Transacción | E48: 02/10/2025 | F48: 0,60 % | G48: 293293.89 | H48: 1759.76
A49: 128313425810 | C49: 02/10/2025 | D49: Transacción | E49: 02/10/2025 | F49: 0,60 % | G49: 193742.33 | H49: 1162.45
A50: 127758769693 | B50: 2000009426923883 | C50: 02/10/2025 | D50: Transacción | E50: 02/10/2025 | F50: 0,60 % | G50: 83790 | H50: 502.74
A51: 128340094018 | C51: 02/10/2025 | D51: Transacción | E51: 02/10/2025 | F51: 0,60 % | G51: 54034.24 | H51: 324.21
A52: 127775080827 | C52: 02/10/2025 | D52: Transacción | E52: 02/10/2025 | F52: 0,60 % | G52: 217667.97 | H52: 1306.01
A53: 127775364243 | C53: 02/10/2025 | D53: Transacción | E53: 02/10/2025 | F53: 0,60 % | G53: 203693.9 | H53: 1222.16
A54: 128398739964 | C54: 02/10/2025 | D54: Transacción | E54: 02/10/2025 | F54: 0,60 % | G54: 9600 | H54: 57.6
A55: 127834303877 | B55: tips-127834309851 | C55: 02/10/2025 | D55: Transacción | E55: 02/10/2025 | F55: 0,60 % | G55: 2145 | H55: 12.87
A56: 128402388274 | C56: 02/10/2025 | D56: Transacción | E56: 02/10/2025 | F56: 0,60 % | G56: 13300 | H56: 79.8
A57: 127836305261 | B57: Venta presencial | C57: 02/10/2025 | D57: Transacción | E57: 02/10/2025 | F57: 0,60 % | G57: 32600 | H57: 195.6
A58: 127826757701 | C58: 02/10/2025 | D58: Transacción | E58: 02/10/2025 | F58: 0,60 % | G58: 9800 | H58: 58.8
A59: 128408853332 | B59: Venta presencial | C59: 02/10/2025 | D59: Transacción | E59: 02/10/2025 | F59: 0,60 % | G59: 4800 | H59: 28.8
A60: 127834309851 | C60: 02/10/2025 | D60: Transacción | E60: 02/10/2025 | F60: 0,60 % | G60: 14300 | H60: 85.8
A61: 128402325040 | B61: tips-128402388274 | C61: 02/10/2025 | D61: Transacción | E61: 02/10/2025 | F61: 0,60 % | G61: 1330 | H61: 7.98
A62: 127845412065 | C62: 02/10/2025 | D62: Transacción | E62: 02/10/2025 | F62: 0,60 % | G62: 4800 | H62: 28.8
A63: 127846108405 | B63: Venta presencial | C63: 02/10/2025 | D63: Transacción | E63: 02/10/2025 | F63: 0,60 % | G63: 4200 | H63: 25.2
A64: 127846250789 | B64: Venta presencial | C64: 02/10/2025 | D64: Transacción | E64: 02/10/2025 | F64: 0,60 % | G64: 4200 | H64: 25.2
A65: 128412427806 | B65: Venta presencial | C65: 02/10/2025 | D65: Transacción | E65: 02/10/2025 | F65: 0,60 % | G65: 27000 | H65: 162
A66: 128413285526 | B66: Venta presencial | C66: 02/10/2025 | D66: Transacción | E66: 02/10/2025 | F66: 0,60 % | G66: 4800 | H66: 28.8
A67: 127847143045 | C67: 02/10/2025 | D67: Transacción | E67: 02/10/2025 | F67: 0,60 % | G67: 4800 | H67: 28.8
A68: 127848195943 | C68: 02/10/2025 | D68: Transacción | E68: 02/10/2025 | F68: 0,60 % | G68: 34800 | H68: 208.8
A69: 128414396282 | B69: tips-127848195943 | C69: 02/10/2025 | D69: Transacción | E69: 02/10/2025 | F69: 0,60 % | G69: 5220 | H69: 31.32
A70: 127848730441 | C70: 02/10/2025 | D70: Transacción | E70: 02/10/2025 | F70: 0,60 % | G70: 9000 | H70: 54
A71: 127850602909 | C71: 02/10/2025 | D71: Transacción | E71: 02/10/2025 | F71: 0,60 % | G71: 4000 | H71: 24
A72: 128408491342 | C72: 02/10/2025 | D72: Transacción | E72: 02/10/2025 | F72: 0,60 % | G72: 4800 | H72: 28.8
A73: 128417090472 | C73: 02/10/2025 | D73: Transacción | E73: 02/10/2025 | F73: 0,60 % | G73: 37400 | H73: 224.4
A74: 127851297553 | B74: Venta presencial | C74: 02/10/2025 | D74: Transacción | E74: 02/10/2025 | F74: 0,60 % | G74: 4200 | H74: 25.2
A75: 127851529137 | C75: 02/10/2025 | D75: Transacción | E75: 02/10/2025 | F75: 0,60 % | G75: 10000 | H75: 60
A76: 127843829541 | C76: 02/10/2025 | D76: Transacción | E76: 02/10/2025 | F76: 0,60 % | G76: 38700 | H76: 232.2
A77: 128410134666 | B77: tips-127843829541 | C77: 02/10/2025 | D77: Transacción | E77: 02/10/2025 | F77: 0,60 % | G77: 1935 | H77: 11.61
A78: 127852662327 | C78: 02/10/2025 | D78: Transacción | E78: 02/10/2025 | F78: 0,60 % | G78: 30700 | H78: 184.2
A79: 128418794938 | C79: 02/10/2025 | D79: Transacción | E79: 02/10/2025 | F79: 0,60 % | G79: 4000 | H79: 24
A80: 128419350310 | C80: 02/10/2025 | D80: Transacción | E80: 02/10/2025 | F80: 0,60 % | G80: 96300 | H80: 577.8
A81: 127845010923 | C81: 02/10/2025 | D81: Transacción | E81: 02/10/2025 | F81: 0,60 % | G81: 9000 | H81: 54
A82: 128419431770 | C82: 02/10/2025 | D82: Transacción | E82: 02/10/2025 | F82: 0,60 % | G82: 24400 | H82: 146.4
A83: 127853669293 | B83: tips-127853704713 | C83: 02/10/2025 | D83: Transacción | E83: 02/10/2025 | F83: 0,60 % | G83: 500 | H83: 3
A84: 127853704713 | C84: 02/10/2025 | D84: Transacción | E84: 02/10/2025 | F84: 0,60 % | G84: 10000 | H84: 60
A85: 128411521730 | B85: tips-127845412065 | C85: 02/10/2025 | D85: Transacción | E85: 02/10/2025 | F85: 0,60 % | G85: 480 | H85: 2.88
A86: 127845621093 | C86: 02/10/2025 | D86: Transacción | E86: 02/10/2025 | F86: 0,60 % | G86: 4400 | H86: 26.4
A87: 127853815447 | C87: 02/10/2025 | D87: Transacción | E87: 02/10/2025 | F87: 0,60 % | G87: 18600 | H87: 111.6
A88: 128420232980 | B88: Venta presencial | C88: 02/10/2025 | D88: Transacción | E88: 02/10/2025 | F88: 0,60 % | G88: 44100 | H88: 264.6
A89: 127854278121 | C89: 02/10/2025 | D89: Transacción | E89: 02/10/2025 | F89: 0,60 % | G89: 6300 | H89: 37.8
A90: 128420454022 | C90: 02/10/2025 | D90: Transacción | E90: 02/10/2025 | F90: 0,60 % | G90: 10000 | H90: 60
A91: 128420793726 | C91: 02/10/2025 | D91: Transacción | E91: 02/10/2025 | F91: 0,60 % | G91: 7300 | H91: 43.8
A92: 127854922579 | C92: 02/10/2025 | D92: Transacción | E92: 03/10/2025 | F92: 0,60 % | G92: 32600 | H92: 195.6
A93: 128421266626 | C93: 02/10/2025 | D93: Transacción | E93: 03/10/2025 | F93: 0,60 % | G93: 4300 | H93: 25.8
A94: 128421434434 | C94: 02/10/2025 | D94: Transacción | E94: 03/10/2025 | F94: 0,60 % | G94: 9600 | H94: 57.6
A95: 128421490336 | C95: 02/10/2025 | D95: Transacción | E95: 03/10/2025 | F95: 0,60 % | G95: 13600 | H95: 81.6
A96: 127847014705 | C96: 02/10/2025 | D96: Transacción | E96: 02/10/2025 | F96: 0,60 % | G96: 14700 | H96: 88.2
A97: 127855461023 | B97: Venta presencial | C97: 02/10/2025 | D97: Transacción | E97: 03/10/2025 | F97: 0,60 % | G97: 16100 | H97: 96.6
A98: 128413748622 | C98: 02/10/2025 | D98: Transacción | E98: 02/10/2025 | F98: 0,60 % | G98: 10000 | H98: 60
A99: 128422276166 | B99: tips-128422197004 | C99: 02/10/2025 | D99: Transacción | E99: 03/10/2025 | F99: 0,60 % | G99: 600 | H99: 3.6
A100: 128422197004 | C100: 02/10/2025 | D100: Transacción | E100: 03/10/2025 | F100: 0,60 % | G100: 4000 | H100: 24
A101: 128421075828 | B101: Venta presencial | C101: 02/10/2025 | D101: Devolución | E101: 03/10/2025 | F101: 0,60 % | G101: -113700 | H101: -682.2
A102: 127856064757 | B102: Venta presencial | C102: 02/10/2025 | D102: Transacción | E102: 03/10/2025 | F102: 0,60 % | G102: 36600 | H102: 219.6
A103: 127856418189 | C103: 02/10/2025 | D103: Transacción | E103: 03/10/2025 | F103: 0,60 % | G103: 7000 | H103: 42
A104: 127847979869 | C104: 02/10/2025 | D104: Transacción | E104: 02/10/2025 | F104: 0,60 % | G104: 32200 | H104: 193.2
A105: 128414602122 | B105: Venta presencial | C105: 02/10/2025 | D105: Transacción | E105: 02/10/2025 | F105: 0,60 % | G105: 6200 | H105: 37.2
...
